Workbook

Sheet Frequency
B2: TIER | E2: ODDS | F2: ODDS | G2: PRIZE | K2: % OF | M2: Prize Structure
B3: NUMBER | C3: WIN METHOD | D3: PRIZE | E3: UP | F3: DOWN | G3: COST | H3: HUMAN NAME | I3: 1 in X Odds | J3: COUNT | K3: PRIZE FUND | M3: Kentucky Lottery
B4: =Tiers!B3 -> 0 | C4: =Tiers!X3 -> 0||||||||| | D4: =Tiers!C3 -> 0 | E4: =F4-SUM(E5:E410) -> 1486523 | F4: 2000000 | G4: =E4*D4 -> 0 | H4: Non-Win | I4: =F4/E4 -> 1.3454215 | J4: =ROUND(IF(D4=0,($N$17*0.3),((((N$17*0.7)-(N$19*N$18)))*(E4/$N$14)+$N$19)),0) -> 1800 | M4: King Kong Jackpots(MMJ3) Standard
B5: =Tiers!B4 -> 1 | C5: =Tiers!X4 -> main-0||||||||| | D5: =Tiers!C4 -> 0.1 | E5: 48698 | F5: 2000000 | G5: =E5*D5 -> 4869.8 | H5: ='Data Analysis'!BK3 & " | " & 'Data Analysis'!BL3 -> Less than Stake | Single Win | I5: =F5/E5 -> 41.069448 | J5: =ROUND(IF(D5=0,($N$17*0.3),((((N$17*0.7)-(N$19*N$18)))*(E5/$N$14)+$N$19)),0) -> 173 | K5: =G5/N$9 -> 0.0030685058
B6: =Tiers!B5 -> 2 | C6: =Tiers!X5 -> main-1||||||||| | D6: =Tiers!C5 -> 0.2 | E6: 35002 | F6: 2000000 | G6: =E6*D6 -> 7000.4 | H6: ='Data Analysis'!BK4 & " | " & 'Data Analysis'!BL4 -> Less than Stake | Single Win | I6: =F6/E6 -> 57.139592 | J6: =ROUND(IF(D6=0,($N$17*0.3),((((N$17*0.7)-(N$19*N$18)))*(E6/$N$14)+$N$19)),0) -> 126 | K6: =G6/N$9 -> 0.0044110165 | M6: Odds Down (ticket quantity if pool based): | N6: 2000000
B7: =Tiers!B6 -> 3 | C7: =Tiers!X6 -> main-2||||||||| | D7: =Tiers!C6 -> 0.5 | E7: 20000 | F7: 2000000 | G7: =E7*D7 -> 10000 | H7: ='Data Analysis'!BK5 & " | " & 'Data Analysis'!BL5 -> Less than Stake | Single Win | I7: =F7/E7 -> 100 | J7: =ROUND(IF(D7=0,($N$17*0.3),((((N$17*0.7)-(N$19*N$18)))*(E7/$N$14)+$N$19)),0) -> 75 | K7: =G7/N$9 -> 0.006301092 | M7: Base: | N7: 1
B8: =Tiers!B7 -> 4 | C8: =Tiers!X7 -> main-3||||||||| | D8: =Tiers!C7 -> 1 | E8: 27000 | F8: 2000000 | G8: =E8*D8 -> 27000 | H8: ='Data Analysis'!BK6 & " | " & 'Data Analysis'!BL6 -> Stake Back | Single Win | I8: =F8/E8 -> 74.074074 | J8: =ROUND(IF(D8=0,($N$17*0.3),((((N$17*0.7)-(N$19*N$18)))*(E8/$N$14)+$N$19)),0) -> 99 | K8: =G8/N$9 -> 0.017012948 | M8: Revenus (if pool based): | N8: =N6*N7 -> 2000000
B9: =Tiers!B8 -> 5 | C9: =Tiers!X8 -> main-4||||||||| | D9: =Tiers!C8 -> 2 | E9: 5000 | F9: 2000000 | G9: =E9*D9 -> 10000 | H9: ='Data Analysis'!BK7 & " | " & 'Data Analysis'!BL7 -> Standard Win | Single Win | I9: =F9/E9 -> 400 | J9: =ROUND(IF(D9=0,($N$17*0.3),((((N$17*0.7)-(N$19*N$18)))*(E9/$N$14)+$N$19)),0) -> 23 | K9: =G9/N$9 -> 0.006301092 | M9: Prize Fund (if pool based): | N9: =SUM(G4:G410) -> 1587026.5
B10: =Tiers!B9 -> 6 | C10: =Tiers!X9 -> main-5||||||||| | D10: =Tiers!C9 -> 5 | E10: 1000 | F10: 2000000 | G10: =E10*D10 -> 5000 | H10: ='Data Analysis'!BK8 & " | " & 'Data Analysis'!BL8 -> Standard Win | Single Win | I10: =F10/E10 -> 2000 | J10: =ROUND(IF(D10=0,($N$17*0.3),((((N$17*0.7)-(N$19*N$18)))*(E10/$N$14)+$N$19)),0) -> 9 | K10: =G10/N$9 -> 0.003150546 | M10: RTP Setting | N10: 0.84
B11: =Tiers!B10 -> 7 | C11: =Tiers!X10 -> main-6||||||||| | D11: =Tiers!C10 -> 10 | E11: 188 | F11: 2000000 | G11: =E11*D11 -> 1880 | H11: ='Data Analysis'!BK9 & " | " & 'Data Analysis'!BL9 -> Big Win | Single Win | I11: =F11/E11 -> 10638.298 | J11: =ROUND(IF(D11=0,($N$17*0.3),((((N$17*0.7)-(N$19*N$18)))*(E11/$N$14)+$N$19)),0) -> 7 | K11: =G11/N$9 -> 0.0011846053 | M11: Base RTP: | N11: =G411/N8 -> 0.79351325
B12: =Tiers!B11 -> 8 | C12: =Tiers!X11 -> main-7||||||||| | D12: =Tiers!C11 -> 20 | E12: 50 | F12: 2000000 | G12: =E12*D12 -> 1000 | H12: ='Data Analysis'!BK10 & " | " & 'Data Analysis'!BL10 -> Big Win | Single Win | I12: =F12/E12 -> 40000 | J12: =ROUND(IF(D12=0,($N$17*0.3),((((N$17*0.7)-(N$19*N$18)))*(E12/$N$14)+$N$19)),0) -> 6 | K12: =G12/N$9 -> 0.0006301092 | M12: JP RTP: | N12: ='Progressive Jackpots'!C14+'Progressive Jackpots'!C21 -> 0.03
B13: =Tiers!B12 -> 9 | C13: =Tiers!X12 -> main-8||||||||| | D13: =Tiers!C12 -> 30 | E13: 10 | F13: 2000000 | G13: =E13*D13 -> 300 | H13: ='Data Analysis'!BK11 & " | " & 'Data Analysis'!BL11 -> Big Win | Single Win | I13: =F13/E13 -> 200000 | J13: =ROUND(IF(D13=0,($N$17*0.3),((((N$17*0.7)-(N$19*N$18)))*(E13/$N$14)+$N$19)),0) -> 6 | K13: =G13/N$9 -> 0.00018903276 | M13: Total RTP | N13: =N11+N12 -> 0.82351325
B14: =Tiers!B13 -> 10 | C14: =Tiers!X13 -> main-9||||||||| | D14: =Tiers!C13 -> 40 | E14: 5 | F14: 2000000 | G14: =E14*D14 -> 200 | H14: ='Data Analysis'!BK12 & " | " & 'Data Analysis'!BL12 -> Big Win | Single Win | I14: =F14/E14 -> 400000 | J14: =ROUND(IF(D14=0,($N$17*0.3),((((N$17*0.7)-(N$19*N$18)))*(E14/$N$14)+$N$19)),0) -> 6 | K14: =G14/N$9 -> 0.00012602184 | M14: Winning Tiers Freq: | N14: =SUM(E5:E410) -> 513477
B15: =Tiers!B14 -> 11 | C15: =Tiers!X14 -> main-10||||||||| | D15: =Tiers!C14 -> 1 | E15: 30152 | F15: 2000000 | G15: =E15*D15 -> 30152 | H15: ='Data Analysis'!BK13 & " | " & 'Data Analysis'!BL13 -> Stake Back | Single Win | I15: =F15/E15 -> 66.330592 | J15: =ROUND(IF(D15=0,($N$17*0.3),((((N$17*0.7)-(N$19*N$18)))*(E15/$N$14)+$N$19)),0) -> 110 | K15: =G15/N$9 -> 0.018999053 | M15: Hit Rate: | N15: =N6/N14 -> 3.8950138
B16: =Tiers!B15 -> 12 | C16: =Tiers!X15 -> main-11||||||||| | D16: =Tiers!C15 -> 2 | E16: 8400 | F16: 2000000 | G16: =E16*D16 -> 16800 | H16: ='Data Analysis'!BK14 & " | " & 'Data Analysis'!BL14 -> Standard Win | Single Win | I16: =F16/E16 -> 238.09524 | J16: =ROUND(IF(D16=0,($N$17*0.3),((((N$17*0.7)-(N$19*N$18)))*(E16/$N$14)+$N$19)),0) -> 35 | K16: =G16/N$9 -> 0.010585835
B17: =Tiers!B16 -> 13 | C17: =Tiers!X16 -> main-12||||||||| | D17: =Tiers!C16 -> 3 | E17: 1000 | F17: 2000000 | G17: =E17*D17 -> 3000 | H17: ='Data Analysis'!BK15 & " | " & 'Data Analysis'!BL15 -> Standard Win | Single Win | I17: =F17/E17 -> 2000 | J17: =ROUND(IF(D17=0,($N$17*0.3),((((N$17*0.7)-(N$19*N$18)))*(E17/$N$14)+$N$19)),0) -> 9 | K17: =G17/N$9 -> 0.0018903276 | M17: Approx Count: | N17: 6000
B18: =Tiers!B17 -> 14 | C18: =Tiers!X17 -> main-13||||||||| | D18: =Tiers!C17 -> 5 | E18: 941 | F18: 2000000 | G18: =E18*D18 -> 4705 | H18: ='Data Analysis'!BK16 & " | " & 'Data Analysis'!BL16 -> Standard Win | Single Win | I18: =F18/E18 -> 2125.3985 | J18: =ROUND(IF(D18=0,($N$17*0.3),((((N$17*0.7)-(N$19*N$18)))*(E18/$N$14)+$N$19)),0) -> 9 | K18: =G18/N$9 -> 0.0029646638 | M18: Winning Tiers | N18: =COUNT(E5:E410) -> 406
B19: =Tiers!B18 -> 15 | C19: =Tiers!X18 -> main-14||||||||| | D19: =Tiers!C18 -> 10 | E19: 10 | F19: 2000000 | G19: =E19*D19 -> 100 | H19: ='Data Analysis'!BK17 & " | " & 'Data Analysis'!BL17 -> Big Win | Single Win | I19: =F19/E19 -> 200000 | J19: =ROUND(IF(D19=0,($N$17*0.3),((((N$17*0.7)-(N$19*N$18)))*(E19/$N$14)+$N$19)),0) -> 6 | K19: =G19/N$9 -> 6.301092e-05 | M19: Min per tier | N19: 6
B20: =Tiers!B19 -> 16 | C20: =Tiers!X19 -> main-15||||||||| | D20: =Tiers!C19 -> 20 | E20: 5 | F20: 2000000 | G20: =E20*D20 -> 100 | H20: ='Data Analysis'!BK18 & " | " & 'Data Analysis'!BL18 -> Big Win | Single Win | I20: =F20/E20 -> 400000 | J20: =ROUND(IF(D20=0,($N$17*0.3),((((N$17*0.7)-(N$19*N$18)))*(E20/$N$14)+$N$19)),0) -> 6 | K20: =G20/N$9 -> 6.301092e-05
B21: =Tiers!B20 -> 17 | C21: =Tiers!X20 -> main-16||||||||| | D21: =Tiers!C20 -> 100 | E21: 2 | F21: 2000000 | G21: =E21*D21 -> 200 | H21: ='Data Analysis'!BK19 & " | " & 'Data Analysis'!BL19 -> Huge Win | Single Win | I21: =F21/E21 -> 1000000 | J21: =ROUND(IF(D21=0,($N$17*0.3),((((N$17*0.7)-(N$19*N$18)))*(E21/$N$14)+$N$19)),0) -> 6 | K21: =G21/N$9 -> 0.00012602184 | M21: PPS Source(if any) | N21: Same as the Vanilla Version
B22: =Tiers!B21 -> 18 | C22: =Tiers!X21 -> main-17||||||||| | D22: =Tiers!C21 -> 2 | E22: 20000 | F22: 2000000 | G22: =E22*D22 -> 40000 | H22: ='Data Analysis'!BK20 & " | " & 'Data Analysis'!BL20 -> Standard Win | Single Win | I22: =F22/E22 -> 100 | J22: =ROUND(IF(D22=0,($N$17*0.3),((((N$17*0.7)-(N$19*N$18)))*(E22/$N$14)+$N$19)),0) -> 75 | K22: =G22/N$9 -> 0.025204368 | M22: Difference: | N22: =N8*N10-N9 -> 92973.5
B23: =Tiers!B22 -> 19 | C23: =Tiers!X22 -> main-18||||||||| | D23: =Tiers!C22 -> 3 | E23: 1000 | F23: 2000000 | G23: =E23*D23 -> 3000 | H23: ='Data Analysis'!BK21 & " | " & 'Data Analysis'!BL21 -> Standard Win | Single Win | I23: =F23/E23 -> 2000 | J23: =ROUND(IF(D23=0,($N$17*0.3),((((N$17*0.7)-(N$19*N$18)))*(E23/$N$14)+$N$19)),0) -> 9 | K23: =G23/N$9 -> 0.0018903276
B24: =Tiers!B23 -> 20 | C24: =Tiers!X23 -> main-19||||||||| | D24: =Tiers!C23 -> 5 | E24: 500 | F24: 2000000 | G24: =E24*D24 -> 2500 | H24: ='Data Analysis'!BK22 & " | " & 'Data Analysis'!BL22 -> Standard Win | Single Win | I24: =F24/E24 -> 4000 | J24: =ROUND(IF(D24=0,($N$17*0.3),((((N$17*0.7)-(N$19*N$18)))*(E24/$N$14)+$N$19)),0) -> 8 | K24: =G24/N$9 -> 0.001575273
B25: =Tiers!B24 -> 21 | C25: =Tiers!X24 -> main-20||||||||| | D25: =Tiers!C24 -> 10 | E25: 100 | F25: 2000000 | G25: =E25*D25 -> 1000 | H25: ='Data Analysis'!BK23 & " | " & 'Data Analysis'!BL23 -> Big Win | Single Win | I25: =F25/E25 -> 20000 | J25: =ROUND(IF(D25=0,($N$17*0.3),((((N$17*0.7)-(N$19*N$18)))*(E25/$N$14)+$N$19)),0) -> 6 | K25: =G25/N$9 -> 0.0006301092
B26: =Tiers!B25 -> 22 | C26: =Tiers!X25 -> main-21||||||||| | D26: =Tiers!C25 -> 20 | E26: 10 | F26: 2000000 | G26: =E26*D26 -> 200 | H26: ='Data Analysis'!BK24 & " | " & 'Data Analysis'!BL24 -> Big Win | Single Win | I26: =F26/E26 -> 200000 | J26: =ROUND(IF(D26=0,($N$17*0.3),((((N$17*0.7)-(N$19*N$18)))*(E26/$N$14)+$N$19)),0) -> 6 | K26: =G26/N$9 -> 0.00012602184
B27: =Tiers!B26 -> 23 | C27: =Tiers!X26 -> main-22||||||||| | D27: =Tiers!C26 -> 100 | E27: 2 | F27: 2000000 | G27: =E27*D27 -> 200 | H27: ='Data Analysis'!BK25 & " | " & 'Data Analysis'!BL25 -> Huge Win | Single Win | I27: =F27/E27 -> 1000000 | J27: =ROUND(IF(D27=0,($N$17*0.3),((((N$17*0.7)-(N$19*N$18)))*(E27/$N$14)+$N$19)),0) -> 6 | K27: =G27/N$9 -> 0.00012602184
B28: =Tiers!B27 -> 24 | C28: =Tiers!X27 -> main-23||||||||| | D28: =Tiers!C27 -> 200 | E28: 1 | F28: 2000000 | G28: =E28*D28 -> 200 | H28: ='Data Analysis'!BK26 & " | " & 'Data Analysis'!BL26 -> Huge Win | Single Win | I28: =F28/E28 -> 2000000 | J28: =ROUND(IF(D28=0,($N$17*0.3),((((N$17*0.7)-(N$19*N$18)))*(E28/$N$14)+$N$19)),0) -> 6 | K28: =G28/N$9 -> 0.00012602184
B29: =Tiers!B28 -> 25 | C29: =Tiers!X28 -> main-24||||||||| | D29: =Tiers!C28 -> 3 | E29: 2800 | F29: 2000000 | G29: =E29*D29 -> 8400 | H29: ='Data Analysis'!BK27 & " | " & 'Data Analysis'!BL27 -> Standard Win | Single Win | I29: =F29/E29 -> 714.28571 | J29: =ROUND(IF(D29=0,($N$17*0.3),((((N$17*0.7)-(N$19*N$18)))*(E29/$N$14)+$N$19)),0) -> 16 | K29: =G29/N$9 -> 0.0052929173
B30: =Tiers!B29 -> 26 | C30: =Tiers!X29 -> main-25||||||||| | D30: =Tiers!C29 -> 5 | E30: 941 | F30: 2000000 | G30: =E30*D30 -> 4705 | H30: ='Data Analysis'!BK28 & " | " & 'Data Analysis'!BL28 -> Standard Win | Single Win | I30: =F30/E30 -> 2125.3985 | J30: =ROUND(IF(D30=0,($N$17*0.3),((((N$17*0.7)-(N$19*N$18)))*(E30/$N$14)+$N$19)),0) -> 9 | K30: =G30/N$9 -> 0.0029646638
B31: =Tiers!B30 -> 27 | C31: =Tiers!X30 -> main-26||||||||| | D31: =Tiers!C30 -> 10 | E31: 110 | F31: 2000000 | G31: =E31*D31 -> 1100 | H31: ='Data Analysis'!BK29 & " | " & 'Data Analysis'!BL29 -> Big Win | Single Win | I31: =F31/E31 -> 18181.818 | J31: =ROUND(IF(D31=0,($N$17*0.3),((((N$17*0.7)-(N$19*N$18)))*(E31/$N$14)+$N$19)),0) -> 6 | K31: =G31/N$9 -> 0.00069312012
B32: =Tiers!B31 -> 28 | C32: =Tiers!X31 -> main-27||||||||| | D32: =Tiers!C31 -> 20 | E32: 10 | F32: 2000000 | G32: =E32*D32 -> 200 | H32: ='Data Analysis'!BK30 & " | " & 'Data Analysis'!BL30 -> Big Win | Single Win | I32: =F32/E32 -> 200000 | J32: =ROUND(IF(D32=0,($N$17*0.3),((((N$17*0.7)-(N$19*N$18)))*(E32/$N$14)+$N$19)),0) -> 6 | K32: =G32/N$9 -> 0.00012602184
B33: =Tiers!B32 -> 29 | C33: =Tiers!X32 -> main-28||||||||| | D33: =Tiers!C32 -> 100 | E33: 5 | F33: 2000000 | G33: =E33*D33 -> 500 | H33: ='Data Analysis'!BK31 & " | " & 'Data Analysis'!BL31 -> Huge Win | Single Win | I33: =F33/E33 -> 400000 | J33: =ROUND(IF(D33=0,($N$17*0.3),((((N$17*0.7)-(N$19*N$18)))*(E33/$N$14)+$N$19)),0) -> 6 | K33: =G33/N$9 -> 0.0003150546
B34: =Tiers!B33 -> 30 | C34: =Tiers!X33 -> main-29||||||||| | D34: =Tiers!C33 -> 200 | E34: 2 | F34: 2000000 | G34: =E34*D34 -> 400 | H34: ='Data Analysis'!BK32 & " | " & 'Data Analysis'!BL32 -> Huge Win | Single Win | I34: =F34/E34 -> 1000000 | J34: =ROUND(IF(D34=0,($N$17*0.3),((((N$17*0.7)-(N$19*N$18)))*(E34/$N$14)+$N$19)),0) -> 6 | K34: =G34/N$9 -> 0.00025204368
... B410: =Tiers!B409 -> 406 | C410: =Tiers!X409 -> bonusC-8||||||||| | D410: =Tiers!C409 -> 500 | E410: 1 | F410: 2000000 | G410: =E410*D410 -> 500 | H410: ='Data Analysis'!BK408 & " | " & 'Data Analysis'!BL408 -> Huge Win | Bonus Game C | I410: =F410/E410 -> 2000000 | J410: =ROUND(IF(D410=0,($N$17*0.3),((((N$17*0.7)-(N$19*N$18)))*(E410/$N$14)+$N$19)),0) -> 6 | K410: =G410/N$9 -> 0.0003150546
E411: =SUM(E4:E410) -> 2000000 | G411: =SUM(G4:G410) -> 1587026.5 | K411: =SUM(K4:K410) -> 1

Sheet Progressive Jackpots
B2: Base JP Odds Down | C2: 150000000 | E2: json setup form
B3: JP Stake | C3: 1 | E3: JP | F3: large1 | G3: large2
B4: Revenue | C4: =C2*C3 -> 150000000 | E4: initialAmount | F4: =N11 -> 225000 | G4: =N12 -> 225000
B5: Contribution | C5: =C3*C6 -> 0.03 | E5: increment | F5: =K18*100 -> 1.35 | G5: =K19*100 -> 1.35
B6: Contribution % | C6: =W15 -> 0.03
B7: Estimated plays per day | C7: 450000
B9: Seed | K9: =C6-C21 -> 0.003 | M9: BASE
B10: Number | C10: Name | D10: Bonus | E10: Prize | F10: Base Odds Up | G10: Odds Down | H10: Base 1 in x Odds | I10: Prize Cost | J10: Contribution split | K10: Contribution | M10: Odds Up | N10: Seed | O10: Target trigger | P10: Count | Q10: Odds Down | R10: 1 in x Odds | S10: Prize Cost | T10: Trigger minus Seed | U10: JP Contrib Cost | V10: Split (use on JP split above) | W10: Total JP Prize cost
B11: 1 | C11: large1 | D11: bonusA | E11: =N11 -> 225000 | F11: =C3*M11 -> 1 | G11: =C2 -> 150000000 | H11: =G11/F11 -> 150000000 | I11: =E11*F11 -> 225000 | J11: =I11/I14 -> 0.5 | K11: =S15*J11*C3 -> 0.0015 | M11: 1 | N11: 225000 | O11: 2250000 | P11: 4 | Q11: =C2 -> 150000000 | R11: =Q11/F11 -> 150000000 | S11: =M11*E11 -> 225000 | T11: =O11-N11 -> 2025000 | U11: =T11*M11 -> 2025000 | V11: =U11/U14 -> 0.5 | W11: =O11*M11 -> 2250000
B12: 2 | C12: large2 | D12: bonusB | E12: =N12 -> 225000 | F12: =C3*M12 -> 1 | G12: =C2 -> 150000000 | H12: =G12/F12 -> 150000000 | I12: =E12*F12 -> 225000 | J12: =I12/I14 -> 0.5 | K12: =S15*J12*C3 -> 0.0015 | M12: 1 | N12: 225000 | O12: 2250000 | P12: 4 | Q12: =C2 -> 150000000 | R12: =Q12/F12 -> 150000000 | S12: =M12*E12 -> 225000 | T12: =O12-N12 -> 2025000 | U12: =T12*M12 -> 2025000 | V12: =U12/U14 -> 0.5 | W12: =O12*M12 -> 2250000
B14: RTP | C14: =I14/C4 -> 0.003 | F14: =SUM(F11:F13) -> 2 | H14: =C2/F14 -> 75000000 | I14: =SUM(I11:I13) -> 450000 | J14: =SUM(J11:J13) -> 1 | K14: =SUM(K11:K13) -> 0.003 | M14: =SUM(M11:M13) -> 2 | S14: =SUM(S11:S13) -> 450000 | U14: =SUM(U11:U13) -> 4050000 | V14: =SUM(V11:V13) -> 1 | W14: =SUM(W11:W13) -> 4500000
S15: =S14/C2 -> 0.003 | U15: =U14/C2 -> 0.027 | W15: =W14/C2 -> 0.03
B16: Jackpot Contributions (excluding seed) | K16: =C6-C14 -> 0.027
B17: Number | C17: Name | D17: Bonus | E17: Average Prize | F17: Base Odds Up | G17: Odds Down | H17: Base 1 in x Odds | I17: Prize Cost | J17: Contribution split | K17: Contribution
B18: 1 | C18: large1 | D18: bonusA | E18: =K18*H18 -> 2025000 | F18: =C3*M11 -> 1 | G18: =C2 -> 150000000 | H18: =G18/F18 -> 150000000 | I18: =E18*F18 -> 2025000 | J18: =V11 -> 0.5 | K18: =U15*J18*C3 -> 0.0135
B19: 2 | C19: large2 | D19: bonusB | E19: =K19*H19 -> 2025000 | F19: =C3*M12 -> 1 | G19: =C2 -> 150000000 | H19: =G19/F19 -> 150000000 | I19: =E19*F19 -> 2025000 | J19: =V12 -> 0.5 | K19: =U15*J19*C3 -> 0.0135
B21: RTP | C21: =I21/C4 -> 0.027 | I21: =SUM(I18:I20) -> 4050000 | J21: =SUM(J18:J20) -> 1 | K21: =SUM(K18:K20) -> 0.027
B24: Overal Game Summary
B25: JP Event Prob | C25: =C2/F14 -> 75000000
B26: Total win Odds (JP+main) | C26: =1/((1/C25) + (1/Frequency!N15)) -> 3.8950136
B27: Total non-win Prob Up | C27: =Frequency!N6-(F14/(G12/Frequency!N6)+Frequency!N14) -> 1486523
B28: Total non-win Pob Down | C28: =Frequency!N6 -> 2000000
B29: main Game RTP | C29: =Frequency!N11 -> 0.79351325
B30: Seed contribution RTP | C30: =C14 -> 0.003
B31: JP Contribution RTP | C31: =C21 -> 0.027
B32: TOTAL | C32: =C29+C30+C31 -> 0.82351325

Sheet Delivery
B2: DIVISION | C2: METHOD | D2: PRIZE FACTOR | E2: PRICE POINT | F2: EXPECTED WINNERS PER CARD | G2: ODDS PER GRID | H2: TOTAL PRIZE | I2: PRIZE % | J2: PAYOUT % | L2: Prize Structure
L3: Kentucky Lottery
B4: 1 | C4: main-30||||||||| | D4: 1000 | E4: =D4*$M$7 -> 1000 | F4: 1 | G4: =$M$6/F4 -> 2000000 | H4: =F4*E4 -> 1000 | I4: =H4/$M$9 -> 0.0005952381 | J4: =H4/$M$8 -> 0.0005 | L4: King Kong Jackpots(MMJ3) Standard
B5: 2 | C5: bonusC-8||||||||| | D5: 500 | E5: =D5*$M$7 -> 500 | F5: 1 | G5: =$M$6/F5 -> 2000000 | H5: =F5*E5 -> 500 | I5: =H5/$M$9 -> 0.00029761905 | J5: =H5/$M$8 -> 0.00025
B6: 3 | C6: main-23||||||||| | D6: 200 | E6: =D6*$M$7 -> 200 | F6: 1 | G6: =$M$6/F6 -> 2000000 | H6: =F6*E6 -> 200 | I6: =H6/$M$9 -> 0.00011904762 | J6: =H6/$M$8 -> 0.0001 | L6: Odds Down (ticket quantity if pool based): | M6: 2000000
B7: 4 | C7: main-29||||||||| | D7: 200 | E7: =D7*$M$7 -> 200 | F7: 2 | G7: =$M$6/F7 -> 1000000 | H7: =F7*E7 -> 400 | I7: =H7/$M$9 -> 0.00023809524 | J7: =H7/$M$8 -> 0.0002 | L7: Base: | M7: 1
B8: 5 | C8: main-4|main-28|main-3|freeplayA-14|||||| | D8: 123.7 | E8: =D8*$M$7 -> 123.7 | F8: 2 | G8: =$M$6/F8 -> 1000000 | H8: =F8*E8 -> 247.4 | I8: =H8/$M$9 -> 0.0001472619 | J8: =H8/$M$8 -> 0.0001237 | L8: Revenus (if pool based): | M8: =M7*M6 -> 2000000
B9: 6 | C9: main-28|bonusA-5|||||||| | D9: 115 | E9: =D9*$M$7 -> 115 | F9: 5 | G9: =$M$6/F9 -> 400000 | H9: =F9*E9 -> 575 | I9: =H9/$M$9 -> 0.0003422619 | J9: =H9/$M$8 -> 0.0002875 | L9: Prize Fund (if pool based): | M9: =H411 -> 1680000
B10: 7 | C10: main-28|bonusB-5|||||||| | D10: 115 | E10: =D10*$M$7 -> 115 | F10: 5 | G10: =$M$6/F10 -> 400000 | H10: =F10*E10 -> 575 | I10: =H10/$M$9 -> 0.0003422619 | J10: =H10/$M$8 -> 0.0002875 | L10: RTP Setting | M10: 0.84
B11: 8 | C11: main-28|bonusC-5|||||||| | D11: 115 | E11: =D11*$M$7 -> 115 | F11: 5 | G11: =$M$6/F11 -> 400000 | H11: =F11*E11 -> 575 | I11: =H11/$M$9 -> 0.0003422619 | J11: =H11/$M$8 -> 0.0002875 | L11: Actual RTP: | M11: =M9/M8 -> 0.84
B12: 9 | C12: main-4|main-18|main-28|main-0|wild-15||||| | D12: 108.1 | E12: =D12*$M$7 -> 108.1 | F12: 2 | G12: =$M$6/F12 -> 1000000 | H12: =F12*E12 -> 216.2 | I12: =H12/$M$9 -> 0.00012869048 | J12: =H12/$M$8 -> 0.0001081 | L12: JP RTP: | M12: 0.03
B13: 10 | C13: main-4|main-28|main-3|wild-5|||||| | D13: 108 | E13: =D13*$M$7 -> 108 | F13: 3 | G13: =$M$6/F13 -> 666666.67 | H13: =F13*E13 -> 324 | I13: =H13/$M$9 -> 0.00019285714 | J13: =H13/$M$8 -> 0.000162 | L13: Total RTP: | M13: =M12+M11 -> 0.87
B14: 11 | C14: main-4|main-18|main-28|main-0|||||| | D14: 105.1 | E14: =D14*$M$7 -> 105.1 | F14: 2 | G14: =$M$6/F14 -> 1000000 | H14: =F14*E14 -> 210.2 | I14: =H14/$M$9 -> 0.00012511905 | J14: =H14/$M$8 -> 0.0001051 | L14: Winning Tiers Freq | M14: =SUM(F4:F409) -> 513477
B15: 12 | C15: main-4|main-28|main-3||||||| | D15: 103 | E15: =D15*$M$7 -> 103 | F15: 2 | G15: =$M$6/F15 -> 1000000 | H15: =F15*E15 -> 206 | I15: =H15/$M$9 -> 0.00012261905 | J15: =H15/$M$8 -> 0.000103 | L15: Hit Rate: | M15: =M6/M14 -> 3.8950138
B16: 13 | C16: main-16||||||||| | D16: 100 | E16: =D16*$M$7 -> 100 | F16: 2 | G16: =$M$6/F16 -> 1000000 | H16: =F16*E16 -> 200 | I16: =H16/$M$9 -> 0.00011904762 | J16: =H16/$M$8 -> 0.0001
B17: 14 | C17: main-22||||||||| | D17: 100 | E17: =D17*$M$7 -> 100 | F17: 2 | G17: =$M$6/F17 -> 1000000 | H17: =F17*E17 -> 200 | I17: =H17/$M$9 -> 0.00011904762 | J17: =H17/$M$8 -> 0.0001 | L17: The information contained in this document and all attached documents is strictly confidential and contains proprietary information. It is provided solely for use by the designated recipients and is subject to the terms of any confidentiality obligations or non-disclosure agreements between the parties. All other use is strictly prohibited.
B18: 15 | C18: main-28||||||||| | D18: 100 | E18: =D18*$M$7 -> 100 | F18: 5 | G18: =$M$6/F18 -> 400000 | H18: =F18*E18 -> 500 | I18: =H18/$M$9 -> 0.00029761905 | J18: =H18/$M$8 -> 0.00025
B19: 16 | C19: bonusA-10||||||||| | D19: 100 | E19: =D19*$M$7 -> 100 | F19: 50 | G19: =$M$6/F19 -> 40000 | H19: =F19*E19 -> 5000 | I19: =H19/$M$9 -> 0.0029761905 | J19: =H19/$M$8 -> 0.0025
B20: 17 | C20: bonusB-10||||||||| | D20: 100 | E20: =D20*$M$7 -> 100 | F20: 50 | G20: =$M$6/F20 -> 40000 | H20: =F20*E20 -> 5000 | I20: =H20/$M$9 -> 0.0029761905 | J20: =H20/$M$8 -> 0.0025
B21: 18 | C21: bonusC-7||||||||| | D21: 100 | E21: =D21*$M$7 -> 100 | F21: 50 | G21: =$M$6/F21 -> 40000 | H21: =F21*E21 -> 5000 | I21: =H21/$M$9 -> 0.0029761905 | J21: =H21/$M$8 -> 0.0025
B22: 19 | C22: main-4|main-14|main-15|wild-4|freeplayA-26||||| | D22: 60.2 | E22: =D22*$M$7 -> 60.2 | F22: 2 | G22: =$M$6/F22 -> 1000000 | H22: =F22*E22 -> 120.4 | I22: =H22/$M$9 -> 7.1666667e-05 | J22: =H22/$M$8 -> 6.02e-05
B23: 20 | C23: main-4|wild-9|bonusA-5||||||| | D23: 57 | E23: =D23*$M$7 -> 57 | F23: 2 | G23: =$M$6/F23 -> 1000000 | H23: =F23*E23 -> 114 | I23: =H23/$M$9 -> 6.7857143e-05 | J23: =H23/$M$8 -> 5.7e-05
B24: 21 | C24: main-4|wild-9|bonusB-5||||||| | D24: 57 | E24: =D24*$M$7 -> 57 | F24: 2 | G24: =$M$6/F24 -> 1000000 | H24: =F24*E24 -> 114 | I24: =H24/$M$9 -> 6.7857143e-05 | J24: =H24/$M$8 -> 5.7e-05
B25: 22 | C25: main-4|wild-9|bonusC-5||||||| | D25: 57 | E25: =D25*$M$7 -> 57 | F25: 2 | G25: =$M$6/F25 -> 1000000 | H25: =F25*E25 -> 114 | I25: =H25/$M$9 -> 6.7857143e-05 | J25: =H25/$M$8 -> 5.7e-05
B26: 23 | C26: freeplayA-31||||||||| | D26: 54.4 | E26: =D26*$M$7 -> 54.4 | F26: 10 | G26: =$M$6/F26 -> 200000 | H26: =F26*E26 -> 544 | I26: =H26/$M$9 -> 0.00032380952 | J26: =H26/$M$8 -> 0.000272
B27: 24 | C27: main-5|main-26|wild-14|freeplayA-24|||||| | D27: 51.7 | E27: =D27*$M$7 -> 51.7 | F27: 10 | G27: =$M$6/F27 -> 200000 | H27: =F27*E27 -> 517 | I27: =H27/$M$9 -> 0.0003077381 | J27: =H27/$M$8 -> 0.0002585
B28: 25 | C28: main-4|main-14|main-15|freeplayA-13|||||| | D28: 50.5 | E28: =D28*$M$7 -> 50.5 | F28: 2 | G28: =$M$6/F28 -> 1000000 | H28: =F28*E28 -> 101 | I28: =H28/$M$9 -> 6.0119048e-05 | J28: =H28/$M$8 -> 5.05e-05
B29: 26 | C29: bonusA-9||||||||| | D29: 50 | E29: =D29*$M$7 -> 50 | F29: 500 | G29: =$M$6/F29 -> 4000 | H29: =F29*E29 -> 25000 | I29: =H29/$M$9 -> 0.014880952 | J29: =H29/$M$8 -> 0.0125
... B409: 406 | C409: wild-0||||||||| | D409: 0.1 | E409: =D409*$M$7 -> 0.1 | F409: 25000 | G409: =$M$6/F409 -> 80 | H409: =F409*E409 -> 2500 | I409: =H409/$M$9 -> 0.0014880952 | J409: =H409/$M$8 -> 0.00125
B410: 407 | C410: Non Winning tickets | D410: 0 | E410: 0 | F410: 1486523 | G410: =$M$6/F410 -> 1.3454215 | H410: 0 | I410: 0 | J410: 0
F411: =SUM(F4:F410) -> 2000000 | H411: =SUM(H4:H410) -> 1680000 | I411: =SUM(I4:I410) -> 1 | J411: =SUM(J4:J410) -> 0.84
B413: Base JP Odds Down | C413: 150000000 | E413: json setup form
B414: JP Stake | C414: 1 | E414: JP | F414: large1 | G414: large2
B415: Revenue | C415: =C413*C414 -> 150000000 | E415: initialAmount | F415: =N422 -> 225000 | G415: =N423 -> 225000
B416: Contribution | C416: =C414*C417 -> 0.03 | E416: increment | F416: =K429*100 -> 1.35 | G416: =K430*100 -> 1.35
B417: Contribution % | C417: =W426 -> 0.03
B418: Estimated plays per day | C418: 450000
B420: Seed | K420: =C417-C432 -> 0.003 | M420: BASE
B421: Number | C421: Name | D421: Bonus | E421: Prize | F421: Base Odds Up | G421: Odds Down | H421: Base 1 in x Odds | I421: Prize Cost | J421: Contribution split | K421: Contribution | M421: Odds Up | N421: Seed | O421: Target trigger | P421: Count | Q421: Odds Down | R421: 1 in x Odds | S421: Prize Cost | T421: Trigger minus Seed | U421: JP Contrib Cost | V421: Split (use on JP split above) | W421: Total JP Prize cost
B422: 1 | C422: large1 | D422: bonusA | E422: =N422 -> 225000 | F422: =C414*M422 -> 1 | G422: =C413 -> 150000000 | H422: =G422/F422 -> 150000000 | I422: =E422*F422 -> 225000 | J422: =I422/I425 -> 0.5 | K422: =S426*J422*C414 -> 0.0015 | M422: 1 | N422: 225000 | O422: 2250000 | P422: 4 | Q422: =C413 -> 150000000 | R422: =Q422/F422 -> 150000000 | S422: =M422*E422 -> 225000 | T422: =O422-N422 -> 2025000 | U422: =T422*M422 -> 2025000 | V422: =U422/U425 -> 0.5 | W422: =O422*M422 -> 2250000
B423: 2 | C423: large2 | D423: bonusB | E423: =N423 -> 225000 | F423: =C414*M423 -> 1 | G423: =C413 -> 150000000 | H423: =G423/F423 -> 150000000 | I423: =E423*F423 -> 225000 | J423: =I423/I425 -> 0.5 | K423: =S426*J423*C414 -> 0.0015 | M423: 1 | N423: 225000 | O423: 2250000 | P423: 4 | Q423: =C413 -> 150000000 | R423: =Q423/F423 -> 150000000 | S423: =M423*E423 -> 225000 | T423: =O423-N423 -> 2025000 | U423: =T423*M423 -> 2025000 | V423: =U423/U425 -> 0.5 | W423: =O423*M423 -> 2250000
B425: RTP | C425: =I425/C415 -> 0.003 | F425: =SUM(F422:F424) -> 2 | H425: =C413/F425 -> 75000000 | I425: =SUM(I422:I424) -> 450000 | J425: =SUM(J422:J424) -> 1 | K425: =SUM(K422:K424) -> 0.003 | M425: =SUM(M422:M424) -> 2 | S425: =SUM(S422:S424) -> 450000 | U425: =SUM(U422:U424) -> 4050000 | V425: =SUM(V422:V424) -> 1 | W425: =SUM(W422:W424) -> 4500000
S426: =S425/C413 -> 0.003 | U426: =U425/C413 -> 0.027 | W426: =W425/C413 -> 0.03
B427: Jackpot Contributions (excluding seed) | K427: =C417-C425 -> 0.027
B428: Number | C428: Name | D428: Bonus | E428: Average Prize | F428: Base Odds Up | G428: Odds Down | H428: Base 1 in x Odds | I428: Prize Cost | J428: Contribution split | K428: Contribution
B429: 1 | C429: large1 | D429: bonusA | E429: =K429*H429 -> 2025000 | F429: =C414*M422 -> 1 | G429: =C413 -> 150000000 | H429: =G429/F429 -> 150000000 | I429: =E429*F429 -> 2025000 | J429: =V422 -> 0.5 | K429: =U426*J429*C414 -> 0.0135
B430: 2 | C430: large2 | D430: bonusB | E430: =K430*H430 -> 2025000 | F430: =C414*M423 -> 1 | G430: =C413 -> 150000000 | H430: =G430/F430 -> 150000000 | I430: =E430*F430 -> 2025000 | J430: =V423 -> 0.5 | K430: =U426*J430*C414 -> 0.0135
B432: RTP | C432: =I432/C415 -> 0.027 | I432: =SUM(I429:I431) -> 4050000 | J432: =SUM(J429:J431) -> 1 | K432: =SUM(K429:K431) -> 0.027
B435: Overal Game Summary
B436: JP Event Prob | C436: =C413/F425 -> 75000000
B437: Total win Odds (JP+main) | C437: =1/((1/C436) + (1/Frequency!N426)) -> #DIV/0!
B438: Total non-win Prob Up | C438: =Frequency!N417-(F425/(G423/Frequency!N417)+Frequency!N425) -> #DIV/0!
B439: Total non-win Pob Down | C439: =Frequency!N417 -> 0
B440: main Game RTP | C440: =Frequency!N422 -> 0
B441: Seed contribution RTP | C441: =C425 -> 0.003
B442: JP Contribution RTP | C442: =C432 -> 0.027
B443: TOTAL | C443: =C440+C441+C442 -> 0.03

Sheet Odds Table
A1: Ticket Price | B1: 0.5 | C1: 1 in X Odds | D1: 1 | E1: 1 in X Odds | F1: 2 | G1: 1 in X Odds | H1: 5 | I1: 1 in X Odds | J1: 10 | K1: 1 in X Odds | L1: 20 | M1: 1 in X Odds | N1: 30 | O1: 1 in X Odds | P1: 50 | Q1: 1 in X Odds
A2: JP1 | B2: $225,000.00* | C2: =E2*($D$1/$B$1) -> 300000000 | D2: $225,000.00* | E2: 150000000 | F2: $225,000.00* | G2: =E2/F$1 -> 75000000 | H2: $225,000.00* | I2: =E2/H$1 -> 30000000 | J2: $225,000.00* | K2: =E2/J$1 -> 15000000 | L2: $225,000.00* | M2: =E2/L$1 -> 7500000 | N2: $225,000.00* | O2: =E2/N$1 -> 5000000 | P2: $225,000.00* | Q2: =E2/P$1 -> 3000000
A3: JP2 | B3: $225,000.00* | C3: =E3*($D$1/$B$1) -> 300000000 | D3: $225,000.00* | E3: 150000000 | F3: $225,000.00* | G3: =E3/F$1 -> 75000000 | H3: $225,000.00* | I3: =E3/H$1 -> 30000000 | J3: $225,000.00* | K3: =E3/J$1 -> 15000000 | L3: $225,000.00* | M3: =E3/L$1 -> 7500000 | N3: $225,000.00* | O3: =E3/N$1 -> 5000000 | P3: $225,000.00* | Q3: =E3/P$1 -> 3000000
A4: Prize | B4: =$D4*B$1 -> 500 | C4: =$E4 -> 2000000 | D4: 1000 | E4: 2000000 | F4: =$D4*F$1 -> 2000 | G4: =$E4 -> 2000000 | H4: =$D4*H$1 -> 5000 | I4: =$E4 -> 2000000 | J4: =$D4*J$1 -> 10000 | K4: =$E4 -> 2000000 | L4: =$D4*L$1 -> 20000 | M4: =$E4 -> 2000000 | N4: =$D4*N$1 -> 30000 | O4: =$E4 -> 2000000 | P4: =$D4*P$1 -> 50000 | Q4: =$E4 -> 2000000
B5: =$D5*B$1 -> 250 | C5: =$E5 -> 2000000 | D5: 500 | E5: 2000000 | F5: =$D5*F$1 -> 1000 | G5: =$E5 -> 2000000 | H5: =$D5*H$1 -> 2500 | I5: =$E5 -> 2000000 | J5: =$D5*J$1 -> 5000 | K5: =$E5 -> 2000000 | L5: =$D5*L$1 -> 10000 | M5: =$E5 -> 2000000 | N5: =$D5*N$1 -> 15000 | O5: =$E5 -> 2000000 | P5: =$D5*P$1 -> 25000 | Q5: =$E5 -> 2000000
B6: =$D6*B$1 -> 100 | C6: =$E6 -> 666666.67 | D6: 200 | E6: 666666.67 | F6: =$D6*F$1 -> 400 | G6: =$E6 -> 666666.67 | H6: =$D6*H$1 -> 1000 | I6: =$E6 -> 666666.67 | J6: =$D6*J$1 -> 2000 | K6: =$E6 -> 666666.67 | L6: =$D6*L$1 -> 4000 | M6: =$E6 -> 666666.67 | N6: =$D6*N$1 -> 6000 | O6: =$E6 -> 666666.67 | P6: =$D6*P$1 -> 10000 | Q6: =$E6 -> 666666.67
B7: =$D7*B$1 -> 61.85 | C7: =$E7 -> 1000000 | D7: 123.7 | E7: 1000000 | F7: =$D7*F$1 -> 247.4 | G7: =$E7 -> 1000000 | H7: =$D7*H$1 -> 618.5 | I7: =$E7 -> 1000000 | J7: =$D7*J$1 -> 1237 | K7: =$E7 -> 1000000 | L7: =$D7*L$1 -> 2474 | M7: =$E7 -> 1000000 | N7: =$D7*N$1 -> 3711 | O7: =$E7 -> 1000000 | P7: =$D7*P$1 -> 6185 | Q7: =$E7 -> 1000000
B8: =$D8*B$1 -> 57.5 | C8: =$E8 -> 133333.33 | D8: 115 | E8: 133333.33 | F8: =$D8*F$1 -> 230 | G8: =$E8 -> 133333.33 | H8: =$D8*H$1 -> 575 | I8: =$E8 -> 133333.33 | J8: =$D8*J$1 -> 1150 | K8: =$E8 -> 133333.33 | L8: =$D8*L$1 -> 2300 | M8: =$E8 -> 133333.33 | N8: =$D8*N$1 -> 3450 | O8: =$E8 -> 133333.33 | P8: =$D8*P$1 -> 5750 | Q8: =$E8 -> 133333.33
B9: =$D9*B$1 -> 54.05 | C9: =$E9 -> 1000000 | D9: 108.1 | E9: 1000000 | F9: =$D9*F$1 -> 216.2 | G9: =$E9 -> 1000000 | H9: =$D9*H$1 -> 540.5 | I9: =$E9 -> 1000000 | J9: =$D9*J$1 -> 1081 | K9: =$E9 -> 1000000 | L9: =$D9*L$1 -> 2162 | M9: =$E9 -> 1000000 | N9: =$D9*N$1 -> 3243 | O9: =$E9 -> 1000000 | P9: =$D9*P$1 -> 5405 | Q9: =$E9 -> 1000000
B10: =$D10*B$1 -> 54 | C10: =$E10 -> 666666.67 | D10: 108 | E10: 666666.67 | F10: =$D10*F$1 -> 216 | G10: =$E10 -> 666666.67 | H10: =$D10*H$1 -> 540 | I10: =$E10 -> 666666.67 | J10: =$D10*J$1 -> 1080 | K10: =$E10 -> 666666.67 | L10: =$D10*L$1 -> 2160 | M10: =$E10 -> 666666.67 | N10: =$D10*N$1 -> 3240 | O10: =$E10 -> 666666.67 | P10: =$D10*P$1 -> 5400 | Q10: =$E10 -> 666666.67
B11: =$D11*B$1 -> 52.55 | C11: =$E11 -> 1000000 | D11: 105.1 | E11: 1000000 | F11: =$D11*F$1 -> 210.2 | G11: =$E11 -> 1000000 | H11: =$D11*H$1 -> 525.5 | I11: =$E11 -> 1000000 | J11: =$D11*J$1 -> 1051 | K11: =$E11 -> 1000000 | L11: =$D11*L$1 -> 2102 | M11: =$E11 -> 1000000 | N11: =$D11*N$1 -> 3153 | O11: =$E11 -> 1000000 | P11: =$D11*P$1 -> 5255 | Q11: =$E11 -> 1000000
B12: =$D12*B$1 -> 51.5 | C12: =$E12 -> 1000000 | D12: 103 | E12: 1000000 | F12: =$D12*F$1 -> 206 | G12: =$E12 -> 1000000 | H12: =$D12*H$1 -> 515 | I12: =$E12 -> 1000000 | J12: =$D12*J$1 -> 1030 | K12: =$E12 -> 1000000 | L12: =$D12*L$1 -> 2060 | M12: =$E12 -> 1000000 | N12: =$D12*N$1 -> 3090 | O12: =$E12 -> 1000000 | P12: =$D12*P$1 -> 5150 | Q12: =$E12 -> 1000000
B13: =$D13*B$1 -> 50 | C13: =$E13 -> 12578.616 | D13: 100 | E13: 12578.616 | F13: =$D13*F$1 -> 200 | G13: =$E13 -> 12578.616 | H13: =$D13*H$1 -> 500 | I13: =$E13 -> 12578.616 | J13: =$D13*J$1 -> 1000 | K13: =$E13 -> 12578.616 | L13: =$D13*L$1 -> 2000 | M13: =$E13 -> 12578.616 | N13: =$D13*N$1 -> 3000 | O13: =$E13 -> 12578.616 | P13: =$D13*P$1 -> 5000 | Q13: =$E13 -> 12578.616
B14: =$D14*B$1 -> 30.1 | C14: =$E14 -> 1000000 | D14: 60.2 | E14: 1000000 | F14: =$D14*F$1 -> 120.4 | G14: =$E14 -> 1000000 | H14: =$D14*H$1 -> 301 | I14: =$E14 -> 1000000 | J14: =$D14*J$1 -> 602 | K14: =$E14 -> 1000000 | L14: =$D14*L$1 -> 1204 | M14: =$E14 -> 1000000 | N14: =$D14*N$1 -> 1806 | O14: =$E14 -> 1000000 | P14: =$D14*P$1 -> 3010 | Q14: =$E14 -> 1000000
B15: =$D15*B$1 -> 28.5 | C15: =$E15 -> 333333.33 | D15: 57 | E15: 333333.33 | F15: =$D15*F$1 -> 114 | G15: =$E15 -> 333333.33 | H15: =$D15*H$1 -> 285 | I15: =$E15 -> 333333.33 | J15: =$D15*J$1 -> 570 | K15: =$E15 -> 333333.33 | L15: =$D15*L$1 -> 1140 | M15: =$E15 -> 333333.33 | N15: =$D15*N$1 -> 1710 | O15: =$E15 -> 333333.33 | P15: =$D15*P$1 -> 2850 | Q15: =$E15 -> 333333.33
B16: =$D16*B$1 -> 27.2 | C16: =$E16 -> 200000 | D16: 54.4 | E16: 200000 | F16: =$D16*F$1 -> 108.8 | G16: =$E16 -> 200000 | H16: =$D16*H$1 -> 272 | I16: =$E16 -> 200000 | J16: =$D16*J$1 -> 544 | K16: =$E16 -> 200000 | L16: =$D16*L$1 -> 1088 | M16: =$E16 -> 200000 | N16: =$D16*N$1 -> 1632 | O16: =$E16 -> 200000 | P16: =$D16*P$1 -> 2720 | Q16: =$E16 -> 200000
... B180: =$D180*B$1 -> 0.05 | C180: =$E180 -> 27.137779 | D180: 0.1 | E180: 27.137779 | F180: =$D180*F$1 -> 0.2 | G180: =$E180 -> 27.137779 | H180: =$D180*H$1 -> 0.5 | I180: =$E180 -> 27.137779 | J180: =$D180*J$1 -> 1 | K180: =$E180 -> 27.137779 | L180: =$D180*L$1 -> 2 | M180: =$E180 -> 27.137779 | N180: =$D180*N$1 -> 3 | O180: =$E180 -> 27.137779 | P180: =$D180*P$1 -> 5 | Q180: =$E180 -> 27.137779
B181: NON WINNING | C181: =$E181 -> 1.3454215 | D181: NON WINNING | E181: 1.3454215 | F181: NON WINNING | G181: =$E181 -> 1.3454215 | H181: NON WINNING | I181: =$E181 -> 1.3454215 | J181: NON WINNING | K181: =$E181 -> 1.3454215 | L181: NON WINNING | M181: =$E181 -> 1.3454215 | N181: NON WINNING | O181: =$E181 -> 1.3454215 | P181: NON WINNING | Q181: =$E181 -> 1.3454215

Sheet Summary(Delivery)
A1: Size of Grid | B1: 0.5 | C1: 1 | D1: 2 | E1: 5 | F1: 10 | G1: 20 | H1: 30 | I1: 50
A2: Top Prize | B2: =$C$2*B$1 -> 500 | C2: 1000 | D2: =$C$2*D$1 -> 2000 | E2: =$C$2*E$1 -> 5000 | F2: =$C$2*F$1 -> 10000 | G2: =$C$2*G$1 -> 20000 | H2: =$C$2*H$1 -> 30000 | I2: =$C$2*I$1 -> 50000
A3: Version | B3: v1 | C3: v1 | D3: v1 | E3: v1 | F3: v1 | G3: v1 | H3: v1 | I3: v1
A4: Payout | B4: =$C$4 -> 0.84 | C4: 0.84 | D4: =$C$4 -> 0.84 | E4: =$C$4 -> 0.84 | F4: =$C$4 -> 0.84 | G4: =$C$4 -> 0.84 | H4: =$C$4 -> 0.84 | I4: =$C$4 -> 0.84
A5: Breakeven | B5: =$C$5 -> 0.047576 | C5: 0.047576 | D5: =$C$5 -> 0.047576 | E5: =$C$5 -> 0.047576 | F5: =$C$5 -> 0.047576 | G5: =$C$5 -> 0.047576 | H5: =$C$5 -> 0.047576 | I5: =$C$5 -> 0.047576
A6: Odds | B6: =$C$6 -> 3.8950138 | C6: 3.8950138 | D6: =$C$6 -> 3.8950138 | E6: =$C$6 -> 3.8950138 | F6: =$C$6 -> 3.8950138 | G6: =$C$6 -> 3.8950138 | H6: =$C$6 -> 3.8950138 | I6: =$C$6 -> 3.8950138
A7: Size of Grid | B7: 2000000 | C7: 2000000 | D7: 2000000 | E7: 2000000 | F7: 2000000 | G7: 2000000 | H7: 2000000 | I7: 2000000
A8: Low Tier Winning Range | B8: x0 - x5 | C8: x0 - x5 | D8: x0 - x5 | E8: x0 - x5 | F8: x0 - x5 | G8: x0 - x5 | H8: x0 - x5 | I8: x0 - x5
A9: Percentage in Low Tier | B9: =$C$9 -> 0.27970429 | C9: 0.27970429 | D9: =$C$9 -> 0.27970429 | E9: =$C$9 -> 0.27970429 | F9: =$C$9 -> 0.27970429 | G9: =$C$9 -> 0.27970429 | H9: =$C$9 -> 0.27970429 | I9: =$C$9 -> 0.27970429
A10: Medium Tier Winning Range | B10: x5 - x20 | C10: x5 - x20 | D10: x5 - x20 | E10: x5 - x20 | F10: x5 - x20 | G10: x5 - x20 | H10: x5 - x20 | I10: x5 - x20
A11: Percentage in Medium Tier | B11: =$C$11 -> 0.45495405 | C11: 0.45495405 | D11: =$C$11 -> 0.45495405 | E11: =$C$11 -> 0.45495405 | F11: =$C$11 -> 0.45495405 | G11: =$C$11 -> 0.45495405 | H11: =$C$11 -> 0.45495405 | I11: =$C$11 -> 0.45495405
A12: High Tier Winning Range | B12: x20 - top | C12: x20 - top | D12: x20 - top | E12: x20 - top | F12: x20 - top | G12: x20 - top | H12: x20 - top | I12: x20 - top
A13: Percentage in High Tier | B13: =$C$13 -> 0.26534167 | C13: 0.26534167 | D13: =$C$13 -> 0.26534167 | E13: =$C$13 -> 0.26534167 | F13: =$C$13 -> 0.26534167 | G13: =$C$13 -> 0.26534167 | H13: =$C$13 -> 0.26534167 | I13: =$C$13 -> 0.26534167
A14: Total Pool Amount | B14: =B7*B4*B1 -> 840000 | C14: =C7*C4*C1 -> 1680000 | D14: =D7*D4*D1 -> 3360000 | E14: =E7*E4*E1 -> 8400000 | F14: =F7*F4*F1 -> 16800000 | G14: =G7*G4*G1 -> 33600000 | H14: =H7*H4*H1 -> 50400000 | I14: =I7*I4*I1 -> 84000000
A15: Progressive Jackpot Info | B15: 0.5 | C15: 1 | D15: 2 | E15: 5 | F15: 10 | G15: 20 | H15: 30 | I15: 50
A16: Size of Grid | B16: 150000000 | C16: 150000000 | D16: 150000000 | E16: 150000000 | F16: 150000000 | G16: 150000000 | H16: 150000000 | I16: 150000000
A17: JP1 Wins/Grid | B17: =$C$17*B$15 -> 0.5 | C17: 1 | D17: =$C$17*D$15 -> 2 | E17: =$C$17*E$15 -> 5 | F17: =$C$17*F$15 -> 10 | G17: =$C$17*G$15 -> 20 | H17: =$C$17*H$15 -> 30 | I17: =$C$17*I$15 -> 50
A18: JP2 Wins/Grid | B18: =$C$18*B$15 -> 0.5 | C18: 1 | D18: =$C$18*D$15 -> 2 | E18: =$C$18*E$15 -> 5 | F18: =$C$18*F$15 -> 10 | G18: =$C$18*G$15 -> 20 | H18: =$C$18*H$15 -> 30 | I18: =$C$18*I$15 -> 50
A19: JP1 Wins/Price Ratio | B19: =$C$19 -> 1 | C19: 1 | D19: =$C$19 -> 1 | E19: =$C$19 -> 1 | F19: =$C$19 -> 1 | G19: =$C$19 -> 1 | H19: =$C$19 -> 1 | I19: =$C$19 -> 1
A20: JP2 Wins/Price Ratio | B20: =$C$20 -> 1 | C20: 1 | D20: =$C$20 -> 1 | E20: =$C$20 -> 1 | F20: =$C$20 -> 1 | G20: =$C$20 -> 1 | H20: =$C$20 -> 1 | I20: =$C$20 -> 1
A21: Odds of JP1 Win | B21: =$C$21/B$15 -> 300000000 | C21: 150000000 | D21: =$C$21/D$15 -> 75000000 | E21: =$C$21/E$15 -> 30000000 | F21: =$C$21/F$15 -> 15000000 | G21: =$C$21/G$15 -> 7500000 | H21: =$C$21/H$15 -> 5000000 | I21: =$C$21/I$15 -> 3000000
A22: Odds of JP2 Win | B22: =$C$22/B$15 -> 300000000 | C22: 150000000 | D22: =$C$22/D$15 -> 75000000 | E22: =$C$22/E$15 -> 30000000 | F22: =$C$22/F$15 -> 15000000 | G22: =$C$22/G$15 -> 7500000 | H22: =$C$22/H$15 -> 5000000 | I22: =$C$22/I$15 -> 3000000
A23: Revenue/JP win | B23: =B16*B15 -> 75000000 | C23: =C16*C15 -> 150000000 | D23: =D16*D15 -> 300000000 | E23: =E16*E15 -> 750000000 | F23: =F16*F15 -> 1500000000 | G23: =G16*G15 -> 3000000000 | H23: =H16*H15 -> 4500000000 | I23: =I16*I15 -> 7500000000
A24: Jackpot Reset % | B24: =$C$24 -> 0.003 | C24: 0.003 | D24: =$C$24 -> 0.003 | E24: =$C$24 -> 0.003 | F24: =$C$24 -> 0.003 | G24: =$C$24 -> 0.003 | H24: =$C$24 -> 0.003 | I24: =$C$24 -> 0.003
A25: JP1 Reset Value | B25: =$C$25 -> 225000 | C25: 225000 | D25: =$C$25 -> 225000 | E25: =$C$25 -> 225000 | F25: =$C$25 -> 225000 | G25: =$C$25 -> 225000 | H25: =$C$25 -> 225000 | I25: =$C$25 -> 225000
A26: JP2 Reset Value | B26: =$C$26 -> 225000 | C26: 225000 | D26: =$C$26 -> 225000 | E26: =$C$26 -> 225000 | F26: =$C$26 -> 225000 | G26: =$C$26 -> 225000 | H26: =$C$26 -> 225000 | I26: =$C$26 -> 225000
A27: Jackpot Increment % | B27: =$C$27 -> 0.027 | C27: 0.027 | D27: =$C$27 -> 0.027 | E27: =$C$27 -> 0.027 | F27: =$C$27 -> 0.027 | G27: =$C$27 -> 0.027 | H27: =$C$27 -> 0.027 | I27: =$C$27 -> 0.027
A28: Jackpot Increment Amount | B28: =B27*B15 -> 0.0135 | C28: =C27*C15 -> 0.027 | D28: =D27*D15 -> 0.054 | E28: =E27*E15 -> 0.135 | F28: =F27*F15 -> 0.27 | G28: =G27*G15 -> 0.54 | H28: =H27*H15 -> 0.81 | I28: =I27*I15 -> 1.35

Sheet Prize Breakdown
B2: Tier | C2: Win Methods | D2: Prize | E2: Symbol | F2: Quantity of Symbols
B3: 1 | C3: main-0 | D3: 0.1 | E3: 0,1,2,3 | F3: 3 | G3: A/B/C/D
B4: 2 | C4: main-1 | D4: 0.2 | E4: 0,1,2,3 | F4: 4 | G4: A/B/C/D
B5: 3 | C5: main-2 | D5: 0.5 | E5: 0,1,2,3 | F5: 5 | G5: A/B/C/D
B6: 4 | C6: main-3 | D6: 1 | E6: 0,1,2,3 | F6: 6 | G6: A/B/C/D
B7: 5 | C7: main-4 | D7: 2 | E7: 0,1,2,3 | F7: 7 | G7: A/B/C/D
B8: 6 | C8: main-5 | D8: 5 | E8: 0,1,2,3 | F8: 8 | G8: A/B/C/D | I8: A | J8: B | K8: C | L8: D | M8: E | N8: F | O8: G
B9: 7 | C9: main-6 | D9: 10 | E9: 0 | F9: 9 | H9: 3 | I9: 0.1 | J9: 0.1 | K9: 0.1 | L9: 0.1 | M9: 1 | N9: 2 | O9: 3
B10: 8 | C10: main-7 | D10: 20 | E10: 1 | F10: 9 | H10: 4 | I10: 0.2 | J10: 0.2 | K10: 0.2 | L10: 0.2 | M10: 2 | N10: 3 | O10: 5
B11: 9 | C11: main-8 | D11: 30 | E11: 2 | F11: 9 | H11: 5 | I11: 0.5 | J11: 0.5 | K11: 0.5 | L11: 0.5 | M11: 3 | N11: 5 | O11: 10
B12: 10 | C12: main-9 | D12: 40 | E12: 3 | F12: 9 | H12: 6 | I12: 1 | J12: 1 | K12: 1 | L12: 1 | M12: 5 | N12: 10 | O12: 20
B13: 11 | C13: main-10 | D13: 1 | E13: 4 | F13: 3 | H13: 7 | I13: 2 | J13: 2 | K13: 2 | L13: 2 | M13: 10 | N13: 20 | O13: 100
B14: 12 | C14: main-11 | D14: 2 | E14: 4 | F14: 4 | H14: 8 | I14: 5 | J14: 5 | K14: 5 | L14: 5 | M14: 20 | N14: 100 | O14: 200
B15: 13 | C15: main-12 | D15: 3 | E15: 4 | F15: 5 | H15: 9 | I15: 10 | J15: 20 | K15: 30 | L15: 40 | M15: 100 | N15: 200 | O15: 1000
B16: 14 | C16: main-13 | D16: 5 | E16: 4 | F16: 6
B17: 15 | C17: main-14 | D17: 10 | E17: 4 | F17: 7
B18: 16 | C18: main-15 | D18: 20 | E18: 4 | F18: 8
B19: 17 | C19: main-16 | D19: 100 | E19: 4 | F19: 9
B20: 18 | C20: main-17 | D20: 2 | E20: 5 | F20: 3
B21: 19 | C21: main-18 | D21: 3 | E21: 5 | F21: 4
B22: 20 | C22: main-19 | D22: 5 | E22: 5 | F22: 5
B23: 21 | C23: main-20 | D23: 10 | E23: 5 | F23: 6
B24: 22 | C24: main-21 | D24: 20 | E24: 5 | F24: 7
B25: 23 | C25: main-22 | D25: 100 | E25: 5 | F25: 8
B26: 24 | C26: main-23 | D26: 200 | E26: 5 | F26: 9
B27: 25 | C27: main-24 | D27: 3 | E27: 6 | F27: 3
... B33: 31 | C33: main-30 | D33: 1000 | E33: 6 | F33: 9
B34: 32 | C34: wild-0 | D34: 0.1 | E34: 0,1,2,3 | F34: 3 | G34: A/B/C/D
B35: 33 | C35: wild-1 | D35: 0.2 | E35: 0,1,2,3 | F35: 4 | G35: A/B/C/D
B36: 34 | C36: wild-2 | D36: 0.5 | E36: 0,1,2,3 | F36: 5 | G36: A/B/C/D
B37: 35 | C37: wild-3 | D37: 1 | E37: 0,1,2,3 | F37: 6 | G37: A/B/C/D
B38: 36 | C38: wild-4 | D38: 2 | E38: 0,1,2,3 | F38: 7 | G38: A/B/C/D
B39: 37 | C39: wild-5 | D39: 5 | E39: 0,1,2,3 | F39: 8 | G39: A/B/C/D
B40: 38 | C40: wild-6 | D40: 10 | E40: 0 | F40: 9
B41: 39 | C41: wild-7 | D41: 20 | E41: 1 | F41: 9
B42: 40 | C42: wild-8 | D42: 30 | E42: 2 | F42: 9
B43: 41 | C43: wild-9 | D43: 40 | E43: 3 | F43: 9
B44: 42 | C44: wild-10 | D44: 1 | E44: 4 | F44: 3
B45: 43 | C45: wild-11 | D45: 2 | E45: 4 | F45: 4
B46: 44 | C46: wild-12 | D46: 3 | E46: 4 | F46: 5
B47: 45 | C47: wild-13 | D47: 5 | E47: 4 | F47: 6
B48: 46 | C48: wild-14 | D48: 2 | E48: 5 | F48: 3
B49: 47 | C49: wild-15 | D49: 3 | E49: 5 | F49: 4
B50: 48 | C50: wild-16 | D50: 5 | E50: 5 | F50: 5
B51: 49 | C51: wild-17 | D51: 10 | E51: 5 | F51: 6
... B55: 53 | C55: wild-21 | D55: 20 | E55: 6 | F55: 6
B56: 54 | C56: freeplayA-0 | D56: 3.2 | E56: Free Plays | F56: 10
B57: 55 | C57: freeplayA-1 | D57: 10.6 | E57: Free Plays | F57: 10
B58: 56 | C58: freeplayA-2 | D58: 11 | E58: Free Plays | F58: 10
B59: 57 | C59: freeplayA-3 | D59: 12.3 | E59: Free Plays | F59: 10
B60: 58 | C60: freeplayA-4 | D60: 13.7 | E60: Free Plays | F60: 10
B61: 59 | C61: freeplayA-5 | D61: 16 | E61: Free Plays | F61: 10
B62: 60 | C62: freeplayA-6 | D62: 17.7 | E62: Free Plays | F62: 10
B63: 61 | C63: freeplayA-7 | D63: 20.3 | E63: Free Plays | F63: 10
B64: 62 | C64: freeplayA-8 | D64: 11.4 | E64: Free Plays | F64: 10
B65: 63 | C65: freeplayA-9 | D65: 22.1 | E65: Free Plays | F65: 10
B66: 64 | C66: freeplayA-10 | D66: 17.2 | E66: Free Plays | F66: 10
B67: 65 | C67: freeplayA-11 | D67: 20.1 | E67: Free Plays | F67: 10
... B89: 87 | C89: freeplayA-33 | D89: 33 | E89: Free Plays | F89: 10
B90: 88 | C90: freeplayA-34 | D90: 37.8 | E90: Free Plays | F90: 10 | G90: retrigger freeplay
B91: 89 | C91: freeplayA-35 | D91: 30.9 | E91: Free Plays | F91: 10 | G91: retrigger freeplay
B92: 90 | C92: freeplayA-36 | D92: 33.4 | E92: Free Plays | F92: 10 | G92: retrigger freeplay
B93: 91 | C93: freeplayA-37 | D93: 33.7 | E93: Free Plays | F93: 10 | G93: trigger bonusA
B94: 92 | C94: freeplayA-38 | D94: 32.3 | E94: Free Plays | F94: 10 | G94: trigger bonusA
B95: 93 | C95: freeplayA-39 | D95: 49.5 | E95: Free Plays | F95: 10 | G95: trigger bonusA
B96: 94 | C96: freeplayA-40 | D96: 35.4 | E96: Free Plays | F96: 10 | G96: trigger bonusA
B97: 95 | C97: freeplayA-41 | D97: 33.7 | E97: Free Plays | F97: 10 | G97: trigger bonusB
B98: 96 | C98: freeplayA-42 | D98: 32.3 | E98: Free Plays | F98: 10 | G98: trigger bonusB
B99: 97 | C99: freeplayA-43 | D99: 49.5 | E99: Free Plays | F99: 10 | G99: trigger bonusB
B100: 98 | C100: freeplayA-44 | D100: 35.4 | E100: Free Plays | F100: 10 | G100: trigger bonusB
B101: 371 | C101: instantA-0 | D101: 3 | E101: Instant Win | F101: 1
B102: 372 | C102: instantA-1 | D102: 5 | E102: Instant Win | F102: 1
B103: 373 | C103: instantA-2 | D103: 8 | E103: Instant Win | F103: 1
B104: 374 | C104: instantA-3 | D104: 10 | E104: Instant Win | F104: 1
B105: 375 | C105: instantA-4 | D105: 20 | E105: Instant Win | F105: 1
B106: 376 | C106: bonusA-0 | D106: 3 | E106: Power Bonus | F106: 1 | G106: Power Bonus
B107: 377 | C107: bonusA-1 | D107: 5 | E107: Power Bonus | F107: 1
B108: 378 | C108: bonusA-2 | D108: 8 | E108: Power Bonus | F108: 1
B109: 379 | C109: bonusA-3 | D109: 10 | E109: Power Bonus | F109: 1
B110: 380 | C110: bonusA-4 | D110: 12 | E110: Power Bonus | F110: 1
B111: 381 | C111: bonusA-5 | D111: 15 | E111: Power Bonus | F111: 1
B112: 382 | C112: bonusA-6 | D112: 20 | E112: Power Bonus | F112: 1 | G112: Right col
B113: 383 | C113: bonusA-7 | D113: 25 | E113: Power Bonus | F113: 1
B114: 384 | C114: bonusA-8 | D114: 30 | E114: Power Bonus | F114: 1
B115: 385 | C115: bonusA-9 | D115: 50 | E115: Power Bonus | F115: 1
B116: 386 | C116: bonusA-10 | D116: 100 | E116: Power Bonus | F116: 1
B117: 387 | C117: bonusB-0 | D117: 3 | E117: Boost Bonus | F117: 1 | G117: Boost Bonus
B118: 388 | C118: bonusB-1 | D118: 5 | E118: Boost Bonus | F118: 1
B119: 389 | C119: bonusB-2 | D119: 8 | E119: Boost Bonus | F119: 1
B120: 390 | C120: bonusB-3 | D120: 10 | E120: Boost Bonus | F120: 1
B121: 391 | C121: bonusB-4 | D121: 12 | E121: Boost Bonus | F121: 1
B122: 392 | C122: bonusB-5 | D122: 15 | E122: Boost Bonus | F122: 1
B123: 393 | C123: bonusB-6 | D123: 20 | E123: Boost Bonus | F123: 1 | G123: Right col
B124: 394 | C124: bonusB-7 | D124: 25 | E124: Boost Bonus | F124: 1
B125: 395 | C125: bonusB-8 | D125: 30 | E125: Boost Bonus | F125: 1
B126: 396 | C126: bonusB-9 | D126: 50 | E126: Boost Bonus | F126: 1
B127: 397 | C127: bonusB-10 | D127: 100 | E127: Boost Bonus | F127: 1
B128: 398 | C128: bonusC-0 | D128: 3 | E128: Barrel Stack | F128: 1 | G128: Barrel Stack
B129: 399 | C129: bonusC-1 | D129: 5 | E129: Barrel Stack | F129: 1
B130: 400 | C130: bonusC-2 | D130: 8 | E130: Barrel Stack | F130: 1
...

Sheet Summary
B3: ODDS DOWN (ticket quantity if pool based): | C3: 2000000
B4: BASE(ticket price): | C4: =Frequency!N7 -> 1
B5: REVENUE (if pool based): | C5: =C3*C4 -> 2000000
B6: Max prize | C6: =MAX(Tiers!C3:C4921) -> 1000
B7: Base RTP setting(JP exclude) | C7: =Frequency!N10 -> 0.84
B8: PRIZE FUND (if pool based): | C8: =C5*C7 -> 1680000
B9: Hit Rate | C9: =Summary!C3/(C3-Frequency!E4) -> 3.8950138
B10: Std. Dev. | C10: =('Data Analysis'!BM409/Summary!C3)^0.5 -> 3.510735
B12: wild Freq | C12: =Summary!C3/'Data Analysis'!AM409 -> 12.465875 | E12: Overall Feature Freq | F12: =C3/('Data Analysis'!AE409+'Data Analysis'!AF409) -> 57.053202
B13: wild Multi | C13: ='Data Analysis'!AN409/'Data Analysis'!AM409 -> 1.6053055 | E13: Overall Feature Avg. Multi | F13: =('Data Analysis'!BN409+'Data Analysis'!AG409)/('Data Analysis'!AE409+'Data Analysis'!AF409) -> 17.719681
B14: Standard wild Freq | C14: =C3/'Data Analysis'!AP409 -> 12.465875
B15: Standard wild Avg. Multi | C15: ='Data Analysis'!AQ409/'Data Analysis'!AP409 -> 1.6053055
B17: Freeplay Freq | C17: =Summary!C3/'Data Analysis'!AE409 -> 268.27632
B18: Freeplay Avg. Multi | C18: ='Data Analysis'!BN409/'Data Analysis'!AE409 -> 3.5505567
B19: Freeplay Value Share | C19: ='Data Analysis'!BN409/C8 -> 0.015755595
B21: bonus Freq | C21: =C3/('Data Analysis'!AY409+'Data Analysis'!BB409+'Data Analysis'!BE409) -> 27.89128
B22: bonus Multi | C22: =('Data Analysis'!BF409+'Data Analysis'!BC409+'Data Analysis'!AZ409)/('Data Analysis'!BE409+'Data Analysis'!BB409+'Data Analysis'!AY409) -> 14.556531
B23: bonus Value Share | C23: =('Data Analysis'!BF409+'Data Analysis'!BC409+'Data Analysis'!AZ409)/C8 -> 0.62131262
B24: bonusA Freq | C24: =C3/'Data Analysis'!AY409 -> 144.92754 | D24: Power Bonus
B25: bonusA Multi | C25: ='Data Analysis'!AZ409/'Data Analysis'!AY409 -> 21.546884
B26: bonusA Value Share | C26: ='Data Analysis'!AZ409/C8 -> 0.17699226
B27: bonusB Freq | C27: =C3/'Data Analysis'!BB409 -> 144.92754 | D27: Boost Bonus
B28: bonusB Multi | C28: ='Data Analysis'!BC409/'Data Analysis'!BB409 -> 21.546884
B29: bonusB Value Share | C29: ='Data Analysis'!BC409/C8 -> 0.17699226
B30: bonusC Freq | C30: =C3/'Data Analysis'!BE409 -> 45.344276 | D30: Barrel Stack
B31: bonusC Multi | C31: ='Data Analysis'!BF409/'Data Analysis'!BE409 -> 10.182311
B32: bonusC Value Share | C32: ='Data Analysis'!BF409/C8 -> 0.2673281
B35: instantA Freq | C35: =C3/'Data Analysis'!BH409 -> 465.11628
B36: instantA Multi | C36: ='Data Analysis'!BI409/'Data Analysis'!BH409 -> 6.1395349
B37: instantA Value Share | C37: ='Data Analysis'!BI409/C8 -> 0.015714286
G39: Odds Up | H39: %
B40: Combo Win Freq | C40: =C3/'Data Analysis'!AJ409 -> 22.652622 | E40: Single Feature | G40: ='Data Analysis'!BQ409+'Data Analysis'!BU409 -> 33352 | H40: =G40/G42 -> 0.9514192
B41: Combo Win Multi | C41: ='Data Analysis'!AK409/'Data Analysis'!AJ409 -> 1.9936607 | E41: Base game & Feature | G41: ='Data Analysis'!BS409+'Data Analysis'!BW409 -> 1703 | H41: =G41/G42 -> 0.048580802
G42: =SUM(G40:G41) -> 35055
B44: Category | C44: Freq | D44: Prob. | E44: Odds Dist. | F44: Value Dist. | G44: Hit Dist.
B45: NIL | C45: ='Data Analysis'!E2 -> 1486523 | D45: =C45/$C$56 -> 0.7432615 | E45: =1/D45 -> 1.3454215 | F45: - | G45: -
B46: >0 to <1 | C46: ='Data Analysis'!K409 -> 201550 | D46: =C46/$C$56 -> 0.100775 | E46: =1/D46 -> 9.923096 | F46: ='Data Analysis'!L409/Summary!C8 -> 0.031544167 | G46: =C46/SUM($C$46:$C$55) -> 0.39252002
B47: =1 -> 1 | C47: ='Data Analysis'!M409 -> 95322 | D47: =C47/$C$56 -> 0.047661 | E47: =1/D47 -> 20.981515 | F47: ='Data Analysis'!N409/Summary!C8 -> 0.056739286 | G47: =C47/SUM($C$46:$C$55) -> 0.18564025
B48: >1 to 2 | C48: ='Data Analysis'!O409 -> 108887 | D48: =C48/$C$56 -> 0.0544435 | E48: =1/D48 -> 18.367666 | F48: ='Data Analysis'!P409/Summary!C8 -> 0.1070578 | G48: =C48/SUM($C$46:$C$55) -> 0.21205818
B49: >2 to 5 | C49: ='Data Analysis'!Q409 -> 39268 | D49: =C49/$C$56 -> 0.019634 | E49: =1/D49 -> 50.932057 | F49: ='Data Analysis'!R409/Summary!C8 -> 0.091648393 | G49: =C49/SUM($C$46:$C$55) -> 0.076474701
B50: >5 to 10 | C50: ='Data Analysis'!S409 -> 23973 | D50: =C50/$C$56 -> 0.0119865 | E50: =1/D50 -> 83.427189 | F50: ='Data Analysis'!T409/Summary!C8 -> 0.12784232 | G50: =C50/SUM($C$46:$C$55) -> 0.046687583
B51: >10 to 20 | C51: ='Data Analysis'!U409 -> 30875 | D51: =C51/$C$56 -> 0.0154375 | E51: =1/D51 -> 64.777328 | F51: ='Data Analysis'!V409/Summary!C8 -> 0.28805601 | G51: =C51/SUM($C$46:$C$55) -> 0.060129276
B52: >20 to 30 | C52: ='Data Analysis'!W409 -> 11915 | D52: =C52/$C$56 -> 0.0059575 | E52: =1/D52 -> 167.85564 | F52: ='Data Analysis'!X409/Summary!C8 -> 0.18904869 | G52: =C52/SUM($C$46:$C$55) -> 0.023204545
B53: >30 to 50 | C53: ='Data Analysis'!Y409 -> 1491 | D53: =C53/$C$56 -> 0.0007455 | E53: =1/D53 -> 1341.3816 | F53: ='Data Analysis'!Z409/Summary!C8 -> 0.040081845 | G53: =C53/SUM($C$46:$C$55) -> 0.0029037328
B54: >50 to 100 | C54: ='Data Analysis'!AA409 -> 165 | D54: =C54/$C$56 -> 8.25e-05 | E54: =1/D54 -> 12121.212 | F54: ='Data Analysis'!AB409/Summary!C8 -> 0.0096678571 | G54: =C54/SUM($C$46:$C$55) -> 0.00032133864
B55: >100 | C55: ='Data Analysis'!AC409 -> 31 | D55: =C55/$C$56 -> 1.55e-05 | E55: =1/D55 -> 64516.129 | F55: ='Data Analysis'!AD409/Summary!C8 -> 0.0029722619 | G55: =C55/SUM($C$46:$C$55) -> 6.0372714e-05
C56: =SUM(C45:C55) -> 2000000 | D56: =SUM(D45:D55) -> 1 | E56: =1/D56 -> 1 | F56: =SUM(F46:F55) -> 0.94465863 | G56: =SUM(G46:G55) -> 1

Sheet Tiers
B2: Tier | C2: Total Prize | D2: Method 1 | E2: Prize 1 | F2: Method 2 | G2: Prize 2 | H2: Method 3 | I2: Prize 3 | J2: Method 4 | K2: Prize 4 | L2: Method 5 | M2: Prize 5 | N2: Method 6 | O2: Prize 6 | P2: Method 7 | Q2: Prize 7 | R2: Method 8 | S2: Prize 8 | T2: Method 9 | U2: Prize 9 | V2: Method 10 | W2: Prize 10 | X2: Method
B3: 0 | C3: =(E3+G3+I3+K3+M3+O3+Q3+S3+U3+W3) -> 0 | D3: 0 | E3: =VLOOKUP(D3,'Win Methods'!$C$4:$F$379,4,FALSE) -> 0 | G3: =VLOOKUP(F3,'Win Methods'!$C$4:$F$379,4,FALSE) -> 0 | I3: =VLOOKUP(H3,'Win Methods'!$C$4:$F$379,4,FALSE) -> 0 | K3: =VLOOKUP(J3,'Win Methods'!$C$4:$F$379,4,FALSE) -> 0 | M3: =VLOOKUP(L3,'Win Methods'!$C$4:$F$379,4,FALSE) -> 0 | O3: =VLOOKUP(N3,'Win Methods'!$C$4:$F$379,4,FALSE) -> 0 | Q3: =VLOOKUP(P3,'Win Methods'!$C$4:$F$379,4,FALSE) -> 0 | S3: =VLOOKUP(R3,'Win Methods'!$C$4:$F$379,4,FALSE) -> 0 | U3: =VLOOKUP(T3,'Win Methods'!$C$4:$F$379,4,FALSE) -> 0 | W3: =VLOOKUP(V3,'Win Methods'!$C$4:$F$379,4,FALSE) -> 0 | X3: =D3&"|"&F3&"|"&H3&"|"&J3&"|"&L3&"|"&N3&"|"&P3&"|"&R3&"|"&T3&"|"&V3 -> 0|||||||||
B4: 1 | C4: =(E4+G4+I4+K4+M4+O4+Q4+S4+U4+W4) -> 0.1 | D4: main-0 | E4: =VLOOKUP(D4,'Win Methods'!$C$4:$F$379,4,FALSE) -> 0.1 | G4: =VLOOKUP(F4,'Win Methods'!$C$4:$F$379,4,FALSE) -> 0 | I4: =VLOOKUP(H4,'Win Methods'!$C$4:$F$379,4,FALSE) -> 0 | K4: =VLOOKUP(J4,'Win Methods'!$C$4:$F$379,4,FALSE) -> 0 | M4: =VLOOKUP(L4,'Win Methods'!$C$4:$F$379,4,FALSE) -> 0 | O4: =VLOOKUP(N4,'Win Methods'!$C$4:$F$379,4,FALSE) -> 0 | Q4: =VLOOKUP(P4,'Win Methods'!$C$4:$F$379,4,FALSE) -> 0 | S4: =VLOOKUP(R4,'Win Methods'!$C$4:$F$379,4,FALSE) -> 0 | U4: =VLOOKUP(T4,'Win Methods'!$C$4:$F$379,4,FALSE) -> 0 | W4: =VLOOKUP(V4,'Win Methods'!$C$4:$F$379,4,FALSE) -> 0 | X4: =D4&"|"&F4&"|"&H4&"|"&J4&"|"&L4&"|"&N4&"|"&P4&"|"&R4&"|"&T4&"|"&V4 -> main-0|||||||||
B5: 2 | C5: =(E5+G5+I5+K5+M5+O5+Q5+S5+U5+W5) -> 0.2 | D5: main-1 | E5: =VLOOKUP(D5,'Win Methods'!$C$4:$F$379,4,FALSE) -> 0.2 | G5: =VLOOKUP(F5,'Win Methods'!$C$4:$F$379,4,FALSE) -> 0 | I5: =VLOOKUP(H5,'Win Methods'!$C$4:$F$379,4,FALSE) -> 0 | K5: =VLOOKUP(J5,'Win Methods'!$C$4:$F$379,4,FALSE) -> 0 | M5: =VLOOKUP(L5,'Win Methods'!$C$4:$F$379,4,FALSE) -> 0 | O5: =VLOOKUP(N5,'Win Methods'!$C$4:$F$379,4,FALSE) -> 0 | Q5: =VLOOKUP(P5,'Win Methods'!$C$4:$F$379,4,FALSE) -> 0 | S5: =VLOOKUP(R5,'Win Methods'!$C$4:$F$379,4,FALSE) -> 0 | U5: =VLOOKUP(T5,'Win Methods'!$C$4:$F$379,4,FALSE) -> 0 | W5: =VLOOKUP(V5,'Win Methods'!$C$4:$F$379,4,FALSE) -> 0 | X5: =D5&"|"&F5&"|"&H5&"|"&J5&"|"&L5&"|"&N5&"|"&P5&"|"&R5&"|"&T5&"|"&V5 -> main-1|||||||||
B6: 3 | C6: =(E6+G6+I6+K6+M6+O6+Q6+S6+U6+W6) -> 0.5 | D6: main-2 | E6: =VLOOKUP(D6,'Win Methods'!$C$4:$F$379,4,FALSE) -> 0.5 | G6: =VLOOKUP(F6,'Win Methods'!$C$4:$F$379,4,FALSE) -> 0 | I6: =VLOOKUP(H6,'Win Methods'!$C$4:$F$379,4,FALSE) -> 0 | K6: =VLOOKUP(J6,'Win Methods'!$C$4:$F$379,4,FALSE) -> 0 | M6: =VLOOKUP(L6,'Win Methods'!$C$4:$F$379,4,FALSE) -> 0 | O6: =VLOOKUP(N6,'Win Methods'!$C$4:$F$379,4,FALSE) -> 0 | Q6: =VLOOKUP(P6,'Win Methods'!$C$4:$F$379,4,FALSE) -> 0 | S6: =VLOOKUP(R6,'Win Methods'!$C$4:$F$379,4,FALSE) -> 0 | U6: =VLOOKUP(T6,'Win Methods'!$C$4:$F$379,4,FALSE) -> 0 | W6: =VLOOKUP(V6,'Win Methods'!$C$4:$F$379,4,FALSE) -> 0 | X6: =D6&"|"&F6&"|"&H6&"|"&J6&"|"&L6&"|"&N6&"|"&P6&"|"&R6&"|"&T6&"|"&V6 -> main-2|||||||||
B7: 4 | C7: =(E7+G7+I7+K7+M7+O7+Q7+S7+U7+W7) -> 1 | D7: main-3 | E7: =VLOOKUP(D7,'Win Methods'!$C$4:$F$379,4,FALSE) -> 1 | G7: =VLOOKUP(F7,'Win Methods'!$C$4:$F$379,4,FALSE) -> 0 | I7: =VLOOKUP(H7,'Win Methods'!$C$4:$F$379,4,FALSE) -> 0 | K7: =VLOOKUP(J7,'Win Methods'!$C$4:$F$379,4,FALSE) -> 0 | M7: =VLOOKUP(L7,'Win Methods'!$C$4:$F$379,4,FALSE) -> 0 | O7: =VLOOKUP(N7,'Win Methods'!$C$4:$F$379,4,FALSE) -> 0 | Q7: =VLOOKUP(P7,'Win Methods'!$C$4:$F$379,4,FALSE) -> 0 | S7: =VLOOKUP(R7,'Win Methods'!$C$4:$F$379,4,FALSE) -> 0 | U7: =VLOOKUP(T7,'Win Methods'!$C$4:$F$379,4,FALSE) -> 0 | W7: =VLOOKUP(V7,'Win Methods'!$C$4:$F$379,4,FALSE) -> 0 | X7: =D7&"|"&F7&"|"&H7&"|"&J7&"|"&L7&"|"&N7&"|"&P7&"|"&R7&"|"&T7&"|"&V7 -> main-3|||||||||
B8: 5 | C8: =(E8+G8+I8+K8+M8+O8+Q8+S8+U8+W8) -> 2 | D8: main-4 | E8: =VLOOKUP(D8,'Win Methods'!$C$4:$F$379,4,FALSE) -> 2 | G8: =VLOOKUP(F8,'Win Methods'!$C$4:$F$379,4,FALSE) -> 0 | I8: =VLOOKUP(H8,'Win Methods'!$C$4:$F$379,4,FALSE) -> 0 | K8: =VLOOKUP(J8,'Win Methods'!$C$4:$F$379,4,FALSE) -> 0 | M8: =VLOOKUP(L8,'Win Methods'!$C$4:$F$379,4,FALSE) -> 0 | O8: =VLOOKUP(N8,'Win Methods'!$C$4:$F$379,4,FALSE) -> 0 | Q8: =VLOOKUP(P8,'Win Methods'!$C$4:$F$379,4,FALSE) -> 0 | S8: =VLOOKUP(R8,'Win Methods'!$C$4:$F$379,4,FALSE) -> 0 | U8: =VLOOKUP(T8,'Win Methods'!$C$4:$F$379,4,FALSE) -> 0 | W8: =VLOOKUP(V8,'Win Methods'!$C$4:$F$379,4,FALSE) -> 0 | X8: =D8&"|"&F8&"|"&H8&"|"&J8&"|"&L8&"|"&N8&"|"&P8&"|"&R8&"|"&T8&"|"&V8 -> main-4|||||||||
B9: 6 | C9: =(E9+G9+I9+K9+M9+O9+Q9+S9+U9+W9) -> 5 | D9: main-5 | E9: =VLOOKUP(D9,'Win Methods'!$C$4:$F$379,4,FALSE) -> 5 | G9: =VLOOKUP(F9,'Win Methods'!$C$4:$F$379,4,FALSE) -> 0 | I9: =VLOOKUP(H9,'Win Methods'!$C$4:$F$379,4,FALSE) -> 0 | K9: =VLOOKUP(J9,'Win Methods'!$C$4:$F$379,4,FALSE) -> 0 | M9: =VLOOKUP(L9,'Win Methods'!$C$4:$F$379,4,FALSE) -> 0 | O9: =VLOOKUP(N9,'Win Methods'!$C$4:$F$379,4,FALSE) -> 0 | Q9: =VLOOKUP(P9,'Win Methods'!$C$4:$F$379,4,FALSE) -> 0 | S9: =VLOOKUP(R9,'Win Methods'!$C$4:$F$379,4,FALSE) -> 0 | U9: =VLOOKUP(T9,'Win Methods'!$C$4:$F$379,4,FALSE) -> 0 | W9: =VLOOKUP(V9,'Win Methods'!$C$4:$F$379,4,FALSE) -> 0 | X9: =D9&"|"&F9&"|"&H9&"|"&J9&"|"&L9&"|"&N9&"|"&P9&"|"&R9&"|"&T9&"|"&V9 -> main-5|||||||||
B10: 7 | C10: =(E10+G10+I10+K10+M10+O10+Q10+S10+U10+W10) -> 10 | D10: main-6 | E10: =VLOOKUP(D10,'Win Methods'!$C$4:$F$379,4,FALSE) -> 10 | G10: =VLOOKUP(F10,'Win Methods'!$C$4:$F$379,4,FALSE) -> 0 | I10: =VLOOKUP(H10,'Win Methods'!$C$4:$F$379,4,FALSE) -> 0 | K10: =VLOOKUP(J10,'Win Methods'!$C$4:$F$379,4,FALSE) -> 0 | M10: =VLOOKUP(L10,'Win Methods'!$C$4:$F$379,4,FALSE) -> 0 | O10: =VLOOKUP(N10,'Win Methods'!$C$4:$F$379,4,FALSE) -> 0 | Q10: =VLOOKUP(P10,'Win Methods'!$C$4:$F$379,4,FALSE) -> 0 | S10: =VLOOKUP(R10,'Win Methods'!$C$4:$F$379,4,FALSE) -> 0 | U10: =VLOOKUP(T10,'Win Methods'!$C$4:$F$379,4,FALSE) -> 0 | W10: =VLOOKUP(V10,'Win Methods'!$C$4:$F$379,4,FALSE) -> 0 | X10: =D10&"|"&F10&"|"&H10&"|"&J10&"|"&L10&"|"&N10&"|"&P10&"|"&R10&"|"&T10&"|"&V10 -> main-6|||||||||
B11: 8 | C11: =(E11+G11+I11+K11+M11+O11+Q11+S11+U11+W11) -> 20 | D11: main-7 | E11: =VLOOKUP(D11,'Win Methods'!$C$4:$F$379,4,FALSE) -> 20 | G11: =VLOOKUP(F11,'Win Methods'!$C$4:$F$379,4,FALSE) -> 0 | I11: =VLOOKUP(H11,'Win Methods'!$C$4:$F$379,4,FALSE) -> 0 | K11: =VLOOKUP(J11,'Win Methods'!$C$4:$F$379,4,FALSE) -> 0 | M11: =VLOOKUP(L11,'Win Methods'!$C$4:$F$379,4,FALSE) -> 0 | O11: =VLOOKUP(N11,'Win Methods'!$C$4:$F$379,4,FALSE) -> 0 | Q11: =VLOOKUP(P11,'Win Methods'!$C$4:$F$379,4,FALSE) -> 0 | S11: =VLOOKUP(R11,'Win Methods'!$C$4:$F$379,4,FALSE) -> 0 | U11: =VLOOKUP(T11,'Win Methods'!$C$4:$F$379,4,FALSE) -> 0 | W11: =VLOOKUP(V11,'Win Methods'!$C$4:$F$379,4,FALSE) -> 0 | X11: =D11&"|"&F11&"|"&H11&"|"&J11&"|"&L11&"|"&N11&"|"&P11&"|"&R11&"|"&T11&"|"&V11 -> main-7|||||||||
B12: 9 | C12: =(E12+G12+I12+K12+M12+O12+Q12+S12+U12+W12) -> 30 | D12: main-8 | E12: =VLOOKUP(D12,'Win Methods'!$C$4:$F$379,4,FALSE) -> 30 | G12: =VLOOKUP(F12,'Win Methods'!$C$4:$F$379,4,FALSE) -> 0 | I12: =VLOOKUP(H12,'Win Methods'!$C$4:$F$379,4,FALSE) -> 0 | K12: =VLOOKUP(J12,'Win Methods'!$C$4:$F$379,4,FALSE) -> 0 | M12: =VLOOKUP(L12,'Win Methods'!$C$4:$F$379,4,FALSE) -> 0 | O12: =VLOOKUP(N12,'Win Methods'!$C$4:$F$379,4,FALSE) -> 0 | Q12: =VLOOKUP(P12,'Win Methods'!$C$4:$F$379,4,FALSE) -> 0 | S12: =VLOOKUP(R12,'Win Methods'!$C$4:$F$379,4,FALSE) -> 0 | U12: =VLOOKUP(T12,'Win Methods'!$C$4:$F$379,4,FALSE) -> 0 | W12: =VLOOKUP(V12,'Win Methods'!$C$4:$F$379,4,FALSE) -> 0 | X12: =D12&"|"&F12&"|"&H12&"|"&J12&"|"&L12&"|"&N12&"|"&P12&"|"&R12&"|"&T12&"|"&V12 -> main-8|||||||||
B13: 10 | C13: =(E13+G13+I13+K13+M13+O13+Q13+S13+U13+W13) -> 40 | D13: main-9 | E13: =VLOOKUP(D13,'Win Methods'!$C$4:$F$379,4,FALSE) -> 40 | G13: =VLOOKUP(F13,'Win Methods'!$C$4:$F$379,4,FALSE) -> 0 | I13: =VLOOKUP(H13,'Win Methods'!$C$4:$F$379,4,FALSE) -> 0 | K13: =VLOOKUP(J13,'Win Methods'!$C$4:$F$379,4,FALSE) -> 0 | M13: =VLOOKUP(L13,'Win Methods'!$C$4:$F$379,4,FALSE) -> 0 | O13: =VLOOKUP(N13,'Win Methods'!$C$4:$F$379,4,FALSE) -> 0 | Q13: =VLOOKUP(P13,'Win Methods'!$C$4:$F$379,4,FALSE) -> 0 | S13: =VLOOKUP(R13,'Win Methods'!$C$4:$F$379,4,FALSE) -> 0 | U13: =VLOOKUP(T13,'Win Methods'!$C$4:$F$379,4,FALSE) -> 0 | W13: =VLOOKUP(V13,'Win Methods'!$C$4:$F$379,4,FALSE) -> 0 | X13: =D13&"|"&F13&"|"&H13&"|"&J13&"|"&L13&"|"&N13&"|"&P13&"|"&R13&"|"&T13&"|"&V13 -> main-9|||||||||
B14: 11 | C14: =(E14+G14+I14+K14+M14+O14+Q14+S14+U14+W14) -> 1 | D14: main-10 | E14: =VLOOKUP(D14,'Win Methods'!$C$4:$F$379,4,FALSE) -> 1 | G14: =VLOOKUP(F14,'Win Methods'!$C$4:$F$379,4,FALSE) -> 0 | I14: =VLOOKUP(H14,'Win Methods'!$C$4:$F$379,4,FALSE) -> 0 | K14: =VLOOKUP(J14,'Win Methods'!$C$4:$F$379,4,FALSE) -> 0 | M14: =VLOOKUP(L14,'Win Methods'!$C$4:$F$379,4,FALSE) -> 0 | O14: =VLOOKUP(N14,'Win Methods'!$C$4:$F$379,4,FALSE) -> 0 | Q14: =VLOOKUP(P14,'Win Methods'!$C$4:$F$379,4,FALSE) -> 0 | S14: =VLOOKUP(R14,'Win Methods'!$C$4:$F$379,4,FALSE) -> 0 | U14: =VLOOKUP(T14,'Win Methods'!$C$4:$F$379,4,FALSE) -> 0 | W14: =VLOOKUP(V14,'Win Methods'!$C$4:$F$379,4,FALSE) -> 0 | X14: =D14&"|"&F14&"|"&H14&"|"&J14&"|"&L14&"|"&N14&"|"&P14&"|"&R14&"|"&T14&"|"&V14 -> main-10|||||||||
B15: 12 | C15: =(E15+G15+I15+K15+M15+O15+Q15+S15+U15+W15) -> 2 | D15: main-11 | E15: =VLOOKUP(D15,'Win Methods'!$C$4:$F$379,4,FALSE) -> 2 | G15: =VLOOKUP(F15,'Win Methods'!$C$4:$F$379,4,FALSE) -> 0 | I15: =VLOOKUP(H15,'Win Methods'!$C$4:$F$379,4,FALSE) -> 0 | K15: =VLOOKUP(J15,'Win Methods'!$C$4:$F$379,4,FALSE) -> 0 | M15: =VLOOKUP(L15,'Win Methods'!$C$4:$F$379,4,FALSE) -> 0 | O15: =VLOOKUP(N15,'Win Methods'!$C$4:$F$379,4,FALSE) -> 0 | Q15: =VLOOKUP(P15,'Win Methods'!$C$4:$F$379,4,FALSE) -> 0 | S15: =VLOOKUP(R15,'Win Methods'!$C$4:$F$379,4,FALSE) -> 0 | U15: =VLOOKUP(T15,'Win Methods'!$C$4:$F$379,4,FALSE) -> 0 | W15: =VLOOKUP(V15,'Win Methods'!$C$4:$F$379,4,FALSE) -> 0 | X15: =D15&"|"&F15&"|"&H15&"|"&J15&"|"&L15&"|"&N15&"|"&P15&"|"&R15&"|"&T15&"|"&V15 -> main-11|||||||||
... B101: 98 | C101: =(E101+G101+I101+K101+M101+O101+Q101+S101+U101+W101) -> 0.2 | D101: freeplayA-44 | E101: =VLOOKUP(D101,'Win Methods'!$C$4:$F$379,4,FALSE) -> 0.2 | G101: =VLOOKUP(F101,'Win Methods'!$C$4:$F$379,4,FALSE) -> 0 | I101: =VLOOKUP(H101,'Win Methods'!$C$4:$F$379,4,FALSE) -> 0 | K101: =VLOOKUP(J101,'Win Methods'!$C$4:$F$379,4,FALSE) -> 0 | M101: =VLOOKUP(L101,'Win Methods'!$C$4:$F$379,4,FALSE) -> 0 | O101: =VLOOKUP(N101,'Win Methods'!$C$4:$F$379,4,FALSE) -> 0 | Q101: =VLOOKUP(P101,'Win Methods'!$C$4:$F$379,4,FALSE) -> 0 | S101: =VLOOKUP(R101,'Win Methods'!$C$4:$F$379,4,FALSE) -> 0 | U101: =VLOOKUP(T101,'Win Methods'!$C$4:$F$379,4,FALSE) -> 0 | W101: =VLOOKUP(V101,'Win Methods'!$C$4:$F$379,4,FALSE) -> 0 | X101: =D101&"|"&F101&"|"&H101&"|"&J101&"|"&L101&"|"&N101&"|"&P101&"|"&R101&"|"&T101&"|"&V101 -> freeplayA-44|||||||||
B102: 99 | C102: =(E102+G102+I102+K102+M102+O102+Q102+S102+U102+W102) -> 0.2 | D102: main-0 | E102: =VLOOKUP(D102,'Win Methods'!$C$4:$F$379,4,FALSE) -> 0.1 | F102: main-0 | G102: =VLOOKUP(F102,'Win Methods'!$C$4:$F$379,4,FALSE) -> 0.1 | I102: =VLOOKUP(H102,'Win Methods'!$C$4:$F$379,4,FALSE) -> 0 | K102: =VLOOKUP(J102,'Win Methods'!$C$4:$F$379,4,FALSE) -> 0 | M102: =VLOOKUP(L102,'Win Methods'!$C$4:$F$379,4,FALSE) -> 0 | O102: =VLOOKUP(N102,'Win Methods'!$C$4:$F$379,4,FALSE) -> 0 | Q102: =VLOOKUP(P102,'Win Methods'!$C$4:$F$379,4,FALSE) -> 0 | S102: =VLOOKUP(R102,'Win Methods'!$C$4:$F$379,4,FALSE) -> 0 | U102: =VLOOKUP(T102,'Win Methods'!$C$4:$F$379,4,FALSE) -> 0 | W102: =VLOOKUP(V102,'Win Methods'!$C$4:$F$379,4,FALSE) -> 0 | X102: =D102&"|"&F102&"|"&H102&"|"&J102&"|"&L102&"|"&N102&"|"&P102&"|"&R102&"|"&T102&"|"&V102 -> main-0|main-0||||||||
B103: 100 | C103: =(E103+G103+I103+K103+M103+O103+Q103+S103+U103+W103) -> 0.3 | D103: main-0 | E103: =VLOOKUP(D103,'Win Methods'!$C$4:$F$379,4,FALSE) -> 0.1 | F103: main-1 | G103: =VLOOKUP(F103,'Win Methods'!$C$4:$F$379,4,FALSE) -> 0.2 | I103: =VLOOKUP(H103,'Win Methods'!$C$4:$F$379,4,FALSE) -> 0 | K103: =VLOOKUP(J103,'Win Methods'!$C$4:$F$379,4,FALSE) -> 0 | M103: =VLOOKUP(L103,'Win Methods'!$C$4:$F$379,4,FALSE) -> 0 | O103: =VLOOKUP(N103,'Win Methods'!$C$4:$F$379,4,FALSE) -> 0 | Q103: =VLOOKUP(P103,'Win Methods'!$C$4:$F$379,4,FALSE) -> 0 | S103: =VLOOKUP(R103,'Win Methods'!$C$4:$F$379,4,FALSE) -> 0 | U103: =VLOOKUP(T103,'Win Methods'!$C$4:$F$379,4,FALSE) -> 0 | W103: =VLOOKUP(V103,'Win Methods'!$C$4:$F$379,4,FALSE) -> 0 | X103: =D103&"|"&F103&"|"&H103&"|"&J103&"|"&L103&"|"&N103&"|"&P103&"|"&R103&"|"&T103&"|"&V103 -> main-0|main-1||||||||
B104: 101 | C104: =(E104+G104+I104+K104+M104+O104+Q104+S104+U104+W104) -> 0.4 | D104: main-1 | E104: =VLOOKUP(D104,'Win Methods'!$C$4:$F$379,4,FALSE) -> 0.2 | F104: main-1 | G104: =VLOOKUP(F104,'Win Methods'!$C$4:$F$379,4,FALSE) -> 0.2 | I104: =VLOOKUP(H104,'Win Methods'!$C$4:$F$379,4,FALSE) -> 0 | K104: =VLOOKUP(J104,'Win Methods'!$C$4:$F$379,4,FALSE) -> 0 | M104: =VLOOKUP(L104,'Win Methods'!$C$4:$F$379,4,FALSE) -> 0 | O104: =VLOOKUP(N104,'Win Methods'!$C$4:$F$379,4,FALSE) -> 0 | Q104: =VLOOKUP(P104,'Win Methods'!$C$4:$F$379,4,FALSE) -> 0 | S104: =VLOOKUP(R104,'Win Methods'!$C$4:$F$379,4,FALSE) -> 0 | U104: =VLOOKUP(T104,'Win Methods'!$C$4:$F$379,4,FALSE) -> 0 | W104: =VLOOKUP(V104,'Win Methods'!$C$4:$F$379,4,FALSE) -> 0 | X104: =D104&"|"&F104&"|"&H104&"|"&J104&"|"&L104&"|"&N104&"|"&P104&"|"&R104&"|"&T104&"|"&V104 -> main-1|main-1||||||||
B105: 102 | C105: =(E105+G105+I105+K105+M105+O105+Q105+S105+U105+W105) -> 0.6 | D105: main-0 | E105: =VLOOKUP(D105,'Win Methods'!$C$4:$F$379,4,FALSE) -> 0.1 | F105: main-2 | G105: =VLOOKUP(F105,'Win Methods'!$C$4:$F$379,4,FALSE) -> 0.5 | I105: =VLOOKUP(H105,'Win Methods'!$C$4:$F$379,4,FALSE) -> 0 | K105: =VLOOKUP(J105,'Win Methods'!$C$4:$F$379,4,FALSE) -> 0 | M105: =VLOOKUP(L105,'Win Methods'!$C$4:$F$379,4,FALSE) -> 0 | O105: =VLOOKUP(N105,'Win Methods'!$C$4:$F$379,4,FALSE) -> 0 | Q105: =VLOOKUP(P105,'Win Methods'!$C$4:$F$379,4,FALSE) -> 0 | S105: =VLOOKUP(R105,'Win Methods'!$C$4:$F$379,4,FALSE) -> 0 | U105: =VLOOKUP(T105,'Win Methods'!$C$4:$F$379,4,FALSE) -> 0 | W105: =VLOOKUP(V105,'Win Methods'!$C$4:$F$379,4,FALSE) -> 0 | X105: =D105&"|"&F105&"|"&H105&"|"&J105&"|"&L105&"|"&N105&"|"&P105&"|"&R105&"|"&T105&"|"&V105 -> main-0|main-2||||||||
B106: 103 | C106: =(E106+G106+I106+K106+M106+O106+Q106+S106+U106+W106) -> 0.7 | D106: main-1 | E106: =VLOOKUP(D106,'Win Methods'!$C$4:$F$379,4,FALSE) -> 0.2 | F106: main-2 | G106: =VLOOKUP(F106,'Win Methods'!$C$4:$F$379,4,FALSE) -> 0.5 | I106: =VLOOKUP(H106,'Win Methods'!$C$4:$F$379,4,FALSE) -> 0 | K106: =VLOOKUP(J106,'Win Methods'!$C$4:$F$379,4,FALSE) -> 0 | M106: =VLOOKUP(L106,'Win Methods'!$C$4:$F$379,4,FALSE) -> 0 | O106: =VLOOKUP(N106,'Win Methods'!$C$4:$F$379,4,FALSE) -> 0 | Q106: =VLOOKUP(P106,'Win Methods'!$C$4:$F$379,4,FALSE) -> 0 | S106: =VLOOKUP(R106,'Win Methods'!$C$4:$F$379,4,FALSE) -> 0 | U106: =VLOOKUP(T106,'Win Methods'!$C$4:$F$379,4,FALSE) -> 0 | W106: =VLOOKUP(V106,'Win Methods'!$C$4:$F$379,4,FALSE) -> 0 | X106: =D106&"|"&F106&"|"&H106&"|"&J106&"|"&L106&"|"&N106&"|"&P106&"|"&R106&"|"&T106&"|"&V106 -> main-1|main-2||||||||
B107: 104 | C107: =(E107+G107+I107+K107+M107+O107+Q107+S107+U107+W107) -> 1.1 | D107: main-3 | E107: =VLOOKUP(D107,'Win Methods'!$C$4:$F$379,4,FALSE) -> 1 | F107: main-0 | G107: =VLOOKUP(F107,'Win Methods'!$C$4:$F$379,4,FALSE) -> 0.1 | I107: =VLOOKUP(H107,'Win Methods'!$C$4:$F$379,4,FALSE) -> 0 | K107: =VLOOKUP(J107,'Win Methods'!$C$4:$F$379,4,FALSE) -> 0 | M107: =VLOOKUP(L107,'Win Methods'!$C$4:$F$379,4,FALSE) -> 0 | O107: =VLOOKUP(N107,'Win Methods'!$C$4:$F$379,4,FALSE) -> 0 | Q107: =VLOOKUP(P107,'Win Methods'!$C$4:$F$379,4,FALSE) -> 0 | S107: =VLOOKUP(R107,'Win Methods'!$C$4:$F$379,4,FALSE) -> 0 | U107: =VLOOKUP(T107,'Win Methods'!$C$4:$F$379,4,FALSE) -> 0 | W107: =VLOOKUP(V107,'Win Methods'!$C$4:$F$379,4,FALSE) -> 0 | X107: =D107&"|"&F107&"|"&H107&"|"&J107&"|"&L107&"|"&N107&"|"&P107&"|"&R107&"|"&T107&"|"&V107 -> main-3|main-0||||||||
B108: 105 | C108: =(E108+G108+I108+K108+M108+O108+Q108+S108+U108+W108) -> 1.2 | D108: main-3 | E108: =VLOOKUP(D108,'Win Methods'!$C$4:$F$379,4,FALSE) -> 1 | F108: main-1 | G108: =VLOOKUP(F108,'Win Methods'!$C$4:$F$379,4,FALSE) -> 0.2 | I108: =VLOOKUP(H108,'Win Methods'!$C$4:$F$379,4,FALSE) -> 0 | K108: =VLOOKUP(J108,'Win Methods'!$C$4:$F$379,4,FALSE) -> 0 | M108: =VLOOKUP(L108,'Win Methods'!$C$4:$F$379,4,FALSE) -> 0 | O108: =VLOOKUP(N108,'Win Methods'!$C$4:$F$379,4,FALSE) -> 0 | Q108: =VLOOKUP(P108,'Win Methods'!$C$4:$F$379,4,FALSE) -> 0 | S108: =VLOOKUP(R108,'Win Methods'!$C$4:$F$379,4,FALSE) -> 0 | U108: =VLOOKUP(T108,'Win Methods'!$C$4:$F$379,4,FALSE) -> 0 | W108: =VLOOKUP(V108,'Win Methods'!$C$4:$F$379,4,FALSE) -> 0 | X108: =D108&"|"&F108&"|"&H108&"|"&J108&"|"&L108&"|"&N108&"|"&P108&"|"&R108&"|"&T108&"|"&V108 -> main-3|main-1||||||||
B109: 106 | C109: =(E109+G109+I109+K109+M109+O109+Q109+S109+U109+W109) -> 5.2 | D109: main-1 | E109: =VLOOKUP(D109,'Win Methods'!$C$4:$F$379,4,FALSE) -> 0.2 | F109: main-5 | G109: =VLOOKUP(F109,'Win Methods'!$C$4:$F$379,4,FALSE) -> 5 | I109: =VLOOKUP(H109,'Win Methods'!$C$4:$F$379,4,FALSE) -> 0 | K109: =VLOOKUP(J109,'Win Methods'!$C$4:$F$379,4,FALSE) -> 0 | M109: =VLOOKUP(L109,'Win Methods'!$C$4:$F$379,4,FALSE) -> 0 | O109: =VLOOKUP(N109,'Win Methods'!$C$4:$F$379,4,FALSE) -> 0 | Q109: =VLOOKUP(P109,'Win Methods'!$C$4:$F$379,4,FALSE) -> 0 | S109: =VLOOKUP(R109,'Win Methods'!$C$4:$F$379,4,FALSE) -> 0 | U109: =VLOOKUP(T109,'Win Methods'!$C$4:$F$379,4,FALSE) -> 0 | W109: =VLOOKUP(V109,'Win Methods'!$C$4:$F$379,4,FALSE) -> 0 | X109: =D109&"|"&F109&"|"&H109&"|"&J109&"|"&L109&"|"&N109&"|"&P109&"|"&R109&"|"&T109&"|"&V109 -> main-1|main-5||||||||
B110: 107 | C110: =(E110+G110+I110+K110+M110+O110+Q110+S110+U110+W110) -> 7 | D110: main-4 | E110: =VLOOKUP(D110,'Win Methods'!$C$4:$F$379,4,FALSE) -> 2 | F110: main-19 | G110: =VLOOKUP(F110,'Win Methods'!$C$4:$F$379,4,FALSE) -> 5 | I110: =VLOOKUP(H110,'Win Methods'!$C$4:$F$379,4,FALSE) -> 0 | K110: =VLOOKUP(J110,'Win Methods'!$C$4:$F$379,4,FALSE) -> 0 | M110: =VLOOKUP(L110,'Win Methods'!$C$4:$F$379,4,FALSE) -> 0 | O110: =VLOOKUP(N110,'Win Methods'!$C$4:$F$379,4,FALSE) -> 0 | Q110: =VLOOKUP(P110,'Win Methods'!$C$4:$F$379,4,FALSE) -> 0 | S110: =VLOOKUP(R110,'Win Methods'!$C$4:$F$379,4,FALSE) -> 0 | U110: =VLOOKUP(T110,'Win Methods'!$C$4:$F$379,4,FALSE) -> 0 | W110: =VLOOKUP(V110,'Win Methods'!$C$4:$F$379,4,FALSE) -> 0 | X110: =D110&"|"&F110&"|"&H110&"|"&J110&"|"&L110&"|"&N110&"|"&P110&"|"&R110&"|"&T110&"|"&V110 -> main-4|main-19||||||||
B111: 108 | C111: =(E111+G111+I111+K111+M111+O111+Q111+S111+U111+W111) -> 11 | D111: main-3 | E111: =VLOOKUP(D111,'Win Methods'!$C$4:$F$379,4,FALSE) -> 1 | F111: main-20 | G111: =VLOOKUP(F111,'Win Methods'!$C$4:$F$379,4,FALSE) -> 10 | I111: =VLOOKUP(H111,'Win Methods'!$C$4:$F$379,4,FALSE) -> 0 | K111: =VLOOKUP(J111,'Win Methods'!$C$4:$F$379,4,FALSE) -> 0 | M111: =VLOOKUP(L111,'Win Methods'!$C$4:$F$379,4,FALSE) -> 0 | O111: =VLOOKUP(N111,'Win Methods'!$C$4:$F$379,4,FALSE) -> 0 | Q111: =VLOOKUP(P111,'Win Methods'!$C$4:$F$379,4,FALSE) -> 0 | S111: =VLOOKUP(R111,'Win Methods'!$C$4:$F$379,4,FALSE) -> 0 | U111: =VLOOKUP(T111,'Win Methods'!$C$4:$F$379,4,FALSE) -> 0 | W111: =VLOOKUP(V111,'Win Methods'!$C$4:$F$379,4,FALSE) -> 0 | X111: =D111&"|"&F111&"|"&H111&"|"&J111&"|"&L111&"|"&N111&"|"&P111&"|"&R111&"|"&T111&"|"&V111 -> main-3|main-20||||||||
B112: 109 | C112: =(E112+G112+I112+K112+M112+O112+Q112+S112+U112+W112) -> 7 | D112: main-4 | E112: =VLOOKUP(D112,'Win Methods'!$C$4:$F$379,4,FALSE) -> 2 | F112: main-5 | G112: =VLOOKUP(F112,'Win Methods'!$C$4:$F$379,4,FALSE) -> 5 | I112: =VLOOKUP(H112,'Win Methods'!$C$4:$F$379,4,FALSE) -> 0 | K112: =VLOOKUP(J112,'Win Methods'!$C$4:$F$379,4,FALSE) -> 0 | M112: =VLOOKUP(L112,'Win Methods'!$C$4:$F$379,4,FALSE) -> 0 | O112: =VLOOKUP(N112,'Win Methods'!$C$4:$F$379,4,FALSE) -> 0 | Q112: =VLOOKUP(P112,'Win Methods'!$C$4:$F$379,4,FALSE) -> 0 | S112: =VLOOKUP(R112,'Win Methods'!$C$4:$F$379,4,FALSE) -> 0 | U112: =VLOOKUP(T112,'Win Methods'!$C$4:$F$379,4,FALSE) -> 0 | W112: =VLOOKUP(V112,'Win Methods'!$C$4:$F$379,4,FALSE) -> 0 | X112: =D112&"|"&F112&"|"&H112&"|"&J112&"|"&L112&"|"&N112&"|"&P112&"|"&R112&"|"&T112&"|"&V112 -> main-4|main-5||||||||
B113: 110 | C113: =(E113+G113+I113+K113+M113+O113+Q113+S113+U113+W113) -> 10 | D113: main-5 | E113: =VLOOKUP(D113,'Win Methods'!$C$4:$F$379,4,FALSE) -> 5 | F113: main-25 | G113: =VLOOKUP(F113,'Win Methods'!$C$4:$F$379,4,FALSE) -> 5 | I113: =VLOOKUP(H113,'Win Methods'!$C$4:$F$379,4,FALSE) -> 0 | K113: =VLOOKUP(J113,'Win Methods'!$C$4:$F$379,4,FALSE) -> 0 | M113: =VLOOKUP(L113,'Win Methods'!$C$4:$F$379,4,FALSE) -> 0 | O113: =VLOOKUP(N113,'Win Methods'!$C$4:$F$379,4,FALSE) -> 0 | Q113: =VLOOKUP(P113,'Win Methods'!$C$4:$F$379,4,FALSE) -> 0 | S113: =VLOOKUP(R113,'Win Methods'!$C$4:$F$379,4,FALSE) -> 0 | U113: =VLOOKUP(T113,'Win Methods'!$C$4:$F$379,4,FALSE) -> 0 | W113: =VLOOKUP(V113,'Win Methods'!$C$4:$F$379,4,FALSE) -> 0 | X113: =D113&"|"&F113&"|"&H113&"|"&J113&"|"&L113&"|"&N113&"|"&P113&"|"&R113&"|"&T113&"|"&V113 -> main-5|main-25||||||||
... B116: 113 | C116: =(E116+G116+I116+K116+M116+O116+Q116+S116+U116+W116) -> 22 | D116: main-4 | E116: =VLOOKUP(D116,'Win Methods'!$C$4:$F$379,4,FALSE) -> 2 | F116: main-21 | G116: =VLOOKUP(F116,'Win Methods'!$C$4:$F$379,4,FALSE) -> 20 | I116: =VLOOKUP(H116,'Win Methods'!$C$4:$F$379,4,FALSE) -> 0 | K116: =VLOOKUP(J116,'Win Methods'!$C$4:$F$379,4,FALSE) -> 0 | M116: =VLOOKUP(L116,'Win Methods'!$C$4:$F$379,4,FALSE) -> 0 | O116: =VLOOKUP(N116,'Win Methods'!$C$4:$F$379,4,FALSE) -> 0 | Q116: =VLOOKUP(P116,'Win Methods'!$C$4:$F$379,4,FALSE) -> 0 | S116: =VLOOKUP(R116,'Win Methods'!$C$4:$F$379,4,FALSE) -> 0 | U116: =VLOOKUP(T116,'Win Methods'!$C$4:$F$379,4,FALSE) -> 0 | W116: =VLOOKUP(V116,'Win Methods'!$C$4:$F$379,4,FALSE) -> 0 | X116: =D116&"|"&F116&"|"&H116&"|"&J116&"|"&L116&"|"&N116&"|"&P116&"|"&R116&"|"&T116&"|"&V116 -> main-4|main-21||||||||
B117: 114 | C117: =(E117+G117+I117+K117+M117+O117+Q117+S117+U117+W117) -> 5.1 | D117: main-0 | E117: =VLOOKUP(D117,'Win Methods'!$C$4:$F$379,4,FALSE) -> 0.1 | F117: main-18 | G117: =VLOOKUP(F117,'Win Methods'!$C$4:$F$379,4,FALSE) -> 3 | H117: main-4 | I117: =VLOOKUP(H117,'Win Methods'!$C$4:$F$379,4,FALSE) -> 2 | K117: =VLOOKUP(J117,'Win Methods'!$C$4:$F$379,4,FALSE) -> 0 | M117: =VLOOKUP(L117,'Win Methods'!$C$4:$F$379,4,FALSE) -> 0 | O117: =VLOOKUP(N117,'Win Methods'!$C$4:$F$379,4,FALSE) -> 0 | Q117: =VLOOKUP(P117,'Win Methods'!$C$4:$F$379,4,FALSE) -> 0 | S117: =VLOOKUP(R117,'Win Methods'!$C$4:$F$379,4,FALSE) -> 0 | U117: =VLOOKUP(T117,'Win Methods'!$C$4:$F$379,4,FALSE) -> 0 | W117: =VLOOKUP(V117,'Win Methods'!$C$4:$F$379,4,FALSE) -> 0 | X117: =D117&"|"&F117&"|"&H117&"|"&J117&"|"&L117&"|"&N117&"|"&P117&"|"&R117&"|"&T117&"|"&V117 -> main-0|main-18|main-4|||||||
B118: 115 | C118: =(E118+G118+I118+K118+M118+O118+Q118+S118+U118+W118) -> 8.2 | D118: main-1 | E118: =VLOOKUP(D118,'Win Methods'!$C$4:$F$379,4,FALSE) -> 0.2 | F118: main-25 | G118: =VLOOKUP(F118,'Win Methods'!$C$4:$F$379,4,FALSE) -> 5 | H118: main-18 | I118: =VLOOKUP(H118,'Win Methods'!$C$4:$F$379,4,FALSE) -> 3 | K118: =VLOOKUP(J118,'Win Methods'!$C$4:$F$379,4,FALSE) -> 0 | M118: =VLOOKUP(L118,'Win Methods'!$C$4:$F$379,4,FALSE) -> 0 | O118: =VLOOKUP(N118,'Win Methods'!$C$4:$F$379,4,FALSE) -> 0 | Q118: =VLOOKUP(P118,'Win Methods'!$C$4:$F$379,4,FALSE) -> 0 | S118: =VLOOKUP(R118,'Win Methods'!$C$4:$F$379,4,FALSE) -> 0 | U118: =VLOOKUP(T118,'Win Methods'!$C$4:$F$379,4,FALSE) -> 0 | W118: =VLOOKUP(V118,'Win Methods'!$C$4:$F$379,4,FALSE) -> 0 | X118: =D118&"|"&F118&"|"&H118&"|"&J118&"|"&L118&"|"&N118&"|"&P118&"|"&R118&"|"&T118&"|"&V118 -> main-1|main-25|main-18|||||||
B119: 116 | C119: =(E119+G119+I119+K119+M119+O119+Q119+S119+U119+W119) -> 6.5 | D119: main-2 | E119: =VLOOKUP(D119,'Win Methods'!$C$4:$F$379,4,FALSE) -> 0.5 | F119: main-19 | G119: =VLOOKUP(F119,'Win Methods'!$C$4:$F$379,4,FALSE) -> 5 | H119: main-3 | I119: =VLOOKUP(H119,'Win Methods'!$C$4:$F$379,4,FALSE) -> 1 | K119: =VLOOKUP(J119,'Win Methods'!$C$4:$F$379,4,FALSE) -> 0 | M119: =VLOOKUP(L119,'Win Methods'!$C$4:$F$379,4,FALSE) -> 0 | O119: =VLOOKUP(N119,'Win Methods'!$C$4:$F$379,4,FALSE) -> 0 | Q119: =VLOOKUP(P119,'Win Methods'!$C$4:$F$379,4,FALSE) -> 0 | S119: =VLOOKUP(R119,'Win Methods'!$C$4:$F$379,4,FALSE) -> 0 | U119: =VLOOKUP(T119,'Win Methods'!$C$4:$F$379,4,FALSE) -> 0 | W119: =VLOOKUP(V119,'Win Methods'!$C$4:$F$379,4,FALSE) -> 0 | X119: =D119&"|"&F119&"|"&H119&"|"&J119&"|"&L119&"|"&N119&"|"&P119&"|"&R119&"|"&T119&"|"&V119 -> main-2|main-19|main-3|||||||
B120: 117 | C120: =(E120+G120+I120+K120+M120+O120+Q120+S120+U120+W120) -> 7.1 | D120: main-4 | E120: =VLOOKUP(D120,'Win Methods'!$C$4:$F$379,4,FALSE) -> 2 | F120: main-13 | G120: =VLOOKUP(F120,'Win Methods'!$C$4:$F$379,4,FALSE) -> 5 | H120: main-0 | I120: =VLOOKUP(H120,'Win Methods'!$C$4:$F$379,4,FALSE) -> 0.1 | K120: =VLOOKUP(J120,'Win Methods'!$C$4:$F$379,4,FALSE) -> 0 | M120: =VLOOKUP(L120,'Win Methods'!$C$4:$F$379,4,FALSE) -> 0 | O120: =VLOOKUP(N120,'Win Methods'!$C$4:$F$379,4,FALSE) -> 0 | Q120: =VLOOKUP(P120,'Win Methods'!$C$4:$F$379,4,FALSE) -> 0 | S120: =VLOOKUP(R120,'Win Methods'!$C$4:$F$379,4,FALSE) -> 0 | U120: =VLOOKUP(T120,'Win Methods'!$C$4:$F$379,4,FALSE) -> 0 | W120: =VLOOKUP(V120,'Win Methods'!$C$4:$F$379,4,FALSE) -> 0 | X120: =D120&"|"&F120&"|"&H120&"|"&J120&"|"&L120&"|"&N120&"|"&P120&"|"&R120&"|"&T120&"|"&V120 -> main-4|main-13|main-0|||||||
B121: 118 | C121: =(E121+G121+I121+K121+M121+O121+Q121+S121+U121+W121) -> 13.2 | D121: main-1 | E121: =VLOOKUP(D121,'Win Methods'!$C$4:$F$379,4,FALSE) -> 0.2 | F121: main-18 | G121: =VLOOKUP(F121,'Win Methods'!$C$4:$F$379,4,FALSE) -> 3 | H121: main-26 | I121: =VLOOKUP(H121,'Win Methods'!$C$4:$F$379,4,FALSE) -> 10 | K121: =VLOOKUP(J121,'Win Methods'!$C$4:$F$379,4,FALSE) -> 0 | M121: =VLOOKUP(L121,'Win Methods'!$C$4:$F$379,4,FALSE) -> 0 | O121: =VLOOKUP(N121,'Win Methods'!$C$4:$F$379,4,FALSE) -> 0 | Q121: =VLOOKUP(P121,'Win Methods'!$C$4:$F$379,4,FALSE) -> 0 | S121: =VLOOKUP(R121,'Win Methods'!$C$4:$F$379,4,FALSE) -> 0 | U121: =VLOOKUP(T121,'Win Methods'!$C$4:$F$379,4,FALSE) -> 0 | W121: =VLOOKUP(V121,'Win Methods'!$C$4:$F$379,4,FALSE) -> 0 | X121: =D121&"|"&F121&"|"&H121&"|"&J121&"|"&L121&"|"&N121&"|"&P121&"|"&R121&"|"&T121&"|"&V121 -> main-1|main-18|main-26|||||||
B122: 119 | C122: =(E122+G122+I122+K122+M122+O122+Q122+S122+U122+W122) -> 10.1 | D122: main-5 | E122: =VLOOKUP(D122,'Win Methods'!$C$4:$F$379,4,FALSE) -> 5 | F122: main-25 | G122: =VLOOKUP(F122,'Win Methods'!$C$4:$F$379,4,FALSE) -> 5 | H122: main-0 | I122: =VLOOKUP(H122,'Win Methods'!$C$4:$F$379,4,FALSE) -> 0.1 | K122: =VLOOKUP(J122,'Win Methods'!$C$4:$F$379,4,FALSE) -> 0 | M122: =VLOOKUP(L122,'Win Methods'!$C$4:$F$379,4,FALSE) -> 0 | O122: =VLOOKUP(N122,'Win Methods'!$C$4:$F$379,4,FALSE) -> 0 | Q122: =VLOOKUP(P122,'Win Methods'!$C$4:$F$379,4,FALSE) -> 0 | S122: =VLOOKUP(R122,'Win Methods'!$C$4:$F$379,4,FALSE) -> 0 | U122: =VLOOKUP(T122,'Win Methods'!$C$4:$F$379,4,FALSE) -> 0 | W122: =VLOOKUP(V122,'Win Methods'!$C$4:$F$379,4,FALSE) -> 0 | X122: =D122&"|"&F122&"|"&H122&"|"&J122&"|"&L122&"|"&N122&"|"&P122&"|"&R122&"|"&T122&"|"&V122 -> main-5|main-25|main-0|||||||
B123: 120 | C123: =(E123+G123+I123+K123+M123+O123+Q123+S123+U123+W123) -> 12.1 | D123: main-4 | E123: =VLOOKUP(D123,'Win Methods'!$C$4:$F$379,4,FALSE) -> 2 | F123: main-0 | G123: =VLOOKUP(F123,'Win Methods'!$C$4:$F$379,4,FALSE) -> 0.1 | H123: main-20 | I123: =VLOOKUP(H123,'Win Methods'!$C$4:$F$379,4,FALSE) -> 10 | K123: =VLOOKUP(J123,'Win Methods'!$C$4:$F$379,4,FALSE) -> 0 | M123: =VLOOKUP(L123,'Win Methods'!$C$4:$F$379,4,FALSE) -> 0 | O123: =VLOOKUP(N123,'Win Methods'!$C$4:$F$379,4,FALSE) -> 0 | Q123: =VLOOKUP(P123,'Win Methods'!$C$4:$F$379,4,FALSE) -> 0 | S123: =VLOOKUP(R123,'Win Methods'!$C$4:$F$379,4,FALSE) -> 0 | U123: =VLOOKUP(T123,'Win Methods'!$C$4:$F$379,4,FALSE) -> 0 | W123: =VLOOKUP(V123,'Win Methods'!$C$4:$F$379,4,FALSE) -> 0 | X123: =D123&"|"&F123&"|"&H123&"|"&J123&"|"&L123&"|"&N123&"|"&P123&"|"&R123&"|"&T123&"|"&V123 -> main-4|main-0|main-20|||||||
B124: 121 | C124: =(E124+G124+I124+K124+M124+O124+Q124+S124+U124+W124) -> 12 | D124: main-11 | E124: =VLOOKUP(D124,'Win Methods'!$C$4:$F$379,4,FALSE) -> 2 | F124: main-25 | G124: =VLOOKUP(F124,'Win Methods'!$C$4:$F$379,4,FALSE) -> 5 | H124: main-5 | I124: =VLOOKUP(H124,'Win Methods'!$C$4:$F$379,4,FALSE) -> 5 | K124: =VLOOKUP(J124,'Win Methods'!$C$4:$F$379,4,FALSE) -> 0 | M124: =VLOOKUP(L124,'Win Methods'!$C$4:$F$379,4,FALSE) -> 0 | O124: =VLOOKUP(N124,'Win Methods'!$C$4:$F$379,4,FALSE) -> 0 | Q124: =VLOOKUP(P124,'Win Methods'!$C$4:$F$379,4,FALSE) -> 0 | S124: =VLOOKUP(R124,'Win Methods'!$C$4:$F$379,4,FALSE) -> 0 | U124: =VLOOKUP(T124,'Win Methods'!$C$4:$F$379,4,FALSE) -> 0 | W124: =VLOOKUP(V124,'Win Methods'!$C$4:$F$379,4,FALSE) -> 0 | X124: =D124&"|"&F124&"|"&H124&"|"&J124&"|"&L124&"|"&N124&"|"&P124&"|"&R124&"|"&T124&"|"&V124 -> main-11|main-25|main-5|||||||
B125: 122 | C125: =(E125+G125+I125+K125+M125+O125+Q125+S125+U125+W125) -> 13 | D125: main-18 | E125: =VLOOKUP(D125,'Win Methods'!$C$4:$F$379,4,FALSE) -> 3 | F125: main-19 | G125: =VLOOKUP(F125,'Win Methods'!$C$4:$F$379,4,FALSE) -> 5 | H125: main-5 | I125: =VLOOKUP(H125,'Win Methods'!$C$4:$F$379,4,FALSE) -> 5 | K125: =VLOOKUP(J125,'Win Methods'!$C$4:$F$379,4,FALSE) -> 0 | M125: =VLOOKUP(L125,'Win Methods'!$C$4:$F$379,4,FALSE) -> 0 | O125: =VLOOKUP(N125,'Win Methods'!$C$4:$F$379,4,FALSE) -> 0 | Q125: =VLOOKUP(P125,'Win Methods'!$C$4:$F$379,4,FALSE) -> 0 | S125: =VLOOKUP(R125,'Win Methods'!$C$4:$F$379,4,FALSE) -> 0 | U125: =VLOOKUP(T125,'Win Methods'!$C$4:$F$379,4,FALSE) -> 0 | W125: =VLOOKUP(V125,'Win Methods'!$C$4:$F$379,4,FALSE) -> 0 | X125: =D125&"|"&F125&"|"&H125&"|"&J125&"|"&L125&"|"&N125&"|"&P125&"|"&R125&"|"&T125&"|"&V125 -> main-18|main-19|main-5|||||||
B126: 123 | C126: =(E126+G126+I126+K126+M126+O126+Q126+S126+U126+W126) -> 13 | D126: main-3 | E126: =VLOOKUP(D126,'Win Methods'!$C$4:$F$379,4,FALSE) -> 1 | F126: main-20 | G126: =VLOOKUP(F126,'Win Methods'!$C$4:$F$379,4,FALSE) -> 10 | H126: main-4 | I126: =VLOOKUP(H126,'Win Methods'!$C$4:$F$379,4,FALSE) -> 2 | K126: =VLOOKUP(J126,'Win Methods'!$C$4:$F$379,4,FALSE) -> 0 | M126: =VLOOKUP(L126,'Win Methods'!$C$4:$F$379,4,FALSE) -> 0 | O126: =VLOOKUP(N126,'Win Methods'!$C$4:$F$379,4,FALSE) -> 0 | Q126: =VLOOKUP(P126,'Win Methods'!$C$4:$F$379,4,FALSE) -> 0 | S126: =VLOOKUP(R126,'Win Methods'!$C$4:$F$379,4,FALSE) -> 0 | U126: =VLOOKUP(T126,'Win Methods'!$C$4:$F$379,4,FALSE) -> 0 | W126: =VLOOKUP(V126,'Win Methods'!$C$4:$F$379,4,FALSE) -> 0 | X126: =D126&"|"&F126&"|"&H126&"|"&J126&"|"&L126&"|"&N126&"|"&P126&"|"&R126&"|"&T126&"|"&V126 -> main-3|main-20|main-4|||||||
B127: 124 | C127: =(E127+G127+I127+K127+M127+O127+Q127+S127+U127+W127) -> 11 | D127: main-3 | E127: =VLOOKUP(D127,'Win Methods'!$C$4:$F$379,4,FALSE) -> 1 | F127: main-5 | G127: =VLOOKUP(F127,'Win Methods'!$C$4:$F$379,4,FALSE) -> 5 | H127: main-19 | I127: =VLOOKUP(H127,'Win Methods'!$C$4:$F$379,4,FALSE) -> 5 | K127: =VLOOKUP(J127,'Win Methods'!$C$4:$F$379,4,FALSE) -> 0 | M127: =VLOOKUP(L127,'Win Methods'!$C$4:$F$379,4,FALSE) -> 0 | O127: =VLOOKUP(N127,'Win Methods'!$C$4:$F$379,4,FALSE) -> 0 | Q127: =VLOOKUP(P127,'Win Methods'!$C$4:$F$379,4,FALSE) -> 0 | S127: =VLOOKUP(R127,'Win Methods'!$C$4:$F$379,4,FALSE) -> 0 | U127: =VLOOKUP(T127,'Win Methods'!$C$4:$F$379,4,FALSE) -> 0 | W127: =VLOOKUP(V127,'Win Methods'!$C$4:$F$379,4,FALSE) -> 0 | X127: =D127&"|"&F127&"|"&H127&"|"&J127&"|"&L127&"|"&N127&"|"&P127&"|"&R127&"|"&T127&"|"&V127 -> main-3|main-5|main-19|||||||
B128: 125 | C128: =(E128+G128+I128+K128+M128+O128+Q128+S128+U128+W128) -> 15.2 | D128: main-5 | E128: =VLOOKUP(D128,'Win Methods'!$C$4:$F$379,4,FALSE) -> 5 | F128: main-26 | G128: =VLOOKUP(F128,'Win Methods'!$C$4:$F$379,4,FALSE) -> 10 | H128: main-1 | I128: =VLOOKUP(H128,'Win Methods'!$C$4:$F$379,4,FALSE) -> 0.2 | K128: =VLOOKUP(J128,'Win Methods'!$C$4:$F$379,4,FALSE) -> 0 | M128: =VLOOKUP(L128,'Win Methods'!$C$4:$F$379,4,FALSE) -> 0 | O128: =VLOOKUP(N128,'Win Methods'!$C$4:$F$379,4,FALSE) -> 0 | Q128: =VLOOKUP(P128,'Win Methods'!$C$4:$F$379,4,FALSE) -> 0 | S128: =VLOOKUP(R128,'Win Methods'!$C$4:$F$379,4,FALSE) -> 0 | U128: =VLOOKUP(T128,'Win Methods'!$C$4:$F$379,4,FALSE) -> 0 | W128: =VLOOKUP(V128,'Win Methods'!$C$4:$F$379,4,FALSE) -> 0 | X128: =D128&"|"&F128&"|"&H128&"|"&J128&"|"&L128&"|"&N128&"|"&P128&"|"&R128&"|"&T128&"|"&V128 -> main-5|main-26|main-1|||||||
... B133: 130 | C133: =(E133+G133+I133+K133+M133+O133+Q133+S133+U133+W133) -> 103 | D133: main-4 | E133: =VLOOKUP(D133,'Win Methods'!$C$4:$F$379,4,FALSE) -> 2 | F133: main-28 | G133: =VLOOKUP(F133,'Win Methods'!$C$4:$F$379,4,FALSE) -> 100 | H133: main-3 | I133: =VLOOKUP(H133,'Win Methods'!$C$4:$F$379,4,FALSE) -> 1 | K133: =VLOOKUP(J133,'Win Methods'!$C$4:$F$379,4,FALSE) -> 0 | M133: =VLOOKUP(L133,'Win Methods'!$C$4:$F$379,4,FALSE) -> 0 | O133: =VLOOKUP(N133,'Win Methods'!$C$4:$F$379,4,FALSE) -> 0 | Q133: =VLOOKUP(P133,'Win Methods'!$C$4:$F$379,4,FALSE) -> 0 | S133: =VLOOKUP(R133,'Win Methods'!$C$4:$F$379,4,FALSE) -> 0 | U133: =VLOOKUP(T133,'Win Methods'!$C$4:$F$379,4,FALSE) -> 0 | W133: =VLOOKUP(V133,'Win Methods'!$C$4:$F$379,4,FALSE) -> 0 | X133: =D133&"|"&F133&"|"&H133&"|"&J133&"|"&L133&"|"&N133&"|"&P133&"|"&R133&"|"&T133&"|"&V133 -> main-4|main-28|main-3|||||||
B134: 131 | C134: =(E134+G134+I134+K134+M134+O134+Q134+S134+U134+W134) -> 5.3 | D134: main-4 | E134: =VLOOKUP(D134,'Win Methods'!$C$4:$F$379,4,FALSE) -> 2 | F134: main-0 | G134: =VLOOKUP(F134,'Win Methods'!$C$4:$F$379,4,FALSE) -> 0.1 | H134: main-1 | I134: =VLOOKUP(H134,'Win Methods'!$C$4:$F$379,4,FALSE) -> 0.2 | J134: main-18 | K134: =VLOOKUP(J134,'Win Methods'!$C$4:$F$379,4,FALSE) -> 3 | M134: =VLOOKUP(L134,'Win Methods'!$C$4:$F$379,4,FALSE) -> 0 | O134: =VLOOKUP(N134,'Win Methods'!$C$4:$F$379,4,FALSE) -> 0 | Q134: =VLOOKUP(P134,'Win Methods'!$C$4:$F$379,4,FALSE) -> 0 | S134: =VLOOKUP(R134,'Win Methods'!$C$4:$F$379,4,FALSE) -> 0 | U134: =VLOOKUP(T134,'Win Methods'!$C$4:$F$379,4,FALSE) -> 0 | W134: =VLOOKUP(V134,'Win Methods'!$C$4:$F$379,4,FALSE) -> 0 | X134: =D134&"|"&F134&"|"&H134&"|"&J134&"|"&L134&"|"&N134&"|"&P134&"|"&R134&"|"&T134&"|"&V134 -> main-4|main-0|main-1|main-18||||||
B135: 132 | C135: =(E135+G135+I135+K135+M135+O135+Q135+S135+U135+W135) -> 7.2 | D135: main-0 | E135: =VLOOKUP(D135,'Win Methods'!$C$4:$F$379,4,FALSE) -> 0.1 | F135: main-4 | G135: =VLOOKUP(F135,'Win Methods'!$C$4:$F$379,4,FALSE) -> 2 | H135: main-0 | I135: =VLOOKUP(H135,'Win Methods'!$C$4:$F$379,4,FALSE) -> 0.1 | J135: main-19 | K135: =VLOOKUP(J135,'Win Methods'!$C$4:$F$379,4,FALSE) -> 5 | M135: =VLOOKUP(L135,'Win Methods'!$C$4:$F$379,4,FALSE) -> 0 | O135: =VLOOKUP(N135,'Win Methods'!$C$4:$F$379,4,FALSE) -> 0 | Q135: =VLOOKUP(P135,'Win Methods'!$C$4:$F$379,4,FALSE) -> 0 | S135: =VLOOKUP(R135,'Win Methods'!$C$4:$F$379,4,FALSE) -> 0 | U135: =VLOOKUP(T135,'Win Methods'!$C$4:$F$379,4,FALSE) -> 0 | W135: =VLOOKUP(V135,'Win Methods'!$C$4:$F$379,4,FALSE) -> 0 | X135: =D135&"|"&F135&"|"&H135&"|"&J135&"|"&L135&"|"&N135&"|"&P135&"|"&R135&"|"&T135&"|"&V135 -> main-0|main-4|main-0|main-19||||||
B136: 133 | C136: =(E136+G136+I136+K136+M136+O136+Q136+S136+U136+W136) -> 18.1 | D136: main-0 | E136: =VLOOKUP(D136,'Win Methods'!$C$4:$F$379,4,FALSE) -> 0.1 | F136: main-13 | G136: =VLOOKUP(F136,'Win Methods'!$C$4:$F$379,4,FALSE) -> 5 | H136: main-26 | I136: =VLOOKUP(H136,'Win Methods'!$C$4:$F$379,4,FALSE) -> 10 | J136: main-18 | K136: =VLOOKUP(J136,'Win Methods'!$C$4:$F$379,4,FALSE) -> 3 | M136: =VLOOKUP(L136,'Win Methods'!$C$4:$F$379,4,FALSE) -> 0 | O136: =VLOOKUP(N136,'Win Methods'!$C$4:$F$379,4,FALSE) -> 0 | Q136: =VLOOKUP(P136,'Win Methods'!$C$4:$F$379,4,FALSE) -> 0 | S136: =VLOOKUP(R136,'Win Methods'!$C$4:$F$379,4,FALSE) -> 0 | U136: =VLOOKUP(T136,'Win Methods'!$C$4:$F$379,4,FALSE) -> 0 | W136: =VLOOKUP(V136,'Win Methods'!$C$4:$F$379,4,FALSE) -> 0 | X136: =D136&"|"&F136&"|"&H136&"|"&J136&"|"&L136&"|"&N136&"|"&P136&"|"&R136&"|"&T136&"|"&V136 -> main-0|main-13|main-26|main-18||||||
B137: 134 | C137: =(E137+G137+I137+K137+M137+O137+Q137+S137+U137+W137) -> 15.1 | D137: main-5 | E137: =VLOOKUP(D137,'Win Methods'!$C$4:$F$379,4,FALSE) -> 5 | F137: main-13 | G137: =VLOOKUP(F137,'Win Methods'!$C$4:$F$379,4,FALSE) -> 5 | H137: main-25 | I137: =VLOOKUP(H137,'Win Methods'!$C$4:$F$379,4,FALSE) -> 5 | J137: main-0 | K137: =VLOOKUP(J137,'Win Methods'!$C$4:$F$379,4,FALSE) -> 0.1 | M137: =VLOOKUP(L137,'Win Methods'!$C$4:$F$379,4,FALSE) -> 0 | O137: =VLOOKUP(N137,'Win Methods'!$C$4:$F$379,4,FALSE) -> 0 | Q137: =VLOOKUP(P137,'Win Methods'!$C$4:$F$379,4,FALSE) -> 0 | S137: =VLOOKUP(R137,'Win Methods'!$C$4:$F$379,4,FALSE) -> 0 | U137: =VLOOKUP(T137,'Win Methods'!$C$4:$F$379,4,FALSE) -> 0 | W137: =VLOOKUP(V137,'Win Methods'!$C$4:$F$379,4,FALSE) -> 0 | X137: =D137&"|"&F137&"|"&H137&"|"&J137&"|"&L137&"|"&N137&"|"&P137&"|"&R137&"|"&T137&"|"&V137 -> main-5|main-13|main-25|main-0||||||
B138: 135 | C138: =(E138+G138+I138+K138+M138+O138+Q138+S138+U138+W138) -> 14 | D138: main-18 | E138: =VLOOKUP(D138,'Win Methods'!$C$4:$F$379,4,FALSE) -> 3 | F138: main-5 | G138: =VLOOKUP(F138,'Win Methods'!$C$4:$F$379,4,FALSE) -> 5 | H138: main-13 | I138: =VLOOKUP(H138,'Win Methods'!$C$4:$F$379,4,FALSE) -> 5 | J138: main-3 | K138: =VLOOKUP(J138,'Win Methods'!$C$4:$F$379,4,FALSE) -> 1 | M138: =VLOOKUP(L138,'Win Methods'!$C$4:$F$379,4,FALSE) -> 0 | O138: =VLOOKUP(N138,'Win Methods'!$C$4:$F$379,4,FALSE) -> 0 | Q138: =VLOOKUP(P138,'Win Methods'!$C$4:$F$379,4,FALSE) -> 0 | S138: =VLOOKUP(R138,'Win Methods'!$C$4:$F$379,4,FALSE) -> 0 | U138: =VLOOKUP(T138,'Win Methods'!$C$4:$F$379,4,FALSE) -> 0 | W138: =VLOOKUP(V138,'Win Methods'!$C$4:$F$379,4,FALSE) -> 0 | X138: =D138&"|"&F138&"|"&H138&"|"&J138&"|"&L138&"|"&N138&"|"&P138&"|"&R138&"|"&T138&"|"&V138 -> main-18|main-5|main-13|main-3||||||
B139: 136 | C139: =(E139+G139+I139+K139+M139+O139+Q139+S139+U139+W139) -> 21 | D139: main-3 | E139: =VLOOKUP(D139,'Win Methods'!$C$4:$F$379,4,FALSE) -> 1 | F139: main-19 | G139: =VLOOKUP(F139,'Win Methods'!$C$4:$F$379,4,FALSE) -> 5 | H139: main-13 | I139: =VLOOKUP(H139,'Win Methods'!$C$4:$F$379,4,FALSE) -> 5 | J139: main-26 | K139: =VLOOKUP(J139,'Win Methods'!$C$4:$F$379,4,FALSE) -> 10 | M139: =VLOOKUP(L139,'Win Methods'!$C$4:$F$379,4,FALSE) -> 0 | O139: =VLOOKUP(N139,'Win Methods'!$C$4:$F$379,4,FALSE) -> 0 | Q139: =VLOOKUP(P139,'Win Methods'!$C$4:$F$379,4,FALSE) -> 0 | S139: =VLOOKUP(R139,'Win Methods'!$C$4:$F$379,4,FALSE) -> 0 | U139: =VLOOKUP(T139,'Win Methods'!$C$4:$F$379,4,FALSE) -> 0 | W139: =VLOOKUP(V139,'Win Methods'!$C$4:$F$379,4,FALSE) -> 0 | X139: =D139&"|"&F139&"|"&H139&"|"&J139&"|"&L139&"|"&N139&"|"&P139&"|"&R139&"|"&T139&"|"&V139 -> main-3|main-19|main-13|main-26||||||
B140: 137 | C140: =(E140+G140+I140+K140+M140+O140+Q140+S140+U140+W140) -> 27.2 | D140: main-19 | E140: =VLOOKUP(D140,'Win Methods'!$C$4:$F$379,4,FALSE) -> 5 | F140: main-4 | G140: =VLOOKUP(F140,'Win Methods'!$C$4:$F$379,4,FALSE) -> 2 | H140: main-1 | I140: =VLOOKUP(H140,'Win Methods'!$C$4:$F$379,4,FALSE) -> 0.2 | J140: main-15 | K140: =VLOOKUP(J140,'Win Methods'!$C$4:$F$379,4,FALSE) -> 20 | M140: =VLOOKUP(L140,'Win Methods'!$C$4:$F$379,4,FALSE) -> 0 | O140: =VLOOKUP(N140,'Win Methods'!$C$4:$F$379,4,FALSE) -> 0 | Q140: =VLOOKUP(P140,'Win Methods'!$C$4:$F$379,4,FALSE) -> 0 | S140: =VLOOKUP(R140,'Win Methods'!$C$4:$F$379,4,FALSE) -> 0 | U140: =VLOOKUP(T140,'Win Methods'!$C$4:$F$379,4,FALSE) -> 0 | W140: =VLOOKUP(V140,'Win Methods'!$C$4:$F$379,4,FALSE) -> 0 | X140: =D140&"|"&F140&"|"&H140&"|"&J140&"|"&L140&"|"&N140&"|"&P140&"|"&R140&"|"&T140&"|"&V140 -> main-19|main-4|main-1|main-15||||||
B141: 138 | C141: =(E141+G141+I141+K141+M141+O141+Q141+S141+U141+W141) -> 31 | D141: main-5 | E141: =VLOOKUP(D141,'Win Methods'!$C$4:$F$379,4,FALSE) -> 5 | F141: main-3 | G141: =VLOOKUP(F141,'Win Methods'!$C$4:$F$379,4,FALSE) -> 1 | H141: main-5 | I141: =VLOOKUP(H141,'Win Methods'!$C$4:$F$379,4,FALSE) -> 5 | J141: main-15 | K141: =VLOOKUP(J141,'Win Methods'!$C$4:$F$379,4,FALSE) -> 20 | M141: =VLOOKUP(L141,'Win Methods'!$C$4:$F$379,4,FALSE) -> 0 | O141: =VLOOKUP(N141,'Win Methods'!$C$4:$F$379,4,FALSE) -> 0 | Q141: =VLOOKUP(P141,'Win Methods'!$C$4:$F$379,4,FALSE) -> 0 | S141: =VLOOKUP(R141,'Win Methods'!$C$4:$F$379,4,FALSE) -> 0 | U141: =VLOOKUP(T141,'Win Methods'!$C$4:$F$379,4,FALSE) -> 0 | W141: =VLOOKUP(V141,'Win Methods'!$C$4:$F$379,4,FALSE) -> 0 | X141: =D141&"|"&F141&"|"&H141&"|"&J141&"|"&L141&"|"&N141&"|"&P141&"|"&R141&"|"&T141&"|"&V141 -> main-5|main-3|main-5|main-15||||||
B142: 139 | C142: =(E142+G142+I142+K142+M142+O142+Q142+S142+U142+W142) -> 105.1 | D142: main-4 | E142: =VLOOKUP(D142,'Win Methods'!$C$4:$F$379,4,FALSE) -> 2 | F142: main-18 | G142: =VLOOKUP(F142,'Win Methods'!$C$4:$F$379,4,FALSE) -> 3 | H142: main-28 | I142: =VLOOKUP(H142,'Win Methods'!$C$4:$F$379,4,FALSE) -> 100 | J142: main-0 | K142: =VLOOKUP(J142,'Win Methods'!$C$4:$F$379,4,FALSE) -> 0.1 | M142: =VLOOKUP(L142,'Win Methods'!$C$4:$F$379,4,FALSE) -> 0 | O142: =VLOOKUP(N142,'Win Methods'!$C$4:$F$379,4,FALSE) -> 0 | Q142: =VLOOKUP(P142,'Win Methods'!$C$4:$F$379,4,FALSE) -> 0 | S142: =VLOOKUP(R142,'Win Methods'!$C$4:$F$379,4,FALSE) -> 0 | U142: =VLOOKUP(T142,'Win Methods'!$C$4:$F$379,4,FALSE) -> 0 | W142: =VLOOKUP(V142,'Win Methods'!$C$4:$F$379,4,FALSE) -> 0 | X142: =D142&"|"&F142&"|"&H142&"|"&J142&"|"&L142&"|"&N142&"|"&P142&"|"&R142&"|"&T142&"|"&V142 -> main-4|main-18|main-28|main-0||||||
B143: 140 | C143: =(E143+G143+I143+K143+M143+O143+Q143+S143+U143+W143) -> 11.2 | D143: main-19 | E143: =VLOOKUP(D143,'Win Methods'!$C$4:$F$379,4,FALSE) -> 5 | F143: main-3 | G143: =VLOOKUP(F143,'Win Methods'!$C$4:$F$379,4,FALSE) -> 1 | H143: main-1 | I143: =VLOOKUP(H143,'Win Methods'!$C$4:$F$379,4,FALSE) -> 0.2 | J143: main-18 | K143: =VLOOKUP(J143,'Win Methods'!$C$4:$F$379,4,FALSE) -> 3 | L143: main-4 | M143: =VLOOKUP(L143,'Win Methods'!$C$4:$F$379,4,FALSE) -> 2 | O143: =VLOOKUP(N143,'Win Methods'!$C$4:$F$379,4,FALSE) -> 0 | Q143: =VLOOKUP(P143,'Win Methods'!$C$4:$F$379,4,FALSE) -> 0 | S143: =VLOOKUP(R143,'Win Methods'!$C$4:$F$379,4,FALSE) -> 0 | U143: =VLOOKUP(T143,'Win Methods'!$C$4:$F$379,4,FALSE) -> 0 | W143: =VLOOKUP(V143,'Win Methods'!$C$4:$F$379,4,FALSE) -> 0 | X143: =D143&"|"&F143&"|"&H143&"|"&J143&"|"&L143&"|"&N143&"|"&P143&"|"&R143&"|"&T143&"|"&V143 -> main-19|main-3|main-1|main-18|main-4|||||
B144: 141 | C144: =(E144+G144+I144+K144+M144+O144+Q144+S144+U144+W144) -> 17.1 | D144: main-26 | E144: =VLOOKUP(D144,'Win Methods'!$C$4:$F$379,4,FALSE) -> 10 | F144: main-0 | G144: =VLOOKUP(F144,'Win Methods'!$C$4:$F$379,4,FALSE) -> 0.1 | H144: main-3 | I144: =VLOOKUP(H144,'Win Methods'!$C$4:$F$379,4,FALSE) -> 1 | J144: main-18 | K144: =VLOOKUP(J144,'Win Methods'!$C$4:$F$379,4,FALSE) -> 3 | L144: main-18 | M144: =VLOOKUP(L144,'Win Methods'!$C$4:$F$379,4,FALSE) -> 3 | O144: =VLOOKUP(N144,'Win Methods'!$C$4:$F$379,4,FALSE) -> 0 | Q144: =VLOOKUP(P144,'Win Methods'!$C$4:$F$379,4,FALSE) -> 0 | S144: =VLOOKUP(R144,'Win Methods'!$C$4:$F$379,4,FALSE) -> 0 | U144: =VLOOKUP(T144,'Win Methods'!$C$4:$F$379,4,FALSE) -> 0 | W144: =VLOOKUP(V144,'Win Methods'!$C$4:$F$379,4,FALSE) -> 0 | X144: =D144&"|"&F144&"|"&H144&"|"&J144&"|"&L144&"|"&N144&"|"&P144&"|"&R144&"|"&T144&"|"&V144 -> main-26|main-0|main-3|main-18|main-18|||||
B145: 142 | C145: =(E145+G145+I145+K145+M145+O145+Q145+S145+U145+W145) -> 9.5 | D145: main-4 | E145: =VLOOKUP(D145,'Win Methods'!$C$4:$F$379,4,FALSE) -> 2 | F145: main-2 | G145: =VLOOKUP(F145,'Win Methods'!$C$4:$F$379,4,FALSE) -> 0.5 | H145: main-5 | I145: =VLOOKUP(H145,'Win Methods'!$C$4:$F$379,4,FALSE) -> 5 | J145: main-3 | K145: =VLOOKUP(J145,'Win Methods'!$C$4:$F$379,4,FALSE) -> 1 | L145: main-3 | M145: =VLOOKUP(L145,'Win Methods'!$C$4:$F$379,4,FALSE) -> 1 | O145: =VLOOKUP(N145,'Win Methods'!$C$4:$F$379,4,FALSE) -> 0 | Q145: =VLOOKUP(P145,'Win Methods'!$C$4:$F$379,4,FALSE) -> 0 | S145: =VLOOKUP(R145,'Win Methods'!$C$4:$F$379,4,FALSE) -> 0 | U145: =VLOOKUP(T145,'Win Methods'!$C$4:$F$379,4,FALSE) -> 0 | W145: =VLOOKUP(V145,'Win Methods'!$C$4:$F$379,4,FALSE) -> 0 | X145: =D145&"|"&F145&"|"&H145&"|"&J145&"|"&L145&"|"&N145&"|"&P145&"|"&R145&"|"&T145&"|"&V145 -> main-4|main-2|main-5|main-3|main-3|||||
B146: 143 | C146: =(E146+G146+I146+K146+M146+O146+Q146+S146+U146+W146) -> 12.1 | D146: main-5 | E146: =VLOOKUP(D146,'Win Methods'!$C$4:$F$379,4,FALSE) -> 5 | F146: main-0 | G146: =VLOOKUP(F146,'Win Methods'!$C$4:$F$379,4,FALSE) -> 0.1 | H146: main-4 | I146: =VLOOKUP(H146,'Win Methods'!$C$4:$F$379,4,FALSE) -> 2 | J146: main-4 | K146: =VLOOKUP(J146,'Win Methods'!$C$4:$F$379,4,FALSE) -> 2 | L146: main-18 | M146: =VLOOKUP(L146,'Win Methods'!$C$4:$F$379,4,FALSE) -> 3 | O146: =VLOOKUP(N146,'Win Methods'!$C$4:$F$379,4,FALSE) -> 0 | Q146: =VLOOKUP(P146,'Win Methods'!$C$4:$F$379,4,FALSE) -> 0 | S146: =VLOOKUP(R146,'Win Methods'!$C$4:$F$379,4,FALSE) -> 0 | U146: =VLOOKUP(T146,'Win Methods'!$C$4:$F$379,4,FALSE) -> 0 | W146: =VLOOKUP(V146,'Win Methods'!$C$4:$F$379,4,FALSE) -> 0 | X146: =D146&"|"&F146&"|"&H146&"|"&J146&"|"&L146&"|"&N146&"|"&P146&"|"&R146&"|"&T146&"|"&V146 -> main-5|main-0|main-4|main-4|main-18|||||
B147: 144 | C147: =(E147+G147+I147+K147+M147+O147+Q147+S147+U147+W147) -> 19.1 | D147: main-5 | E147: =VLOOKUP(D147,'Win Methods'!$C$4:$F$379,4,FALSE) -> 5 | F147: main-3 | G147: =VLOOKUP(F147,'Win Methods'!$C$4:$F$379,4,FALSE) -> 1 | H147: main-18 | I147: =VLOOKUP(H147,'Win Methods'!$C$4:$F$379,4,FALSE) -> 3 | J147: main-0 | K147: =VLOOKUP(J147,'Win Methods'!$C$4:$F$379,4,FALSE) -> 0.1 | L147: main-26 | M147: =VLOOKUP(L147,'Win Methods'!$C$4:$F$379,4,FALSE) -> 10 | O147: =VLOOKUP(N147,'Win Methods'!$C$4:$F$379,4,FALSE) -> 0 | Q147: =VLOOKUP(P147,'Win Methods'!$C$4:$F$379,4,FALSE) -> 0 | S147: =VLOOKUP(R147,'Win Methods'!$C$4:$F$379,4,FALSE) -> 0 | U147: =VLOOKUP(T147,'Win Methods'!$C$4:$F$379,4,FALSE) -> 0 | W147: =VLOOKUP(V147,'Win Methods'!$C$4:$F$379,4,FALSE) -> 0 | X147: =D147&"|"&F147&"|"&H147&"|"&J147&"|"&L147&"|"&N147&"|"&P147&"|"&R147&"|"&T147&"|"&V147 -> main-5|main-3|main-18|main-0|main-26|||||
B148: 145 | C148: =(E148+G148+I148+K148+M148+O148+Q148+S148+U148+W148) -> 23.2 | D148: main-3 | E148: =VLOOKUP(D148,'Win Methods'!$C$4:$F$379,4,FALSE) -> 1 | F148: main-1 | G148: =VLOOKUP(F148,'Win Methods'!$C$4:$F$379,4,FALSE) -> 0.2 | H148: main-4 | I148: =VLOOKUP(H148,'Win Methods'!$C$4:$F$379,4,FALSE) -> 2 | J148: main-26 | K148: =VLOOKUP(J148,'Win Methods'!$C$4:$F$379,4,FALSE) -> 10 | L148: main-26 | M148: =VLOOKUP(L148,'Win Methods'!$C$4:$F$379,4,FALSE) -> 10 | O148: =VLOOKUP(N148,'Win Methods'!$C$4:$F$379,4,FALSE) -> 0 | Q148: =VLOOKUP(P148,'Win Methods'!$C$4:$F$379,4,FALSE) -> 0 | S148: =VLOOKUP(R148,'Win Methods'!$C$4:$F$379,4,FALSE) -> 0 | U148: =VLOOKUP(T148,'Win Methods'!$C$4:$F$379,4,FALSE) -> 0 | W148: =VLOOKUP(V148,'Win Methods'!$C$4:$F$379,4,FALSE) -> 0 | X148: =D148&"|"&F148&"|"&H148&"|"&J148&"|"&L148&"|"&N148&"|"&P148&"|"&R148&"|"&T148&"|"&V148 -> main-3|main-1|main-4|main-26|main-26|||||
B149: 146 | C149: =(E149+G149+I149+K149+M149+O149+Q149+S149+U149+W149) -> 24.1 | D149: main-26 | E149: =VLOOKUP(D149,'Win Methods'!$C$4:$F$379,4,FALSE) -> 10 | F149: main-4 | G149: =VLOOKUP(F149,'Win Methods'!$C$4:$F$379,4,FALSE) -> 2 | H149: main-4 | I149: =VLOOKUP(H149,'Win Methods'!$C$4:$F$379,4,FALSE) -> 2 | J149: main-0 | K149: =VLOOKUP(J149,'Win Methods'!$C$4:$F$379,4,FALSE) -> 0.1 | L149: main-26 | M149: =VLOOKUP(L149,'Win Methods'!$C$4:$F$379,4,FALSE) -> 10 | O149: =VLOOKUP(N149,'Win Methods'!$C$4:$F$379,4,FALSE) -> 0 | Q149: =VLOOKUP(P149,'Win Methods'!$C$4:$F$379,4,FALSE) -> 0 | S149: =VLOOKUP(R149,'Win Methods'!$C$4:$F$379,4,FALSE) -> 0 | U149: =VLOOKUP(T149,'Win Methods'!$C$4:$F$379,4,FALSE) -> 0 | W149: =VLOOKUP(V149,'Win Methods'!$C$4:$F$379,4,FALSE) -> 0 | X149: =D149&"|"&F149&"|"&H149&"|"&J149&"|"&L149&"|"&N149&"|"&P149&"|"&R149&"|"&T149&"|"&V149 -> main-26|main-4|main-4|main-0|main-26|||||
B150: 147 | C150: =(E150+G150+I150+K150+M150+O150+Q150+S150+U150+W150) -> 27.2 | D150: main-20 | E150: =VLOOKUP(D150,'Win Methods'!$C$4:$F$379,4,FALSE) -> 10 | F150: main-4 | G150: =VLOOKUP(F150,'Win Methods'!$C$4:$F$379,4,FALSE) -> 2 | H150: main-1 | I150: =VLOOKUP(H150,'Win Methods'!$C$4:$F$379,4,FALSE) -> 0.2 | J150: main-26 | K150: =VLOOKUP(J150,'Win Methods'!$C$4:$F$379,4,FALSE) -> 10 | L150: main-5 | M150: =VLOOKUP(L150,'Win Methods'!$C$4:$F$379,4,FALSE) -> 5 | O150: =VLOOKUP(N150,'Win Methods'!$C$4:$F$379,4,FALSE) -> 0 | Q150: =VLOOKUP(P150,'Win Methods'!$C$4:$F$379,4,FALSE) -> 0 | S150: =VLOOKUP(R150,'Win Methods'!$C$4:$F$379,4,FALSE) -> 0 | U150: =VLOOKUP(T150,'Win Methods'!$C$4:$F$379,4,FALSE) -> 0 | W150: =VLOOKUP(V150,'Win Methods'!$C$4:$F$379,4,FALSE) -> 0 | X150: =D150&"|"&F150&"|"&H150&"|"&J150&"|"&L150&"|"&N150&"|"&P150&"|"&R150&"|"&T150&"|"&V150 -> main-20|main-4|main-1|main-26|main-5|||||
B151: 148 | C151: =(E151+G151+I151+K151+M151+O151+Q151+S151+U151+W151) -> 35.5 | D151: main-21 | E151: =VLOOKUP(D151,'Win Methods'!$C$4:$F$379,4,FALSE) -> 20 | F151: main-5 | G151: =VLOOKUP(F151,'Win Methods'!$C$4:$F$379,4,FALSE) -> 5 | H151: main-2 | I151: =VLOOKUP(H151,'Win Methods'!$C$4:$F$379,4,FALSE) -> 0.5 | J151: main-19 | K151: =VLOOKUP(J151,'Win Methods'!$C$4:$F$379,4,FALSE) -> 5 | L151: main-19 | M151: =VLOOKUP(L151,'Win Methods'!$C$4:$F$379,4,FALSE) -> 5 | O151: =VLOOKUP(N151,'Win Methods'!$C$4:$F$379,4,FALSE) -> 0 | Q151: =VLOOKUP(P151,'Win Methods'!$C$4:$F$379,4,FALSE) -> 0 | S151: =VLOOKUP(R151,'Win Methods'!$C$4:$F$379,4,FALSE) -> 0 | U151: =VLOOKUP(T151,'Win Methods'!$C$4:$F$379,4,FALSE) -> 0 | W151: =VLOOKUP(V151,'Win Methods'!$C$4:$F$379,4,FALSE) -> 0 | X151: =D151&"|"&F151&"|"&H151&"|"&J151&"|"&L151&"|"&N151&"|"&P151&"|"&R151&"|"&T151&"|"&V151 -> main-21|main-5|main-2|main-19|main-19|||||
B152: 149 | C152: =(E152+G152+I152+K152+M152+O152+Q152+S152+U152+W152) -> 36 | D152: main-27 | E152: =VLOOKUP(D152,'Win Methods'!$C$4:$F$379,4,FALSE) -> 20 | F152: main-5 | G152: =VLOOKUP(F152,'Win Methods'!$C$4:$F$379,4,FALSE) -> 5 | H152: main-5 | I152: =VLOOKUP(H152,'Win Methods'!$C$4:$F$379,4,FALSE) -> 5 | J152: main-19 | K152: =VLOOKUP(J152,'Win Methods'!$C$4:$F$379,4,FALSE) -> 5 | L152: main-3 | M152: =VLOOKUP(L152,'Win Methods'!$C$4:$F$379,4,FALSE) -> 1 | O152: =VLOOKUP(N152,'Win Methods'!$C$4:$F$379,4,FALSE) -> 0 | Q152: =VLOOKUP(P152,'Win Methods'!$C$4:$F$379,4,FALSE) -> 0 | S152: =VLOOKUP(R152,'Win Methods'!$C$4:$F$379,4,FALSE) -> 0 | U152: =VLOOKUP(T152,'Win Methods'!$C$4:$F$379,4,FALSE) -> 0 | W152: =VLOOKUP(V152,'Win Methods'!$C$4:$F$379,4,FALSE) -> 0 | X152: =D152&"|"&F152&"|"&H152&"|"&J152&"|"&L152&"|"&N152&"|"&P152&"|"&R152&"|"&T152&"|"&V152 -> main-27|main-5|main-5|main-19|main-3|||||
B153: 150 | C153: =(E153+G153+I153+K153+M153+O153+Q153+S153+U153+W153) -> 0.6 | D153: main-0 | E153: =VLOOKUP(D153,'Win Methods'!$C$4:$F$379,4,FALSE) -> 0.1 | F153: wild-2 | G153: =VLOOKUP(F153,'Win Methods'!$C$4:$F$379,4,FALSE) -> 0.5 | I153: =VLOOKUP(H153,'Win Methods'!$C$4:$F$379,4,FALSE) -> 0 | K153: =VLOOKUP(J153,'Win Methods'!$C$4:$F$379,4,FALSE) -> 0 | M153: =VLOOKUP(L153,'Win Methods'!$C$4:$F$379,4,FALSE) -> 0 | O153: =VLOOKUP(N153,'Win Methods'!$C$4:$F$379,4,FALSE) -> 0 | Q153: =VLOOKUP(P153,'Win Methods'!$C$4:$F$379,4,FALSE) -> 0 | S153: =VLOOKUP(R153,'Win Methods'!$C$4:$F$379,4,FALSE) -> 0 | U153: =VLOOKUP(T153,'Win Methods'!$C$4:$F$379,4,FALSE) -> 0 | W153: =VLOOKUP(V153,'Win Methods'!$C$4:$F$379,4,FALSE) -> 0 | X153: =D153&"|"&F153&"|"&H153&"|"&J153&"|"&L153&"|"&N153&"|"&P153&"|"&R153&"|"&T153&"|"&V153 -> main-0|wild-2||||||||
B154: 151 | C154: =(E154+G154+I154+K154+M154+O154+Q154+S154+U154+W154) -> 1.2 | D154: main-1 | E154: =VLOOKUP(D154,'Win Methods'!$C$4:$F$379,4,FALSE) -> 0.2 | F154: wild-3 | G154: =VLOOKUP(F154,'Win Methods'!$C$4:$F$379,4,FALSE) -> 1 | I154: =VLOOKUP(H154,'Win Methods'!$C$4:$F$379,4,FALSE) -> 0 | K154: =VLOOKUP(J154,'Win Methods'!$C$4:$F$379,4,FALSE) -> 0 | M154: =VLOOKUP(L154,'Win Methods'!$C$4:$F$379,4,FALSE) -> 0 | O154: =VLOOKUP(N154,'Win Methods'!$C$4:$F$379,4,FALSE) -> 0 | Q154: =VLOOKUP(P154,'Win Methods'!$C$4:$F$379,4,FALSE) -> 0 | S154: =VLOOKUP(R154,'Win Methods'!$C$4:$F$379,4,FALSE) -> 0 | U154: =VLOOKUP(T154,'Win Methods'!$C$4:$F$379,4,FALSE) -> 0 | W154: =VLOOKUP(V154,'Win Methods'!$C$4:$F$379,4,FALSE) -> 0 | X154: =D154&"|"&F154&"|"&H154&"|"&J154&"|"&L154&"|"&N154&"|"&P154&"|"&R154&"|"&T154&"|"&V154 -> main-1|wild-3||||||||
B155: 152 | C155: =(E155+G155+I155+K155+M155+O155+Q155+S155+U155+W155) -> 2.5 | D155: main-2 | E155: =VLOOKUP(D155,'Win Methods'!$C$4:$F$379,4,FALSE) -> 0.5 | F155: wild-4 | G155: =VLOOKUP(F155,'Win Methods'!$C$4:$F$379,4,FALSE) -> 2 | I155: =VLOOKUP(H155,'Win Methods'!$C$4:$F$379,4,FALSE) -> 0 | K155: =VLOOKUP(J155,'Win Methods'!$C$4:$F$379,4,FALSE) -> 0 | M155: =VLOOKUP(L155,'Win Methods'!$C$4:$F$379,4,FALSE) -> 0 | O155: =VLOOKUP(N155,'Win Methods'!$C$4:$F$379,4,FALSE) -> 0 | Q155: =VLOOKUP(P155,'Win Methods'!$C$4:$F$379,4,FALSE) -> 0 | S155: =VLOOKUP(R155,'Win Methods'!$C$4:$F$379,4,FALSE) -> 0 | U155: =VLOOKUP(T155,'Win Methods'!$C$4:$F$379,4,FALSE) -> 0 | W155: =VLOOKUP(V155,'Win Methods'!$C$4:$F$379,4,FALSE) -> 0 | X155: =D155&"|"&F155&"|"&H155&"|"&J155&"|"&L155&"|"&N155&"|"&P155&"|"&R155&"|"&T155&"|"&V155 -> main-2|wild-4||||||||
B156: 153 | C156: =(E156+G156+I156+K156+M156+O156+Q156+S156+U156+W156) -> 6 | D156: main-3 | E156: =VLOOKUP(D156,'Win Methods'!$C$4:$F$379,4,FALSE) -> 1 | F156: wild-5 | G156: =VLOOKUP(F156,'Win Methods'!$C$4:$F$379,4,FALSE) -> 5 | I156: =VLOOKUP(H156,'Win Methods'!$C$4:$F$379,4,FALSE) -> 0 | K156: =VLOOKUP(J156,'Win Methods'!$C$4:$F$379,4,FALSE) -> 0 | M156: =VLOOKUP(L156,'Win Methods'!$C$4:$F$379,4,FALSE) -> 0 | O156: =VLOOKUP(N156,'Win Methods'!$C$4:$F$379,4,FALSE) -> 0 | Q156: =VLOOKUP(P156,'Win Methods'!$C$4:$F$379,4,FALSE) -> 0 | S156: =VLOOKUP(R156,'Win Methods'!$C$4:$F$379,4,FALSE) -> 0 | U156: =VLOOKUP(T156,'Win Methods'!$C$4:$F$379,4,FALSE) -> 0 | W156: =VLOOKUP(V156,'Win Methods'!$C$4:$F$379,4,FALSE) -> 0 | X156: =D156&"|"&F156&"|"&H156&"|"&J156&"|"&L156&"|"&N156&"|"&P156&"|"&R156&"|"&T156&"|"&V156 -> main-3|wild-5||||||||
B157: 154 | C157: =(E157+G157+I157+K157+M157+O157+Q157+S157+U157+W157) -> 4 | D157: main-4 | E157: =VLOOKUP(D157,'Win Methods'!$C$4:$F$379,4,FALSE) -> 2 | F157: wild-14 | G157: =VLOOKUP(F157,'Win Methods'!$C$4:$F$379,4,FALSE) -> 2 | I157: =VLOOKUP(H157,'Win Methods'!$C$4:$F$379,4,FALSE) -> 0 | K157: =VLOOKUP(J157,'Win Methods'!$C$4:$F$379,4,FALSE) -> 0 | M157: =VLOOKUP(L157,'Win Methods'!$C$4:$F$379,4,FALSE) -> 0 | O157: =VLOOKUP(N157,'Win Methods'!$C$4:$F$379,4,FALSE) -> 0 | Q157: =VLOOKUP(P157,'Win Methods'!$C$4:$F$379,4,FALSE) -> 0 | S157: =VLOOKUP(R157,'Win Methods'!$C$4:$F$379,4,FALSE) -> 0 | U157: =VLOOKUP(T157,'Win Methods'!$C$4:$F$379,4,FALSE) -> 0 | W157: =VLOOKUP(V157,'Win Methods'!$C$4:$F$379,4,FALSE) -> 0 | X157: =D157&"|"&F157&"|"&H157&"|"&J157&"|"&L157&"|"&N157&"|"&P157&"|"&R157&"|"&T157&"|"&V157 -> main-4|wild-14||||||||
B158: 155 | C158: =(E158+G158+I158+K158+M158+O158+Q158+S158+U158+W158) -> 10 | D158: main-5 | E158: =VLOOKUP(D158,'Win Methods'!$C$4:$F$379,4,FALSE) -> 5 | F158: wild-16 | G158: =VLOOKUP(F158,'Win Methods'!$C$4:$F$379,4,FALSE) -> 5 | I158: =VLOOKUP(H158,'Win Methods'!$C$4:$F$379,4,FALSE) -> 0 | K158: =VLOOKUP(J158,'Win Methods'!$C$4:$F$379,4,FALSE) -> 0 | M158: =VLOOKUP(L158,'Win Methods'!$C$4:$F$379,4,FALSE) -> 0 | O158: =VLOOKUP(N158,'Win Methods'!$C$4:$F$379,4,FALSE) -> 0 | Q158: =VLOOKUP(P158,'Win Methods'!$C$4:$F$379,4,FALSE) -> 0 | S158: =VLOOKUP(R158,'Win Methods'!$C$4:$F$379,4,FALSE) -> 0 | U158: =VLOOKUP(T158,'Win Methods'!$C$4:$F$379,4,FALSE) -> 0 | W158: =VLOOKUP(V158,'Win Methods'!$C$4:$F$379,4,FALSE) -> 0 | X158: =D158&"|"&F158&"|"&H158&"|"&J158&"|"&L158&"|"&N158&"|"&P158&"|"&R158&"|"&T158&"|"&V158 -> main-5|wild-16||||||||
B159: 156 | C159: =(E159+G159+I159+K159+M159+O159+Q159+S159+U159+W159) -> 10.1 | D159: main-0 | E159: =VLOOKUP(D159,'Win Methods'!$C$4:$F$379,4,FALSE) -> 0.1 | F159: wild-17 | G159: =VLOOKUP(F159,'Win Methods'!$C$4:$F$379,4,FALSE) -> 10 | I159: =VLOOKUP(H159,'Win Methods'!$C$4:$F$379,4,FALSE) -> 0 | K159: =VLOOKUP(J159,'Win Methods'!$C$4:$F$379,4,FALSE) -> 0 | M159: =VLOOKUP(L159,'Win Methods'!$C$4:$F$379,4,FALSE) -> 0 | O159: =VLOOKUP(N159,'Win Methods'!$C$4:$F$379,4,FALSE) -> 0 | Q159: =VLOOKUP(P159,'Win Methods'!$C$4:$F$379,4,FALSE) -> 0 | S159: =VLOOKUP(R159,'Win Methods'!$C$4:$F$379,4,FALSE) -> 0 | U159: =VLOOKUP(T159,'Win Methods'!$C$4:$F$379,4,FALSE) -> 0 | W159: =VLOOKUP(V159,'Win Methods'!$C$4:$F$379,4,FALSE) -> 0 | X159: =D159&"|"&F159&"|"&H159&"|"&J159&"|"&L159&"|"&N159&"|"&P159&"|"&R159&"|"&T159&"|"&V159 -> main-0|wild-17||||||||
B160: 157 | C160: =(E160+G160+I160+K160+M160+O160+Q160+S160+U160+W160) -> 3.2 | D160: main-1 | E160: =VLOOKUP(D160,'Win Methods'!$C$4:$F$379,4,FALSE) -> 0.2 | F160: wild-18 | G160: =VLOOKUP(F160,'Win Methods'!$C$4:$F$379,4,FALSE) -> 3 | I160: =VLOOKUP(H160,'Win Methods'!$C$4:$F$379,4,FALSE) -> 0 | K160: =VLOOKUP(J160,'Win Methods'!$C$4:$F$379,4,FALSE) -> 0 | M160: =VLOOKUP(L160,'Win Methods'!$C$4:$F$379,4,FALSE) -> 0 | O160: =VLOOKUP(N160,'Win Methods'!$C$4:$F$379,4,FALSE) -> 0 | Q160: =VLOOKUP(P160,'Win Methods'!$C$4:$F$379,4,FALSE) -> 0 | S160: =VLOOKUP(R160,'Win Methods'!$C$4:$F$379,4,FALSE) -> 0 | U160: =VLOOKUP(T160,'Win Methods'!$C$4:$F$379,4,FALSE) -> 0 | W160: =VLOOKUP(V160,'Win Methods'!$C$4:$F$379,4,FALSE) -> 0 | X160: =D160&"|"&F160&"|"&H160&"|"&J160&"|"&L160&"|"&N160&"|"&P160&"|"&R160&"|"&T160&"|"&V160 -> main-1|wild-18||||||||
B161: 158 | C161: =(E161+G161+I161+K161+M161+O161+Q161+S161+U161+W161) -> 0.7 | D161: main-2 | E161: =VLOOKUP(D161,'Win Methods'!$C$4:$F$379,4,FALSE) -> 0.5 | F161: wild-1 | G161: =VLOOKUP(F161,'Win Methods'!$C$4:$F$379,4,FALSE) -> 0.2 | I161: =VLOOKUP(H161,'Win Methods'!$C$4:$F$379,4,FALSE) -> 0 | K161: =VLOOKUP(J161,'Win Methods'!$C$4:$F$379,4,FALSE) -> 0 | M161: =VLOOKUP(L161,'Win Methods'!$C$4:$F$379,4,FALSE) -> 0 | O161: =VLOOKUP(N161,'Win Methods'!$C$4:$F$379,4,FALSE) -> 0 | Q161: =VLOOKUP(P161,'Win Methods'!$C$4:$F$379,4,FALSE) -> 0 | S161: =VLOOKUP(R161,'Win Methods'!$C$4:$F$379,4,FALSE) -> 0 | U161: =VLOOKUP(T161,'Win Methods'!$C$4:$F$379,4,FALSE) -> 0 | W161: =VLOOKUP(V161,'Win Methods'!$C$4:$F$379,4,FALSE) -> 0 | X161: =D161&"|"&F161&"|"&H161&"|"&J161&"|"&L161&"|"&N161&"|"&P161&"|"&R161&"|"&T161&"|"&V161 -> main-2|wild-1||||||||
B162: 159 | C162: =(E162+G162+I162+K162+M162+O162+Q162+S162+U162+W162) -> 1.5 | D162: main-3 | E162: =VLOOKUP(D162,'Win Methods'!$C$4:$F$379,4,FALSE) -> 1 | F162: wild-2 | G162: =VLOOKUP(F162,'Win Methods'!$C$4:$F$379,4,FALSE) -> 0.5 | I162: =VLOOKUP(H162,'Win Methods'!$C$4:$F$379,4,FALSE) -> 0 | K162: =VLOOKUP(J162,'Win Methods'!$C$4:$F$379,4,FALSE) -> 0 | M162: =VLOOKUP(L162,'Win Methods'!$C$4:$F$379,4,FALSE) -> 0 | O162: =VLOOKUP(N162,'Win Methods'!$C$4:$F$379,4,FALSE) -> 0 | Q162: =VLOOKUP(P162,'Win Methods'!$C$4:$F$379,4,FALSE) -> 0 | S162: =VLOOKUP(R162,'Win Methods'!$C$4:$F$379,4,FALSE) -> 0 | U162: =VLOOKUP(T162,'Win Methods'!$C$4:$F$379,4,FALSE) -> 0 | W162: =VLOOKUP(V162,'Win Methods'!$C$4:$F$379,4,FALSE) -> 0 | X162: =D162&"|"&F162&"|"&H162&"|"&J162&"|"&L162&"|"&N162&"|"&P162&"|"&R162&"|"&T162&"|"&V162 -> main-3|wild-2||||||||
B163: 160 | C163: =(E163+G163+I163+K163+M163+O163+Q163+S163+U163+W163) -> 3 | D163: main-4 | E163: =VLOOKUP(D163,'Win Methods'!$C$4:$F$379,4,FALSE) -> 2 | F163: wild-3 | G163: =VLOOKUP(F163,'Win Methods'!$C$4:$F$379,4,FALSE) -> 1 | I163: =VLOOKUP(H163,'Win Methods'!$C$4:$F$379,4,FALSE) -> 0 | K163: =VLOOKUP(J163,'Win Methods'!$C$4:$F$379,4,FALSE) -> 0 | M163: =VLOOKUP(L163,'Win Methods'!$C$4:$F$379,4,FALSE) -> 0 | O163: =VLOOKUP(N163,'Win Methods'!$C$4:$F$379,4,FALSE) -> 0 | Q163: =VLOOKUP(P163,'Win Methods'!$C$4:$F$379,4,FALSE) -> 0 | S163: =VLOOKUP(R163,'Win Methods'!$C$4:$F$379,4,FALSE) -> 0 | U163: =VLOOKUP(T163,'Win Methods'!$C$4:$F$379,4,FALSE) -> 0 | W163: =VLOOKUP(V163,'Win Methods'!$C$4:$F$379,4,FALSE) -> 0 | X163: =D163&"|"&F163&"|"&H163&"|"&J163&"|"&L163&"|"&N163&"|"&P163&"|"&R163&"|"&T163&"|"&V163 -> main-4|wild-3||||||||
B164: 161 | C164: =(E164+G164+I164+K164+M164+O164+Q164+S164+U164+W164) -> 7 | D164: main-5 | E164: =VLOOKUP(D164,'Win Methods'!$C$4:$F$379,4,FALSE) -> 5 | F164: wild-4 | G164: =VLOOKUP(F164,'Win Methods'!$C$4:$F$379,4,FALSE) -> 2 | I164: =VLOOKUP(H164,'Win Methods'!$C$4:$F$379,4,FALSE) -> 0 | K164: =VLOOKUP(J164,'Win Methods'!$C$4:$F$379,4,FALSE) -> 0 | M164: =VLOOKUP(L164,'Win Methods'!$C$4:$F$379,4,FALSE) -> 0 | O164: =VLOOKUP(N164,'Win Methods'!$C$4:$F$379,4,FALSE) -> 0 | Q164: =VLOOKUP(P164,'Win Methods'!$C$4:$F$379,4,FALSE) -> 0 | S164: =VLOOKUP(R164,'Win Methods'!$C$4:$F$379,4,FALSE) -> 0 | U164: =VLOOKUP(T164,'Win Methods'!$C$4:$F$379,4,FALSE) -> 0 | W164: =VLOOKUP(V164,'Win Methods'!$C$4:$F$379,4,FALSE) -> 0 | X164: =D164&"|"&F164&"|"&H164&"|"&J164&"|"&L164&"|"&N164&"|"&P164&"|"&R164&"|"&T164&"|"&V164 -> main-5|wild-4||||||||
... B184: 181 | C184: =(E184+G184+I184+K184+M184+O184+Q184+S184+U184+W184) -> 22 | D184: main-4 | E184: =VLOOKUP(D184,'Win Methods'!$C$4:$F$379,4,FALSE) -> 2 | F184: wild-21 | G184: =VLOOKUP(F184,'Win Methods'!$C$4:$F$379,4,FALSE) -> 20 | I184: =VLOOKUP(H184,'Win Methods'!$C$4:$F$379,4,FALSE) -> 0 | K184: =VLOOKUP(J184,'Win Methods'!$C$4:$F$379,4,FALSE) -> 0 | M184: =VLOOKUP(L184,'Win Methods'!$C$4:$F$379,4,FALSE) -> 0 | O184: =VLOOKUP(N184,'Win Methods'!$C$4:$F$379,4,FALSE) -> 0 | Q184: =VLOOKUP(P184,'Win Methods'!$C$4:$F$379,4,FALSE) -> 0 | S184: =VLOOKUP(R184,'Win Methods'!$C$4:$F$379,4,FALSE) -> 0 | U184: =VLOOKUP(T184,'Win Methods'!$C$4:$F$379,4,FALSE) -> 0 | W184: =VLOOKUP(V184,'Win Methods'!$C$4:$F$379,4,FALSE) -> 0 | X184: =D184&"|"&F184&"|"&H184&"|"&J184&"|"&L184&"|"&N184&"|"&P184&"|"&R184&"|"&T184&"|"&V184 -> main-4|wild-21||||||||
B185: 182 | C185: =(E185+G185+I185+K185+M185+O185+Q185+S185+U185+W185) -> 0.7 | D185: main-0 | E185: =VLOOKUP(D185,'Win Methods'!$C$4:$F$379,4,FALSE) -> 0.1 | F185: main-0 | G185: =VLOOKUP(F185,'Win Methods'!$C$4:$F$379,4,FALSE) -> 0.1 | H185: wild-2 | I185: =VLOOKUP(H185,'Win Methods'!$C$4:$F$379,4,FALSE) -> 0.5 | K185: =VLOOKUP(J185,'Win Methods'!$C$4:$F$379,4,FALSE) -> 0 | M185: =VLOOKUP(L185,'Win Methods'!$C$4:$F$379,4,FALSE) -> 0 | O185: =VLOOKUP(N185,'Win Methods'!$C$4:$F$379,4,FALSE) -> 0 | Q185: =VLOOKUP(P185,'Win Methods'!$C$4:$F$379,4,FALSE) -> 0 | S185: =VLOOKUP(R185,'Win Methods'!$C$4:$F$379,4,FALSE) -> 0 | U185: =VLOOKUP(T185,'Win Methods'!$C$4:$F$379,4,FALSE) -> 0 | W185: =VLOOKUP(V185,'Win Methods'!$C$4:$F$379,4,FALSE) -> 0 | X185: =D185&"|"&F185&"|"&H185&"|"&J185&"|"&L185&"|"&N185&"|"&P185&"|"&R185&"|"&T185&"|"&V185 -> main-0|main-0|wild-2|||||||
B186: 183 | C186: =(E186+G186+I186+K186+M186+O186+Q186+S186+U186+W186) -> 1.3 | D186: main-0 | E186: =VLOOKUP(D186,'Win Methods'!$C$4:$F$379,4,FALSE) -> 0.1 | F186: main-1 | G186: =VLOOKUP(F186,'Win Methods'!$C$4:$F$379,4,FALSE) -> 0.2 | H186: wild-3 | I186: =VLOOKUP(H186,'Win Methods'!$C$4:$F$379,4,FALSE) -> 1 | K186: =VLOOKUP(J186,'Win Methods'!$C$4:$F$379,4,FALSE) -> 0 | M186: =VLOOKUP(L186,'Win Methods'!$C$4:$F$379,4,FALSE) -> 0 | O186: =VLOOKUP(N186,'Win Methods'!$C$4:$F$379,4,FALSE) -> 0 | Q186: =VLOOKUP(P186,'Win Methods'!$C$4:$F$379,4,FALSE) -> 0 | S186: =VLOOKUP(R186,'Win Methods'!$C$4:$F$379,4,FALSE) -> 0 | U186: =VLOOKUP(T186,'Win Methods'!$C$4:$F$379,4,FALSE) -> 0 | W186: =VLOOKUP(V186,'Win Methods'!$C$4:$F$379,4,FALSE) -> 0 | X186: =D186&"|"&F186&"|"&H186&"|"&J186&"|"&L186&"|"&N186&"|"&P186&"|"&R186&"|"&T186&"|"&V186 -> main-0|main-1|wild-3|||||||
B187: 184 | C187: =(E187+G187+I187+K187+M187+O187+Q187+S187+U187+W187) -> 2.4 | D187: main-1 | E187: =VLOOKUP(D187,'Win Methods'!$C$4:$F$379,4,FALSE) -> 0.2 | F187: main-1 | G187: =VLOOKUP(F187,'Win Methods'!$C$4:$F$379,4,FALSE) -> 0.2 | H187: wild-4 | I187: =VLOOKUP(H187,'Win Methods'!$C$4:$F$379,4,FALSE) -> 2 | K187: =VLOOKUP(J187,'Win Methods'!$C$4:$F$379,4,FALSE) -> 0 | M187: =VLOOKUP(L187,'Win Methods'!$C$4:$F$379,4,FALSE) -> 0 | O187: =VLOOKUP(N187,'Win Methods'!$C$4:$F$379,4,FALSE) -> 0 | Q187: =VLOOKUP(P187,'Win Methods'!$C$4:$F$379,4,FALSE) -> 0 | S187: =VLOOKUP(R187,'Win Methods'!$C$4:$F$379,4,FALSE) -> 0 | U187: =VLOOKUP(T187,'Win Methods'!$C$4:$F$379,4,FALSE) -> 0 | W187: =VLOOKUP(V187,'Win Methods'!$C$4:$F$379,4,FALSE) -> 0 | X187: =D187&"|"&F187&"|"&H187&"|"&J187&"|"&L187&"|"&N187&"|"&P187&"|"&R187&"|"&T187&"|"&V187 -> main-1|main-1|wild-4|||||||
B188: 185 | C188: =(E188+G188+I188+K188+M188+O188+Q188+S188+U188+W188) -> 2.6 | D188: main-0 | E188: =VLOOKUP(D188,'Win Methods'!$C$4:$F$379,4,FALSE) -> 0.1 | F188: main-2 | G188: =VLOOKUP(F188,'Win Methods'!$C$4:$F$379,4,FALSE) -> 0.5 | H188: wild-11 | I188: =VLOOKUP(H188,'Win Methods'!$C$4:$F$379,4,FALSE) -> 2 | K188: =VLOOKUP(J188,'Win Methods'!$C$4:$F$379,4,FALSE) -> 0 | M188: =VLOOKUP(L188,'Win Methods'!$C$4:$F$379,4,FALSE) -> 0 | O188: =VLOOKUP(N188,'Win Methods'!$C$4:$F$379,4,FALSE) -> 0 | Q188: =VLOOKUP(P188,'Win Methods'!$C$4:$F$379,4,FALSE) -> 0 | S188: =VLOOKUP(R188,'Win Methods'!$C$4:$F$379,4,FALSE) -> 0 | U188: =VLOOKUP(T188,'Win Methods'!$C$4:$F$379,4,FALSE) -> 0 | W188: =VLOOKUP(V188,'Win Methods'!$C$4:$F$379,4,FALSE) -> 0 | X188: =D188&"|"&F188&"|"&H188&"|"&J188&"|"&L188&"|"&N188&"|"&P188&"|"&R188&"|"&T188&"|"&V188 -> main-0|main-2|wild-11|||||||
B189: 186 | C189: =(E189+G189+I189+K189+M189+O189+Q189+S189+U189+W189) -> 3.7 | D189: main-1 | E189: =VLOOKUP(D189,'Win Methods'!$C$4:$F$379,4,FALSE) -> 0.2 | F189: main-2 | G189: =VLOOKUP(F189,'Win Methods'!$C$4:$F$379,4,FALSE) -> 0.5 | H189: wild-12 | I189: =VLOOKUP(H189,'Win Methods'!$C$4:$F$379,4,FALSE) -> 3 | K189: =VLOOKUP(J189,'Win Methods'!$C$4:$F$379,4,FALSE) -> 0 | M189: =VLOOKUP(L189,'Win Methods'!$C$4:$F$379,4,FALSE) -> 0 | O189: =VLOOKUP(N189,'Win Methods'!$C$4:$F$379,4,FALSE) -> 0 | Q189: =VLOOKUP(P189,'Win Methods'!$C$4:$F$379,4,FALSE) -> 0 | S189: =VLOOKUP(R189,'Win Methods'!$C$4:$F$379,4,FALSE) -> 0 | U189: =VLOOKUP(T189,'Win Methods'!$C$4:$F$379,4,FALSE) -> 0 | W189: =VLOOKUP(V189,'Win Methods'!$C$4:$F$379,4,FALSE) -> 0 | X189: =D189&"|"&F189&"|"&H189&"|"&J189&"|"&L189&"|"&N189&"|"&P189&"|"&R189&"|"&T189&"|"&V189 -> main-1|main-2|wild-12|||||||
B190: 187 | C190: =(E190+G190+I190+K190+M190+O190+Q190+S190+U190+W190) -> 6.1 | D190: main-3 | E190: =VLOOKUP(D190,'Win Methods'!$C$4:$F$379,4,FALSE) -> 1 | F190: main-0 | G190: =VLOOKUP(F190,'Win Methods'!$C$4:$F$379,4,FALSE) -> 0.1 | H190: wild-13 | I190: =VLOOKUP(H190,'Win Methods'!$C$4:$F$379,4,FALSE) -> 5 | K190: =VLOOKUP(J190,'Win Methods'!$C$4:$F$379,4,FALSE) -> 0 | M190: =VLOOKUP(L190,'Win Methods'!$C$4:$F$379,4,FALSE) -> 0 | O190: =VLOOKUP(N190,'Win Methods'!$C$4:$F$379,4,FALSE) -> 0 | Q190: =VLOOKUP(P190,'Win Methods'!$C$4:$F$379,4,FALSE) -> 0 | S190: =VLOOKUP(R190,'Win Methods'!$C$4:$F$379,4,FALSE) -> 0 | U190: =VLOOKUP(T190,'Win Methods'!$C$4:$F$379,4,FALSE) -> 0 | W190: =VLOOKUP(V190,'Win Methods'!$C$4:$F$379,4,FALSE) -> 0 | X190: =D190&"|"&F190&"|"&H190&"|"&J190&"|"&L190&"|"&N190&"|"&P190&"|"&R190&"|"&T190&"|"&V190 -> main-3|main-0|wild-13|||||||
B191: 188 | C191: =(E191+G191+I191+K191+M191+O191+Q191+S191+U191+W191) -> 4.2 | D191: main-3 | E191: =VLOOKUP(D191,'Win Methods'!$C$4:$F$379,4,FALSE) -> 1 | F191: main-1 | G191: =VLOOKUP(F191,'Win Methods'!$C$4:$F$379,4,FALSE) -> 0.2 | H191: wild-15 | I191: =VLOOKUP(H191,'Win Methods'!$C$4:$F$379,4,FALSE) -> 3 | K191: =VLOOKUP(J191,'Win Methods'!$C$4:$F$379,4,FALSE) -> 0 | M191: =VLOOKUP(L191,'Win Methods'!$C$4:$F$379,4,FALSE) -> 0 | O191: =VLOOKUP(N191,'Win Methods'!$C$4:$F$379,4,FALSE) -> 0 | Q191: =VLOOKUP(P191,'Win Methods'!$C$4:$F$379,4,FALSE) -> 0 | S191: =VLOOKUP(R191,'Win Methods'!$C$4:$F$379,4,FALSE) -> 0 | U191: =VLOOKUP(T191,'Win Methods'!$C$4:$F$379,4,FALSE) -> 0 | W191: =VLOOKUP(V191,'Win Methods'!$C$4:$F$379,4,FALSE) -> 0 | X191: =D191&"|"&F191&"|"&H191&"|"&J191&"|"&L191&"|"&N191&"|"&P191&"|"&R191&"|"&T191&"|"&V191 -> main-3|main-1|wild-15|||||||
B192: 189 | C192: =(E192+G192+I192+K192+M192+O192+Q192+S192+U192+W192) -> 10.2 | D192: main-1 | E192: =VLOOKUP(D192,'Win Methods'!$C$4:$F$379,4,FALSE) -> 0.2 | F192: main-5 | G192: =VLOOKUP(F192,'Win Methods'!$C$4:$F$379,4,FALSE) -> 5 | H192: wild-16 | I192: =VLOOKUP(H192,'Win Methods'!$C$4:$F$379,4,FALSE) -> 5 | K192: =VLOOKUP(J192,'Win Methods'!$C$4:$F$379,4,FALSE) -> 0 | M192: =VLOOKUP(L192,'Win Methods'!$C$4:$F$379,4,FALSE) -> 0 | O192: =VLOOKUP(N192,'Win Methods'!$C$4:$F$379,4,FALSE) -> 0 | Q192: =VLOOKUP(P192,'Win Methods'!$C$4:$F$379,4,FALSE) -> 0 | S192: =VLOOKUP(R192,'Win Methods'!$C$4:$F$379,4,FALSE) -> 0 | U192: =VLOOKUP(T192,'Win Methods'!$C$4:$F$379,4,FALSE) -> 0 | W192: =VLOOKUP(V192,'Win Methods'!$C$4:$F$379,4,FALSE) -> 0 | X192: =D192&"|"&F192&"|"&H192&"|"&J192&"|"&L192&"|"&N192&"|"&P192&"|"&R192&"|"&T192&"|"&V192 -> main-1|main-5|wild-16|||||||
B193: 190 | C193: =(E193+G193+I193+K193+M193+O193+Q193+S193+U193+W193) -> 17 | D193: main-4 | E193: =VLOOKUP(D193,'Win Methods'!$C$4:$F$379,4,FALSE) -> 2 | F193: main-19 | G193: =VLOOKUP(F193,'Win Methods'!$C$4:$F$379,4,FALSE) -> 5 | H193: wild-17 | I193: =VLOOKUP(H193,'Win Methods'!$C$4:$F$379,4,FALSE) -> 10 | K193: =VLOOKUP(J193,'Win Methods'!$C$4:$F$379,4,FALSE) -> 0 | M193: =VLOOKUP(L193,'Win Methods'!$C$4:$F$379,4,FALSE) -> 0 | O193: =VLOOKUP(N193,'Win Methods'!$C$4:$F$379,4,FALSE) -> 0 | Q193: =VLOOKUP(P193,'Win Methods'!$C$4:$F$379,4,FALSE) -> 0 | S193: =VLOOKUP(R193,'Win Methods'!$C$4:$F$379,4,FALSE) -> 0 | U193: =VLOOKUP(T193,'Win Methods'!$C$4:$F$379,4,FALSE) -> 0 | W193: =VLOOKUP(V193,'Win Methods'!$C$4:$F$379,4,FALSE) -> 0 | X193: =D193&"|"&F193&"|"&H193&"|"&J193&"|"&L193&"|"&N193&"|"&P193&"|"&R193&"|"&T193&"|"&V193 -> main-4|main-19|wild-17|||||||
B194: 191 | C194: =(E194+G194+I194+K194+M194+O194+Q194+S194+U194+W194) -> 13 | D194: main-3 | E194: =VLOOKUP(D194,'Win Methods'!$C$4:$F$379,4,FALSE) -> 1 | F194: main-20 | G194: =VLOOKUP(F194,'Win Methods'!$C$4:$F$379,4,FALSE) -> 10 | H194: wild-11 | I194: =VLOOKUP(H194,'Win Methods'!$C$4:$F$379,4,FALSE) -> 2 | K194: =VLOOKUP(J194,'Win Methods'!$C$4:$F$379,4,FALSE) -> 0 | M194: =VLOOKUP(L194,'Win Methods'!$C$4:$F$379,4,FALSE) -> 0 | O194: =VLOOKUP(N194,'Win Methods'!$C$4:$F$379,4,FALSE) -> 0 | Q194: =VLOOKUP(P194,'Win Methods'!$C$4:$F$379,4,FALSE) -> 0 | S194: =VLOOKUP(R194,'Win Methods'!$C$4:$F$379,4,FALSE) -> 0 | U194: =VLOOKUP(T194,'Win Methods'!$C$4:$F$379,4,FALSE) -> 0 | W194: =VLOOKUP(V194,'Win Methods'!$C$4:$F$379,4,FALSE) -> 0 | X194: =D194&"|"&F194&"|"&H194&"|"&J194&"|"&L194&"|"&N194&"|"&P194&"|"&R194&"|"&T194&"|"&V194 -> main-3|main-20|wild-11|||||||
B195: 192 | C195: =(E195+G195+I195+K195+M195+O195+Q195+S195+U195+W195) -> 10 | D195: main-4 | E195: =VLOOKUP(D195,'Win Methods'!$C$4:$F$379,4,FALSE) -> 2 | F195: main-5 | G195: =VLOOKUP(F195,'Win Methods'!$C$4:$F$379,4,FALSE) -> 5 | H195: wild-12 | I195: =VLOOKUP(H195,'Win Methods'!$C$4:$F$379,4,FALSE) -> 3 | K195: =VLOOKUP(J195,'Win Methods'!$C$4:$F$379,4,FALSE) -> 0 | M195: =VLOOKUP(L195,'Win Methods'!$C$4:$F$379,4,FALSE) -> 0 | O195: =VLOOKUP(N195,'Win Methods'!$C$4:$F$379,4,FALSE) -> 0 | Q195: =VLOOKUP(P195,'Win Methods'!$C$4:$F$379,4,FALSE) -> 0 | S195: =VLOOKUP(R195,'Win Methods'!$C$4:$F$379,4,FALSE) -> 0 | U195: =VLOOKUP(T195,'Win Methods'!$C$4:$F$379,4,FALSE) -> 0 | W195: =VLOOKUP(V195,'Win Methods'!$C$4:$F$379,4,FALSE) -> 0 | X195: =D195&"|"&F195&"|"&H195&"|"&J195&"|"&L195&"|"&N195&"|"&P195&"|"&R195&"|"&T195&"|"&V195 -> main-4|main-5|wild-12|||||||
B196: 193 | C196: =(E196+G196+I196+K196+M196+O196+Q196+S196+U196+W196) -> 15 | D196: main-5 | E196: =VLOOKUP(D196,'Win Methods'!$C$4:$F$379,4,FALSE) -> 5 | F196: main-25 | G196: =VLOOKUP(F196,'Win Methods'!$C$4:$F$379,4,FALSE) -> 5 | H196: wild-13 | I196: =VLOOKUP(H196,'Win Methods'!$C$4:$F$379,4,FALSE) -> 5 | K196: =VLOOKUP(J196,'Win Methods'!$C$4:$F$379,4,FALSE) -> 0 | M196: =VLOOKUP(L196,'Win Methods'!$C$4:$F$379,4,FALSE) -> 0 | O196: =VLOOKUP(N196,'Win Methods'!$C$4:$F$379,4,FALSE) -> 0 | Q196: =VLOOKUP(P196,'Win Methods'!$C$4:$F$379,4,FALSE) -> 0 | S196: =VLOOKUP(R196,'Win Methods'!$C$4:$F$379,4,FALSE) -> 0 | U196: =VLOOKUP(T196,'Win Methods'!$C$4:$F$379,4,FALSE) -> 0 | W196: =VLOOKUP(V196,'Win Methods'!$C$4:$F$379,4,FALSE) -> 0 | X196: =D196&"|"&F196&"|"&H196&"|"&J196&"|"&L196&"|"&N196&"|"&P196&"|"&R196&"|"&T196&"|"&V196 -> main-5|main-25|wild-13|||||||
... B199: 196 | C199: =(E199+G199+I199+K199+M199+O199+Q199+S199+U199+W199) -> 27 | D199: main-4 | E199: =VLOOKUP(D199,'Win Methods'!$C$4:$F$379,4,FALSE) -> 2 | F199: main-21 | G199: =VLOOKUP(F199,'Win Methods'!$C$4:$F$379,4,FALSE) -> 20 | H199: wild-16 | I199: =VLOOKUP(H199,'Win Methods'!$C$4:$F$379,4,FALSE) -> 5 | K199: =VLOOKUP(J199,'Win Methods'!$C$4:$F$379,4,FALSE) -> 0 | M199: =VLOOKUP(L199,'Win Methods'!$C$4:$F$379,4,FALSE) -> 0 | O199: =VLOOKUP(N199,'Win Methods'!$C$4:$F$379,4,FALSE) -> 0 | Q199: =VLOOKUP(P199,'Win Methods'!$C$4:$F$379,4,FALSE) -> 0 | S199: =VLOOKUP(R199,'Win Methods'!$C$4:$F$379,4,FALSE) -> 0 | U199: =VLOOKUP(T199,'Win Methods'!$C$4:$F$379,4,FALSE) -> 0 | W199: =VLOOKUP(V199,'Win Methods'!$C$4:$F$379,4,FALSE) -> 0 | X199: =D199&"|"&F199&"|"&H199&"|"&J199&"|"&L199&"|"&N199&"|"&P199&"|"&R199&"|"&T199&"|"&V199 -> main-4|main-21|wild-16|||||||
B200: 197 | C200: =(E200+G200+I200+K200+M200+O200+Q200+S200+U200+W200) -> 25.1 | D200: main-0 | E200: =VLOOKUP(D200,'Win Methods'!$C$4:$F$379,4,FALSE) -> 0.1 | F200: main-18 | G200: =VLOOKUP(F200,'Win Methods'!$C$4:$F$379,4,FALSE) -> 3 | H200: main-4 | I200: =VLOOKUP(H200,'Win Methods'!$C$4:$F$379,4,FALSE) -> 2 | J200: wild-21 | K200: =VLOOKUP(J200,'Win Methods'!$C$4:$F$379,4,FALSE) -> 20 | M200: =VLOOKUP(L200,'Win Methods'!$C$4:$F$379,4,FALSE) -> 0 | O200: =VLOOKUP(N200,'Win Methods'!$C$4:$F$379,4,FALSE) -> 0 | Q200: =VLOOKUP(P200,'Win Methods'!$C$4:$F$379,4,FALSE) -> 0 | S200: =VLOOKUP(R200,'Win Methods'!$C$4:$F$379,4,FALSE) -> 0 | U200: =VLOOKUP(T200,'Win Methods'!$C$4:$F$379,4,FALSE) -> 0 | W200: =VLOOKUP(V200,'Win Methods'!$C$4:$F$379,4,FALSE) -> 0 | X200: =D200&"|"&F200&"|"&H200&"|"&J200&"|"&L200&"|"&N200&"|"&P200&"|"&R200&"|"&T200&"|"&V200 -> main-0|main-18|main-4|wild-21||||||
B201: 198 | C201: =(E201+G201+I201+K201+M201+O201+Q201+S201+U201+W201) -> 8.7 | D201: main-1 | E201: =VLOOKUP(D201,'Win Methods'!$C$4:$F$379,4,FALSE) -> 0.2 | F201: main-25 | G201: =VLOOKUP(F201,'Win Methods'!$C$4:$F$379,4,FALSE) -> 5 | H201: main-18 | I201: =VLOOKUP(H201,'Win Methods'!$C$4:$F$379,4,FALSE) -> 3 | J201: wild-2 | K201: =VLOOKUP(J201,'Win Methods'!$C$4:$F$379,4,FALSE) -> 0.5 | M201: =VLOOKUP(L201,'Win Methods'!$C$4:$F$379,4,FALSE) -> 0 | O201: =VLOOKUP(N201,'Win Methods'!$C$4:$F$379,4,FALSE) -> 0 | Q201: =VLOOKUP(P201,'Win Methods'!$C$4:$F$379,4,FALSE) -> 0 | S201: =VLOOKUP(R201,'Win Methods'!$C$4:$F$379,4,FALSE) -> 0 | U201: =VLOOKUP(T201,'Win Methods'!$C$4:$F$379,4,FALSE) -> 0 | W201: =VLOOKUP(V201,'Win Methods'!$C$4:$F$379,4,FALSE) -> 0 | X201: =D201&"|"&F201&"|"&H201&"|"&J201&"|"&L201&"|"&N201&"|"&P201&"|"&R201&"|"&T201&"|"&V201 -> main-1|main-25|main-18|wild-2||||||
B202: 199 | C202: =(E202+G202+I202+K202+M202+O202+Q202+S202+U202+W202) -> 7.5 | D202: main-2 | E202: =VLOOKUP(D202,'Win Methods'!$C$4:$F$379,4,FALSE) -> 0.5 | F202: main-19 | G202: =VLOOKUP(F202,'Win Methods'!$C$4:$F$379,4,FALSE) -> 5 | H202: main-3 | I202: =VLOOKUP(H202,'Win Methods'!$C$4:$F$379,4,FALSE) -> 1 | J202: wild-3 | K202: =VLOOKUP(J202,'Win Methods'!$C$4:$F$379,4,FALSE) -> 1 | M202: =VLOOKUP(L202,'Win Methods'!$C$4:$F$379,4,FALSE) -> 0 | O202: =VLOOKUP(N202,'Win Methods'!$C$4:$F$379,4,FALSE) -> 0 | Q202: =VLOOKUP(P202,'Win Methods'!$C$4:$F$379,4,FALSE) -> 0 | S202: =VLOOKUP(R202,'Win Methods'!$C$4:$F$379,4,FALSE) -> 0 | U202: =VLOOKUP(T202,'Win Methods'!$C$4:$F$379,4,FALSE) -> 0 | W202: =VLOOKUP(V202,'Win Methods'!$C$4:$F$379,4,FALSE) -> 0 | X202: =D202&"|"&F202&"|"&H202&"|"&J202&"|"&L202&"|"&N202&"|"&P202&"|"&R202&"|"&T202&"|"&V202 -> main-2|main-19|main-3|wild-3||||||
B203: 200 | C203: =(E203+G203+I203+K203+M203+O203+Q203+S203+U203+W203) -> 9.1 | D203: main-4 | E203: =VLOOKUP(D203,'Win Methods'!$C$4:$F$379,4,FALSE) -> 2 | F203: main-13 | G203: =VLOOKUP(F203,'Win Methods'!$C$4:$F$379,4,FALSE) -> 5 | H203: main-0 | I203: =VLOOKUP(H203,'Win Methods'!$C$4:$F$379,4,FALSE) -> 0.1 | J203: wild-4 | K203: =VLOOKUP(J203,'Win Methods'!$C$4:$F$379,4,FALSE) -> 2 | M203: =VLOOKUP(L203,'Win Methods'!$C$4:$F$379,4,FALSE) -> 0 | O203: =VLOOKUP(N203,'Win Methods'!$C$4:$F$379,4,FALSE) -> 0 | Q203: =VLOOKUP(P203,'Win Methods'!$C$4:$F$379,4,FALSE) -> 0 | S203: =VLOOKUP(R203,'Win Methods'!$C$4:$F$379,4,FALSE) -> 0 | U203: =VLOOKUP(T203,'Win Methods'!$C$4:$F$379,4,FALSE) -> 0 | W203: =VLOOKUP(V203,'Win Methods'!$C$4:$F$379,4,FALSE) -> 0 | X203: =D203&"|"&F203&"|"&H203&"|"&J203&"|"&L203&"|"&N203&"|"&P203&"|"&R203&"|"&T203&"|"&V203 -> main-4|main-13|main-0|wild-4||||||
B204: 201 | C204: =(E204+G204+I204+K204+M204+O204+Q204+S204+U204+W204) -> 18.2 | D204: main-1 | E204: =VLOOKUP(D204,'Win Methods'!$C$4:$F$379,4,FALSE) -> 0.2 | F204: main-18 | G204: =VLOOKUP(F204,'Win Methods'!$C$4:$F$379,4,FALSE) -> 3 | H204: main-26 | I204: =VLOOKUP(H204,'Win Methods'!$C$4:$F$379,4,FALSE) -> 10 | J204: wild-16 | K204: =VLOOKUP(J204,'Win Methods'!$C$4:$F$379,4,FALSE) -> 5 | M204: =VLOOKUP(L204,'Win Methods'!$C$4:$F$379,4,FALSE) -> 0 | O204: =VLOOKUP(N204,'Win Methods'!$C$4:$F$379,4,FALSE) -> 0 | Q204: =VLOOKUP(P204,'Win Methods'!$C$4:$F$379,4,FALSE) -> 0 | S204: =VLOOKUP(R204,'Win Methods'!$C$4:$F$379,4,FALSE) -> 0 | U204: =VLOOKUP(T204,'Win Methods'!$C$4:$F$379,4,FALSE) -> 0 | W204: =VLOOKUP(V204,'Win Methods'!$C$4:$F$379,4,FALSE) -> 0 | X204: =D204&"|"&F204&"|"&H204&"|"&J204&"|"&L204&"|"&N204&"|"&P204&"|"&R204&"|"&T204&"|"&V204 -> main-1|main-18|main-26|wild-16||||||
B205: 202 | C205: =(E205+G205+I205+K205+M205+O205+Q205+S205+U205+W205) -> 20.1 | D205: main-5 | E205: =VLOOKUP(D205,'Win Methods'!$C$4:$F$379,4,FALSE) -> 5 | F205: main-25 | G205: =VLOOKUP(F205,'Win Methods'!$C$4:$F$379,4,FALSE) -> 5 | H205: main-0 | I205: =VLOOKUP(H205,'Win Methods'!$C$4:$F$379,4,FALSE) -> 0.1 | J205: wild-17 | K205: =VLOOKUP(J205,'Win Methods'!$C$4:$F$379,4,FALSE) -> 10 | M205: =VLOOKUP(L205,'Win Methods'!$C$4:$F$379,4,FALSE) -> 0 | O205: =VLOOKUP(N205,'Win Methods'!$C$4:$F$379,4,FALSE) -> 0 | Q205: =VLOOKUP(P205,'Win Methods'!$C$4:$F$379,4,FALSE) -> 0 | S205: =VLOOKUP(R205,'Win Methods'!$C$4:$F$379,4,FALSE) -> 0 | U205: =VLOOKUP(T205,'Win Methods'!$C$4:$F$379,4,FALSE) -> 0 | W205: =VLOOKUP(V205,'Win Methods'!$C$4:$F$379,4,FALSE) -> 0 | X205: =D205&"|"&F205&"|"&H205&"|"&J205&"|"&L205&"|"&N205&"|"&P205&"|"&R205&"|"&T205&"|"&V205 -> main-5|main-25|main-0|wild-17||||||
B206: 203 | C206: =(E206+G206+I206+K206+M206+O206+Q206+S206+U206+W206) -> 15.1 | D206: main-4 | E206: =VLOOKUP(D206,'Win Methods'!$C$4:$F$379,4,FALSE) -> 2 | F206: main-0 | G206: =VLOOKUP(F206,'Win Methods'!$C$4:$F$379,4,FALSE) -> 0.1 | H206: main-20 | I206: =VLOOKUP(H206,'Win Methods'!$C$4:$F$379,4,FALSE) -> 10 | J206: wild-18 | K206: =VLOOKUP(J206,'Win Methods'!$C$4:$F$379,4,FALSE) -> 3 | M206: =VLOOKUP(L206,'Win Methods'!$C$4:$F$379,4,FALSE) -> 0 | O206: =VLOOKUP(N206,'Win Methods'!$C$4:$F$379,4,FALSE) -> 0 | Q206: =VLOOKUP(P206,'Win Methods'!$C$4:$F$379,4,FALSE) -> 0 | S206: =VLOOKUP(R206,'Win Methods'!$C$4:$F$379,4,FALSE) -> 0 | U206: =VLOOKUP(T206,'Win Methods'!$C$4:$F$379,4,FALSE) -> 0 | W206: =VLOOKUP(V206,'Win Methods'!$C$4:$F$379,4,FALSE) -> 0 | X206: =D206&"|"&F206&"|"&H206&"|"&J206&"|"&L206&"|"&N206&"|"&P206&"|"&R206&"|"&T206&"|"&V206 -> main-4|main-0|main-20|wild-18||||||
B207: 204 | C207: =(E207+G207+I207+K207+M207+O207+Q207+S207+U207+W207) -> 15 | D207: main-11 | E207: =VLOOKUP(D207,'Win Methods'!$C$4:$F$379,4,FALSE) -> 2 | F207: main-25 | G207: =VLOOKUP(F207,'Win Methods'!$C$4:$F$379,4,FALSE) -> 5 | H207: main-5 | I207: =VLOOKUP(H207,'Win Methods'!$C$4:$F$379,4,FALSE) -> 5 | J207: wild-12 | K207: =VLOOKUP(J207,'Win Methods'!$C$4:$F$379,4,FALSE) -> 3 | M207: =VLOOKUP(L207,'Win Methods'!$C$4:$F$379,4,FALSE) -> 0 | O207: =VLOOKUP(N207,'Win Methods'!$C$4:$F$379,4,FALSE) -> 0 | Q207: =VLOOKUP(P207,'Win Methods'!$C$4:$F$379,4,FALSE) -> 0 | S207: =VLOOKUP(R207,'Win Methods'!$C$4:$F$379,4,FALSE) -> 0 | U207: =VLOOKUP(T207,'Win Methods'!$C$4:$F$379,4,FALSE) -> 0 | W207: =VLOOKUP(V207,'Win Methods'!$C$4:$F$379,4,FALSE) -> 0 | X207: =D207&"|"&F207&"|"&H207&"|"&J207&"|"&L207&"|"&N207&"|"&P207&"|"&R207&"|"&T207&"|"&V207 -> main-11|main-25|main-5|wild-12||||||
B208: 205 | C208: =(E208+G208+I208+K208+M208+O208+Q208+S208+U208+W208) -> 18 | D208: main-18 | E208: =VLOOKUP(D208,'Win Methods'!$C$4:$F$379,4,FALSE) -> 3 | F208: main-19 | G208: =VLOOKUP(F208,'Win Methods'!$C$4:$F$379,4,FALSE) -> 5 | H208: main-5 | I208: =VLOOKUP(H208,'Win Methods'!$C$4:$F$379,4,FALSE) -> 5 | J208: wild-13 | K208: =VLOOKUP(J208,'Win Methods'!$C$4:$F$379,4,FALSE) -> 5 | M208: =VLOOKUP(L208,'Win Methods'!$C$4:$F$379,4,FALSE) -> 0 | O208: =VLOOKUP(N208,'Win Methods'!$C$4:$F$379,4,FALSE) -> 0 | Q208: =VLOOKUP(P208,'Win Methods'!$C$4:$F$379,4,FALSE) -> 0 | S208: =VLOOKUP(R208,'Win Methods'!$C$4:$F$379,4,FALSE) -> 0 | U208: =VLOOKUP(T208,'Win Methods'!$C$4:$F$379,4,FALSE) -> 0 | W208: =VLOOKUP(V208,'Win Methods'!$C$4:$F$379,4,FALSE) -> 0 | X208: =D208&"|"&F208&"|"&H208&"|"&J208&"|"&L208&"|"&N208&"|"&P208&"|"&R208&"|"&T208&"|"&V208 -> main-18|main-19|main-5|wild-13||||||
B209: 206 | C209: =(E209+G209+I209+K209+M209+O209+Q209+S209+U209+W209) -> 16 | D209: main-3 | E209: =VLOOKUP(D209,'Win Methods'!$C$4:$F$379,4,FALSE) -> 1 | F209: main-20 | G209: =VLOOKUP(F209,'Win Methods'!$C$4:$F$379,4,FALSE) -> 10 | H209: main-4 | I209: =VLOOKUP(H209,'Win Methods'!$C$4:$F$379,4,FALSE) -> 2 | J209: wild-15 | K209: =VLOOKUP(J209,'Win Methods'!$C$4:$F$379,4,FALSE) -> 3 | M209: =VLOOKUP(L209,'Win Methods'!$C$4:$F$379,4,FALSE) -> 0 | O209: =VLOOKUP(N209,'Win Methods'!$C$4:$F$379,4,FALSE) -> 0 | Q209: =VLOOKUP(P209,'Win Methods'!$C$4:$F$379,4,FALSE) -> 0 | S209: =VLOOKUP(R209,'Win Methods'!$C$4:$F$379,4,FALSE) -> 0 | U209: =VLOOKUP(T209,'Win Methods'!$C$4:$F$379,4,FALSE) -> 0 | W209: =VLOOKUP(V209,'Win Methods'!$C$4:$F$379,4,FALSE) -> 0 | X209: =D209&"|"&F209&"|"&H209&"|"&J209&"|"&L209&"|"&N209&"|"&P209&"|"&R209&"|"&T209&"|"&V209 -> main-3|main-20|main-4|wild-15||||||
B210: 207 | C210: =(E210+G210+I210+K210+M210+O210+Q210+S210+U210+W210) -> 16 | D210: main-3 | E210: =VLOOKUP(D210,'Win Methods'!$C$4:$F$379,4,FALSE) -> 1 | F210: main-5 | G210: =VLOOKUP(F210,'Win Methods'!$C$4:$F$379,4,FALSE) -> 5 | H210: main-19 | I210: =VLOOKUP(H210,'Win Methods'!$C$4:$F$379,4,FALSE) -> 5 | J210: wild-16 | K210: =VLOOKUP(J210,'Win Methods'!$C$4:$F$379,4,FALSE) -> 5 | M210: =VLOOKUP(L210,'Win Methods'!$C$4:$F$379,4,FALSE) -> 0 | O210: =VLOOKUP(N210,'Win Methods'!$C$4:$F$379,4,FALSE) -> 0 | Q210: =VLOOKUP(P210,'Win Methods'!$C$4:$F$379,4,FALSE) -> 0 | S210: =VLOOKUP(R210,'Win Methods'!$C$4:$F$379,4,FALSE) -> 0 | U210: =VLOOKUP(T210,'Win Methods'!$C$4:$F$379,4,FALSE) -> 0 | W210: =VLOOKUP(V210,'Win Methods'!$C$4:$F$379,4,FALSE) -> 0 | X210: =D210&"|"&F210&"|"&H210&"|"&J210&"|"&L210&"|"&N210&"|"&P210&"|"&R210&"|"&T210&"|"&V210 -> main-3|main-5|main-19|wild-16||||||
B211: 208 | C211: =(E211+G211+I211+K211+M211+O211+Q211+S211+U211+W211) -> 25.2 | D211: main-5 | E211: =VLOOKUP(D211,'Win Methods'!$C$4:$F$379,4,FALSE) -> 5 | F211: main-26 | G211: =VLOOKUP(F211,'Win Methods'!$C$4:$F$379,4,FALSE) -> 10 | H211: main-1 | I211: =VLOOKUP(H211,'Win Methods'!$C$4:$F$379,4,FALSE) -> 0.2 | J211: wild-17 | K211: =VLOOKUP(J211,'Win Methods'!$C$4:$F$379,4,FALSE) -> 10 | M211: =VLOOKUP(L211,'Win Methods'!$C$4:$F$379,4,FALSE) -> 0 | O211: =VLOOKUP(N211,'Win Methods'!$C$4:$F$379,4,FALSE) -> 0 | Q211: =VLOOKUP(P211,'Win Methods'!$C$4:$F$379,4,FALSE) -> 0 | S211: =VLOOKUP(R211,'Win Methods'!$C$4:$F$379,4,FALSE) -> 0 | U211: =VLOOKUP(T211,'Win Methods'!$C$4:$F$379,4,FALSE) -> 0 | W211: =VLOOKUP(V211,'Win Methods'!$C$4:$F$379,4,FALSE) -> 0 | X211: =D211&"|"&F211&"|"&H211&"|"&J211&"|"&L211&"|"&N211&"|"&P211&"|"&R211&"|"&T211&"|"&V211 -> main-5|main-26|main-1|wild-17||||||
... B216: 213 | C216: =(E216+G216+I216+K216+M216+O216+Q216+S216+U216+W216) -> 108 | D216: main-4 | E216: =VLOOKUP(D216,'Win Methods'!$C$4:$F$379,4,FALSE) -> 2 | F216: main-28 | G216: =VLOOKUP(F216,'Win Methods'!$C$4:$F$379,4,FALSE) -> 100 | H216: main-3 | I216: =VLOOKUP(H216,'Win Methods'!$C$4:$F$379,4,FALSE) -> 1 | J216: wild-5 | K216: =VLOOKUP(J216,'Win Methods'!$C$4:$F$379,4,FALSE) -> 5 | M216: =VLOOKUP(L216,'Win Methods'!$C$4:$F$379,4,FALSE) -> 0 | O216: =VLOOKUP(N216,'Win Methods'!$C$4:$F$379,4,FALSE) -> 0 | Q216: =VLOOKUP(P216,'Win Methods'!$C$4:$F$379,4,FALSE) -> 0 | S216: =VLOOKUP(R216,'Win Methods'!$C$4:$F$379,4,FALSE) -> 0 | U216: =VLOOKUP(T216,'Win Methods'!$C$4:$F$379,4,FALSE) -> 0 | W216: =VLOOKUP(V216,'Win Methods'!$C$4:$F$379,4,FALSE) -> 0 | X216: =D216&"|"&F216&"|"&H216&"|"&J216&"|"&L216&"|"&N216&"|"&P216&"|"&R216&"|"&T216&"|"&V216 -> main-4|main-28|main-3|wild-5||||||
B217: 214 | C217: =(E217+G217+I217+K217+M217+O217+Q217+S217+U217+W217) -> 15.3 | D217: main-4 | E217: =VLOOKUP(D217,'Win Methods'!$C$4:$F$379,4,FALSE) -> 2 | F217: main-0 | G217: =VLOOKUP(F217,'Win Methods'!$C$4:$F$379,4,FALSE) -> 0.1 | H217: main-1 | I217: =VLOOKUP(H217,'Win Methods'!$C$4:$F$379,4,FALSE) -> 0.2 | J217: main-18 | K217: =VLOOKUP(J217,'Win Methods'!$C$4:$F$379,4,FALSE) -> 3 | L217: wild-6 | M217: =VLOOKUP(L217,'Win Methods'!$C$4:$F$379,4,FALSE) -> 10 | O217: =VLOOKUP(N217,'Win Methods'!$C$4:$F$379,4,FALSE) -> 0 | Q217: =VLOOKUP(P217,'Win Methods'!$C$4:$F$379,4,FALSE) -> 0 | S217: =VLOOKUP(R217,'Win Methods'!$C$4:$F$379,4,FALSE) -> 0 | U217: =VLOOKUP(T217,'Win Methods'!$C$4:$F$379,4,FALSE) -> 0 | W217: =VLOOKUP(V217,'Win Methods'!$C$4:$F$379,4,FALSE) -> 0 | X217: =D217&"|"&F217&"|"&H217&"|"&J217&"|"&L217&"|"&N217&"|"&P217&"|"&R217&"|"&T217&"|"&V217 -> main-4|main-0|main-1|main-18|wild-6|||||
...

Sheet Win Methods
B2: Win methods
B3: Methods | C3: Win Methods | D3: Symbol | E3: Quantity | F3: Prize | G3: Multiplier | H3: Note
B4: x | C4: 0
B5: 1 | C5: main-0 | D5: 0,1,2,3 | E5: 3 | F5: =VLOOKUP(D5,'Pay Table'!$C$3:$M$12,E5-1,FALSE)*G5*Frequency!$N$7 -> 0.1 | G5: 1 | H5: A/B/C/D
B6: 2 | C6: main-1 | D6: 0,1,2,3 | E6: 4 | F6: =VLOOKUP(D6,'Pay Table'!$C$3:$M$12,E6-1,FALSE)*G6*Frequency!$N$7 -> 0.2 | G6: 1 | H6: A/B/C/D
B7: 3 | C7: main-2 | D7: 0,1,2,3 | E7: 5 | F7: =VLOOKUP(D7,'Pay Table'!$C$3:$M$12,E7-1,FALSE)*G7*Frequency!$N$7 -> 0.5 | G7: 1 | H7: A/B/C/D
B8: 4 | C8: main-3 | D8: 0,1,2,3 | E8: 6 | F8: =VLOOKUP(D8,'Pay Table'!$C$3:$M$12,E8-1,FALSE)*G8*Frequency!$N$7 -> 1 | G8: 1 | H8: A/B/C/D
B9: 5 | C9: main-4 | D9: 0,1,2,3 | E9: 7 | F9: =VLOOKUP(D9,'Pay Table'!$C$3:$M$12,E9-1,FALSE)*G9*Frequency!$N$7 -> 2 | G9: 1 | H9: A/B/C/D
B10: 6 | C10: main-5 | D10: 0,1,2,3 | E10: 8 | F10: =VLOOKUP(D10,'Pay Table'!$C$3:$M$12,E10-1,FALSE)*G10*Frequency!$N$7 -> 5 | G10: 1 | H10: A/B/C/D
B11: 7 | C11: main-6 | D11: 0 | E11: 9 | F11: =VLOOKUP(D11,'Pay Table'!$C$3:$M$12,E11-1,FALSE)*G11*Frequency!$N$7 -> 10 | G11: 1
B12: 8 | C12: main-7 | D12: 1 | E12: 9 | F12: =VLOOKUP(D12,'Pay Table'!$C$3:$M$12,E12-1,FALSE)*G12*Frequency!$N$7 -> 20 | G12: 1
B13: 9 | C13: main-8 | D13: 2 | E13: 9 | F13: =VLOOKUP(D13,'Pay Table'!$C$3:$M$12,E13-1,FALSE)*G13*Frequency!$N$7 -> 30 | G13: 1
B14: 10 | C14: main-9 | D14: 3 | E14: 9 | F14: =VLOOKUP(D14,'Pay Table'!$C$3:$M$12,E14-1,FALSE)*G14*Frequency!$N$7 -> 40 | G14: 1
B15: 11 | C15: main-10 | D15: 4 | E15: 3 | F15: =VLOOKUP(D15,'Pay Table'!$C$3:$M$12,E15-1,FALSE)*G15*Frequency!$N$7 -> 1 | G15: 1
B16: 12 | C16: main-11 | D16: 4 | E16: 4 | F16: =VLOOKUP(D16,'Pay Table'!$C$3:$M$12,E16-1,FALSE)*G16*Frequency!$N$7 -> 2 | G16: 1
B17: 13 | C17: main-12 | D17: 4 | E17: 5 | F17: =VLOOKUP(D17,'Pay Table'!$C$3:$M$12,E17-1,FALSE)*G17*Frequency!$N$7 -> 3 | G17: 1
B18: 14 | C18: main-13 | D18: 4 | E18: 6 | F18: =VLOOKUP(D18,'Pay Table'!$C$3:$M$12,E18-1,FALSE)*G18*Frequency!$N$7 -> 5 | G18: 1
B19: 15 | C19: main-14 | D19: 4 | E19: 7 | F19: =VLOOKUP(D19,'Pay Table'!$C$3:$M$12,E19-1,FALSE)*G19*Frequency!$N$7 -> 10 | G19: 1
B20: 16 | C20: main-15 | D20: 4 | E20: 8 | F20: =VLOOKUP(D20,'Pay Table'!$C$3:$M$12,E20-1,FALSE)*G20*Frequency!$N$7 -> 20 | G20: 1
B21: 17 | C21: main-16 | D21: 4 | E21: 9 | F21: =VLOOKUP(D21,'Pay Table'!$C$3:$M$12,E21-1,FALSE)*G21*Frequency!$N$7 -> 100 | G21: 1
B22: 18 | C22: main-17 | D22: 5 | E22: 3 | F22: =VLOOKUP(D22,'Pay Table'!$C$3:$M$12,E22-1,FALSE)*G22*Frequency!$N$7 -> 2 | G22: 1
... B35: 31 | C35: main-30 | D35: 6 | E35: 9 | F35: =VLOOKUP(D35,'Pay Table'!$C$3:$M$12,E35-1,FALSE)*G35*Frequency!$N$7 -> 1000 | G35: 1
B36: 32 | C36: wild-0 | D36: 0,1,2,3 | E36: 3 | F36: =VLOOKUP(D36,'Pay Table'!$C$3:$M$12,E36-1,FALSE)*G36*Frequency!$N$7 -> 0.1 | G36: 1 | H36: A/B/C/D
B37: 33 | C37: wild-1 | D37: 0,1,2,3 | E37: 4 | F37: =VLOOKUP(D37,'Pay Table'!$C$3:$M$12,E37-1,FALSE)*G37*Frequency!$N$7 -> 0.2 | G37: 1 | H37: A/B/C/D
B38: 34 | C38: wild-2 | D38: 0,1,2,3 | E38: 5 | F38: =VLOOKUP(D38,'Pay Table'!$C$3:$M$12,E38-1,FALSE)*G38*Frequency!$N$7 -> 0.5 | G38: 1 | H38: A/B/C/D
B39: 35 | C39: wild-3 | D39: 0,1,2,3 | E39: 6 | F39: =VLOOKUP(D39,'Pay Table'!$C$3:$M$12,E39-1,FALSE)*G39*Frequency!$N$7 -> 1 | G39: 1 | H39: A/B/C/D
B40: 36 | C40: wild-4 | D40: 0,1,2,3 | E40: 7 | F40: =VLOOKUP(D40,'Pay Table'!$C$3:$M$12,E40-1,FALSE)*G40*Frequency!$N$7 -> 2 | G40: 1 | H40: A/B/C/D
B41: 37 | C41: wild-5 | D41: 0,1,2,3 | E41: 8 | F41: =VLOOKUP(D41,'Pay Table'!$C$3:$M$12,E41-1,FALSE)*G41*Frequency!$N$7 -> 5 | G41: 1 | H41: A/B/C/D
B42: 38 | C42: wild-6 | D42: 0 | E42: 9 | F42: =VLOOKUP(D42,'Pay Table'!$C$3:$M$12,E42-1,FALSE)*G42*Frequency!$N$7 -> 10 | G42: 1
B43: 39 | C43: wild-7 | D43: 1 | E43: 9 | F43: =VLOOKUP(D43,'Pay Table'!$C$3:$M$12,E43-1,FALSE)*G43*Frequency!$N$7 -> 20 | G43: 1
B44: 40 | C44: wild-8 | D44: 2 | E44: 9 | F44: =VLOOKUP(D44,'Pay Table'!$C$3:$M$12,E44-1,FALSE)*G44*Frequency!$N$7 -> 30 | G44: 1
B45: 41 | C45: wild-9 | D45: 3 | E45: 9 | F45: =VLOOKUP(D45,'Pay Table'!$C$3:$M$12,E45-1,FALSE)*G45*Frequency!$N$7 -> 40 | G45: 1
B46: 42 | C46: wild-10 | D46: 4 | E46: 3 | F46: =VLOOKUP(D46,'Pay Table'!$C$3:$M$12,E46-1,FALSE)*G46*Frequency!$N$7 -> 1 | G46: 1
B47: 43 | C47: wild-11 | D47: 4 | E47: 4 | F47: =VLOOKUP(D47,'Pay Table'!$C$3:$M$12,E47-1,FALSE)*G47*Frequency!$N$7 -> 2 | G47: 1
B48: 44 | C48: wild-12 | D48: 4 | E48: 5 | F48: =VLOOKUP(D48,'Pay Table'!$C$3:$M$12,E48-1,FALSE)*G48*Frequency!$N$7 -> 3 | G48: 1
B49: 45 | C49: wild-13 | D49: 4 | E49: 6 | F49: =VLOOKUP(D49,'Pay Table'!$C$3:$M$12,E49-1,FALSE)*G49*Frequency!$N$7 -> 5 | G49: 1
B50: 46 | C50: wild-14 | D50: 5 | E50: 3 | F50: =VLOOKUP(D50,'Pay Table'!$C$3:$M$12,E50-1,FALSE)*G50*Frequency!$N$7 -> 2 | G50: 1
B51: 47 | C51: wild-15 | D51: 5 | E51: 4 | F51: =VLOOKUP(D51,'Pay Table'!$C$3:$M$12,E51-1,FALSE)*G51*Frequency!$N$7 -> 3 | G51: 1
B52: 48 | C52: wild-16 | D52: 5 | E52: 5 | F52: =VLOOKUP(D52,'Pay Table'!$C$3:$M$12,E52-1,FALSE)*G52*Frequency!$N$7 -> 5 | G52: 1
B53: 49 | C53: wild-17 | D53: 5 | E53: 6 | F53: =VLOOKUP(D53,'Pay Table'!$C$3:$M$12,E53-1,FALSE)*G53*Frequency!$N$7 -> 10 | G53: 1
... B57: 53 | C57: wild-21 | D57: 6 | E57: 6 | F57: =VLOOKUP(D57,'Pay Table'!$C$3:$M$12,E57-1,FALSE)*G57*Frequency!$N$7 -> 20 | G57: 1
B58: 54 | C58: freeplayA-0 | F58: {=SUM(VLOOKUP('Free Plays'!E3:AH3,Tiers!$B:$C,2,FALSE))*G58} -> 0.7 | G58: 1
B59: 55 | C59: freeplayA-1 | F59: {=SUM(VLOOKUP('Free Plays'!E4:AH4,Tiers!$B:$C,2,FALSE))*G59} -> 3 | G59: 1
B60: 56 | C60: freeplayA-2 | F60: {=SUM(VLOOKUP('Free Plays'!E5:AH5,Tiers!$B:$C,2,FALSE))*G60} -> 0.5 | G60: 1
B61: 57 | C61: freeplayA-3 | F61: {=SUM(VLOOKUP('Free Plays'!E6:AH6,Tiers!$B:$C,2,FALSE))*G61} -> 0.1 | G61: 1
B62: 58 | C62: freeplayA-4 | F62: {=SUM(VLOOKUP('Free Plays'!E7:AH7,Tiers!$B:$C,2,FALSE))*G62} -> 0.7 | G62: 1
B63: 59 | C63: freeplayA-5 | F63: {=SUM(VLOOKUP('Free Plays'!E8:AH8,Tiers!$B:$C,2,FALSE))*G63} -> 5 | G63: 1
B64: 60 | C64: freeplayA-6 | F64: {=SUM(VLOOKUP('Free Plays'!E9:AH9,Tiers!$B:$C,2,FALSE))*G64} -> 5 | G64: 1
B65: 61 | C65: freeplayA-7 | F65: {=SUM(VLOOKUP('Free Plays'!E10:AH10,Tiers!$B:$C,2,FALSE))*G65} -> 0.2 | G65: 1
B66: 62 | C66: freeplayA-8 | F66: {=SUM(VLOOKUP('Free Plays'!E11:AH11,Tiers!$B:$C,2,FALSE))*G66} -> 0.2 | G66: 1
B67: 63 | C67: freeplayA-9 | F67: {=SUM(VLOOKUP('Free Plays'!E12:AH12,Tiers!$B:$C,2,FALSE))*G67} -> 3 | G67: 1
B68: 64 | C68: freeplayA-10 | F68: {=SUM(VLOOKUP('Free Plays'!E13:AH13,Tiers!$B:$C,2,FALSE))*G68} -> 5 | G68: 1
B69: 65 | C69: freeplayA-11 | F69: {=SUM(VLOOKUP('Free Plays'!E14:AH14,Tiers!$B:$C,2,FALSE))*G69} -> 3 | G69: 1
... B91: 87 | C91: freeplayA-33 | F91: {=SUM(VLOOKUP('Free Plays'!E36:AH36,Tiers!$B:$C,2,FALSE))*G91} -> 5 | G91: 1
B92: 88 | C92: freeplayA-34 | F92: {=SUM(VLOOKUP('Free Plays'!E37:AH37,Tiers!$B:$C,2,FALSE))*G92} -> 20 | G92: 1 | H92: retrigger freeplay
B93: 89 | C93: freeplayA-35 | F93: {=SUM(VLOOKUP('Free Plays'!E38:AH38,Tiers!$B:$C,2,FALSE))*G93} -> 0.2 | G93: 1 | H93: retrigger freeplay
B94: 90 | C94: freeplayA-36 | F94: {=SUM(VLOOKUP('Free Plays'!E39:AH39,Tiers!$B:$C,2,FALSE))*G94} -> 2 | G94: 1 | H94: retrigger freeplay
B95: 91 | C95: freeplayA-37 | F95: {=SUM(VLOOKUP('Free Plays'!E40:AH40,Tiers!$B:$C,2,FALSE))*G95} -> 1 | G95: 1 | H95: trigger bonusA
B96: 92 | C96: freeplayA-38 | F96: {=SUM(VLOOKUP('Free Plays'!E41:AH41,Tiers!$B:$C,2,FALSE))*G96} -> 5 | G96: 1 | H96: trigger bonusA
B97: 93 | C97: freeplayA-39 | F97: {=SUM(VLOOKUP('Free Plays'!E42:AH42,Tiers!$B:$C,2,FALSE))*G97} -> 3 | G97: 1 | H97: trigger bonusA
B98: 94 | C98: freeplayA-40 | F98: {=SUM(VLOOKUP('Free Plays'!E43:AH43,Tiers!$B:$C,2,FALSE))*G98} -> 0.2 | G98: 1 | H98: trigger bonusA
B99: 95 | C99: freeplayA-41 | F99: {=SUM(VLOOKUP('Free Plays'!E44:AH44,Tiers!$B:$C,2,FALSE))*G99} -> 1 | G99: 1 | H99: trigger bonusB
B100: 96 | C100: freeplayA-42 | F100: {=SUM(VLOOKUP('Free Plays'!E45:AH45,Tiers!$B:$C,2,FALSE))*G100} -> 5 | G100: 1 | H100: trigger bonusB
B101: 97 | C101: freeplayA-43 | F101: {=SUM(VLOOKUP('Free Plays'!E46:AH46,Tiers!$B:$C,2,FALSE))*G101} -> 3 | G101: 1 | H101: trigger bonusB
B102: 98 | C102: freeplayA-44 | F102: {=SUM(VLOOKUP('Free Plays'!E47:AH47,Tiers!$B:$C,2,FALSE))*G102} -> 0.2 | G102: 1 | H102: trigger bonusB
B103: 371 | C103: instantA-0 | F103: =VLOOKUP(C103,'Pay Table'!$B:$C,2,FALSE)*G103*Frequency!$N$7 -> 3 | G103: 1
B104: 372 | C104: instantA-1 | F104: =VLOOKUP(C104,'Pay Table'!$B:$C,2,FALSE)*G104*Frequency!$N$7 -> 5 | G104: 1
B105: 373 | C105: instantA-2 | F105: =VLOOKUP(C105,'Pay Table'!$B:$C,2,FALSE)*G105*Frequency!$N$7 -> 8 | G105: 1
B106: 374 | C106: instantA-3 | F106: =VLOOKUP(C106,'Pay Table'!$B:$C,2,FALSE)*G106*Frequency!$N$7 -> 10 | G106: 1
B107: 375 | C107: instantA-4 | F107: =VLOOKUP(C107,'Pay Table'!$B:$C,2,FALSE)*G107*Frequency!$N$7 -> 20 | G107: 1
B108: 376 | C108: bonusA-0 | F108: =VLOOKUP(C108,'Pay Table'!$B:$C,2,FALSE)*G108*Frequency!$N$7 -> 3 | G108: 1 | H108: Power Bonus
B109: 377 | C109: bonusA-1 | F109: =VLOOKUP(C109,'Pay Table'!$B:$C,2,FALSE)*G109*Frequency!$N$7 -> 5 | G109: 1
B110: 378 | C110: bonusA-2 | F110: =VLOOKUP(C110,'Pay Table'!$B:$C,2,FALSE)*G110*Frequency!$N$7 -> 8 | G110: 1
B111: 379 | C111: bonusA-3 | F111: =VLOOKUP(C111,'Pay Table'!$B:$C,2,FALSE)*G111*Frequency!$N$7 -> 10 | G111: 1
B112: 380 | C112: bonusA-4 | F112: =VLOOKUP(C112,'Pay Table'!$B:$C,2,FALSE)*G112*Frequency!$N$7 -> 12 | G112: 1
B113: 381 | C113: bonusA-5 | F113: =VLOOKUP(C113,'Pay Table'!$B:$C,2,FALSE)*G113*Frequency!$N$7 -> 15 | G113: 1
B114: 382 | C114: bonusA-6 | F114: =VLOOKUP(C114,'Pay Table'!$B:$C,2,FALSE)*G114*Frequency!$N$7 -> 20 | G114: 1 | H114: Right col
B115: 383 | C115: bonusA-7 | F115: =VLOOKUP(C115,'Pay Table'!$B:$C,2,FALSE)*G115*Frequency!$N$7 -> 25 | G115: 1
B116: 384 | C116: bonusA-8 | F116: =VLOOKUP(C116,'Pay Table'!$B:$C,2,FALSE)*G116*Frequency!$N$7 -> 30 | G116: 1
B117: 385 | C117: bonusA-9 | F117: =VLOOKUP(C117,'Pay Table'!$B:$C,2,FALSE)*G117*Frequency!$N$7 -> 50 | G117: 1
B118: 386 | C118: bonusA-10 | F118: =VLOOKUP(C118,'Pay Table'!$B:$C,2,FALSE)*G118*Frequency!$N$7 -> 100 | G118: 1
B119: 387 | C119: bonusB-0 | F119: =VLOOKUP(C119,'Pay Table'!$B:$C,2,FALSE)*G119*Frequency!$N$7 -> 3 | G119: 1 | H119: Boost Bonus
B120: 388 | C120: bonusB-1 | F120: =VLOOKUP(C120,'Pay Table'!$B:$C,2,FALSE)*G120*Frequency!$N$7 -> 5 | G120: 1
B121: 389 | C121: bonusB-2 | F121: =VLOOKUP(C121,'Pay Table'!$B:$C,2,FALSE)*G121*Frequency!$N$7 -> 8 | G121: 1
B122: 390 | C122: bonusB-3 | F122: =VLOOKUP(C122,'Pay Table'!$B:$C,2,FALSE)*G122*Frequency!$N$7 -> 10 | G122: 1
B123: 391 | C123: bonusB-4 | F123: =VLOOKUP(C123,'Pay Table'!$B:$C,2,FALSE)*G123*Frequency!$N$7 -> 12 | G123: 1
B124: 392 | C124: bonusB-5 | F124: =VLOOKUP(C124,'Pay Table'!$B:$C,2,FALSE)*G124*Frequency!$N$7 -> 15 | G124: 1
B125: 393 | C125: bonusB-6 | F125: =VLOOKUP(C125,'Pay Table'!$B:$C,2,FALSE)*G125*Frequency!$N$7 -> 20 | G125: 1 | H125: Right col
B126: 394 | C126: bonusB-7 | F126: =VLOOKUP(C126,'Pay Table'!$B:$C,2,FALSE)*G126*Frequency!$N$7 -> 25 | G126: 1
B127: 395 | C127: bonusB-8 | F127: =VLOOKUP(C127,'Pay Table'!$B:$C,2,FALSE)*G127*Frequency!$N$7 -> 30 | G127: 1
B128: 396 | C128: bonusB-9 | F128: =VLOOKUP(C128,'Pay Table'!$B:$C,2,FALSE)*G128*Frequency!$N$7 -> 50 | G128: 1
B129: 397 | C129: bonusB-10 | F129: =VLOOKUP(C129,'Pay Table'!$B:$C,2,FALSE)*G129*Frequency!$N$7 -> 100 | G129: 1
B130: 398 | C130: bonusC-0 | F130: =VLOOKUP(C130,'Pay Table'!$B:$C,2,FALSE)*G130*Frequency!$N$7 -> 3 | G130: 1 | H130: Barrel Stack
B131: 399 | C131: bonusC-1 | F131: =VLOOKUP(C131,'Pay Table'!$B:$C,2,FALSE)*G131*Frequency!$N$7 -> 5 | G131: 1
B132: 400 | C132: bonusC-2 | F132: =VLOOKUP(C132,'Pay Table'!$B:$C,2,FALSE)*G132*Frequency!$N$7 -> 8 | G132: 1
B133: 401 | C133: bonusC-3 | F133: =VLOOKUP(C133,'Pay Table'!$B:$C,2,FALSE)*G133*Frequency!$N$7 -> 10 | G133: 1
B134: 402 | C134: bonusC-4 | F134: =VLOOKUP(C134,'Pay Table'!$B:$C,2,FALSE)*G134*Frequency!$N$7 -> 12 | G134: 1
B135: 403 | C135: bonusC-5 | F135: =VLOOKUP(C135,'Pay Table'!$B:$C,2,FALSE)*G135*Frequency!$N$7 -> 15 | G135: 1
B136: 404 | C136: bonusC-6 | F136: =VLOOKUP(C136,'Pay Table'!$B:$C,2,FALSE)*G136*Frequency!$N$7 -> 20 | G136: 1
B137: 405 | C137: bonusC-7 | F137: =VLOOKUP(C137,'Pay Table'!$B:$C,2,FALSE)*G137*Frequency!$N$7 -> 100 | G137: 1
...

Sheet Pay Table
C2: Paytable
B3: Symbols | C3: Code | D3: 3 | E3: 4 | F3: 5 | G3: 6 | H3: 7 | I3: 8 | J3: 9
B4: A | C4: 0 | D4: 0.1 | E4: 0.2 | F4: 0.5 | G4: 1 | H4: 2 | I4: 5 | J4: 10
B5: B | C5: 1 | D5: 0.1 | E5: 0.2 | F5: 0.5 | G5: 1 | H5: 2 | I5: 5 | J5: 20
B6: C | C6: 2 | D6: 0.1 | E6: 0.2 | F6: 0.5 | G6: 1 | H6: 2 | I6: 5 | J6: 30
B7: D | C7: 3 | D7: 0.1 | E7: 0.2 | F7: 0.5 | G7: 1 | H7: 2 | I7: 5 | J7: 40
B8: E | C8: 4 | D8: 1 | E8: 2 | F8: 3 | G8: 5 | H8: 10 | I8: 20 | J8: 100
B9: F | C9: 5 | D9: 2 | E9: 3 | F9: 5 | G9: 10 | H9: 20 | I9: 100 | J9: 200
B10: G | C10: 6 | D10: 3 | E10: 5 | F10: 10 | G10: 20 | H10: 100 | I10: 200 | J10: 1000
B11: A/B/C/D | C11: 0,1,2,3 | D11: 0.1 | E11: 0.2 | F11: 0.5 | G11: 1 | H11: 2 | I11: 5 | J11: -
B14: Bonus | C14: Prize | D14: Rocket Point
B15: bonusA-0 | C15: 3 | D15: 10 | E15: Power Bonus
B16: bonusA-1 | C16: 5 | D16: 20
B17: bonusA-2 | C17: 8 | D17: 30
B18: bonusA-3 | C18: 10 | D18: 40
B19: bonusA-4 | C19: 12 | D19: 50
B20: bonusA-5 | C20: 15 | D20: 60
B21: bonusA-6 | C21: 20 | D21: 70
B22: bonusA-7 | C22: 25 | D22: 80
B23: bonusA-8 | C23: 30 | D23: 90
B24: bonusA-9 | C24: 50 | D24: 100
B25: bonusA-10 | C25: 100 | D25: 150
B26: bonusB-0 | C26: 3 | D26: 10 | E26: Boost Bonus
B27: bonusB-1 | C27: 5 | D27: 20
B28: bonusB-2 | C28: 8 | D28: 30
B29: bonusB-3 | C29: 10 | D29: 40
B30: bonusB-4 | C30: 12 | D30: 50
B31: bonusB-5 | C31: 15 | D31: 60
B32: bonusB-6 | C32: 20 | D32: 70
B33: bonusB-7 | C33: 25 | D33: 80
B34: bonusB-8 | C34: 30 | D34: 90
B35: bonusB-9 | C35: 50 | D35: 100
B36: bonusB-10 | C36: 100 | D36: 150
B38: bonusC-0 | C38: 3 | E38: Barrel Stack
B39: bonusC-1 | C39: 5
B40: bonusC-2 | C40: 8
B41: bonusC-3 | C41: 10
B42: bonusC-4 | C42: 12
B43: bonusC-5 | C43: 15
B44: bonusC-6 | C44: 20
B45: bonusC-7 | C45: 100
B46: bonusC-8 | C46: 500
B49: instantA-0 | C49: 3
B50: instantA-1 | C50: 5
B51: instantA-2 | C51: 8
B52: instantA-3 | C52: 10
B53: instantA-4 | C53: 20

Sheet Free Plays
B2: TIER | C2: ROUNDS | D2: WIN METHOD | E2: ROUND 1 | F2: ROUND 2 | G2: ROUND 3 | H2: ROUND 4 | I2: ROUND 5 | J2: ROUND 6 | K2: ROUND 7 | L2: ROUND 8 | M2: ROUND 9 | N2: ROUND 10 | O2: ROUND 11 | P2: ROUND 12 | Q2: ROUND 13 | R2: ROUND 14 | S2: ROUND 15 | T2: ROUND 16 | U2: ROUND 17 | V2: ROUND 18 | W2: ROUND 19 | X2: ROUND 20 | Y2: ROUND 21 | Z2: ROUND 22 | AA2: ROUND 23 | AB2: ROUND 24 | AC2: ROUND 25 | AD2: ROUND 26 | AE2: ROUND 27 | AF2: ROUND 28 | AG2: ROUND 29 | AH2: ROUND 30
B3: 54 | C3: 10 | D3: freeplayA-0 | E3: 158 | F3: 32 | G3: 36 | H3: 33 | I3: 33
B4: 55 | C4: 10 | D4: freeplayA-1 | E4: 44 | F4: 3 | G4: 4 | H4: 35 | I4: 45 | J4: 1
B5: 56 | C5: 10 | D5: freeplayA-2 | E5: 34 | F5: 33 | G5: 1 | H5: 2 | I5: 21
B6: 57 | C6: 10 | D6: freeplayA-3 | E6: 1 | F6: 105 | G6: 160 | H6: 19 | I6: 6
B7: 58 | C7: 10 | D7: freeplayA-4 | E7: 158 | F7: 34 | G7: 108 | H7: 35 | I7: 34
B8: 59 | C8: 10 | D8: freeplayA-5 | E8: 45 | F8: 4 | G8: 50 | H8: 46 | I8: 48
B9: 60 | C9: 10 | D9: freeplayA-6 | E9: 26 | F9: 108 | G9: 3 | H9: 4 | I9: 33
B10: 61 | C10: 10 | D10: freeplayA-7 | E10: 2 | F10: 15 | G10: 1 | H10: 7
B11: 62 | C11: 10 | D11: freeplayA-8 | E11: 33 | F11: 34 | G11: 37 | H11: 34 | I11: 33 | J11: 48
B12: 63 | C12: 10 | D12: freeplayA-9 | E12: 50 | F12: 7 | G12: 5 | H12: 1 | I12: 48 | J12: 43
B13: 64 | C13: 10 | D13: freeplayA-10 | E13: 48 | F13: 2 | G13: 45 | H13: 12 | I13: 36 | J13: 19
B14: 65 | C14: 10 | D14: freeplayA-11 | E14: 50 | F14: 109 | G14: 20 | H14: 45 | I14: 32
B15: 66 | C15: 10 | D15: freeplayA-12 | E15: 33 | F15: 43 | G15: 37 | H15: 42 | I15: 34 | J15: 163
B16: 67 | C16: 10 | D16: freeplayA-13 | E16: 50 | F16: 46 | G16: 35 | H16: 38 | I16: 152
B17: 68 | C17: 10 | D17: freeplayA-14 | E17: 50 | F17: 19 | G17: 45 | H17: 142 | I17: 99
B18: 69 | C18: 10 | D18: freeplayA-15 | E18: 42 | F18: 1 | G18: 47 | H18: 14 | I18: 38 | J18: 159
B19: 70 | C19: 10 | D19: freeplayA-16 | E19: 53 | F19: 34 | G19: 107 | H19: 35 | I19: 3 | J19: 35
B20: 71 | C20: 10 | D20: freeplayA-17 | E20: 47 | F20: 36 | G20: 153 | H20: 48 | I20: 36
B21: 72 | C21: 10 | D21: freeplayA-18 | E21: 35 | F21: 104 | G21: 49 | H21: 157 | I21: 32 | J21: 44 | K21: 42
B22: 73 | C22: 10 | D22: freeplayA-19 | E22: 36 | F22: 106 | G22: 37 | H22: 37 | I22: 36
B23: 74 | C23: 10 | D23: freeplayA-20 | E23: 52 | F23: 107 | G23: 35 | H23: 46 | I23: 36 | J23: 34
B24: 75 | C24: 10 | D24: freeplayA-21 | E24: 39 | F24: 1 | G24: 105 | H24: 2 | I24: 35 | J24: 47
B25: 76 | C25: 10 | D25: freeplayA-22 | E25: 157 | F25: 5 | G25: 51 | H25: 19 | I25: 47 | J25: 53 | K25: 33
B26: 77 | C26: 10 | D26: freeplayA-23 | E26: 28 | F26: 19 | G26: 45 | H26: 12 | I26: 26
B27: 78 | C27: 10 | D27: freeplayA-24 | E27: 140 | F27: 44 | G27: 106 | H27: 37 | I27: 131 | J27: 37
B28: 79 | C28: 10 | D28: freeplayA-25 | E28: 37 | F28: 105 | G28: 44 | H28: 25 | I28: 35 | J28: 37 | K28: 35
B29: 80 | C29: 10 | D29: freeplayA-26 | E29: 48 | F29: 35 | G29: 51 | H29: 33 | I29: 21 | J29: 45
B30: 81 | C30: 10 | D30: freeplayA-27 | E30: 34 | F30: 107 | G30: 45 | H30: 33 | I30: 36 | J30: 37
B31: 82 | C31: 10 | D31: freeplayA-28 | E31: 178 | F31: 106 | G31: 158 | H31: 20 | I31: 49 | J31: 34 | K31: 37
B32: 83 | C32: 10 | D32: freeplayA-29 | E32: 43 | F32: 2 | G32: 109 | H32: 15 | I32: 44 | J32: 6 | K32: 38
B33: 84 | C33: 10 | D33: freeplayA-30 | E33: 32 | F33: 40 | G33: 34 | H33: 47 | I33: 35 | J33: 34 | K33: 52
B34: 85 | C34: 10 | D34: freeplayA-31 | E34: 7 | F34: 154 | G34: 10 | H34: 33 | I34: 33
B35: 86 | C35: 10 | D35: freeplayA-32 | E35: 32 | F35: 108 | G35: 1 | H35: 37 | I35: 37 | J35: 151 | K35: 51
B36: 87 | C36: 10 | D36: freeplayA-33 | E36: 37 | F36: 26 | G36: 37 | H36: 37 | I36: 37 | J36: 45 | K36: 13
B37: 88 | C37: 10 | D37: freeplayA-34 | E37: 8 | F37: 4 | G37: 19 | H37: 1 | I37: 58
B38: 89 | C38: 10 | D38: freeplayA-35 | E38: 2 | F38: 157 | G38: 159 | H38: 49 | I38: 59
B39: 90 | C39: 10 | D39: freeplayA-36 | E39: 46 | F39: 158 | G39: 21 | H39: 174 | I39: 60
B40: 91 | C40: 10 | D40: freeplayA-37 | E40: 4 | F40: 159 | G40: 4 | H40: 51 | I40: 45 | J40: 15 | K40: 2 | L40: 379
B41: 92 | C41: 10 | D41: freeplayA-38 | E41: 51 | F41: 156 | G41: 6 | H41: 33 | I41: 380
B42: 93 | C42: 10 | D42: freeplayA-39 | E42: 25 | F42: 34 | G42: 8 | H42: 7 | I42: 4 | J42: 381
B43: 94 | C43: 10 | D43: freeplayA-40 | E43: 33 | F43: 13 | G43: 46 | H43: 15 | I43: 33 | J43: 382
B44: 95 | C44: 10 | D44: freeplayA-41 | E44: 4 | F44: 159 | G44: 4 | H44: 51 | I44: 45 | J44: 15 | K44: 2 | L44: 390
B45: 96 | C45: 10 | D45: freeplayA-42 | E45: 51 | F45: 156 | G45: 6 | H45: 33 | I45: 391
B46: 97 | C46: 10 | D46: freeplayA-43 | E46: 25 | F46: 34 | G46: 8 | H46: 7 | I46: 4 | J46: 392
B47: 98 | C47: 10 | D47: freeplayA-44 | E47: 33 | F47: 13 | G47: 46 | H47: 15 | I47: 33 | J47: 393

Sheet Data Analysis
B1: TIER | C1: WIN METHOD | D1: PRIZE | E1: ODDS UP | F1: Value | G1: >0 to <5 value | H1: >=5 to <10 value | I1: >=10 to <25 value | J1: >= 25 value | K1: >0 to <1 | L1: >0 to <1 value | M1: =1 -> 1 | N1: 1 value | O1: >1 to 2 | P1: >1 to 2 value | Q1: >2 to 5 | R1: >2 to 5 value | S1: >5 to 10 | T1: >5 to 10 value | U1: >10 to 20 | V1: >10 to 20 value | W1: >20 to 30 | X1: >20 to 30 value | Y1: >30 to 50 | Z1: >30 to 50 value | AA1: >50 to 100 | AB1: >50 to 100 value | AC1: >100 | AD1: >100 value | AE1: Freeplay Freq | AF1: Bonus Freq | AG1: Bonus Value | AH1: Instant Freq | AI1: is Combo Win | AJ1: Combo Win Freq | AK1: Combo Win Value | AL1: is wild | AM1: wild Freq | AN1: wild Value | AO1: is Normal wild | AP1: Normal wild Freq | AQ1: Normal wild Value | AR1: is Multi wild | AS1: Multi wild Freq | AT1: Multi wild Value | AU1: freeplayA | AV1: FreeplayB | AW1: FreeplayC | AX1: bonusA | AY1: bonusA Freq | AZ1: bonusA Value | BA1: BonusB | BB1: bonusB Freq | BC1: bonusB Value | BD1: BonusC | BE1: bonusC Freq | BF1: bonusC Value | BG1: Instant | BH1: Instant Freq | BI1: Instant Value | BJ1: Freeplay rounds | BK1: Human read part1 | BL1: Human read part2 | BM1: MSE | BN1: Freeplay Multi | BO1: Instant Multi | BP1: sum of Free game rounds | BQ1: Single Freeplay Freq | BR1: Single Freeplay Value | BS1: Base + Freeplay Freq | BT1: Base + Freeplay Value | BU1: Single Bonus Freq | BV1: Single Bonus Value | BW1: Base + Bonus Freq | BX1: Base + Bonus Value
B2: =Tiers!B3 -> 0 | C2: =Tiers!X3 -> 0||||||||| | D2: =Tiers!C3 -> 0 | E2: =Frequency!E4 -> 1486523 | F2: =E2*D2 -> 0 | G2: =IF(AND(D2/Summary!$C$4>0, D2/Summary!$C$4<5),E2,0) * D2 -> 0 | H2: =IF(AND(D2/Summary!$C$4>= 5, D2/Summary!$C$4<10),E2,0) * D2 -> 0 | I2: =IF(AND(D2/Summary!$C$4>=10, D2/Summary!$C$4<25),E2,0)*D2 -> 0 | J2: =IF(D2/Summary!$C$4>=25,E2,0)*D2 -> 0 | K2: =IF(AND(D2/Frequency!$N$7>0, D2/Frequency!$N$7<1),E2,0) -> 0 | L2: =IF(K2>0,D2*E2,0) -> 0 | M2: =IF(D2/Frequency!$N$7=1,1,0)*E2 -> 0 | N2: =IF(M2>0,D2*E2,0) -> 0 | O2: =IF(AND(D2/Frequency!$N$7>1, D2/Frequency!$N$7<=2),1,0)*E2 -> 0 | P2: =IF(O2>0,D2*E2,0) -> 0 | Q2: =IF(AND(D2/Frequency!$N$7>2,D2/Frequency!$N$7<=5),1,0)*E2 -> 0 | R2: =IF(Q2>0,D2*E2,0) -> 0 | S2: =IF(AND(D2/Frequency!$N$7>5, D2/Frequency!$N$7<=10),1,0)*E2 -> 0 | T2: =IF(S2>0,D2*E2,0) -> 0 | U2: =IF(AND(D2/Frequency!$N$7>10, D2/Frequency!$N$7<=20),1,0)*E2 -> 0 | V2: =IF(U2>0,D2*E2,0) -> 0 | W2: =IF(AND(D2/Frequency!$N$7>20, D2/Frequency!$N$7<=30),1,0)*E2 -> 0 | X2: =IF(W2>0,D2*E2,0) -> 0 | Y2: =IF(AND(D2/Frequency!$N$7>30, D2/Frequency!$N$7<=50),1,0)*E2 -> 0 | Z2: =IF(Y2>0,D2*E2,0) -> 0 | AA2: =IF(AND(D2/Frequency!$N$7>50, D2/Frequency!$N$7<=100),1,0)*E2 -> 0 | AB2: =IF(AA2>0,D2*E2,0) -> 0 | AC2: =IF(D2/Frequency!$N$7>100,1,0)*E2 -> 0 | AD2: =IF(AC2>0,D2*E2,0) -> 0 | AE2: =IF(AU2>0,E2,0) -> 0 | AF2: =IF(AX2+BA2>0,E2,0) -> 0 | AG2: =AF2*D2 -> 0 | AH2: =IF(BG2>0,E2,0) -> 0 | AI2: =IF(ISNUMBER(SEARCH("|||||||||",C2)),0,1) -> 0 | AJ2: =IF(AI2=1, E2,0) -> 0 | AK2: =IF(AJ2>0,D2*E2,0) -> 0 | AL2: =IF(ISNUMBER(SEARCH("wild",C2)),1,0) -> 0 | AM2: =IF(AL2=1, E2,0) -> 0 | AN2: =IF(AM2>0,D2*E2,0) -> 0 | AO2: =IF(ISNUMBER(SEARCH("wild-",C2)),1,0) -> 0 | AP2: =IF(AO2=1, E2,0) -> 0 | AQ2: =IF(AP2>0,D2*E2,0) -> 0 | AR2: =IF(ISNUMBER(SEARCH("wildX",C2)),1,0) -> 0 | AS2: =IF(AR2=1, E2,0) -> 0 | AT2: =IF(AS2>0,D2*E2,0) -> 0 | AU2: =IF(ISNUMBER(SEARCH("FreePlay",C2)),1,0) -> 0 | AV2: 0 | AW2: 0 | AX2: =IF(ISNUMBER(SEARCH("bonusA",C2)),1,0) -> 0 | AY2: =AX2*E2 -> 0 | AZ2: =AY2*D2 -> 0 | BA2: =IF(ISNUMBER(SEARCH("bonusB",C2)),1,0) -> 0 | BB2: =BA2*E2 -> 0 | BC2: =BB2*D2 -> 0 | BD2: =IF(ISNUMBER(SEARCH("bonusC",C2)),1,0) -> 0 | BE2: =BD2*E2 -> 0 | BF2: =BE2*D2 -> 0 | BG2: =IF(ISNUMBER(SEARCH("Instant",C2)),1,0) -> 0 | BH2: =BG2*E2 -> 0 | BI2: =BH2*D2 -> 0 | BJ2: 0 | BK2: =IF(D2 < $D$417, $C$417, IF(D2 = $D$418, $C$418, IF(D2 < $D$419, $C$419, IF(D2 < $D$420, $C$420, IF(D2 < $D$421, $C$421, $C$422))))) -> Less than Stake | BL2: =IF(AU2 = 1,$C$426, IF(AV2 = 1,$C$427, IF(AW2 = 1,$C$428, IF(AX2 = 1,$C$429, IF(BA2 = 1,$C$430, IF(BD2 = 1,$C$431, IF(BG2 = 1,$C$432, IF(ISNUMBER(SEARCH("|||||||||",C2)), $C$433,$C$434)))))))) -> Single Win | BM2: =(D2/Frequency!$N$7-Summary!$C$7)^2*E2 -> 1048890.6 | BN2: =IF(AU2=1, E2*D2,0) -> 0 | BO2: =IF(BG2=1, D2*E2,0) -> 0 | BP2: =IF(BJ2>0,BJ2*E2,0) -> 0 | BQ2: =IF(AND(AU2=1, AI2=0),E2,0) -> 0 | BR2: =IF(BQ2>0,E2*D2,0) -> 0 | BS2: =IF(AND(AU2=1, AI2=1),E2,0) -> 0 | BT2: =IF(BS2>0,E2*D2,0) -> 0 | BU2: =IF(AND(AX2+BA2=1, AI2=0),E2,0) -> 0 | BV2: =IF(BU2>0,E2*D2,0) -> 0 | BW2: =IF(AND(AX2+BA2=1, AI2=1),E2,0) -> 0 | BX2: =IF(BW2>0,E2*D2,0) -> 0
B3: =Tiers!B4 -> 1 | C3: =Tiers!X4 -> main-0||||||||| | D3: =Tiers!C4 -> 0.1 | E3: =Frequency!E5 -> 48698 | F3: =E3*D3 -> 4869.8 | G3: =IF(AND(D3/Summary!$C$4>0, D3/Summary!$C$4<5),E3,0) * D3 -> 4869.8 | H3: =IF(AND(D3/Summary!$C$4>= 5, D3/Summary!$C$4<10),E3,0) * D3 -> 0 | I3: =IF(AND(D3/Summary!$C$4>=10, D3/Summary!$C$4<25),E3,0)*D3 -> 0 | J3: =IF(D3/Summary!$C$4>=25,E3,0)*D3 -> 0 | K3: =IF(AND(D3/Frequency!$N$7>0, D3/Frequency!$N$7<1),E3,0) -> 48698 | L3: =IF(K3>0,D3*E3,0) -> 4869.8 | M3: =IF(D3/Frequency!$N$7=1,1,0)*E3 -> 0 | N3: =IF(M3>0,D3*E3,0) -> 0 | O3: =IF(AND(D3/Frequency!$N$7>1, D3/Frequency!$N$7<=2),1,0)*E3 -> 0 | P3: =IF(O3>0,D3*E3,0) -> 0 | Q3: =IF(AND(D3/Frequency!$N$7>2,D3/Frequency!$N$7<=5),1,0)*E3 -> 0 | R3: =IF(Q3>0,D3*E3,0) -> 0 | S3: =IF(AND(D3/Frequency!$N$7>5, D3/Frequency!$N$7<=10),1,0)*E3 -> 0 | T3: =IF(S3>0,D3*E3,0) -> 0 | U3: =IF(AND(D3/Frequency!$N$7>10, D3/Frequency!$N$7<=20),1,0)*E3 -> 0 | V3: =IF(U3>0,D3*E3,0) -> 0 | W3: =IF(AND(D3/Frequency!$N$7>20, D3/Frequency!$N$7<=30),1,0)*E3 -> 0 | X3: =IF(W3>0,D3*E3,0) -> 0 | Y3: =IF(AND(D3/Frequency!$N$7>30, D3/Frequency!$N$7<=50),1,0)*E3 -> 0 | Z3: =IF(Y3>0,D3*E3,0) -> 0 | AA3: =IF(AND(D3/Frequency!$N$7>50, D3/Frequency!$N$7<=100),1,0)*E3 -> 0 | AB3: =IF(AA3>0,D3*E3,0) -> 0 | AC3: =IF(D3/Frequency!$N$7>100,1,0)*E3 -> 0 | AD3: =IF(AC3>0,D3*E3,0) -> 0 | AE3: =IF(AU3>0,E3,0) -> 0 | AF3: =IF(AX3+BA3>0,E3,0) -> 0 | AG3: =AF3*D3 -> 0 | AH3: =IF(BG3>0,E3,0) -> 0 | AI3: =IF(ISNUMBER(SEARCH("|||||||||",C3)),0,1) -> 0 | AJ3: =IF(AI3=1, E3,0) -> 0 | AK3: =IF(AJ3>0,D3*E3,0) -> 0 | AL3: =IF(ISNUMBER(SEARCH("wild",C3)),1,0) -> 0 | AM3: =IF(AL3=1, E3,0) -> 0 | AN3: =IF(AM3>0,D3*E3,0) -> 0 | AO3: =IF(ISNUMBER(SEARCH("wild-",C3)),1,0) -> 0 | AP3: =IF(AO3=1, E3,0) -> 0 | AQ3: =IF(AP3>0,D3*E3,0) -> 0 | AR3: =IF(ISNUMBER(SEARCH("wildX",C3)),1,0) -> 0 | AS3: =IF(AR3=1, E3,0) -> 0 | AT3: =IF(AS3>0,D3*E3,0) -> 0 | AU3: =IF(ISNUMBER(SEARCH("FreePlay",C3)),1,0) -> 0 | AV3: 0 | AW3: 0 | AX3: =IF(ISNUMBER(SEARCH("bonusA",C3)),1,0) -> 0 | AY3: =AX3*E3 -> 0 | AZ3: =AY3*D3 -> 0 | BA3: =IF(ISNUMBER(SEARCH("bonusB",C3)),1,0) -> 0 | BB3: =BA3*E3 -> 0 | BC3: =BB3*D3 -> 0 | BD3: =IF(ISNUMBER(SEARCH("bonusC",C3)),1,0) -> 0 | BE3: =BD3*E3 -> 0 | BF3: =BE3*D3 -> 0 | BG3: =IF(ISNUMBER(SEARCH("Instant",C3)),1,0) -> 0 | BH3: =BG3*E3 -> 0 | BI3: =BH3*D3 -> 0 | BJ3: 0 | BK3: =IF(D3 < $D$417, $C$417, IF(D3 = $D$418, $C$418, IF(D3 < $D$419, $C$419, IF(D3 < $D$420, $C$420, IF(D3 < $D$421, $C$421, $C$422))))) -> Less than Stake | BL3: =IF(AU3 = 1,$C$426, IF(AV3 = 1,$C$427, IF(AW3 = 1,$C$428, IF(AX3 = 1,$C$429, IF(BA3 = 1,$C$430, IF(BD3 = 1,$C$431, IF(BG3 = 1,$C$432, IF(ISNUMBER(SEARCH("|||||||||",C3)), $C$433,$C$434)))))))) -> Single Win | BM3: =(D3/Frequency!$N$7-Summary!$C$7)^2*E3 -> 26667.025 | BN3: =IF(AU3=1, E3*D3,0) -> 0 | BO3: =IF(BG3=1, D3*E3,0) -> 0 | BP3: =IF(BJ3>0,BJ3*E3,0) -> 0 | BQ3: =IF(AND(AU3=1, AI3=0),E3,0) -> 0 | BR3: =IF(BQ3>0,E3*D3,0) -> 0 | BS3: =IF(AND(AU3=1, AI3=1),E3,0) -> 0 | BT3: =IF(BS3>0,E3*D3,0) -> 0 | BU3: =IF(AND(AX3+BA3=1, AI3=0),E3,0) -> 0 | BV3: =IF(BU3>0,E3*D3,0) -> 0 | BW3: =IF(AND(AX3+BA3=1, AI3=1),E3,0) -> 0 | BX3: =IF(BW3>0,E3*D3,0) -> 0
B4: =Tiers!B5 -> 2 | C4: =Tiers!X5 -> main-1||||||||| | D4: =Tiers!C5 -> 0.2 | E4: =Frequency!E6 -> 35002 | F4: =E4*D4 -> 7000.4 | G4: =IF(AND(D4/Summary!$C$4>0, D4/Summary!$C$4<5),E4,0) * D4 -> 7000.4 | H4: =IF(AND(D4/Summary!$C$4>= 5, D4/Summary!$C$4<10),E4,0) * D4 -> 0 | I4: =IF(AND(D4/Summary!$C$4>=10, D4/Summary!$C$4<25),E4,0)*D4 -> 0 | J4: =IF(D4/Summary!$C$4>=25,E4,0)*D4 -> 0 | K4: =IF(AND(D4/Frequency!$N$7>0, D4/Frequency!$N$7<1),E4,0) -> 35002 | L4: =IF(K4>0,D4*E4,0) -> 7000.4 | M4: =IF(D4/Frequency!$N$7=1,1,0)*E4 -> 0 | N4: =IF(M4>0,D4*E4,0) -> 0 | O4: =IF(AND(D4/Frequency!$N$7>1, D4/Frequency!$N$7<=2),1,0)*E4 -> 0 | P4: =IF(O4>0,D4*E4,0) -> 0 | Q4: =IF(AND(D4/Frequency!$N$7>2,D4/Frequency!$N$7<=5),1,0)*E4 -> 0 | R4: =IF(Q4>0,D4*E4,0) -> 0 | S4: =IF(AND(D4/Frequency!$N$7>5, D4/Frequency!$N$7<=10),1,0)*E4 -> 0 | T4: =IF(S4>0,D4*E4,0) -> 0 | U4: =IF(AND(D4/Frequency!$N$7>10, D4/Frequency!$N$7<=20),1,0)*E4 -> 0 | V4: =IF(U4>0,D4*E4,0) -> 0 | W4: =IF(AND(D4/Frequency!$N$7>20, D4/Frequency!$N$7<=30),1,0)*E4 -> 0 | X4: =IF(W4>0,D4*E4,0) -> 0 | Y4: =IF(AND(D4/Frequency!$N$7>30, D4/Frequency!$N$7<=50),1,0)*E4 -> 0 | Z4: =IF(Y4>0,D4*E4,0) -> 0 | AA4: =IF(AND(D4/Frequency!$N$7>50, D4/Frequency!$N$7<=100),1,0)*E4 -> 0 | AB4: =IF(AA4>0,D4*E4,0) -> 0 | AC4: =IF(D4/Frequency!$N$7>100,1,0)*E4 -> 0 | AD4: =IF(AC4>0,D4*E4,0) -> 0 | AE4: =IF(AU4>0,E4,0) -> 0 | AF4: =IF(AX4+BA4>0,E4,0) -> 0 | AG4: =AF4*D4 -> 0 | AH4: =IF(BG4>0,E4,0) -> 0 | AI4: =IF(ISNUMBER(SEARCH("|||||||||",C4)),0,1) -> 0 | AJ4: =IF(AI4=1, E4,0) -> 0 | AK4: =IF(AJ4>0,D4*E4,0) -> 0 | AL4: =IF(ISNUMBER(SEARCH("wild",C4)),1,0) -> 0 | AM4: =IF(AL4=1, E4,0) -> 0 | AN4: =IF(AM4>0,D4*E4,0) -> 0 | AO4: =IF(ISNUMBER(SEARCH("wild-",C4)),1,0) -> 0 | AP4: =IF(AO4=1, E4,0) -> 0 | AQ4: =IF(AP4>0,D4*E4,0) -> 0 | AR4: =IF(ISNUMBER(SEARCH("wildX",C4)),1,0) -> 0 | AS4: =IF(AR4=1, E4,0) -> 0 | AT4: =IF(AS4>0,D4*E4,0) -> 0 | AU4: =IF(ISNUMBER(SEARCH("FreePlay",C4)),1,0) -> 0 | AV4: 0 | AW4: 0 | AX4: =IF(ISNUMBER(SEARCH("bonusA",C4)),1,0) -> 0 | AY4: =AX4*E4 -> 0 | AZ4: =AY4*D4 -> 0 | BA4: =IF(ISNUMBER(SEARCH("bonusB",C4)),1,0) -> 0 | BB4: =BA4*E4 -> 0 | BC4: =BB4*D4 -> 0 | BD4: =IF(ISNUMBER(SEARCH("bonusC",C4)),1,0) -> 0 | BE4: =BD4*E4 -> 0 | BF4: =BE4*D4 -> 0 | BG4: =IF(ISNUMBER(SEARCH("Instant",C4)),1,0) -> 0 | BH4: =BG4*E4 -> 0 | BI4: =BH4*D4 -> 0 | BJ4: 0 | BK4: =IF(D4 < $D$417, $C$417, IF(D4 = $D$418, $C$418, IF(D4 < $D$419, $C$419, IF(D4 < $D$420, $C$420, IF(D4 < $D$421, $C$421, $C$422))))) -> Less than Stake | BL4: =IF(AU4 = 1,$C$426, IF(AV4 = 1,$C$427, IF(AW4 = 1,$C$428, IF(AX4 = 1,$C$429, IF(BA4 = 1,$C$430, IF(BD4 = 1,$C$431, IF(BG4 = 1,$C$432, IF(ISNUMBER(SEARCH("|||||||||",C4)), $C$433,$C$434)))))))) -> Single Win | BM4: =(D4/Frequency!$N$7-Summary!$C$7)^2*E4 -> 14336.819 | BN4: =IF(AU4=1, E4*D4,0) -> 0 | BO4: =IF(BG4=1, D4*E4,0) -> 0 | BP4: =IF(BJ4>0,BJ4*E4,0) -> 0 | BQ4: =IF(AND(AU4=1, AI4=0),E4,0) -> 0 | BR4: =IF(BQ4>0,E4*D4,0) -> 0 | BS4: =IF(AND(AU4=1, AI4=1),E4,0) -> 0 | BT4: =IF(BS4>0,E4*D4,0) -> 0 | BU4: =IF(AND(AX4+BA4=1, AI4=0),E4,0) -> 0 | BV4: =IF(BU4>0,E4*D4,0) -> 0 | BW4: =IF(AND(AX4+BA4=1, AI4=1),E4,0) -> 0 | BX4: =IF(BW4>0,E4*D4,0) -> 0
B5: =Tiers!B6 -> 3 | C5: =Tiers!X6 -> main-2||||||||| | D5: =Tiers!C6 -> 0.5 | E5: =Frequency!E7 -> 20000 | F5: =E5*D5 -> 10000 | G5: =IF(AND(D5/Summary!$C$4>0, D5/Summary!$C$4<5),E5,0) * D5 -> 10000 | H5: =IF(AND(D5/Summary!$C$4>= 5, D5/Summary!$C$4<10),E5,0) * D5 -> 0 | I5: =IF(AND(D5/Summary!$C$4>=10, D5/Summary!$C$4<25),E5,0)*D5 -> 0 | J5: =IF(D5/Summary!$C$4>=25,E5,0)*D5 -> 0 | K5: =IF(AND(D5/Frequency!$N$7>0, D5/Frequency!$N$7<1),E5,0) -> 20000 | L5: =IF(K5>0,D5*E5,0) -> 10000 | M5: =IF(D5/Frequency!$N$7=1,1,0)*E5 -> 0 | N5: =IF(M5>0,D5*E5,0) -> 0 | O5: =IF(AND(D5/Frequency!$N$7>1, D5/Frequency!$N$7<=2),1,0)*E5 -> 0 | P5: =IF(O5>0,D5*E5,0) -> 0 | Q5: =IF(AND(D5/Frequency!$N$7>2,D5/Frequency!$N$7<=5),1,0)*E5 -> 0 | R5: =IF(Q5>0,D5*E5,0) -> 0 | S5: =IF(AND(D5/Frequency!$N$7>5, D5/Frequency!$N$7<=10),1,0)*E5 -> 0 | T5: =IF(S5>0,D5*E5,0) -> 0 | U5: =IF(AND(D5/Frequency!$N$7>10, D5/Frequency!$N$7<=20),1,0)*E5 -> 0 | V5: =IF(U5>0,D5*E5,0) -> 0 | W5: =IF(AND(D5/Frequency!$N$7>20, D5/Frequency!$N$7<=30),1,0)*E5 -> 0 | X5: =IF(W5>0,D5*E5,0) -> 0 | Y5: =IF(AND(D5/Frequency!$N$7>30, D5/Frequency!$N$7<=50),1,0)*E5 -> 0 | Z5: =IF(Y5>0,D5*E5,0) -> 0 | AA5: =IF(AND(D5/Frequency!$N$7>50, D5/Frequency!$N$7<=100),1,0)*E5 -> 0 | AB5: =IF(AA5>0,D5*E5,0) -> 0 | AC5: =IF(D5/Frequency!$N$7>100,1,0)*E5 -> 0 | AD5: =IF(AC5>0,D5*E5,0) -> 0 | AE5: =IF(AU5>0,E5,0) -> 0 | AF5: =IF(AX5+BA5>0,E5,0) -> 0 | AG5: =AF5*D5 -> 0 | AH5: =IF(BG5>0,E5,0) -> 0 | AI5: =IF(ISNUMBER(SEARCH("|||||||||",C5)),0,1) -> 0 | AJ5: =IF(AI5=1, E5,0) -> 0 | AK5: =IF(AJ5>0,D5*E5,0) -> 0 | AL5: =IF(ISNUMBER(SEARCH("wild",C5)),1,0) -> 0 | AM5: =IF(AL5=1, E5,0) -> 0 | AN5: =IF(AM5>0,D5*E5,0) -> 0 | AO5: =IF(ISNUMBER(SEARCH("wild-",C5)),1,0) -> 0 | AP5: =IF(AO5=1, E5,0) -> 0 | AQ5: =IF(AP5>0,D5*E5,0) -> 0 | AR5: =IF(ISNUMBER(SEARCH("wildX",C5)),1,0) -> 0 | AS5: =IF(AR5=1, E5,0) -> 0 | AT5: =IF(AS5>0,D5*E5,0) -> 0 | AU5: =IF(ISNUMBER(SEARCH("FreePlay",C5)),1,0) -> 0 | AV5: 0 | AW5: 0 | AX5: =IF(ISNUMBER(SEARCH("bonusA",C5)),1,0) -> 0 | AY5: =AX5*E5 -> 0 | AZ5: =AY5*D5 -> 0 | BA5: =IF(ISNUMBER(SEARCH("bonusB",C5)),1,0) -> 0 | BB5: =BA5*E5 -> 0 | BC5: =BB5*D5 -> 0 | BD5: =IF(ISNUMBER(SEARCH("bonusC",C5)),1,0) -> 0 | BE5: =BD5*E5 -> 0 | BF5: =BE5*D5 -> 0 | BG5: =IF(ISNUMBER(SEARCH("Instant",C5)),1,0) -> 0 | BH5: =BG5*E5 -> 0 | BI5: =BH5*D5 -> 0 | BJ5: 0 | BK5: =IF(D5 < $D$417, $C$417, IF(D5 = $D$418, $C$418, IF(D5 < $D$419, $C$419, IF(D5 < $D$420, $C$420, IF(D5 < $D$421, $C$421, $C$422))))) -> Less than Stake | BL5: =IF(AU5 = 1,$C$426, IF(AV5 = 1,$C$427, IF(AW5 = 1,$C$428, IF(AX5 = 1,$C$429, IF(BA5 = 1,$C$430, IF(BD5 = 1,$C$431, IF(BG5 = 1,$C$432, IF(ISNUMBER(SEARCH("|||||||||",C5)), $C$433,$C$434)))))))) -> Single Win | BM5: =(D5/Frequency!$N$7-Summary!$C$7)^2*E5 -> 2312 | BN5: =IF(AU5=1, E5*D5,0) -> 0 | BO5: =IF(BG5=1, D5*E5,0) -> 0 | BP5: =IF(BJ5>0,BJ5*E5,0) -> 0 | BQ5: =IF(AND(AU5=1, AI5=0),E5,0) -> 0 | BR5: =IF(BQ5>0,E5*D5,0) -> 0 | BS5: =IF(AND(AU5=1, AI5=1),E5,0) -> 0 | BT5: =IF(BS5>0,E5*D5,0) -> 0 | BU5: =IF(AND(AX5+BA5=1, AI5=0),E5,0) -> 0 | BV5: =IF(BU5>0,E5*D5,0) -> 0 | BW5: =IF(AND(AX5+BA5=1, AI5=1),E5,0) -> 0 | BX5: =IF(BW5>0,E5*D5,0) -> 0
B6: =Tiers!B7 -> 4 | C6: =Tiers!X7 -> main-3||||||||| | D6: =Tiers!C7 -> 1 | E6: =Frequency!E8 -> 27000 | F6: =E6*D6 -> 27000 | G6: =IF(AND(D6/Summary!$C$4>0, D6/Summary!$C$4<5),E6,0) * D6 -> 27000 | H6: =IF(AND(D6/Summary!$C$4>= 5, D6/Summary!$C$4<10),E6,0) * D6 -> 0 | I6: =IF(AND(D6/Summary!$C$4>=10, D6/Summary!$C$4<25),E6,0)*D6 -> 0 | J6: =IF(D6/Summary!$C$4>=25,E6,0)*D6 -> 0 | K6: =IF(AND(D6/Frequency!$N$7>0, D6/Frequency!$N$7<1),E6,0) -> 0 | L6: =IF(K6>0,D6*E6,0) -> 0 | M6: =IF(D6/Frequency!$N$7=1,1,0)*E6 -> 27000 | N6: =IF(M6>0,D6*E6,0) -> 27000 | O6: =IF(AND(D6/Frequency!$N$7>1, D6/Frequency!$N$7<=2),1,0)*E6 -> 0 | P6: =IF(O6>0,D6*E6,0) -> 0 | Q6: =IF(AND(D6/Frequency!$N$7>2,D6/Frequency!$N$7<=5),1,0)*E6 -> 0 | R6: =IF(Q6>0,D6*E6,0) -> 0 | S6: =IF(AND(D6/Frequency!$N$7>5, D6/Frequency!$N$7<=10),1,0)*E6 -> 0 | T6: =IF(S6>0,D6*E6,0) -> 0 | U6: =IF(AND(D6/Frequency!$N$7>10, D6/Frequency!$N$7<=20),1,0)*E6 -> 0 | V6: =IF(U6>0,D6*E6,0) -> 0 | W6: =IF(AND(D6/Frequency!$N$7>20, D6/Frequency!$N$7<=30),1,0)*E6 -> 0 | X6: =IF(W6>0,D6*E6,0) -> 0 | Y6: =IF(AND(D6/Frequency!$N$7>30, D6/Frequency!$N$7<=50),1,0)*E6 -> 0 | Z6: =IF(Y6>0,D6*E6,0) -> 0 | AA6: =IF(AND(D6/Frequency!$N$7>50, D6/Frequency!$N$7<=100),1,0)*E6 -> 0 | AB6: =IF(AA6>0,D6*E6,0) -> 0 | AC6: =IF(D6/Frequency!$N$7>100,1,0)*E6 -> 0 | AD6: =IF(AC6>0,D6*E6,0) -> 0 | AE6: =IF(AU6>0,E6,0) -> 0 | AF6: =IF(AX6+BA6>0,E6,0) -> 0 | AG6: =AF6*D6 -> 0 | AH6: =IF(BG6>0,E6,0) -> 0 | AI6: =IF(ISNUMBER(SEARCH("|||||||||",C6)),0,1) -> 0 | AJ6: =IF(AI6=1, E6,0) -> 0 | AK6: =IF(AJ6>0,D6*E6,0) -> 0 | AL6: =IF(ISNUMBER(SEARCH("wild",C6)),1,0) -> 0 | AM6: =IF(AL6=1, E6,0) -> 0 | AN6: =IF(AM6>0,D6*E6,0) -> 0 | AO6: =IF(ISNUMBER(SEARCH("wild-",C6)),1,0) -> 0 | AP6: =IF(AO6=1, E6,0) -> 0 | AQ6: =IF(AP6>0,D6*E6,0) -> 0 | AR6: =IF(ISNUMBER(SEARCH("wildX",C6)),1,0) -> 0 | AS6: =IF(AR6=1, E6,0) -> 0 | AT6: =IF(AS6>0,D6*E6,0) -> 0 | AU6: =IF(ISNUMBER(SEARCH("FreePlay",C6)),1,0) -> 0 | AV6: 0 | AW6: 0 | AX6: =IF(ISNUMBER(SEARCH("bonusA",C6)),1,0) -> 0 | AY6: =AX6*E6 -> 0 | AZ6: =AY6*D6 -> 0 | BA6: =IF(ISNUMBER(SEARCH("bonusB",C6)),1,0) -> 0 | BB6: =BA6*E6 -> 0 | BC6: =BB6*D6 -> 0 | BD6: =IF(ISNUMBER(SEARCH("bonusC",C6)),1,0) -> 0 | BE6: =BD6*E6 -> 0 | BF6: =BE6*D6 -> 0 | BG6: =IF(ISNUMBER(SEARCH("Instant",C6)),1,0) -> 0 | BH6: =BG6*E6 -> 0 | BI6: =BH6*D6 -> 0 | BJ6: 0 | BK6: =IF(D6 < $D$417, $C$417, IF(D6 = $D$418, $C$418, IF(D6 < $D$419, $C$419, IF(D6 < $D$420, $C$420, IF(D6 < $D$421, $C$421, $C$422))))) -> Stake Back | BL6: =IF(AU6 = 1,$C$426, IF(AV6 = 1,$C$427, IF(AW6 = 1,$C$428, IF(AX6 = 1,$C$429, IF(BA6 = 1,$C$430, IF(BD6 = 1,$C$431, IF(BG6 = 1,$C$432, IF(ISNUMBER(SEARCH("|||||||||",C6)), $C$433,$C$434)))))))) -> Single Win | BM6: =(D6/Frequency!$N$7-Summary!$C$7)^2*E6 -> 691.2 | BN6: =IF(AU6=1, E6*D6,0) -> 0 | BO6: =IF(BG6=1, D6*E6,0) -> 0 | BP6: =IF(BJ6>0,BJ6*E6,0) -> 0 | BQ6: =IF(AND(AU6=1, AI6=0),E6,0) -> 0 | BR6: =IF(BQ6>0,E6*D6,0) -> 0 | BS6: =IF(AND(AU6=1, AI6=1),E6,0) -> 0 | BT6: =IF(BS6>0,E6*D6,0) -> 0 | BU6: =IF(AND(AX6+BA6=1, AI6=0),E6,0) -> 0 | BV6: =IF(BU6>0,E6*D6,0) -> 0 | BW6: =IF(AND(AX6+BA6=1, AI6=1),E6,0) -> 0 | BX6: =IF(BW6>0,E6*D6,0) -> 0
B7: =Tiers!B8 -> 5 | C7: =Tiers!X8 -> main-4||||||||| | D7: =Tiers!C8 -> 2 | E7: =Frequency!E9 -> 5000 | F7: =E7*D7 -> 10000 | G7: =IF(AND(D7/Summary!$C$4>0, D7/Summary!$C$4<5),E7,0) * D7 -> 10000 | H7: =IF(AND(D7/Summary!$C$4>= 5, D7/Summary!$C$4<10),E7,0) * D7 -> 0 | I7: =IF(AND(D7/Summary!$C$4>=10, D7/Summary!$C$4<25),E7,0)*D7 -> 0 | J7: =IF(D7/Summary!$C$4>=25,E7,0)*D7 -> 0 | K7: =IF(AND(D7/Frequency!$N$7>0, D7/Frequency!$N$7<1),E7,0) -> 0 | L7: =IF(K7>0,D7*E7,0) -> 0 | M7: =IF(D7/Frequency!$N$7=1,1,0)*E7 -> 0 | N7: =IF(M7>0,D7*E7,0) -> 0 | O7: =IF(AND(D7/Frequency!$N$7>1, D7/Frequency!$N$7<=2),1,0)*E7 -> 5000 | P7: =IF(O7>0,D7*E7,0) -> 10000 | Q7: =IF(AND(D7/Frequency!$N$7>2,D7/Frequency!$N$7<=5),1,0)*E7 -> 0 | R7: =IF(Q7>0,D7*E7,0) -> 0 | S7: =IF(AND(D7/Frequency!$N$7>5, D7/Frequency!$N$7<=10),1,0)*E7 -> 0 | T7: =IF(S7>0,D7*E7,0) -> 0 | U7: =IF(AND(D7/Frequency!$N$7>10, D7/Frequency!$N$7<=20),1,0)*E7 -> 0 | V7: =IF(U7>0,D7*E7,0) -> 0 | W7: =IF(AND(D7/Frequency!$N$7>20, D7/Frequency!$N$7<=30),1,0)*E7 -> 0 | X7: =IF(W7>0,D7*E7,0) -> 0 | Y7: =IF(AND(D7/Frequency!$N$7>30, D7/Frequency!$N$7<=50),1,0)*E7 -> 0 | Z7: =IF(Y7>0,D7*E7,0) -> 0 | AA7: =IF(AND(D7/Frequency!$N$7>50, D7/Frequency!$N$7<=100),1,0)*E7 -> 0 | AB7: =IF(AA7>0,D7*E7,0) -> 0 | AC7: =IF(D7/Frequency!$N$7>100,1,0)*E7 -> 0 | AD7: =IF(AC7>0,D7*E7,0) -> 0 | AE7: =IF(AU7>0,E7,0) -> 0 | AF7: =IF(AX7+BA7>0,E7,0) -> 0 | AG7: =AF7*D7 -> 0 | AH7: =IF(BG7>0,E7,0) -> 0 | AI7: =IF(ISNUMBER(SEARCH("|||||||||",C7)),0,1) -> 0 | AJ7: =IF(AI7=1, E7,0) -> 0 | AK7: =IF(AJ7>0,D7*E7,0) -> 0 | AL7: =IF(ISNUMBER(SEARCH("wild",C7)),1,0) -> 0 | AM7: =IF(AL7=1, E7,0) -> 0 | AN7: =IF(AM7>0,D7*E7,0) -> 0 | AO7: =IF(ISNUMBER(SEARCH("wild-",C7)),1,0) -> 0 | AP7: =IF(AO7=1, E7,0) -> 0 | AQ7: =IF(AP7>0,D7*E7,0) -> 0 | AR7: =IF(ISNUMBER(SEARCH("wildX",C7)),1,0) -> 0 | AS7: =IF(AR7=1, E7,0) -> 0 | AT7: =IF(AS7>0,D7*E7,0) -> 0 | AU7: =IF(ISNUMBER(SEARCH("FreePlay",C7)),1,0) -> 0 | AV7: 0 | AW7: 0 | AX7: =IF(ISNUMBER(SEARCH("bonusA",C7)),1,0) -> 0 | AY7: =AX7*E7 -> 0 | AZ7: =AY7*D7 -> 0 | BA7: =IF(ISNUMBER(SEARCH("bonusB",C7)),1,0) -> 0 | BB7: =BA7*E7 -> 0 | BC7: =BB7*D7 -> 0 | BD7: =IF(ISNUMBER(SEARCH("bonusC",C7)),1,0) -> 0 | BE7: =BD7*E7 -> 0 | BF7: =BE7*D7 -> 0 | BG7: =IF(ISNUMBER(SEARCH("Instant",C7)),1,0) -> 0 | BH7: =BG7*E7 -> 0 | BI7: =BH7*D7 -> 0 | BJ7: 0 | BK7: =IF(D7 < $D$417, $C$417, IF(D7 = $D$418, $C$418, IF(D7 < $D$419, $C$419, IF(D7 < $D$420, $C$420, IF(D7 < $D$421, $C$421, $C$422))))) -> Standard Win | BL7: =IF(AU7 = 1,$C$426, IF(AV7 = 1,$C$427, IF(AW7 = 1,$C$428, IF(AX7 = 1,$C$429, IF(BA7 = 1,$C$430, IF(BD7 = 1,$C$431, IF(BG7 = 1,$C$432, IF(ISNUMBER(SEARCH("|||||||||",C7)), $C$433,$C$434)))))))) -> Single Win | BM7: =(D7/Frequency!$N$7-Summary!$C$7)^2*E7 -> 6728 | BN7: =IF(AU7=1, E7*D7,0) -> 0 | BO7: =IF(BG7=1, D7*E7,0) -> 0 | BP7: =IF(BJ7>0,BJ7*E7,0) -> 0 | BQ7: =IF(AND(AU7=1, AI7=0),E7,0) -> 0 | BR7: =IF(BQ7>0,E7*D7,0) -> 0 | BS7: =IF(AND(AU7=1, AI7=1),E7,0) -> 0 | BT7: =IF(BS7>0,E7*D7,0) -> 0 | BU7: =IF(AND(AX7+BA7=1, AI7=0),E7,0) -> 0 | BV7: =IF(BU7>0,E7*D7,0) -> 0 | BW7: =IF(AND(AX7+BA7=1, AI7=1),E7,0) -> 0 | BX7: =IF(BW7>0,E7*D7,0) -> 0
B8: =Tiers!B9 -> 6 | C8: =Tiers!X9 -> main-5||||||||| | D8: =Tiers!C9 -> 5 | E8: =Frequency!E10 -> 1000 | F8: =E8*D8 -> 5000 | G8: =IF(AND(D8/Summary!$C$4>0, D8/Summary!$C$4<5),E8,0) * D8 -> 0 | H8: =IF(AND(D8/Summary!$C$4>= 5, D8/Summary!$C$4<10),E8,0) * D8 -> 5000 | I8: =IF(AND(D8/Summary!$C$4>=10, D8/Summary!$C$4<25),E8,0)*D8 -> 0 | J8: =IF(D8/Summary!$C$4>=25,E8,0)*D8 -> 0 | K8: =IF(AND(D8/Frequency!$N$7>0, D8/Frequency!$N$7<1),E8,0) -> 0 | L8: =IF(K8>0,D8*E8,0) -> 0 | M8: =IF(D8/Frequency!$N$7=1,1,0)*E8 -> 0 | N8: =IF(M8>0,D8*E8,0) -> 0 | O8: =IF(AND(D8/Frequency!$N$7>1, D8/Frequency!$N$7<=2),1,0)*E8 -> 0 | P8: =IF(O8>0,D8*E8,0) -> 0 | Q8: =IF(AND(D8/Frequency!$N$7>2,D8/Frequency!$N$7<=5),1,0)*E8 -> 1000 | R8: =IF(Q8>0,D8*E8,0) -> 5000 | S8: =IF(AND(D8/Frequency!$N$7>5, D8/Frequency!$N$7<=10),1,0)*E8 -> 0 | T8: =IF(S8>0,D8*E8,0) -> 0 | U8: =IF(AND(D8/Frequency!$N$7>10, D8/Frequency!$N$7<=20),1,0)*E8 -> 0 | V8: =IF(U8>0,D8*E8,0) -> 0 | W8: =IF(AND(D8/Frequency!$N$7>20, D8/Frequency!$N$7<=30),1,0)*E8 -> 0 | X8: =IF(W8>0,D8*E8,0) -> 0 | Y8: =IF(AND(D8/Frequency!$N$7>30, D8/Frequency!$N$7<=50),1,0)*E8 -> 0 | Z8: =IF(Y8>0,D8*E8,0) -> 0 | AA8: =IF(AND(D8/Frequency!$N$7>50, D8/Frequency!$N$7<=100),1,0)*E8 -> 0 | AB8: =IF(AA8>0,D8*E8,0) -> 0 | AC8: =IF(D8/Frequency!$N$7>100,1,0)*E8 -> 0 | AD8: =IF(AC8>0,D8*E8,0) -> 0 | AE8: =IF(AU8>0,E8,0) -> 0 | AF8: =IF(AX8+BA8>0,E8,0) -> 0 | AG8: =AF8*D8 -> 0 | AH8: =IF(BG8>0,E8,0) -> 0 | AI8: =IF(ISNUMBER(SEARCH("|||||||||",C8)),0,1) -> 0 | AJ8: =IF(AI8=1, E8,0) -> 0 | AK8: =IF(AJ8>0,D8*E8,0) -> 0 | AL8: =IF(ISNUMBER(SEARCH("wild",C8)),1,0) -> 0 | AM8: =IF(AL8=1, E8,0) -> 0 | AN8: =IF(AM8>0,D8*E8,0) -> 0 | AO8: =IF(ISNUMBER(SEARCH("wild-",C8)),1,0) -> 0 | AP8: =IF(AO8=1, E8,0) -> 0 | AQ8: =IF(AP8>0,D8*E8,0) -> 0 | AR8: =IF(ISNUMBER(SEARCH("wildX",C8)),1,0) -> 0 | AS8: =IF(AR8=1, E8,0) -> 0 | AT8: =IF(AS8>0,D8*E8,0) -> 0 | AU8: =IF(ISNUMBER(SEARCH("FreePlay",C8)),1,0) -> 0 | AV8: 0 | AW8: 0 | AX8: =IF(ISNUMBER(SEARCH("bonusA",C8)),1,0) -> 0 | AY8: =AX8*E8 -> 0 | AZ8: =AY8*D8 -> 0 | BA8: =IF(ISNUMBER(SEARCH("bonusB",C8)),1,0) -> 0 | BB8: =BA8*E8 -> 0 | BC8: =BB8*D8 -> 0 | BD8: =IF(ISNUMBER(SEARCH("bonusC",C8)),1,0) -> 0 | BE8: =BD8*E8 -> 0 | BF8: =BE8*D8 -> 0 | BG8: =IF(ISNUMBER(SEARCH("Instant",C8)),1,0) -> 0 | BH8: =BG8*E8 -> 0 | BI8: =BH8*D8 -> 0 | BJ8: 0 | BK8: =IF(D8 < $D$417, $C$417, IF(D8 = $D$418, $C$418, IF(D8 < $D$419, $C$419, IF(D8 < $D$420, $C$420, IF(D8 < $D$421, $C$421, $C$422))))) -> Standard Win | BL8: =IF(AU8 = 1,$C$426, IF(AV8 = 1,$C$427, IF(AW8 = 1,$C$428, IF(AX8 = 1,$C$429, IF(BA8 = 1,$C$430, IF(BD8 = 1,$C$431, IF(BG8 = 1,$C$432, IF(ISNUMBER(SEARCH("|||||||||",C8)), $C$433,$C$434)))))))) -> Single Win | BM8: =(D8/Frequency!$N$7-Summary!$C$7)^2*E8 -> 17305.6 | BN8: =IF(AU8=1, E8*D8,0) -> 0 | BO8: =IF(BG8=1, D8*E8,0) -> 0 | BP8: =IF(BJ8>0,BJ8*E8,0) -> 0 | BQ8: =IF(AND(AU8=1, AI8=0),E8,0) -> 0 | BR8: =IF(BQ8>0,E8*D8,0) -> 0 | BS8: =IF(AND(AU8=1, AI8=1),E8,0) -> 0 | BT8: =IF(BS8>0,E8*D8,0) -> 0 | BU8: =IF(AND(AX8+BA8=1, AI8=0),E8,0) -> 0 | BV8: =IF(BU8>0,E8*D8,0) -> 0 | BW8: =IF(AND(AX8+BA8=1, AI8=1),E8,0) -> 0 | BX8: =IF(BW8>0,E8*D8,0) -> 0
B9: =Tiers!B10 -> 7 | C9: =Tiers!X10 -> main-6||||||||| | D9: =Tiers!C10 -> 10 | E9: =Frequency!E11 -> 188 | F9: =E9*D9 -> 1880 | G9: =IF(AND(D9/Summary!$C$4>0, D9/Summary!$C$4<5),E9,0) * D9 -> 0 | H9: =IF(AND(D9/Summary!$C$4>= 5, D9/Summary!$C$4<10),E9,0) * D9 -> 0 | I9: =IF(AND(D9/Summary!$C$4>=10, D9/Summary!$C$4<25),E9,0)*D9 -> 1880 | J9: =IF(D9/Summary!$C$4>=25,E9,0)*D9 -> 0 | K9: =IF(AND(D9/Frequency!$N$7>0, D9/Frequency!$N$7<1),E9,0) -> 0 | L9: =IF(K9>0,D9*E9,0) -> 0 | M9: =IF(D9/Frequency!$N$7=1,1,0)*E9 -> 0 | N9: =IF(M9>0,D9*E9,0) -> 0 | O9: =IF(AND(D9/Frequency!$N$7>1, D9/Frequency!$N$7<=2),1,0)*E9 -> 0 | P9: =IF(O9>0,D9*E9,0) -> 0 | Q9: =IF(AND(D9/Frequency!$N$7>2,D9/Frequency!$N$7<=5),1,0)*E9 -> 0 | R9: =IF(Q9>0,D9*E9,0) -> 0 | S9: =IF(AND(D9/Frequency!$N$7>5, D9/Frequency!$N$7<=10),1,0)*E9 -> 188 | T9: =IF(S9>0,D9*E9,0) -> 1880 | U9: =IF(AND(D9/Frequency!$N$7>10, D9/Frequency!$N$7<=20),1,0)*E9 -> 0 | V9: =IF(U9>0,D9*E9,0) -> 0 | W9: =IF(AND(D9/Frequency!$N$7>20, D9/Frequency!$N$7<=30),1,0)*E9 -> 0 | X9: =IF(W9>0,D9*E9,0) -> 0 | Y9: =IF(AND(D9/Frequency!$N$7>30, D9/Frequency!$N$7<=50),1,0)*E9 -> 0 | Z9: =IF(Y9>0,D9*E9,0) -> 0 | AA9: =IF(AND(D9/Frequency!$N$7>50, D9/Frequency!$N$7<=100),1,0)*E9 -> 0 | AB9: =IF(AA9>0,D9*E9,0) -> 0 | AC9: =IF(D9/Frequency!$N$7>100,1,0)*E9 -> 0 | AD9: =IF(AC9>0,D9*E9,0) -> 0 | AE9: =IF(AU9>0,E9,0) -> 0 | AF9: =IF(AX9+BA9>0,E9,0) -> 0 | AG9: =AF9*D9 -> 0 | AH9: =IF(BG9>0,E9,0) -> 0 | AI9: =IF(ISNUMBER(SEARCH("|||||||||",C9)),0,1) -> 0 | AJ9: =IF(AI9=1, E9,0) -> 0 | AK9: =IF(AJ9>0,D9*E9,0) -> 0 | AL9: =IF(ISNUMBER(SEARCH("wild",C9)),1,0) -> 0 | AM9: =IF(AL9=1, E9,0) -> 0 | AN9: =IF(AM9>0,D9*E9,0) -> 0 | AO9: =IF(ISNUMBER(SEARCH("wild-",C9)),1,0) -> 0 | AP9: =IF(AO9=1, E9,0) -> 0 | AQ9: =IF(AP9>0,D9*E9,0) -> 0 | AR9: =IF(ISNUMBER(SEARCH("wildX",C9)),1,0) -> 0 | AS9: =IF(AR9=1, E9,0) -> 0 | AT9: =IF(AS9>0,D9*E9,0) -> 0 | AU9: =IF(ISNUMBER(SEARCH("FreePlay",C9)),1,0) -> 0 | AV9: 0 | AW9: 0 | AX9: =IF(ISNUMBER(SEARCH("bonusA",C9)),1,0) -> 0 | AY9: =AX9*E9 -> 0 | AZ9: =AY9*D9 -> 0 | BA9: =IF(ISNUMBER(SEARCH("bonusB",C9)),1,0) -> 0 | BB9: =BA9*E9 -> 0 | BC9: =BB9*D9 -> 0 | BD9: =IF(ISNUMBER(SEARCH("bonusC",C9)),1,0) -> 0 | BE9: =BD9*E9 -> 0 | BF9: =BE9*D9 -> 0 | BG9: =IF(ISNUMBER(SEARCH("Instant",C9)),1,0) -> 0 | BH9: =BG9*E9 -> 0 | BI9: =BH9*D9 -> 0 | BJ9: 0 | BK9: =IF(D9 < $D$417, $C$417, IF(D9 = $D$418, $C$418, IF(D9 < $D$419, $C$419, IF(D9 < $D$420, $C$420, IF(D9 < $D$421, $C$421, $C$422))))) -> Big Win | BL9: =IF(AU9 = 1,$C$426, IF(AV9 = 1,$C$427, IF(AW9 = 1,$C$428, IF(AX9 = 1,$C$429, IF(BA9 = 1,$C$430, IF(BD9 = 1,$C$431, IF(BG9 = 1,$C$432, IF(ISNUMBER(SEARCH("|||||||||",C9)), $C$433,$C$434)))))))) -> Single Win | BM9: =(D9/Frequency!$N$7-Summary!$C$7)^2*E9 -> 15774.253 | BN9: =IF(AU9=1, E9*D9,0) -> 0 | BO9: =IF(BG9=1, D9*E9,0) -> 0 | BP9: =IF(BJ9>0,BJ9*E9,0) -> 0 | BQ9: =IF(AND(AU9=1, AI9=0),E9,0) -> 0 | BR9: =IF(BQ9>0,E9*D9,0) -> 0 | BS9: =IF(AND(AU9=1, AI9=1),E9,0) -> 0 | BT9: =IF(BS9>0,E9*D9,0) -> 0 | BU9: =IF(AND(AX9+BA9=1, AI9=0),E9,0) -> 0 | BV9: =IF(BU9>0,E9*D9,0) -> 0 | BW9: =IF(AND(AX9+BA9=1, AI9=1),E9,0) -> 0 | BX9: =IF(BW9>0,E9*D9,0) -> 0
B10: =Tiers!B11 -> 8 | C10: =Tiers!X11 -> main-7||||||||| | D10: =Tiers!C11 -> 20 | E10: =Frequency!E12 -> 50 | F10: =E10*D10 -> 1000 | G10: =IF(AND(D10/Summary!$C$4>0, D10/Summary!$C$4<5),E10,0) * D10 -> 0 | H10: =IF(AND(D10/Summary!$C$4>= 5, D10/Summary!$C$4<10),E10,0) * D10 -> 0 | I10: =IF(AND(D10/Summary!$C$4>=10, D10/Summary!$C$4<25),E10,0)*D10 -> 1000 | J10: =IF(D10/Summary!$C$4>=25,E10,0)*D10 -> 0 | K10: =IF(AND(D10/Frequency!$N$7>0, D10/Frequency!$N$7<1),E10,0) -> 0 | L10: =IF(K10>0,D10*E10,0) -> 0 | M10: =IF(D10/Frequency!$N$7=1,1,0)*E10 -> 0 | N10: =IF(M10>0,D10*E10,0) -> 0 | O10: =IF(AND(D10/Frequency!$N$7>1, D10/Frequency!$N$7<=2),1,0)*E10 -> 0 | P10: =IF(O10>0,D10*E10,0) -> 0 | Q10: =IF(AND(D10/Frequency!$N$7>2,D10/Frequency!$N$7<=5),1,0)*E10 -> 0 | R10: =IF(Q10>0,D10*E10,0) -> 0 | S10: =IF(AND(D10/Frequency!$N$7>5, D10/Frequency!$N$7<=10),1,0)*E10 -> 0 | T10: =IF(S10>0,D10*E10,0) -> 0 | U10: =IF(AND(D10/Frequency!$N$7>10, D10/Frequency!$N$7<=20),1,0)*E10 -> 50 | V10: =IF(U10>0,D10*E10,0) -> 1000 | W10: =IF(AND(D10/Frequency!$N$7>20, D10/Frequency!$N$7<=30),1,0)*E10 -> 0 | X10: =IF(W10>0,D10*E10,0) -> 0 | Y10: =IF(AND(D10/Frequency!$N$7>30, D10/Frequency!$N$7<=50),1,0)*E10 -> 0 | Z10: =IF(Y10>0,D10*E10,0) -> 0 | AA10: =IF(AND(D10/Frequency!$N$7>50, D10/Frequency!$N$7<=100),1,0)*E10 -> 0 | AB10: =IF(AA10>0,D10*E10,0) -> 0 | AC10: =IF(D10/Frequency!$N$7>100,1,0)*E10 -> 0 | AD10: =IF(AC10>0,D10*E10,0) -> 0 | AE10: =IF(AU10>0,E10,0) -> 0 | AF10: =IF(AX10+BA10>0,E10,0) -> 0 | AG10: =AF10*D10 -> 0 | AH10: =IF(BG10>0,E10,0) -> 0 | AI10: =IF(ISNUMBER(SEARCH("|||||||||",C10)),0,1) -> 0 | AJ10: =IF(AI10=1, E10,0) -> 0 | AK10: =IF(AJ10>0,D10*E10,0) -> 0 | AL10: =IF(ISNUMBER(SEARCH("wild",C10)),1,0) -> 0 | AM10: =IF(AL10=1, E10,0) -> 0 | AN10: =IF(AM10>0,D10*E10,0) -> 0 | AO10: =IF(ISNUMBER(SEARCH("wild-",C10)),1,0) -> 0 | AP10: =IF(AO10=1, E10,0) -> 0 | AQ10: =IF(AP10>0,D10*E10,0) -> 0 | AR10: =IF(ISNUMBER(SEARCH("wildX",C10)),1,0) -> 0 | AS10: =IF(AR10=1, E10,0) -> 0 | AT10: =IF(AS10>0,D10*E10,0) -> 0 | AU10: =IF(ISNUMBER(SEARCH("FreePlay",C10)),1,0) -> 0 | AV10: 0 | AW10: 0 | AX10: =IF(ISNUMBER(SEARCH("bonusA",C10)),1,0) -> 0 | AY10: =AX10*E10 -> 0 | AZ10: =AY10*D10 -> 0 | BA10: =IF(ISNUMBER(SEARCH("bonusB",C10)),1,0) -> 0 | BB10: =BA10*E10 -> 0 | BC10: =BB10*D10 -> 0 | BD10: =IF(ISNUMBER(SEARCH("bonusC",C10)),1,0) -> 0 | BE10: =BD10*E10 -> 0 | BF10: =BE10*D10 -> 0 | BG10: =IF(ISNUMBER(SEARCH("Instant",C10)),1,0) -> 0 | BH10: =BG10*E10 -> 0 | BI10: =BH10*D10 -> 0 | BJ10: 0 | BK10: =IF(D10 < $D$417, $C$417, IF(D10 = $D$418, $C$418, IF(D10 < $D$419, $C$419, IF(D10 < $D$420, $C$420, IF(D10 < $D$421, $C$421, $C$422))))) -> Big Win | BL10: =IF(AU10 = 1,$C$426, IF(AV10 = 1,$C$427, IF(AW10 = 1,$C$428, IF(AX10 = 1,$C$429, IF(BA10 = 1,$C$430, IF(BD10 = 1,$C$431, IF(BG10 = 1,$C$432, IF(ISNUMBER(SEARCH("|||||||||",C10)), $C$433,$C$434)))))))) -> Single Win | BM10: =(D10/Frequency!$N$7-Summary!$C$7)^2*E10 -> 18355.28 | BN10: =IF(AU10=1, E10*D10,0) -> 0 | BO10: =IF(BG10=1, D10*E10,0) -> 0 | BP10: =IF(BJ10>0,BJ10*E10,0) -> 0 | BQ10: =IF(AND(AU10=1, AI10=0),E10,0) -> 0 | BR10: =IF(BQ10>0,E10*D10,0) -> 0 | BS10: =IF(AND(AU10=1, AI10=1),E10,0) -> 0 | BT10: =IF(BS10>0,E10*D10,0) -> 0 | BU10: =IF(AND(AX10+BA10=1, AI10=0),E10,0) -> 0 | BV10: =IF(BU10>0,E10*D10,0) -> 0 | BW10: =IF(AND(AX10+BA10=1, AI10=1),E10,0) -> 0 | BX10: =IF(BW10>0,E10*D10,0) -> 0
B11: =Tiers!B12 -> 9 | C11: =Tiers!X12 -> main-8||||||||| | D11: =Tiers!C12 -> 30 | E11: =Frequency!E13 -> 10 | F11: =E11*D11 -> 300 | G11: =IF(AND(D11/Summary!$C$4>0, D11/Summary!$C$4<5),E11,0) * D11 -> 0 | H11: =IF(AND(D11/Summary!$C$4>= 5, D11/Summary!$C$4<10),E11,0) * D11 -> 0 | I11: =IF(AND(D11/Summary!$C$4>=10, D11/Summary!$C$4<25),E11,0)*D11 -> 0 | J11: =IF(D11/Summary!$C$4>=25,E11,0)*D11 -> 300 | K11: =IF(AND(D11/Frequency!$N$7>0, D11/Frequency!$N$7<1),E11,0) -> 0 | L11: =IF(K11>0,D11*E11,0) -> 0 | M11: =IF(D11/Frequency!$N$7=1,1,0)*E11 -> 0 | N11: =IF(M11>0,D11*E11,0) -> 0 | O11: =IF(AND(D11/Frequency!$N$7>1, D11/Frequency!$N$7<=2),1,0)*E11 -> 0 | P11: =IF(O11>0,D11*E11,0) -> 0 | Q11: =IF(AND(D11/Frequency!$N$7>2,D11/Frequency!$N$7<=5),1,0)*E11 -> 0 | R11: =IF(Q11>0,D11*E11,0) -> 0 | S11: =IF(AND(D11/Frequency!$N$7>5, D11/Frequency!$N$7<=10),1,0)*E11 -> 0 | T11: =IF(S11>0,D11*E11,0) -> 0 | U11: =IF(AND(D11/Frequency!$N$7>10, D11/Frequency!$N$7<=20),1,0)*E11 -> 0 | V11: =IF(U11>0,D11*E11,0) -> 0 | W11: =IF(AND(D11/Frequency!$N$7>20, D11/Frequency!$N$7<=30),1,0)*E11 -> 10 | X11: =IF(W11>0,D11*E11,0) -> 300 | Y11: =IF(AND(D11/Frequency!$N$7>30, D11/Frequency!$N$7<=50),1,0)*E11 -> 0 | Z11: =IF(Y11>0,D11*E11,0) -> 0 | AA11: =IF(AND(D11/Frequency!$N$7>50, D11/Frequency!$N$7<=100),1,0)*E11 -> 0 | AB11: =IF(AA11>0,D11*E11,0) -> 0 | AC11: =IF(D11/Frequency!$N$7>100,1,0)*E11 -> 0 | AD11: =IF(AC11>0,D11*E11,0) -> 0 | AE11: =IF(AU11>0,E11,0) -> 0 | AF11: =IF(AX11+BA11>0,E11,0) -> 0 | AG11: =AF11*D11 -> 0 | AH11: =IF(BG11>0,E11,0) -> 0 | AI11: =IF(ISNUMBER(SEARCH("|||||||||",C11)),0,1) -> 0 | AJ11: =IF(AI11=1, E11,0) -> 0 | AK11: =IF(AJ11>0,D11*E11,0) -> 0 | AL11: =IF(ISNUMBER(SEARCH("wild",C11)),1,0) -> 0 | AM11: =IF(AL11=1, E11,0) -> 0 | AN11: =IF(AM11>0,D11*E11,0) -> 0 | AO11: =IF(ISNUMBER(SEARCH("wild-",C11)),1,0) -> 0 | AP11: =IF(AO11=1, E11,0) -> 0 | AQ11: =IF(AP11>0,D11*E11,0) -> 0 | AR11: =IF(ISNUMBER(SEARCH("wildX",C11)),1,0) -> 0 | AS11: =IF(AR11=1, E11,0) -> 0 | AT11: =IF(AS11>0,D11*E11,0) -> 0 | AU11: =IF(ISNUMBER(SEARCH("FreePlay",C11)),1,0) -> 0 | AV11: 0 | AW11: 0 | AX11: =IF(ISNUMBER(SEARCH("bonusA",C11)),1,0) -> 0 | AY11: =AX11*E11 -> 0 | AZ11: =AY11*D11 -> 0 | BA11: =IF(ISNUMBER(SEARCH("bonusB",C11)),1,0) -> 0 | BB11: =BA11*E11 -> 0 | BC11: =BB11*D11 -> 0 | BD11: =IF(ISNUMBER(SEARCH("bonusC",C11)),1,0) -> 0 | BE11: =BD11*E11 -> 0 | BF11: =BE11*D11 -> 0 | BG11: =IF(ISNUMBER(SEARCH("Instant",C11)),1,0) -> 0 | BH11: =BG11*E11 -> 0 | BI11: =BH11*D11 -> 0 | BJ11: 0 | BK11: =IF(D11 < $D$417, $C$417, IF(D11 = $D$418, $C$418, IF(D11 < $D$419, $C$419, IF(D11 < $D$420, $C$420, IF(D11 < $D$421, $C$421, $C$422))))) -> Big Win | BL11: =IF(AU11 = 1,$C$426, IF(AV11 = 1,$C$427, IF(AW11 = 1,$C$428, IF(AX11 = 1,$C$429, IF(BA11 = 1,$C$430, IF(BD11 = 1,$C$431, IF(BG11 = 1,$C$432, IF(ISNUMBER(SEARCH("|||||||||",C11)), $C$433,$C$434)))))))) -> Single Win | BM11: =(D11/Frequency!$N$7-Summary!$C$7)^2*E11 -> 8503.056 | BN11: =IF(AU11=1, E11*D11,0) -> 0 | BO11: =IF(BG11=1, D11*E11,0) -> 0 | BP11: =IF(BJ11>0,BJ11*E11,0) -> 0 | BQ11: =IF(AND(AU11=1, AI11=0),E11,0) -> 0 | BR11: =IF(BQ11>0,E11*D11,0) -> 0 | BS11: =IF(AND(AU11=1, AI11=1),E11,0) -> 0 | BT11: =IF(BS11>0,E11*D11,0) -> 0 | BU11: =IF(AND(AX11+BA11=1, AI11=0),E11,0) -> 0 | BV11: =IF(BU11>0,E11*D11,0) -> 0 | BW11: =IF(AND(AX11+BA11=1, AI11=1),E11,0) -> 0 | BX11: =IF(BW11>0,E11*D11,0) -> 0
B12: =Tiers!B13 -> 10 | C12: =Tiers!X13 -> main-9||||||||| | D12: =Tiers!C13 -> 40 | E12: =Frequency!E14 -> 5 | F12: =E12*D12 -> 200 | G12: =IF(AND(D12/Summary!$C$4>0, D12/Summary!$C$4<5),E12,0) * D12 -> 0 | H12: =IF(AND(D12/Summary!$C$4>= 5, D12/Summary!$C$4<10),E12,0) * D12 -> 0 | I12: =IF(AND(D12/Summary!$C$4>=10, D12/Summary!$C$4<25),E12,0)*D12 -> 0 | J12: =IF(D12/Summary!$C$4>=25,E12,0)*D12 -> 200 | K12: =IF(AND(D12/Frequency!$N$7>0, D12/Frequency!$N$7<1),E12,0) -> 0 | L12: =IF(K12>0,D12*E12,0) -> 0 | M12: =IF(D12/Frequency!$N$7=1,1,0)*E12 -> 0 | N12: =IF(M12>0,D12*E12,0) -> 0 | O12: =IF(AND(D12/Frequency!$N$7>1, D12/Frequency!$N$7<=2),1,0)*E12 -> 0 | P12: =IF(O12>0,D12*E12,0) -> 0 | Q12: =IF(AND(D12/Frequency!$N$7>2,D12/Frequency!$N$7<=5),1,0)*E12 -> 0 | R12: =IF(Q12>0,D12*E12,0) -> 0 | S12: =IF(AND(D12/Frequency!$N$7>5, D12/Frequency!$N$7<=10),1,0)*E12 -> 0 | T12: =IF(S12>0,D12*E12,0) -> 0 | U12: =IF(AND(D12/Frequency!$N$7>10, D12/Frequency!$N$7<=20),1,0)*E12 -> 0 | V12: =IF(U12>0,D12*E12,0) -> 0 | W12: =IF(AND(D12/Frequency!$N$7>20, D12/Frequency!$N$7<=30),1,0)*E12 -> 0 | X12: =IF(W12>0,D12*E12,0) -> 0 | Y12: =IF(AND(D12/Frequency!$N$7>30, D12/Frequency!$N$7<=50),1,0)*E12 -> 5 | Z12: =IF(Y12>0,D12*E12,0) -> 200 | AA12: =IF(AND(D12/Frequency!$N$7>50, D12/Frequency!$N$7<=100),1,0)*E12 -> 0 | AB12: =IF(AA12>0,D12*E12,0) -> 0 | AC12: =IF(D12/Frequency!$N$7>100,1,0)*E12 -> 0 | AD12: =IF(AC12>0,D12*E12,0) -> 0 | AE12: =IF(AU12>0,E12,0) -> 0 | AF12: =IF(AX12+BA12>0,E12,0) -> 0 | AG12: =AF12*D12 -> 0 | AH12: =IF(BG12>0,E12,0) -> 0 | AI12: =IF(ISNUMBER(SEARCH("|||||||||",C12)),0,1) -> 0 | AJ12: =IF(AI12=1, E12,0) -> 0 | AK12: =IF(AJ12>0,D12*E12,0) -> 0 | AL12: =IF(ISNUMBER(SEARCH("wild",C12)),1,0) -> 0 | AM12: =IF(AL12=1, E12,0) -> 0 | AN12: =IF(AM12>0,D12*E12,0) -> 0 | AO12: =IF(ISNUMBER(SEARCH("wild-",C12)),1,0) -> 0 | AP12: =IF(AO12=1, E12,0) -> 0 | AQ12: =IF(AP12>0,D12*E12,0) -> 0 | AR12: =IF(ISNUMBER(SEARCH("wildX",C12)),1,0) -> 0 | AS12: =IF(AR12=1, E12,0) -> 0 | AT12: =IF(AS12>0,D12*E12,0) -> 0 | AU12: =IF(ISNUMBER(SEARCH("FreePlay",C12)),1,0) -> 0 | AV12: 0 | AW12: 0 | AX12: =IF(ISNUMBER(SEARCH("bonusA",C12)),1,0) -> 0 | AY12: =AX12*E12 -> 0 | AZ12: =AY12*D12 -> 0 | BA12: =IF(ISNUMBER(SEARCH("bonusB",C12)),1,0) -> 0 | BB12: =BA12*E12 -> 0 | BC12: =BB12*D12 -> 0 | BD12: =IF(ISNUMBER(SEARCH("bonusC",C12)),1,0) -> 0 | BE12: =BD12*E12 -> 0 | BF12: =BE12*D12 -> 0 | BG12: =IF(ISNUMBER(SEARCH("Instant",C12)),1,0) -> 0 | BH12: =BG12*E12 -> 0 | BI12: =BH12*D12 -> 0 | BJ12: 0 | BK12: =IF(D12 < $D$417, $C$417, IF(D12 = $D$418, $C$418, IF(D12 < $D$419, $C$419, IF(D12 < $D$420, $C$420, IF(D12 < $D$421, $C$421, $C$422))))) -> Big Win | BL12: =IF(AU12 = 1,$C$426, IF(AV12 = 1,$C$427, IF(AW12 = 1,$C$428, IF(AX12 = 1,$C$429, IF(BA12 = 1,$C$430, IF(BD12 = 1,$C$431, IF(BG12 = 1,$C$432, IF(ISNUMBER(SEARCH("|||||||||",C12)), $C$433,$C$434)))))))) -> Single Win | BM12: =(D12/Frequency!$N$7-Summary!$C$7)^2*E12 -> 7667.528 | BN12: =IF(AU12=1, E12*D12,0) -> 0 | BO12: =IF(BG12=1, D12*E12,0) -> 0 | BP12: =IF(BJ12>0,BJ12*E12,0) -> 0 | BQ12: =IF(AND(AU12=1, AI12=0),E12,0) -> 0 | BR12: =IF(BQ12>0,E12*D12,0) -> 0 | BS12: =IF(AND(AU12=1, AI12=1),E12,0) -> 0 | BT12: =IF(BS12>0,E12*D12,0) -> 0 | BU12: =IF(AND(AX12+BA12=1, AI12=0),E12,0) -> 0 | BV12: =IF(BU12>0,E12*D12,0) -> 0 | BW12: =IF(AND(AX12+BA12=1, AI12=1),E12,0) -> 0 | BX12: =IF(BW12>0,E12*D12,0) -> 0
B13: =Tiers!B14 -> 11 | C13: =Tiers!X14 -> main-10||||||||| | D13: =Tiers!C14 -> 1 | E13: =Frequency!E15 -> 30152 | F13: =E13*D13 -> 30152 | G13: =IF(AND(D13/Summary!$C$4>0, D13/Summary!$C$4<5),E13,0) * D13 -> 30152 | H13: =IF(AND(D13/Summary!$C$4>= 5, D13/Summary!$C$4<10),E13,0) * D13 -> 0 | I13: =IF(AND(D13/Summary!$C$4>=10, D13/Summary!$C$4<25),E13,0)*D13 -> 0 | J13: =IF(D13/Summary!$C$4>=25,E13,0)*D13 -> 0 | K13: =IF(AND(D13/Frequency!$N$7>0, D13/Frequency!$N$7<1),E13,0) -> 0 | L13: =IF(K13>0,D13*E13,0) -> 0 | M13: =IF(D13/Frequency!$N$7=1,1,0)*E13 -> 30152 | N13: =IF(M13>0,D13*E13,0) -> 30152 | O13: =IF(AND(D13/Frequency!$N$7>1, D13/Frequency!$N$7<=2),1,0)*E13 -> 0 | P13: =IF(O13>0,D13*E13,0) -> 0 | Q13: =IF(AND(D13/Frequency!$N$7>2,D13/Frequency!$N$7<=5),1,0)*E13 -> 0 | R13: =IF(Q13>0,D13*E13,0) -> 0 | S13: =IF(AND(D13/Frequency!$N$7>5, D13/Frequency!$N$7<=10),1,0)*E13 -> 0 | T13: =IF(S13>0,D13*E13,0) -> 0 | U13: =IF(AND(D13/Frequency!$N$7>10, D13/Frequency!$N$7<=20),1,0)*E13 -> 0 | V13: =IF(U13>0,D13*E13,0) -> 0 | W13: =IF(AND(D13/Frequency!$N$7>20, D13/Frequency!$N$7<=30),1,0)*E13 -> 0 | X13: =IF(W13>0,D13*E13,0) -> 0 | Y13: =IF(AND(D13/Frequency!$N$7>30, D13/Frequency!$N$7<=50),1,0)*E13 -> 0 | Z13: =IF(Y13>0,D13*E13,0) -> 0 | AA13: =IF(AND(D13/Frequency!$N$7>50, D13/Frequency!$N$7<=100),1,0)*E13 -> 0 | AB13: =IF(AA13>0,D13*E13,0) -> 0 | AC13: =IF(D13/Frequency!$N$7>100,1,0)*E13 -> 0 | AD13: =IF(AC13>0,D13*E13,0) -> 0 | AE13: =IF(AU13>0,E13,0) -> 0 | AF13: =IF(AX13+BA13>0,E13,0) -> 0 | AG13: =AF13*D13 -> 0 | AH13: =IF(BG13>0,E13,0) -> 0 | AI13: =IF(ISNUMBER(SEARCH("|||||||||",C13)),0,1) -> 0 | AJ13: =IF(AI13=1, E13,0) -> 0 | AK13: =IF(AJ13>0,D13*E13,0) -> 0 | AL13: =IF(ISNUMBER(SEARCH("wild",C13)),1,0) -> 0 | AM13: =IF(AL13=1, E13,0) -> 0 | AN13: =IF(AM13>0,D13*E13,0) -> 0 | AO13: =IF(ISNUMBER(SEARCH("wild-",C13)),1,0) -> 0 | AP13: =IF(AO13=1, E13,0) -> 0 | AQ13: =IF(AP13>0,D13*E13,0) -> 0 | AR13: =IF(ISNUMBER(SEARCH("wildX",C13)),1,0) -> 0 | AS13: =IF(AR13=1, E13,0) -> 0 | AT13: =IF(AS13>0,D13*E13,0) -> 0 | AU13: =IF(ISNUMBER(SEARCH("FreePlay",C13)),1,0) -> 0 | AV13: 0 | AW13: 0 | AX13: =IF(ISNUMBER(SEARCH("bonusA",C13)),1,0) -> 0 | AY13: =AX13*E13 -> 0 | AZ13: =AY13*D13 -> 0 | BA13: =IF(ISNUMBER(SEARCH("bonusB",C13)),1,0) -> 0 | BB13: =BA13*E13 -> 0 | BC13: =BB13*D13 -> 0 | BD13: =IF(ISNUMBER(SEARCH("bonusC",C13)),1,0) -> 0 | BE13: =BD13*E13 -> 0 | BF13: =BE13*D13 -> 0 | BG13: =IF(ISNUMBER(SEARCH("Instant",C13)),1,0) -> 0 | BH13: =BG13*E13 -> 0 | BI13: =BH13*D13 -> 0 | BJ13: 0 | BK13: =IF(D13 < $D$417, $C$417, IF(D13 = $D$418, $C$418, IF(D13 < $D$419, $C$419, IF(D13 < $D$420, $C$420, IF(D13 < $D$421, $C$421, $C$422))))) -> Stake Back | BL13: =IF(AU13 = 1,$C$426, IF(AV13 = 1,$C$427, IF(AW13 = 1,$C$428, IF(AX13 = 1,$C$429, IF(BA13 = 1,$C$430, IF(BD13 = 1,$C$431, IF(BG13 = 1,$C$432, IF(ISNUMBER(SEARCH("|||||||||",C13)), $C$433,$C$434)))))))) -> Single Win | BM13: =(D13/Frequency!$N$7-Summary!$C$7)^2*E13 -> 771.8912 | BN13: =IF(AU13=1, E13*D13,0) -> 0 | BO13: =IF(BG13=1, D13*E13,0) -> 0 | BP13: =IF(BJ13>0,BJ13*E13,0) -> 0 | BQ13: =IF(AND(AU13=1, AI13=0),E13,0) -> 0 | BR13: =IF(BQ13>0,E13*D13,0) -> 0 | BS13: =IF(AND(AU13=1, AI13=1),E13,0) -> 0 | BT13: =IF(BS13>0,E13*D13,0) -> 0 | BU13: =IF(AND(AX13+BA13=1, AI13=0),E13,0) -> 0 | BV13: =IF(BU13>0,E13*D13,0) -> 0 | BW13: =IF(AND(AX13+BA13=1, AI13=1),E13,0) -> 0 | BX13: =IF(BW13>0,E13*D13,0) -> 0
... B408: =Tiers!B409 -> 406 | C408: =Tiers!X409 -> bonusC-8||||||||| | D408: =Tiers!C409 -> 500 | E408: =Frequency!E410 -> 1 | F408: =E408*D408 -> 500 | G408: =IF(AND(D408/Summary!$C$4>0, D408/Summary!$C$4<5),E408,0) * D408 -> 0 | H408: =IF(AND(D408/Summary!$C$4>= 5, D408/Summary!$C$4<10),E408,0) * D408 -> 0 | I408: =IF(AND(D408/Summary!$C$4>=10, D408/Summary!$C$4<25),E408,0)*D408 -> 0 | J408: =IF(D408/Summary!$C$4>=25,E408,0)*D408 -> 500 | K408: =IF(AND(D408/Frequency!$N$7>0, D408/Frequency!$N$7<1),E408,0) -> 0 | L408: =IF(K408>0,D408*E408,0) -> 0 | M408: =IF(D408/Frequency!$N$7=1,1,0)*E408 -> 0 | N408: =IF(M408>0,D408*E408,0) -> 0 | O408: =IF(AND(D408/Frequency!$N$7>1, D408/Frequency!$N$7<=2),1,0)*E408 -> 0 | P408: =IF(O408>0,D408*E408,0) -> 0 | Q408: =IF(AND(D408/Frequency!$N$7>2,D408/Frequency!$N$7<=5),1,0)*E408 -> 0 | R408: =IF(Q408>0,D408*E408,0) -> 0 | S408: =IF(AND(D408/Frequency!$N$7>5, D408/Frequency!$N$7<=10),1,0)*E408 -> 0 | T408: =IF(S408>0,D408*E408,0) -> 0 | U408: =IF(AND(D408/Frequency!$N$7>10, D408/Frequency!$N$7<=20),1,0)*E408 -> 0 | V408: =IF(U408>0,D408*E408,0) -> 0 | W408: =IF(AND(D408/Frequency!$N$7>20, D408/Frequency!$N$7<=30),1,0)*E408 -> 0 | X408: =IF(W408>0,D408*E408,0) -> 0 | Y408: =IF(AND(D408/Frequency!$N$7>30, D408/Frequency!$N$7<=50),1,0)*E408 -> 0 | Z408: =IF(Y408>0,D408*E408,0) -> 0 | AA408: =IF(AND(D408/Frequency!$N$7>50, D408/Frequency!$N$7<=100),1,0)*E408 -> 0 | AB408: =IF(AA408>0,D408*E408,0) -> 0 | AC408: =IF(D408/Frequency!$N$7>100,1,0)*E408 -> 1 | AD408: =IF(AC408>0,D408*E408,0) -> 500 | AE408: =IF(AU408>0,E408,0) -> 0 | AF408: =IF(AX408+BA408>0,E408,0) -> 0 | AG408: =AF408*D408 -> 0 | AH408: =IF(BG408>0,E408,0) -> 0 | AI408: =IF(ISNUMBER(SEARCH("|||||||||",C408)),0,1) -> 0 | AJ408: =IF(AI408=1, E408,0) -> 0 | AK408: =IF(AJ408>0,D408*E408,0) -> 0 | AL408: =IF(ISNUMBER(SEARCH("wild",C408)),1,0) -> 0 | AM408: =IF(AL408=1, E408,0) -> 0 | AN408: =IF(AM408>0,D408*E408,0) -> 0 | AO408: =IF(ISNUMBER(SEARCH("wild-",C408)),1,0) -> 0 | AP408: =IF(AO408=1, E408,0) -> 0 | AQ408: =IF(AP408>0,D408*E408,0) -> 0 | AR408: =IF(ISNUMBER(SEARCH("wildX",C408)),1,0) -> 0 | AS408: =IF(AR408=1, E408,0) -> 0 | AT408: =IF(AS408>0,D408*E408,0) -> 0 | AU408: =IF(ISNUMBER(SEARCH("FreePlay",C408)),1,0) -> 0 | AV408: 0 | AW408: 0 | AX408: =IF(ISNUMBER(SEARCH("bonusA",C408)),1,0) -> 0 | AY408: =AX408*E408 -> 0 | AZ408: =AY408*D408 -> 0 | BA408: =IF(ISNUMBER(SEARCH("bonusB",C408)),1,0) -> 0 | BB408: =BA408*E408 -> 0 | BC408: =BB408*D408 -> 0 | BD408: =IF(ISNUMBER(SEARCH("bonusC",C408)),1,0) -> 1 | BE408: =BD408*E408 -> 1 | BF408: =BE408*D408 -> 500 | BG408: =IF(ISNUMBER(SEARCH("Instant",C408)),1,0) -> 0 | BH408: =BG408*E408 -> 0 | BI408: =BH408*D408 -> 0 | BJ408: 10 | BK408: =IF(D408 < $D$417, $C$417, IF(D408 = $D$418, $C$418, IF(D408 < $D$419, $C$419, IF(D408 < $D$420, $C$420, IF(D408 < $D$421, $C$421, $C$422))))) -> Huge Win | BL408: =IF(AU408 = 1,$C$426, IF(AV408 = 1,$C$427, IF(AW408 = 1,$C$428, IF(AX408 = 1,$C$429, IF(BA408 = 1,$C$430, IF(BD408 = 1,$C$431, IF(BG408 = 1,$C$432, IF(ISNUMBER(SEARCH("|||||||||",C408)), $C$433,$C$434)))))))) -> Bonus Game C | BM408: =(D408/Frequency!$N$7-Summary!$C$7)^2*E408 -> 249160.71 | BN408: =IF(AU408=1, E408*D408,0) -> 0 | BO408: =IF(BG408=1, D408*E408,0) -> 0 | BP408: =IF(BJ408>0,BJ408*E408,0) -> 10 | BQ408: =IF(AND(AU408=1, AI408=0),E408,0) -> 0 | BR408: =IF(BQ408>0,E408*D408,0) -> 0 | BS408: =IF(AND(AU408=1, AI408=1),E408,0) -> 0 | BT408: =IF(BS408>0,E408*D408,0) -> 0 | BU408: =IF(AND(AX408+BA408=1, AI408=0),E408,0) -> 0 | BV408: =IF(BU408>0,E408*D408,0) -> 0 | BW408: =IF(AND(AX408+BA408=1, AI408=1),E408,0) -> 0 | BX408: =IF(BW408>0,E408*D408,0) -> 0
E409: =SUM(E2:E408) -> 2000000 | F409: =SUM(F2:F408) -> 1587026.5 | G409: =SUM(G2:G408) -> 391827.6 | H409: =SUM(H2:H408) -> 180760.1 | I409: =SUM(I2:I408) -> 622923.9 | J409: =SUM(J2:J408) -> 391514.9 | K409: =SUM(K2:K408) -> 201550 | L409: =SUM(L2:L408) -> 52994.2 | ... BX409: =SUM(BX2:BX408) -> 17664
C413: Ticket Price | D413: =Summary!C4 -> 1 | G413: =G409/E409 -> 0.1959138
