Workbook

Sheet Frequency
B2: TIER | E2: ODDS | F2: ODDS | G2: PRIZE | K2: % OF | M2: Prize Structure
B3: NUMBER | C3: WIN METHOD | D3: PRIZE | E3: UP | F3: DOWN | G3: COST | H3: 1 in X odds | I3: HUMAN NAME | J3: COUNT | K3: PRIZE FUND | M3: Kentucky Lottery
B4: =Tiers!B3 -> 0 | C4: =Tiers!Y3 -> ||||||||| x 1 | D4: =Tiers!C3 -> 0 | E4: =F4-SUM(E5:E358) -> 1466392 | F4: =$N$6 -> 2000000 | G4: =E4*D4 -> 0 | H4: =F4/E4 -> 1.3638918 | I4: Non-Win | J4: =ROUND(IF(D4=0,($N$17*0.3),((((N$17*0.7)-(N$19*N$18)))*(E4/N$14)+$N$19)),0) -> 1800 | M4: Premium Gold(SSJ)
B5: =Tiers!B4 -> 1 | C5: =Tiers!Y4 -> main-0||||||||| x 1 | D5: =Tiers!C4 -> 0.1 | E5: 70000 | F5: =$N$6 -> 2000000 | G5: =E5*D5 -> 7000 | H5: =F5/E5 -> 28.571429 | I5: ='Data Analysis'!BM3 & " | " & 'Data Analysis'!BN3 -> Less than Stake | Single Win | J5: =ROUND(IF(D5=0,($N$17*0.3),((((N$17*0.7)-(N$19*N$18)))*(E5/N$14)+$N$19)),0) -> 278 | K5: =G5/N$9 -> 0.0042168675
B6: =Tiers!B5 -> 2 | C6: =Tiers!Y5 -> main-1||||||||| x 1 | D6: =Tiers!C5 -> 0.2 | E6: 40003 | F6: =$N$6 -> 2000000 | G6: =E6*D6 -> 8000.6 | H6: =F6/E6 -> 49.99625 | I6: ='Data Analysis'!BM4 & " | " & 'Data Analysis'!BN4 -> Less than Stake | Single Win | J6: =ROUND(IF(D6=0,($N$17*0.3),((((N$17*0.7)-(N$19*N$18)))*(E6/N$14)+$N$19)),0) -> 162 | K6: =G6/N$9 -> 0.0048196386 | M6: Odds Down (ticket quantity if pool based): | N6: 2000000
B7: =Tiers!B6 -> 3 | C7: =Tiers!Y6 -> main-2||||||||| x 1 | D7: =Tiers!C6 -> 0.5 | E7: 20001 | F7: =$N$6 -> 2000000 | G7: =E7*D7 -> 10000.5 | H7: =F7/E7 -> 99.995 | I7: ='Data Analysis'!BM5 & " | " & 'Data Analysis'!BN5 -> Less than Stake | Single Win | J7: =ROUND(IF(D7=0,($N$17*0.3),((((N$17*0.7)-(N$19*N$18)))*(E7/N$14)+$N$19)),0) -> 84 | K7: =G7/N$9 -> 0.0060243976 | M7: Base: | N7: 1
B8: =Tiers!B7 -> 4 | C8: =Tiers!Y7 -> main-3||||||||| x 1 | D8: =Tiers!C7 -> 1 | E8: 66424 | F8: =$N$6 -> 2000000 | G8: =E8*D8 -> 66424 | H8: =F8/E8 -> 30.109599 | I8: ='Data Analysis'!BM6 & " | " & 'Data Analysis'!BN6 -> Stake Back | Single Win | J8: =ROUND(IF(D8=0,($N$17*0.3),((((N$17*0.7)-(N$19*N$18)))*(E8/N$14)+$N$19)),0) -> 264 | K8: =G8/N$9 -> 0.040014458 | M8: Revenus (if pool based): | N8: =N6*N7 -> 2000000
B9: =Tiers!B8 -> 5 | C9: =Tiers!Y8 -> main-4||||||||| x 1 | D9: =Tiers!C8 -> 1.5 | E9: 30000 | F9: =$N$6 -> 2000000 | G9: =E9*D9 -> 45000 | H9: =F9/E9 -> 66.666667 | I9: ='Data Analysis'!BM7 & " | " & 'Data Analysis'!BN7 -> Standard Win | Single Win | J9: =ROUND(IF(D9=0,($N$17*0.3),((((N$17*0.7)-(N$19*N$18)))*(E9/N$14)+$N$19)),0) -> 123 | K9: =G9/N$9 -> 0.027108434 | M9: Prize Fund (if pool based): | N9: =G359 -> 1660000
B10: =Tiers!B9 -> 6 | C10: =Tiers!Y9 -> main-5||||||||| x 1 | D10: =Tiers!C9 -> 2 | E10: 15000 | F10: =$N$6 -> 2000000 | G10: =E10*D10 -> 30000 | H10: =F10/E10 -> 133.33333 | I10: ='Data Analysis'!BM8 & " | " & 'Data Analysis'!BN8 -> Standard Win | Single Win | J10: =ROUND(IF(D10=0,($N$17*0.3),((((N$17*0.7)-(N$19*N$18)))*(E10/N$14)+$N$19)),0) -> 64 | K10: =G10/N$9 -> 0.018072289 | M10: RTP Setting | N10: 0.83
B11: =Tiers!B10 -> 7 | C11: =Tiers!Y10 -> main-6||||||||| x 1 | D11: =Tiers!C10 -> 2.5 | E11: 3000 | F11: =$N$6 -> 2000000 | G11: =E11*D11 -> 7500 | H11: =F11/E11 -> 666.66667 | I11: ='Data Analysis'!BM9 & " | " & 'Data Analysis'!BN9 -> Standard Win | Single Win | J11: =ROUND(IF(D11=0,($N$17*0.3),((((N$17*0.7)-(N$19*N$18)))*(E11/N$14)+$N$19)),0) -> 18 | K11: =G11/N$9 -> 0.0045180723 | M11: Actual RTP: | N11: =N9/N8 -> 0.83 | O11: =IF(N11=N10, "okay", "error") -> okay
B12: =Tiers!B11 -> 8 | C12: =Tiers!Y11 -> main-7||||||||| x 1 | D12: =Tiers!C11 -> 3 | E12: 1000 | F12: =$N$6 -> 2000000 | G12: =E12*D12 -> 3000 | H12: =F12/E12 -> 2000 | I12: ='Data Analysis'!BM10 & " | " & 'Data Analysis'!BN10 -> Standard Win | Single Win | J12: =ROUND(IF(D12=0,($N$17*0.3),((((N$17*0.7)-(N$19*N$18)))*(E12/N$14)+$N$19)),0) -> 10 | K12: =G12/N$9 -> 0.0018072289 | M12: JP RTP: | N12: ='Progressive Jackpots'!C30+'Progressive Jackpots'!C31 -> 0.04
B13: =Tiers!B12 -> 9 | C13: =Tiers!Y12 -> main-8||||||||| x 1 | D13: =Tiers!C12 -> 5 | E13: 967 | F13: =$N$6 -> 2000000 | G13: =E13*D13 -> 4835 | H13: =F13/E13 -> 2068.2523 | I13: ='Data Analysis'!BM11 & " | " & 'Data Analysis'!BN11 -> Standard Win | Single Win | J13: =ROUND(IF(D13=0,($N$17*0.3),((((N$17*0.7)-(N$19*N$18)))*(E13/N$14)+$N$19)),0) -> 10 | K13: =G13/N$9 -> 0.0029126506 | M13: Total RTP: | N13: =N12+N11 -> 0.87
B14: =Tiers!B13 -> 10 | C14: =Tiers!Y13 -> main-9||||||||| x 1 | D14: =Tiers!C13 -> 10 | E14: 484 | F14: =$N$6 -> 2000000 | G14: =E14*D14 -> 4840 | H14: =F14/E14 -> 4132.2314 | I14: ='Data Analysis'!BM12 & " | " & 'Data Analysis'!BN12 -> Big Win | Single Win | J14: =ROUND(IF(D14=0,($N$17*0.3),((((N$17*0.7)-(N$19*N$18)))*(E14/N$14)+$N$19)),0) -> 8 | K14: =G14/N$9 -> 0.0029156627 | M14: Winning Tiers Freq | N14: =SUM(E5:E358) -> 533608
B15: =Tiers!B14 -> 11 | C15: =Tiers!Y14 -> main-10||||||||| x 1 | D15: =Tiers!C14 -> 1 | E15: 67382 | F15: =$N$6 -> 2000000 | G15: =E15*D15 -> 67382 | H15: =F15/E15 -> 29.681517 | I15: ='Data Analysis'!BM13 & " | " & 'Data Analysis'!BN13 -> Stake Back | Single Win | J15: =ROUND(IF(D15=0,($N$17*0.3),((((N$17*0.7)-(N$19*N$18)))*(E15/N$14)+$N$19)),0) -> 268 | K15: =G15/N$9 -> 0.040591566 | M15: Hit Rate: | N15: =N6/N14 -> 3.7480697
B16: =Tiers!B15 -> 12 | C16: =Tiers!Y15 -> main-11||||||||| x 1 | D16: =Tiers!C15 -> 1.5 | E16: 30000 | F16: =$N$6 -> 2000000 | G16: =E16*D16 -> 45000 | H16: =F16/E16 -> 66.666667 | I16: ='Data Analysis'!BM14 & " | " & 'Data Analysis'!BN14 -> Standard Win | Single Win | J16: =ROUND(IF(D16=0,($N$17*0.3),((((N$17*0.7)-(N$19*N$18)))*(E16/N$14)+$N$19)),0) -> 123 | K16: =G16/N$9 -> 0.027108434
B17: =Tiers!B16 -> 13 | C17: =Tiers!Y16 -> main-12||||||||| x 1 | D17: =Tiers!C16 -> 2 | E17: 15000 | F17: =$N$6 -> 2000000 | G17: =E17*D17 -> 30000 | H17: =F17/E17 -> 133.33333 | I17: ='Data Analysis'!BM15 & " | " & 'Data Analysis'!BN15 -> Standard Win | Single Win | J17: =ROUND(IF(D17=0,($N$17*0.3),((((N$17*0.7)-(N$19*N$18)))*(E17/N$14)+$N$19)),0) -> 64 | K17: =G17/N$9 -> 0.018072289 | M17: Approx Count: | N17: 6000
B18: =Tiers!B17 -> 14 | C18: =Tiers!Y17 -> main-13||||||||| x 1 | D18: =Tiers!C17 -> 5 | E18: 967 | F18: =$N$6 -> 2000000 | G18: =E18*D18 -> 4835 | H18: =F18/E18 -> 2068.2523 | I18: ='Data Analysis'!BM16 & " | " & 'Data Analysis'!BN16 -> Standard Win | Single Win | J18: =ROUND(IF(D18=0,($N$17*0.3),((((N$17*0.7)-(N$19*N$18)))*(E18/N$14)+$N$19)),0) -> 10 | K18: =G18/N$9 -> 0.0029126506 | M18: Winning Tiers | N18: =COUNT(E5:E358) -> 354
B19: =Tiers!B18 -> 15 | C19: =Tiers!Y18 -> main-14||||||||| x 1 | D19: =Tiers!C18 -> 10 | E19: 484 | F19: =$N$6 -> 2000000 | G19: =E19*D19 -> 4840 | H19: =F19/E19 -> 4132.2314 | I19: ='Data Analysis'!BM17 & " | " & 'Data Analysis'!BN17 -> Big Win | Single Win | J19: =ROUND(IF(D19=0,($N$17*0.3),((((N$17*0.7)-(N$19*N$18)))*(E19/N$14)+$N$19)),0) -> 8 | K19: =G19/N$9 -> 0.0029156627 | M19: Min per tier | N19: 6
B20: =Tiers!B19 -> 16 | C20: =Tiers!Y19 -> main-15||||||||| x 1 | D20: =Tiers!C19 -> 15 | E20: 323 | F20: =$N$6 -> 2000000 | G20: =E20*D20 -> 4845 | H20: =F20/E20 -> 6191.9505 | I20: ='Data Analysis'!BM18 & " | " & 'Data Analysis'!BN18 -> Big Win | Single Win | J20: =ROUND(IF(D20=0,($N$17*0.3),((((N$17*0.7)-(N$19*N$18)))*(E20/N$14)+$N$19)),0) -> 7 | K20: =G20/N$9 -> 0.0029186747
B21: =Tiers!B20 -> 17 | C21: =Tiers!Y20 -> main-16||||||||| x 1 | D21: =Tiers!C20 -> 20 | E21: 145 | F21: =$N$6 -> 2000000 | G21: =E21*D21 -> 2900 | H21: =F21/E21 -> 13793.103 | I21: ='Data Analysis'!BM19 & " | " & 'Data Analysis'!BN19 -> Big Win | Single Win | J21: =ROUND(IF(D21=0,($N$17*0.3),((((N$17*0.7)-(N$19*N$18)))*(E21/N$14)+$N$19)),0) -> 7 | K21: =G21/N$9 -> 0.001746988 | M21: Difference: | N21: =N8*N10-N9 -> 0
B22: =Tiers!B21 -> 18 | C22: =Tiers!Y21 -> main-17||||||||| x 1 | D22: =Tiers!C21 -> 50 | E22: 10 | F22: =$N$6 -> 2000000 | G22: =E22*D22 -> 500 | H22: =F22/E22 -> 200000 | I22: ='Data Analysis'!BM20 & " | " & 'Data Analysis'!BN20 -> Huge Win | Single Win | J22: =ROUND(IF(D22=0,($N$17*0.3),((((N$17*0.7)-(N$19*N$18)))*(E22/N$14)+$N$19)),0) -> 6 | K22: =G22/N$9 -> 0.00030120482 | M22: PPS Source(if any)
B23: =Tiers!B22 -> 19 | C23: =Tiers!Y22 -> main-18||||||||| x 1 | D23: =Tiers!C22 -> 100 | E23: 3 | F23: =$N$6 -> 2000000 | G23: =E23*D23 -> 300 | H23: =F23/E23 -> 666666.67 | I23: ='Data Analysis'!BM21 & " | " & 'Data Analysis'!BN21 -> Huge Win | Single Win | J23: =ROUND(IF(D23=0,($N$17*0.3),((((N$17*0.7)-(N$19*N$18)))*(E23/N$14)+$N$19)),0) -> 6 | K23: =G23/N$9 -> 0.00018072289
B24: =Tiers!B23 -> 20 | C24: =Tiers!Y23 -> main-19||||||||| x 1 | D24: =Tiers!C23 -> 200 | E24: 2 | F24: =$N$6 -> 2000000 | G24: =E24*D24 -> 400 | H24: =F24/E24 -> 1000000 | I24: ='Data Analysis'!BM22 & " | " & 'Data Analysis'!BN22 -> Huge Win | Single Win | J24: =ROUND(IF(D24=0,($N$17*0.3),((((N$17*0.7)-(N$19*N$18)))*(E24/N$14)+$N$19)),0) -> 6 | K24: =G24/N$9 -> 0.00024096386
B25: =Tiers!B24 -> 21 | C25: =Tiers!Y24 -> main-20||||||||| x 1 | D25: =Tiers!C24 -> 1.5 | E25: 30000 | F25: =$N$6 -> 2000000 | G25: =E25*D25 -> 45000 | H25: =F25/E25 -> 66.666667 | I25: ='Data Analysis'!BM23 & " | " & 'Data Analysis'!BN23 -> Standard Win | Single Win | J25: =ROUND(IF(D25=0,($N$17*0.3),((((N$17*0.7)-(N$19*N$18)))*(E25/N$14)+$N$19)),0) -> 123 | K25: =G25/N$9 -> 0.027108434 | M25: The information contained in this document and all attached documents is strictly confidential and contains proprietary information. It is provided solely for use by the designated recipients and is subject to the terms of any confidentiality obligations or non-disclosure agreements between the parties. All other use is strictly prohibited.
B26: =Tiers!B25 -> 22 | C26: =Tiers!Y25 -> main-21||||||||| x 1 | D26: =Tiers!C25 -> 2 | E26: 15000 | F26: =$N$6 -> 2000000 | G26: =E26*D26 -> 30000 | H26: =F26/E26 -> 133.33333 | I26: ='Data Analysis'!BM24 & " | " & 'Data Analysis'!BN24 -> Standard Win | Single Win | J26: =ROUND(IF(D26=0,($N$17*0.3),((((N$17*0.7)-(N$19*N$18)))*(E26/N$14)+$N$19)),0) -> 64 | K26: =G26/N$9 -> 0.018072289
B27: =Tiers!B26 -> 23 | C27: =Tiers!Y26 -> main-22||||||||| x 1 | D27: =Tiers!C26 -> 5 | E27: 1000 | F27: =$N$6 -> 2000000 | G27: =E27*D27 -> 5000 | H27: =F27/E27 -> 2000 | I27: ='Data Analysis'!BM25 & " | " & 'Data Analysis'!BN25 -> Standard Win | Single Win | J27: =ROUND(IF(D27=0,($N$17*0.3),((((N$17*0.7)-(N$19*N$18)))*(E27/N$14)+$N$19)),0) -> 10 | K27: =G27/N$9 -> 0.0030120482
B28: =Tiers!B27 -> 24 | C28: =Tiers!Y27 -> main-23||||||||| x 1 | D28: =Tiers!C27 -> 10 | E28: 500 | F28: =$N$6 -> 2000000 | G28: =E28*D28 -> 5000 | H28: =F28/E28 -> 4000 | I28: ='Data Analysis'!BM26 & " | " & 'Data Analysis'!BN26 -> Big Win | Single Win | J28: =ROUND(IF(D28=0,($N$17*0.3),((((N$17*0.7)-(N$19*N$18)))*(E28/N$14)+$N$19)),0) -> 8 | K28: =G28/N$9 -> 0.0030120482
B29: =Tiers!B28 -> 25 | C29: =Tiers!Y28 -> main-24||||||||| x 1 | D29: =Tiers!C28 -> 15 | E29: 320 | F29: =$N$6 -> 2000000 | G29: =E29*D29 -> 4800 | H29: =F29/E29 -> 6250 | I29: ='Data Analysis'!BM27 & " | " & 'Data Analysis'!BN27 -> Big Win | Single Win | J29: =ROUND(IF(D29=0,($N$17*0.3),((((N$17*0.7)-(N$19*N$18)))*(E29/N$14)+$N$19)),0) -> 7 | K29: =G29/N$9 -> 0.0028915663
B30: =Tiers!B29 -> 26 | C30: =Tiers!Y29 -> main-25||||||||| x 1 | D30: =Tiers!C29 -> 20 | E30: 142 | F30: =$N$6 -> 2000000 | G30: =E30*D30 -> 2840 | H30: =F30/E30 -> 14084.507 | I30: ='Data Analysis'!BM28 & " | " & 'Data Analysis'!BN28 -> Big Win | Single Win | J30: =ROUND(IF(D30=0,($N$17*0.3),((((N$17*0.7)-(N$19*N$18)))*(E30/N$14)+$N$19)),0) -> 7 | K30: =G30/N$9 -> 0.0017108434
B31: =Tiers!B30 -> 27 | C31: =Tiers!Y30 -> main-26||||||||| x 1 | D31: =Tiers!C30 -> 50 | E31: 10 | F31: =$N$6 -> 2000000 | G31: =E31*D31 -> 500 | H31: =F31/E31 -> 200000 | I31: ='Data Analysis'!BM29 & " | " & 'Data Analysis'!BN29 -> Huge Win | Single Win | J31: =ROUND(IF(D31=0,($N$17*0.3),((((N$17*0.7)-(N$19*N$18)))*(E31/N$14)+$N$19)),0) -> 6 | K31: =G31/N$9 -> 0.00030120482
B32: =Tiers!B31 -> 28 | C32: =Tiers!Y31 -> main-27||||||||| x 1 | D32: =Tiers!C31 -> 100 | E32: 3 | F32: =$N$6 -> 2000000 | G32: =E32*D32 -> 300 | H32: =F32/E32 -> 666666.67 | I32: ='Data Analysis'!BM30 & " | " & 'Data Analysis'!BN30 -> Huge Win | Single Win | J32: =ROUND(IF(D32=0,($N$17*0.3),((((N$17*0.7)-(N$19*N$18)))*(E32/N$14)+$N$19)),0) -> 6 | K32: =G32/N$9 -> 0.00018072289
B33: =Tiers!B32 -> 29 | C33: =Tiers!Y32 -> main-28||||||||| x 1 | D33: =Tiers!C32 -> 200 | E33: 2 | F33: =$N$6 -> 2000000 | G33: =E33*D33 -> 400 | H33: =F33/E33 -> 1000000 | I33: ='Data Analysis'!BM31 & " | " & 'Data Analysis'!BN31 -> Huge Win | Single Win | J33: =ROUND(IF(D33=0,($N$17*0.3),((((N$17*0.7)-(N$19*N$18)))*(E33/N$14)+$N$19)),0) -> 6 | K33: =G33/N$9 -> 0.00024096386
B34: =Tiers!B33 -> 30 | C34: =Tiers!Y33 -> main-29||||||||| x 1 | D34: =Tiers!C33 -> 500 | E34: 2 | F34: =$N$6 -> 2000000 | G34: =E34*D34 -> 1000 | H34: =F34/E34 -> 1000000 | I34: ='Data Analysis'!BM32 & " | " & 'Data Analysis'!BN32 -> Huge Win | Single Win | J34: =ROUND(IF(D34=0,($N$17*0.3),((((N$17*0.7)-(N$19*N$18)))*(E34/N$14)+$N$19)),0) -> 6 | K34: =G34/N$9 -> 0.00060240964
B35: =Tiers!B34 -> 31 | C35: =Tiers!Y34 -> main-30||||||||| x 1 | D35: =Tiers!C34 -> 2 | E35: 2416 | F35: =$N$6 -> 2000000 | G35: =E35*D35 -> 4832 | H35: =F35/E35 -> 827.81457 | I35: ='Data Analysis'!BM33 & " | " & 'Data Analysis'!BN33 -> Standard Win | Single Win | J35: =ROUND(IF(D35=0,($N$17*0.3),((((N$17*0.7)-(N$19*N$18)))*(E35/N$14)+$N$19)),0) -> 15 | K35: =G35/N$9 -> 0.0029108434
B36: =Tiers!B35 -> 32 | C36: =Tiers!Y35 -> main-31||||||||| x 1 | D36: =Tiers!C35 -> 5 | E36: 967 | F36: =$N$6 -> 2000000 | G36: =E36*D36 -> 4835 | H36: =F36/E36 -> 2068.2523 | I36: ='Data Analysis'!BM34 & " | " & 'Data Analysis'!BN34 -> Standard Win | Single Win | J36: =ROUND(IF(D36=0,($N$17*0.3),((((N$17*0.7)-(N$19*N$18)))*(E36/N$14)+$N$19)),0) -> 10 | K36: =G36/N$9 -> 0.0029126506
B37: =Tiers!B36 -> 33 | C37: =Tiers!Y36 -> main-32||||||||| x 1 | D37: =Tiers!C36 -> 10 | E37: 484 | F37: =$N$6 -> 2000000 | G37: =E37*D37 -> 4840 | H37: =F37/E37 -> 4132.2314 | I37: ='Data Analysis'!BM35 & " | " & 'Data Analysis'!BN35 -> Big Win | Single Win | J37: =ROUND(IF(D37=0,($N$17*0.3),((((N$17*0.7)-(N$19*N$18)))*(E37/N$14)+$N$19)),0) -> 8 | K37: =G37/N$9 -> 0.0029156627
... B358: =Tiers!B357 -> 354 | C358: =Tiers!Y357 -> bonusA-6||||||||| x 1 | D358: =Tiers!C357 -> 100 | E358: 100 | F358: =$N$6 -> 2000000 | G358: =E358*D358 -> 10000 | H358: =F358/E358 -> 20000 | I358: ='Data Analysis'!BM356 & " | " & 'Data Analysis'!BN356 -> Huge Win | Bonus Game A | J358: =ROUND(IF(D358=0,($N$17*0.3),((((N$17*0.7)-(N$19*N$18)))*(E358/N$14)+$N$19)),0) -> 6 | K358: =G358/N$9 -> 0.0060240964
E359: =SUM(E4:E358) -> 2000000 | G359: =SUM(G4:G358) -> 1660000 | K359: =SUM(K4:K358) -> 1

Sheet Progressive Jackpots
B2: Base JP Odds Down | C2: 50000000 | E2: json setup form
B3: JP Stake | C3: 1 | E3: JP | F3: small | G3: large
B4: Revenue | C4: =C2*C3 -> 50000000 | E4: initialAmount | F4: 2500 | G4: 150000
B5: Contribution | C5: =C3*C6 -> 0.04 | E5: increment | F5: =K18*100 -> 0.2 | G5: =K19*100 -> 3.3
B6: Contribution % | C6: =X13 -> 0.04
B7: Estimated plays per day | C7: 40000
M8: BASE
B9: Seed | K9: =C6-C21 -> 0.005 | M9: Odds Up | N9: Seed | O9: Target trigger | P9: Count | Q9: Odds Down | R9: 1 in x Odds | S9: Days to Trigger | T9: Prize Cost | U9: Trigger minus Seed | V9: JP Contrib Cost | W9: Split (use on JP split above) | X9: Total JP Prize cost
B10: Number | C10: Name | D10: Bonus | E10: Prize | F10: Base Odds Up | G10: Odds Down | H10: Base 1 in x Odds | I10: Prize Cost | J10: Contribution split | K10: Contribution | M10: 40 | N10: 2500 | O10: 5000 | P10: 4 | Q10: =C2 -> 50000000 | R10: =Q10/F11 -> 1250000 | S10: =R10/C7 -> 31.25 | T10: =M10*E11 -> 100000 | U10: =O10-N10 -> 2500 | V10: =U10*M10 -> 100000 | W10: =V10/V12 -> 0.057142857 | X10: =O10*M10 -> 200000
B11: 1 | C11: small | D11: A | E11: =N10 -> 2500 | F11: =C3*M10 -> 40 | G11: =C2 -> 50000000 | H11: =G11/F11 -> 1250000 | I11: =E11*F11 -> 100000 | J11: =I11/I14 -> 0.4 | K11: =T13*J11*C3 -> 0.002 | M11: 1 | N11: 150000 | O11: 1800000 | P11: 4 | Q11: =C2 -> 50000000 | R11: =Q11/F12 -> 50000000 | S11: =R11/C7 -> 1250 | T11: =E12*M11 -> 150000 | U11: =O11-N11 -> 1650000 | V11: =U11*M11 -> 1650000 | W11: =V11/V12 -> 0.94285714 | X11: =O11*M11 -> 1800000
B12: 2 | C12: large | D12: A | E12: =N11 -> 150000 | F12: =C3*M11 -> 1 | G12: =C2 -> 50000000 | H12: =G12/F12 -> 50000000 | I12: =E12*F12 -> 150000 | J12: =I12/I14 -> 0.6 | K12: =T13*J12*C3 -> 0.003 | M12: =SUM(M10:M11) -> 41 | R12: =SUM(R10:R11) -> 51250000 | T12: =SUM(T10:T11) -> 250000 | U12: =SUM(U10:U11) -> 1652500 | V12: =SUM(V10:V11) -> 1750000 | X12: =SUM(X10:X11) -> 2000000
T13: =T12/C2 -> 0.005 | V13: =V12/C2 -> 0.035 | X13: =X12/C2 -> 0.04
B14: RTP | C14: =I14/C4 -> 0.005 | F14: =SUM(F11:F12) -> 41 | H14: =C2/F14 -> 1219512.2 | I14: =SUM(I11:I12) -> 250000 | J14: =SUM(J11:J12) -> 1 | K14: =SUM(K11:K12) -> 0.005
B16: Jackpot Contributions (excluding seed) | K16: =C6-C14 -> 0.035
B17: Number | C17: Name | D17: Bonus | E17: Average Prize | F17: Base Odds Up | G17: Odds Down | H17: Base 1 in x Odds | I17: Prize Cost | J17: Contribution split | K17: Contribution
B18: 1 | C18: small | D18: A | E18: =K18*H18 -> 2500 | F18: =C3*M10 -> 40 | G18: =C2 -> 50000000 | H18: =G18/F18 -> 1250000 | I18: =E18*F18 -> 100000 | J18: =W10 -> 0.057142857 | K18: =V13*J18*C3 -> 0.002
B19: 2 | C19: large | D19: A | E19: =K19*H19 -> 1650000 | F19: =C3*M11 -> 1 | G19: =C2 -> 50000000 | H19: =G19/F19 -> 50000000 | I19: =E19*F19 -> 1650000 | J19: =W11 -> 0.94285714 | K19: =V13*J19*C3 -> 0.033
B21: RTP | C21: =I21/C4 -> 0.035 | I21: =SUM(I18:I19) -> 1750000 | J21: =SUM(J18:J19) -> 1 | K21: =SUM(K18:K19) -> 0.035
B24: Overal Game Summary
B25: JP Event Prob | C25: =C2/F14 -> 1219512.2
B26: Total win Odds (JP+Main) | C26: =1/((1/C25) + (1/Frequency!N15)) -> 3.7480582
B27: Total non-win Prob Up | C27: =Frequency!N6-(F14/(G12/Frequency!N6)+Frequency!N14) -> 1466390.4
B28: Total non-win Pob Down | C28: =Frequency!N6 -> 2000000
B29: Main Game RTP | C29: =Frequency!N11 -> 0.83
B30: Seed contribution RTP | C30: =C14 -> 0.005
B31: JP Contribution RTP | C31: =C21 -> 0.035
B32: TOTAL | C32: =C29+C30+C31 -> 0.87

Sheet Delivery
B2: DIVISION | C2: METHOD | D2: PRIZE FACTOR | E2: PRICE POINT | F2: EXPECTED WINNERS PER CARD | G2: ODDS PER GRID | H2: TOTAL PRIZE | I2: PRIZE % | J2: PAYOUT % | L2: Prize Structure
L3: Kentucky Lottery
B4: 1 | C4: main-39||||||||| x 1 | D4: 1000 | E4: =D4*$M$7 -> 1000 | F4: 1 | G4: =$M$6/F4 -> 2000000 | H4: =F4*E4 -> 1000 | I4: =H4/$M$9 -> 0.00060240964 | J4: =H4/$M$8 -> 0.0005 | L4: Premium Gold(SSJ)
B5: 2 | C5: main-29||||||||| x 1 | D5: 500 | E5: =D5*$M$7 -> 500 | F5: 2 | G5: =$M$6/F5 -> 1000000 | H5: =F5*E5 -> 1000 | I5: =H5/$M$9 -> 0.00060240964 | J5: =H5/$M$8 -> 0.0005
B6: 3 | C6: main-38||||||||| x 1 | D6: 500 | E6: =D6*$M$7 -> 500 | F6: 1 | G6: =$M$6/F6 -> 2000000 | H6: =F6*E6 -> 500 | I6: =H6/$M$9 -> 0.00030120482 | J6: =H6/$M$8 -> 0.00025 | L6: Odds Down (ticket quantity if pool based): | M6: 2000000
B7: 4 | C7: main-19||||||||| x 1 | D7: 200 | E7: =D7*$M$7 -> 200 | F7: 2 | G7: =$M$6/F7 -> 1000000 | H7: =F7*E7 -> 400 | I7: =H7/$M$9 -> 0.00024096386 | J7: =H7/$M$8 -> 0.0002 | L7: Base: | M7: 1
B8: 5 | C8: main-28||||||||| x 1 | D8: 200 | E8: =D8*$M$7 -> 200 | F8: 2 | G8: =$M$6/F8 -> 1000000 | H8: =F8*E8 -> 400 | I8: =H8/$M$9 -> 0.00024096386 | J8: =H8/$M$8 -> 0.0002 | L8: Revenus (if pool based): | M8: =M7*M6 -> 2000000
B9: 6 | C9: main-37||||||||| x 1 | D9: 200 | E9: =D9*$M$7 -> 200 | F9: 1 | G9: =$M$6/F9 -> 2000000 | H9: =F9*E9 -> 200 | I9: =H9/$M$9 -> 0.00012048193 | J9: =H9/$M$8 -> 0.0001 | L9: Prize Fund (if pool based): | M9: =H359 -> 1660000
B10: 7 | C10: main-13|freeplayA-7|||||||| x 20 | D10: 141.9 | E10: =D10*$M$7 -> 141.9 | F10: 2 | G10: =$M$6/F10 -> 1000000 | H10: =F10*E10 -> 283.8 | I10: =H10/$M$9 -> 0.00017096386 | J10: =H10/$M$8 -> 0.0001419 | L10: RTP Setting | M10: 0.83
B11: 8 | C11: main-13|bonusA-3|||||||| x 20 | D11: 125 | E11: =D11*$M$7 -> 125 | F11: 2 | G11: =$M$6/F11 -> 1000000 | H11: =F11*E11 -> 250 | I11: =H11/$M$9 -> 0.00015060241 | J11: =H11/$M$8 -> 0.000125 | L11: Actual RTP: | M11: =M9/M8 -> 0.83
B12: 9 | C12: main-15|bonusA-6|||||||| x 1 | D12: 115 | E12: =D12*$M$7 -> 115 | F12: 2 | G12: =$M$6/F12 -> 1000000 | H12: =F12*E12 -> 230 | I12: =H12/$M$9 -> 0.00013855422 | J12: =H12/$M$8 -> 0.000115 | L12: JP RTP: | M12: =C373+C380 -> 0.04
B13: 10 | C13: main-18||||||||| x 1 | D13: 100 | E13: =D13*$M$7 -> 100 | F13: 3 | G13: =$M$6/F13 -> 666666.67 | H13: =F13*E13 -> 300 | I13: =H13/$M$9 -> 0.00018072289 | J13: =H13/$M$8 -> 0.00015 | L13: Total RTP: | M13: =M12+M11 -> 0.87
B14: 11 | C14: main-27||||||||| x 1 | D14: 100 | E14: =D14*$M$7 -> 100 | F14: 3 | G14: =$M$6/F14 -> 666666.67 | H14: =F14*E14 -> 300 | I14: =H14/$M$9 -> 0.00018072289 | J14: =H14/$M$8 -> 0.00015 | L14: Winning Tiers Freq | M14: =SUM(F4:F357) -> 533608
B15: 12 | C15: main-36||||||||| x 1 | D15: 100 | E15: =D15*$M$7 -> 100 | F15: 3 | G15: =$M$6/F15 -> 666666.67 | H15: =F15*E15 -> 300 | I15: =H15/$M$9 -> 0.00018072289 | J15: =H15/$M$8 -> 0.00015 | L15: Hit Rate: | M15: =M6/M14 -> 3.7480697
B16: 13 | C16: main-13||||||||| x 20 | D16: 100 | E16: =D16*$M$7 -> 100 | F16: 2 | G16: =$M$6/F16 -> 1000000 | H16: =F16*E16 -> 200 | I16: =H16/$M$9 -> 0.00012048193 | J16: =H16/$M$8 -> 0.0001
B17: 14 | C17: bonusA-6||||||||| x 1 | D17: 100 | E17: =D17*$M$7 -> 100 | F17: 100 | G17: =$M$6/F17 -> 20000 | H17: =F17*E17 -> 10000 | I17: =H17/$M$9 -> 0.0060240964 | J17: =H17/$M$8 -> 0.005 | L17: The information contained in this document and all attached documents is strictly confidential and contains proprietary information. It is provided solely for use by the designated recipients and is subject to the terms of any confidentiality obligations or non-disclosure agreements between the parties. All other use is strictly prohibited.
B18: 15 | C18: main-2|main-3|main-10|freeplayA-7|||||| x 20 | D18: 91.9 | E18: =D18*$M$7 -> 91.9 | F18: 5 | G18: =$M$6/F18 -> 400000 | H18: =F18*E18 -> 459.5 | I18: =H18/$M$9 -> 0.00027680723 | J18: =H18/$M$8 -> 0.00022975
B19: 16 | C19: main-4|main-4|bonusA-4||||||| x 20 | D19: 90 | E19: =D19*$M$7 -> 90 | F19: 2 | G19: =$M$6/F19 -> 1000000 | H19: =F19*E19 -> 180 | I19: =H19/$M$9 -> 0.00010843373 | J19: =H19/$M$8 -> 9e-05
B20: 17 | C20: freeplayA-24||||||||| x 1 | D20: 87.9 | E20: =D20*$M$7 -> 87.9 | F20: 5 | G20: =$M$6/F20 -> 400000 | H20: =F20*E20 -> 439.5 | I20: =H20/$M$9 -> 0.00026475904 | J20: =H20/$M$8 -> 0.00021975
B21: 18 | C21: main-10|main-30|freeplayA-5||||||| x 20 | D21: 85.3 | E21: =D21*$M$7 -> 85.3 | F21: 6 | G21: =$M$6/F21 -> 333333.33 | H21: =F21*E21 -> 511.8 | I21: =H21/$M$9 -> 0.00030831325 | J21: =H21/$M$8 -> 0.0002559
B22: 19 | C22: main-10|main-30|bonusA-3||||||| x 20 | D22: 85 | E22: =D22*$M$7 -> 85 | F22: 2 | G22: =$M$6/F22 -> 1000000 | H22: =F22*E22 -> 170 | I22: =H22/$M$9 -> 0.00010240964 | J22: =H22/$M$8 -> 8.5e-05
B23: 20 | C23: main-21|freeplayA-9|||||||| x 20 | D23: 84.1 | E23: =D23*$M$7 -> 84.1 | F23: 5 | G23: =$M$6/F23 -> 400000 | H23: =F23*E23 -> 420.5 | I23: =H23/$M$9 -> 0.00025331325 | J23: =H23/$M$8 -> 0.00021025
B24: 21 | C24: main-2|main-20|freeplayA-9||||||| x 20 | D24: 84.1 | E24: =D24*$M$7 -> 84.1 | F24: 5 | G24: =$M$6/F24 -> 400000 | H24: =F24*E24 -> 420.5 | I24: =H24/$M$9 -> 0.00025331325 | J24: =H24/$M$8 -> 0.00021025
B25: 22 | C25: main-0|main-0|main-1|main-10|main-20|freeplayA-5|||| x 20 | D25: 83.3 | E25: =D25*$M$7 -> 83.3 | F25: 5 | G25: =$M$6/F25 -> 400000 | H25: =F25*E25 -> 416.5 | I25: =H25/$M$9 -> 0.00025090361 | J25: =H25/$M$8 -> 0.00020825
B26: 23 | C26: freeplayA-29||||||||| x 1 | D26: 81.5 | E26: =D26*$M$7 -> 81.5 | F26: 6 | G26: =$M$6/F26 -> 333333.33 | H26: =F26*E26 -> 489 | I26: =H26/$M$9 -> 0.00029457831 | J26: =H26/$M$8 -> 0.0002445
B27: 24 | C27: main-4|main-11|bonusA-2||||||| x 20 | D27: 80 | E27: =D27*$M$7 -> 80 | F27: 3 | G27: =$M$6/F27 -> 666666.67 | H27: =F27*E27 -> 240 | I27: =H27/$M$9 -> 0.00014457831 | J27: =H27/$M$8 -> 0.00012
B28: 25 | C28: main-2|main-3|main-10|bonusA-4|||||| x 20 | D28: 80 | E28: =D28*$M$7 -> 80 | F28: 3 | G28: =$M$6/F28 -> 666666.67 | H28: =F28*E28 -> 240 | I28: =H28/$M$9 -> 0.00014457831 | J28: =H28/$M$8 -> 0.00012
B29: 26 | C29: main-22|main-13|main-34|main-25|freeplayA-6||||| x 1 | D29: 79 | E29: =D29*$M$7 -> 79 | F29: 3 | G29: =$M$6/F29 -> 666666.67 | H29: =F29*E29 -> 237 | I29: =H29/$M$9 -> 0.00014277108 | J29: =H29/$M$8 -> 0.0001185
... B357: 354 | C357: main-0||||||||| x 1 | D357: 0.1 | E357: =D357*$M$7 -> 0.1 | F357: 70000 | G357: =$M$6/F357 -> 28.571429 | H357: =F357*E357 -> 7000 | I357: =H357/$M$9 -> 0.0042168675 | J357: =H357/$M$8 -> 0.0035
B358: 355 | C358: Non Winning tickets | D358: 0 | E358: =D358*$M$7 -> 0 | F358: =M6-M14 -> 1466392 | G358: =$M$6/F358 -> 1.3638918 | H358: =F358*E358 -> 0 | I358: =H358/$M$9 -> 0 | J358: =H358/$M$8 -> 0
F359: =SUM(F4:F358) -> 2000000 | H359: =SUM(H4:H358) -> 1660000 | I359: =SUM(I4:I358) -> 1 | J359: =SUM(J4:J358) -> 0.83
B361: Base JP Odds Down | C361: 50000000
B362: JP Stake | C362: =$M$7 -> 1
B363: Revenue | C363: =C361*C362 -> 50000000
B364: Contribution | C364: =C362*C365 -> 0.04
B365: Contribution % | C365: =X372 -> 0.04
B366: Estimated plays per day | C366: 40000
M367: BASE
B368: Seed | K368: =C365-C380 -> 0.005 | M368: Odds Up | N368: Seed | O368: Target trigger | P368: Count | Q368: Odds Down | R368: 1 in x Odds | S368: Days to Trigger | T368: Prize Cost | U368: Trigger minus Seed | V368: JP Contrib Cost | W368: Split (use on JP split above) | X368: Total JP Prize cost
B369: Number | C369: Name | D369: Bonus | E369: Prize | F369: Base Odds Up | G369: Odds Down | H369: Base 1 in x Odds | I369: Prize Cost | J369: Contribution split | K369: Contribution | M369: 40 | N369: 2500 | O369: 5000 | P369: 4 | Q369: =C361 -> 50000000 | R369: =Q369/F370 -> 1250000 | S369: =R369/C366 -> 31.25 | T369: =M369*E370 -> 100000 | U369: =O369-N369 -> 2500 | V369: =U369*M369 -> 100000 | W369: =V369/V371 -> 0.057142857 | X369: =O369*M369 -> 200000
B370: 1 | C370: small | D370: BonusA | E370: =N369 -> 2500 | F370: =C362*M369 -> 40 | G370: =C361 -> 50000000 | H370: =G370/F370 -> 1250000 | I370: =E370*F370 -> 100000 | J370: =I370/I373 -> 0.4 | K370: =T372*J370*C362 -> 0.002 | M370: 1 | N370: 150000 | O370: 1800000 | P370: 4 | Q370: =C361 -> 50000000 | R370: =Q370/F371 -> 50000000 | S370: =R370/C366 -> 1250 | T370: =E371*M370 -> 150000 | U370: =O370-N370 -> 1650000 | V370: =U370*M370 -> 1650000 | W370: =V370/V371 -> 0.94285714 | X370: =O370*M370 -> 1800000
B371: 2 | C371: large | D371: BonusA | E371: =N370 -> 150000 | F371: =C362*M370 -> 1 | G371: =C361 -> 50000000 | H371: =G371/F371 -> 50000000 | I371: =E371*F371 -> 150000 | J371: =I371/I373 -> 0.6 | K371: =T372*J371*C362 -> 0.003 | M371: =SUM(M369:M370) -> 41 | R371: =SUM(R369:R370) -> 51250000 | T371: =SUM(T369:T370) -> 250000 | U371: =SUM(U369:U370) -> 1652500 | V371: =SUM(V369:V370) -> 1750000 | X371: =SUM(X369:X370) -> 2000000
T372: =T371/C361 -> 0.005 | V372: =V371/C361 -> 0.035 | X372: =X371/C361 -> 0.04
B373: RTP | C373: =I373/C363 -> 0.005 | F373: =SUM(F370:F371) -> 41 | H373: =C361/F373 -> 1219512.2 | I373: =SUM(I370:I371) -> 250000 | J373: =SUM(J370:J371) -> 1 | K373: =SUM(K370:K371) -> 0.005
B375: Jackpot Contributions (excluding seed) | K375: =C365-C373 -> 0.035
B376: Number | C376: Name | D376: Bonus | E376: Average Prize | F376: Base Odds Up | G376: Odds Down | H376: Base 1 in x Odds | I376: Prize Cost | J376: Contribution split | K376: Contribution
B377: 1 | C377: small | D377: BonusA | E377: =K377*H377 -> 2500 | F377: =C362*M369 -> 40 | G377: =C361 -> 50000000 | H377: =G377/F377 -> 1250000 | I377: =E377*F377 -> 100000 | J377: =W369 -> 0.057142857 | K377: =V372*J377*C362 -> 0.002
B378: 2 | C378: large | D378: BonusA | E378: =K378*H378 -> 1650000 | F378: =C362*M370 -> 1 | G378: =C361 -> 50000000 | H378: =G378/F378 -> 50000000 | I378: =E378*F378 -> 1650000 | J378: =W370 -> 0.94285714 | K378: =V372*J378*C362 -> 0.033
B380: RTP | C380: =I380/C363 -> 0.035 | I380: =SUM(I377:I378) -> 1750000 | J380: =SUM(J377:J378) -> 1 | K380: =SUM(K377:K378) -> 0.035
B383: Overal Game Summary
B384: JP Event Prob | C384: =C361/F373 -> 1219512.2
B385: Total win Odds (JP+Main) | C385: =1/((1/C384) + (1/M15)) -> 3.7480582
B386: Total non-win Prob Up | C386: =M6-(F373/(G371/M6)+M14) -> 1466390.4
B387: Total non-win Pob Down | C387: =M6 -> 2000000
B388: Main Game RTP | C388: =M10 -> 0.83
B389: Seed contribution RTP | C389: =C373 -> 0.005
B390: JP Contribution RTP | C390: =C380 -> 0.035
B391: TOTAL | C391: =C388+C389+C390 -> 0.87

Sheet Odds Table
A1: Ticket Price | B1: 0.5 | C1: 1 in X Odds | D1: 1 | E1: 1 in X Odds | F1: 2 | G1: 1 in X Odds | H1: 5 | I1: 1 in X Odds | J1: 10 | K1: 1 in X Odds | L1: 20 | M1: 1 in X Odds | N1: 30 | O1: 1 in X Odds | P1: 50 | Q1: 1 in X Odds
A2: JP1 | B2: $150,000.00* | C2: =E2*($D$1/$B$1) -> 100000000 | D2: $150,000.00* | E2: 50000000 | F2: $150,000.00* | G2: =E2/$F$1 -> 25000000 | H2: $150,000.00* | I2: =E2/$H$1 -> 10000000 | J2: $150,000.00* | K2: =E2/$J$1 -> 5000000 | L2: $150,000.00* | M2: =E2/$L$1 -> 2500000 | N2: $150,000.00* | O2: =E2/$N$1 -> 1666666.7 | P2: $150,000.00* | Q2: =E2/$P$1 -> 1000000
A3: JP2 | B3: $2,500.00* | C3: =E3*($D$1/$B$1) -> 2500000 | D3: $2,500.00* | E3: 1250000 | F3: $2,500.00* | G3: =E3/$F$1 -> 625000 | H3: $2,500.00* | I3: =E3/$H$1 -> 250000 | J3: $2,500.00* | K3: =E3/$J$1 -> 125000 | L3: $2,500.00* | M3: =E3/$L$1 -> 62500 | N3: $2,500.00* | O3: =E3/$N$1 -> 41666.667 | P3: $2,500.00* | Q3: =E3/$P$1 -> 25000
A4: Prize | B4: =D4*0.5 -> 500 | C4: =E4 -> 2000000 | D4: 1000 | E4: 2000000 | F4: =D4*2 -> 2000 | G4: =E4 -> 2000000 | H4: =D4*5 -> 5000 | I4: =E4 -> 2000000 | J4: =D4*10 -> 10000 | K4: =E4 -> 2000000 | L4: =D4*20 -> 20000 | M4: =K4 -> 2000000 | N4: =D4*30 -> 30000 | O4: =M4 -> 2000000 | P4: =D4*50 -> 50000 | Q4: =O4 -> 2000000
B5: =D5*0.5 -> 250 | C5: =E5 -> 666666.67 | D5: 500 | E5: 666666.67 | F5: =D5*2 -> 1000 | G5: =E5 -> 666666.67 | H5: =D5*5 -> 2500 | I5: =E5 -> 666666.67 | J5: =D5*10 -> 5000 | K5: =E5 -> 666666.67 | L5: =D5*20 -> 10000 | M5: =K5 -> 666666.67 | N5: =D5*30 -> 15000 | O5: =M5 -> 666666.67 | P5: =D5*50 -> 25000 | Q5: =O5 -> 666666.67
B6: =D6*0.5 -> 100 | C6: =E6 -> 400000 | D6: 200 | E6: 400000 | F6: =D6*2 -> 400 | G6: =E6 -> 400000 | H6: =D6*5 -> 1000 | I6: =E6 -> 400000 | J6: =D6*10 -> 2000 | K6: =E6 -> 400000 | L6: =D6*20 -> 4000 | M6: =K6 -> 400000 | N6: =D6*30 -> 6000 | O6: =M6 -> 400000 | P6: =D6*50 -> 10000 | Q6: =O6 -> 400000
B7: =D7*0.5 -> 70.95 | C7: =E7 -> 1000000 | D7: 141.9 | E7: 1000000 | F7: =D7*2 -> 283.8 | G7: =E7 -> 1000000 | H7: =D7*5 -> 709.5 | I7: =E7 -> 1000000 | J7: =D7*10 -> 1419 | K7: =E7 -> 1000000 | L7: =D7*20 -> 2838 | M7: =K7 -> 1000000 | N7: =D7*30 -> 4257 | O7: =M7 -> 1000000 | P7: =D7*50 -> 7095 | Q7: =O7 -> 1000000
B8: =D8*0.5 -> 62.5 | C8: =E8 -> 1000000 | D8: 125 | E8: 1000000 | F8: =D8*2 -> 250 | G8: =E8 -> 1000000 | H8: =D8*5 -> 625 | I8: =E8 -> 1000000 | J8: =D8*10 -> 1250 | K8: =E8 -> 1000000 | L8: =D8*20 -> 2500 | M8: =K8 -> 1000000 | N8: =D8*30 -> 3750 | O8: =M8 -> 1000000 | P8: =D8*50 -> 6250 | Q8: =O8 -> 1000000
B9: =D9*0.5 -> 57.5 | C9: =E9 -> 1000000 | D9: 115 | E9: 1000000 | F9: =D9*2 -> 230 | G9: =E9 -> 1000000 | H9: =D9*5 -> 575 | I9: =E9 -> 1000000 | J9: =D9*10 -> 1150 | K9: =E9 -> 1000000 | L9: =D9*20 -> 2300 | M9: =K9 -> 1000000 | N9: =D9*30 -> 3450 | O9: =M9 -> 1000000 | P9: =D9*50 -> 5750 | Q9: =O9 -> 1000000
B10: =D10*0.5 -> 50 | C10: =E10 -> 18018.018 | D10: 100 | E10: 18018.018 | F10: =D10*2 -> 200 | G10: =E10 -> 18018.018 | H10: =D10*5 -> 500 | I10: =E10 -> 18018.018 | J10: =D10*10 -> 1000 | K10: =E10 -> 18018.018 | L10: =D10*20 -> 2000 | M10: =K10 -> 18018.018 | N10: =D10*30 -> 3000 | O10: =M10 -> 18018.018 | P10: =D10*50 -> 5000 | Q10: =O10 -> 18018.018
B11: =D11*0.5 -> 45.95 | C11: =E11 -> 400000 | D11: 91.9 | E11: 400000 | F11: =D11*2 -> 183.8 | G11: =E11 -> 400000 | H11: =D11*5 -> 459.5 | I11: =E11 -> 400000 | J11: =D11*10 -> 919 | K11: =E11 -> 400000 | L11: =D11*20 -> 1838 | M11: =K11 -> 400000 | N11: =D11*30 -> 2757 | O11: =M11 -> 400000 | P11: =D11*50 -> 4595 | Q11: =O11 -> 400000
B12: =D12*0.5 -> 45 | C12: =E12 -> 1000000 | D12: 90 | E12: 1000000 | F12: =D12*2 -> 180 | G12: =E12 -> 1000000 | H12: =D12*5 -> 450 | I12: =E12 -> 1000000 | J12: =D12*10 -> 900 | K12: =E12 -> 1000000 | L12: =D12*20 -> 1800 | M12: =K12 -> 1000000 | N12: =D12*30 -> 2700 | O12: =M12 -> 1000000 | P12: =D12*50 -> 4500 | Q12: =O12 -> 1000000
B13: =D13*0.5 -> 43.95 | C13: =E13 -> 400000 | D13: 87.9 | E13: 400000 | F13: =D13*2 -> 175.8 | G13: =E13 -> 400000 | H13: =D13*5 -> 439.5 | I13: =E13 -> 400000 | J13: =D13*10 -> 879 | K13: =E13 -> 400000 | L13: =D13*20 -> 1758 | M13: =K13 -> 400000 | N13: =D13*30 -> 2637 | O13: =M13 -> 400000 | P13: =D13*50 -> 4395 | Q13: =O13 -> 400000
B14: =D14*0.5 -> 42.65 | C14: =E14 -> 333333.33 | D14: 85.3 | E14: 333333.33 | F14: =D14*2 -> 170.6 | G14: =E14 -> 333333.33 | H14: =D14*5 -> 426.5 | I14: =E14 -> 333333.33 | J14: =D14*10 -> 853 | K14: =E14 -> 333333.33 | L14: =D14*20 -> 1706 | M14: =K14 -> 333333.33 | N14: =D14*30 -> 2559 | O14: =M14 -> 333333.33 | P14: =D14*50 -> 4265 | Q14: =O14 -> 333333.33
B15: =D15*0.5 -> 42.5 | C15: =E15 -> 1000000 | D15: 85 | E15: 1000000 | F15: =D15*2 -> 170 | G15: =E15 -> 1000000 | H15: =D15*5 -> 425 | I15: =E15 -> 1000000 | J15: =D15*10 -> 850 | K15: =E15 -> 1000000 | L15: =D15*20 -> 1700 | M15: =K15 -> 1000000 | N15: =D15*30 -> 2550 | O15: =M15 -> 1000000 | P15: =D15*50 -> 4250 | Q15: =O15 -> 1000000
B16: =D16*0.5 -> 42.05 | C16: =E16 -> 200000 | D16: 84.1 | E16: 200000 | F16: =D16*2 -> 168.2 | G16: =E16 -> 200000 | H16: =D16*5 -> 420.5 | I16: =E16 -> 200000 | J16: =D16*10 -> 841 | K16: =E16 -> 200000 | L16: =D16*20 -> 1682 | M16: =K16 -> 200000 | N16: =D16*30 -> 2523 | O16: =M16 -> 200000 | P16: =D16*50 -> 4205 | Q16: =O16 -> 200000
... B197: =D197*0.5 -> 0.05 | C197: =E197 -> 28.571429 | D197: 0.1 | E197: 28.571429 | F197: =D197*2 -> 0.2 | G197: =E197 -> 28.571429 | H197: =D197*5 -> 0.5 | I197: =E197 -> 28.571429 | J197: =D197*10 -> 1 | K197: =E197 -> 28.571429 | L197: =D197*20 -> 2 | M197: =K197 -> 28.571429 | N197: =D197*30 -> 3 | O197: =M197 -> 28.571429 | P197: =D197*50 -> 5 | Q197: =O197 -> 28.571429
B198: NON WINNING | C198: =E198 -> 1.3638918 | D198: NON WINNING | E198: 1.3638918 | F198: NON WINNING | G198: =E198 -> 1.3638918 | H198: NON WINNING | I198: =E198 -> 1.3638918 | J198: NON WINNING | K198: =E198 -> 1.3638918 | L198: NON WINNING | M198: =K198 -> 1.3638918 | N198: NON WINNING | O198: =M198 -> 1.3638918 | P198: NON WINNING | Q198: =O198 -> 1.3638918

Sheet Summary(Delivery)
A1: Size of Grid | B1: 0.5 | C1: 1 | D1: 2 | E1: 5 | F1: 10 | G1: 20 | H1: 30 | I1: 50
A2: Top Prize | B2: =$C$2*B1 -> 500 | C2: 1000 | D2: =$C$2*D1 -> 2000 | E2: =$C$2*E1 -> 5000 | F2: =$C$2*F1 -> 10000 | G2: =$C$2*G1 -> 20000 | H2: =$C$2*H1 -> 30000 | I2: =$C$2*I1 -> 50000
A3: Version | B3: v1 | C3: v1 | D3: v1 | E3: v1 | F3: v1 | G3: v1 | H3: v1 | I3: v1
A4: Payout | B4: =C4 -> 0.83 | C4: 0.83 | D4: =C4 -> 0.83 | E4: =C4 -> 0.83 | F4: =C4 -> 0.83 | G4: =C4 -> 0.83 | H4: =C4 -> 0.83 | I4: =C4 -> 0.83
A5: Breakeven | B5: =C5 -> 0 | C5: 0 | D5: =C5 -> 0 | E5: =C5 -> 0 | F5: =C5 -> 0 | G5: =C5 -> 0 | H5: =C5 -> 0 | I5: =C5 -> 0
A6: Odds | B6: =C6 -> 3.7480697 | C6: 3.7480697 | D6: =C6 -> 3.7480697 | E6: =C6 -> 3.7480697 | F6: =C6 -> 3.7480697 | G6: =C6 -> 3.7480697 | H6: =C6 -> 3.7480697 | I6: =C6 -> 3.7480697
A7: Size of Grid | B7: 2000000 | C7: 2000000 | D7: 2000000 | E7: 2000000 | F7: 2000000 | G7: 2000000 | H7: 2000000 | I7: 2000000
A8: Low Tier Winning Range | B8: x0 - x5 | C8: x0 - x5 | D8: x0 - x5 | E8: x0 - x5 | F8: x0 - x5 | G8: x0 - x5 | H8: x0 - x5 | I8: x0 - x5
A9: Percentage in Low Tier | B9: =C9 -> 0.27972325 | C9: 0.27972325 | D9: =C9 -> 0.27972325 | E9: =C9 -> 0.27972325 | F9: =C9 -> 0.27972325 | G9: =C9 -> 0.27972325 | H9: =C9 -> 0.27972325 | I9: =C9 -> 0.27972325
A10: Medium Tier Winning Range | B10: x5 - x20 | C10: x5 - x20 | D10: x5 - x20 | E10: x5 - x20 | F10: x5 - x20 | G10: x5 - x20 | H10: x5 - x20 | I10: x5 - x20
A11: Percentage in Medium Tier | B11: =C11 -> 0.27419319 | C11: 0.27419319 | D11: =C11 -> 0.27419319 | E11: =C11 -> 0.27419319 | F11: =C11 -> 0.27419319 | G11: =C11 -> 0.27419319 | H11: =C11 -> 0.27419319 | I11: =C11 -> 0.27419319
A12: High Tier Winning Range | B12: x20 - top | C12: x20 - top | D12: x20 - top | E12: x20 - top | F12: x20 - top | G12: x20 - top | H12: x20 - top | I12: x20 - top
A13: Percentage in High Tier | B13: =C13 -> 0.44608355 | C13: 0.44608355 | D13: =C13 -> 0.44608355 | E13: =C13 -> 0.44608355 | F13: =C13 -> 0.44608355 | G13: =C13 -> 0.44608355 | H13: =C13 -> 0.44608355 | I13: =C13 -> 0.44608355
A14: Total Pool Amount | B14: =B7*B4*B1 -> 830000 | C14: =C7*C4*C1 -> 1660000 | D14: =D7*D4*D1 -> 3320000 | E14: =E7*E4*E1 -> 8300000 | F14: =F7*F4*F1 -> 16600000 | G14: =G7*G4*G1 -> 33200000 | H14: =H7*H4*H1 -> 49800000 | I14: =I7*I4*I1 -> 83000000
A15: Progressive Jackpot Info | B15: 0.5 | C15: 1 | D15: 2 | E15: 5 | F15: 10 | G15: 20 | H15: 30 | I15: 50
A16: Size of Grid | B16: 50000000 | C16: 50000000 | D16: 50000000 | E16: 50000000 | F16: 50000000 | G16: 50000000 | H16: 50000000 | I16: 50000000
A17: JP2 Wins/Grid | B17: =$C$17*B15 -> 0.5 | C17: 1 | D17: =$C$17*D15 -> 2 | E17: =$C$17*E15 -> 5 | F17: =$C$17*F15 -> 10 | G17: =$C$17*G15 -> 20 | H17: =$C$17*H15 -> 30 | I17: =$C$17*I15 -> 50
A18: JP1 Wins/Grid | B18: =$C$18*B15 -> 20 | C18: 40 | D18: =$C$18*D15 -> 80 | E18: =$C$18*E15 -> 200 | F18: =$C$18*F15 -> 400 | G18: =$C$18*G15 -> 800 | H18: =$C$18*H15 -> 1200 | I18: =$C$18*I15 -> 2000
A19: JP2 Wins/Price Ratio | B19: =C19 -> 1 | C19: 1 | D19: =C19 -> 1 | E19: =C19 -> 1 | F19: =C19 -> 1 | G19: =C19 -> 1 | H19: =C19 -> 1 | I19: =C19 -> 1
A20: JP1 Wins/Price Ratio | B20: =C20 -> 40 | C20: 40 | D20: =C20 -> 40 | E20: =C20 -> 40 | F20: =C20 -> 40 | G20: =C20 -> 40 | H20: =C20 -> 40 | I20: =C20 -> 40
A21: Odds of JP1 Win | B21: =$C$21/B15 -> 2500000 | C21: 1250000 | D21: =$C$21/D15 -> 625000 | E21: =$C$21/E15 -> 250000 | F21: =$C$21/F15 -> 125000 | G21: =$C$21/G15 -> 62500 | H21: =$C$21/H15 -> 41666.667 | I21: =$C$21/I15 -> 25000
A22: Odds of JP2 Win | B22: =$C$22/B15 -> 100000000 | C22: 50000000 | D22: =$C$22/D15 -> 25000000 | E22: =$C$22/E15 -> 10000000 | F22: =$C$22/F15 -> 5000000 | G22: =$C$22/G15 -> 2500000 | H22: =$C$22/H15 -> 1666666.7 | I22: =$C$22/I15 -> 1000000
A23: Revenue/JP win | B23: =B16*B15 -> 25000000 | C23: =C16*C15 -> 50000000 | D23: =D16*D15 -> 100000000 | E23: =E16*E15 -> 250000000 | F23: =F16*F15 -> 500000000 | G23: =G16*G15 -> 1000000000 | H23: =H16*H15 -> 1500000000 | I23: =I16*I15 -> 2500000000
A24: Jackpot Reset % | B24: =C24 -> 0.005 | C24: 0.005 | D24: =C24 -> 0.005 | E24: =C24 -> 0.005 | F24: =C24 -> 0.005 | G24: =C24 -> 0.005 | H24: =C24 -> 0.005 | I24: =C24 -> 0.005
A25: JP1 Reset Value | B25: 2500 | C25: 2500 | D25: 2500 | E25: 2500 | F25: 2500 | G25: 2500 | H25: 2500 | I25: 2500
A26: JP2 Reset Value | B26: 150000 | C26: 150000 | D26: 150000 | E26: 150000 | F26: 150000 | G26: 150000 | H26: 150000 | I26: 150000
A27: Jackpot Increment % | B27: =C27 -> 0.035 | C27: 0.035 | D27: =C27 -> 0.035 | E27: =C27 -> 0.035 | F27: =C27 -> 0.035 | G27: =C27 -> 0.035 | H27: =C27 -> 0.035 | I27: =C27 -> 0.035
A28: Jackpot Increment Amount | B28: =$C$28*B15 -> 0.0175 | C28: =C27*C17 -> 0.035 | D28: =$C$28*D15 -> 0.07 | E28: =$C$28*E15 -> 0.175 | F28: =$C$28*F15 -> 0.35 | G28: =$C$28*G15 -> 0.7 | H28: =$C$28*H15 -> 1.05 | I28: =$C$28*I15 -> 1.75

Sheet Prize Breakdown
B2: Tier | C2: Win Methods | D2: Prize | E2: Symbol | F2: Quantity of Symbols
B3: 1 | C3: main-0 | D3: 0.1 | E3: A/B/C/D | F3: 3
B4: 2 | C4: main-1 | D4: 0.2 | E4: A/B/C/D | F4: 4
B5: 3 | C5: main-2 | D5: 0.5 | E5: A/B/C/D | F5: 5
B6: 4 | C6: main-3 | D6: 1 | E6: A/B/C/D | F6: 6
B7: 5 | C7: main-4 | D7: 1.5 | E7: A/B/C/D | F7: 7
B8: 6 | C8: main-5 | D8: 2 | E8: A/B/C/D | F8: 8 | H8: Quantity of Symbols | I8: A | J8: B | K8: C | L8: D | M8: E | N8: F | O8: G
B9: 7 | C9: main-6 | D9: 2.5 | E9: A/B/C/D | F9: 9 | H9: 3 | I9: 0.1 | J9: 0.1 | K9: 0.1 | L9: 0.1 | M9: 1 | N9: 1.5 | O9: 2
B10: 8 | C10: main-7 | D10: 3 | E10: A/B/C/D | F10: 10 | H10: 4 | I10: 0.2 | J10: 0.2 | K10: 0.2 | L10: 0.2 | M10: 1.5 | N10: 2 | O10: 5
B11: 9 | C11: main-8 | D11: 5 | E11: A/B/C/D | F11: 11 | H11: 5 | I11: 0.5 | J11: 0.5 | K11: 0.5 | L11: 0.5 | M11: 2 | N11: 5 | O11: 10
B12: 10 | C12: main-9 | D12: 10 | E12: A | F12: 12 | H12: 6 | I12: 1 | J12: 1 | K12: 1 | L12: 1 | M12: 5 | N12: 10 | O12: 15
B13: 11 | C13: main-10 | D13: 1 | E13: E | F13: 3 | H13: 7 | I13: 1.5 | J13: 1.5 | K13: 1.5 | L13: 1.5 | M13: 10 | N13: 15 | O13: 20
B14: 12 | C14: main-11 | D14: 1.5 | E14: E | F14: 4 | H14: 8 | I14: 2 | J14: 2 | K14: 2 | L14: 2 | M14: 15 | N14: 20 | O14: 50
B15: 13 | C15: main-12 | D15: 2 | E15: E | F15: 5 | H15: 9 | I15: 2.5 | J15: 2.5 | K15: 2.5 | L15: 2.5 | M15: 20 | N15: 50 | O15: 100
B16: 14 | C16: main-13 | D16: 5 | E16: E | F16: 6 | H16: 10 | I16: 3 | J16: 3 | K16: 3 | L16: 3 | M16: 50 | N16: 100 | O16: 200
B17: 15 | C17: main-14 | D17: 10 | E17: E | F17: 7 | H17: 11 | I17: 5 | J17: 5 | K17: 5 | L17: 5 | M17: 100 | N17: 200 | O17: 500
B18: 16 | C18: main-15 | D18: 15 | E18: E | F18: 8 | H18: 12 | I18: 10 | J18: 15 | K18: 20 | L18: 30 | M18: 200 | N18: 500 | O18: 1000 | P18: -
B19: 17 | C19: main-16 | D19: 20 | E19: E | F19: 9
B20: 18 | C20: main-17 | D20: 50 | E20: E | F20: 10
B21: 19 | C21: main-18 | D21: 100 | E21: E | F21: 11
B22: 20 | C22: main-19 | D22: 200 | E22: E | F22: 12
B23: 21 | C23: main-20 | D23: 1.5 | E23: F | F23: 3
B24: 22 | C24: main-21 | D24: 2 | E24: F | F24: 4
B25: 23 | C25: main-22 | D25: 5 | E25: F | F25: 5
B26: 24 | C26: main-23 | D26: 10 | E26: F | F26: 6
B27: 25 | C27: main-24 | D27: 15 | E27: F | F27: 7
B28: 26 | C28: main-25 | D28: 20 | E28: F | F28: 8
B29: 27 | C29: main-26 | D29: 50 | E29: F | F29: 9
B30: 28 | C30: main-27 | D30: 100 | E30: F | F30: 10
... B83: 354 | C83: bonusA-6 | D83: 100 | E83: Super Spin Jackpot | F83: 3

Sheet Summary
B3: Odds Down (ticket quantity if pool based): | C3: =Frequency!N6 -> 2000000
B4: Base(ticket price): | C4: =Frequency!N7 -> 1
B5: Revenue (if pool based): | C5: =C3*C4 -> 2000000
B6: Base Prize fund (if pool based): | C6: =C5*C8 -> 1660000
B7: Max prize | C7: =MAX(Tiers!C3:C4874) -> 1000
B8: Base RTP setting(JP exclude) | C8: =Frequency!N10 -> 0.83
B9: Hit Rate | C9: =Summary!C3/(C3-Frequency!E4) -> 3.7480697
B10: Std. Dev. | C10: =('Data Analysis'!BO357/Summary!C3)^0.5 -> 4.2248542
B12: Freeplay Overall Freq | C12: =C3/('Data Analysis'!AV357+'Data Analysis'!AX357+'Data Analysis'!AZ357+'Data Analysis'!BB357) -> 195.35065 | E12: 20x Multi Freq | F12: =C3/'Data Analysis'!G357 -> 65.299726
B13: Freeplay Overall Avg. Multi | C13: =('Data Analysis'!BC357+'Data Analysis'!BA357+'Data Analysis'!AY357+'Data Analysis'!AW357)/('Data Analysis'!BB357+'Data Analysis'!AZ357+'Data Analysis'!AX357+'Data Analysis'!AV357) -> 28.147392 | E13: 20x Multi Avg. Payout | F13: ='Data Analysis'!H357/'Data Analysis'!G357 -> 17.957973
B14: Freeplay Overall Value Share | C14: =('Data Analysis'!BC357+'Data Analysis'!BA357+'Data Analysis'!AY357+'Data Analysis'!AW357)/C6 -> 0.17359819 | E14: Multi Value Share | F14: ='Data Analysis'!H357/Summary!C6 -> 0.33133542
B15: freeplayA Freq | C15: =Summary!C3/'Data Analysis'!AV357 -> 195.35065
B16: freeplayA Avg. Multi | C16: ='Data Analysis'!AW357/'Data Analysis'!AV357 -> 28.147392
B17: freeplayA Value Share | C17: ='Data Analysis'!AW357/Summary!C6 -> 0.17359819
B19: Bonus Overall Freq | C19: =C3/('Data Analysis'!BH357+'Data Analysis'!BF357+'Data Analysis'!BD357) -> 84.530854 | D19: SSJ
B20: Bonus Overall Multi | C20: =('Data Analysis'!BI357+'Data Analysis'!BG357+'Data Analysis'!BE357)/('Data Analysis'!BH357+'Data Analysis'!BF357+'Data Analysis'!BD357) -> 23.421188
B21: Bonus Overall Value Share | C21: =('Data Analysis'!BI357+'Data Analysis'!BG357+'Data Analysis'!BE357)/C6 -> 0.33382247
B22: bonusA Freq | C22: =C3/'Data Analysis'!BD357 -> 84.530854
B23: bonusA Multi | C23: ='Data Analysis'!BE357/'Data Analysis'!BD357 -> 23.421188
B24: bonusA Value Share | C24: ='Data Analysis'!BE357/Summary!C6 -> 0.33382247
B26: Feature(Bonus + Freeplay) Freq | C26: =C3/('Data Analysis'!BH357+'Data Analysis'!BF357+'Data Analysis'!BD357+'Data Analysis'!BB357+'Data Analysis'!AZ357+'Data Analysis'!AX357+'Data Analysis'!AV357) -> 59.000531
B27: Feature Overall Multi | C27: =('Data Analysis'!AW357+'Data Analysis'!AY357+'Data Analysis'!BA357+'Data Analysis'!BC357+'Data Analysis'!BE357+'Data Analysis'!BG357+'Data Analysis'!BI357)/('Data Analysis'!BH357+'Data Analysis'!BF357+'Data Analysis'!BD357+'Data Analysis'!BB357+'Data Analysis'!AZ357+'Data Analysis'!AX357+'Data Analysis'!AV357) -> 24.848613
B28: Feature Overall Value Share | C28: =('Data Analysis'!AW357+'Data Analysis'!AY357+'Data Analysis'!BA357+'Data Analysis'!BC357+'Data Analysis'!BE357+'Data Analysis'!BG357+'Data Analysis'!BI357)/C6 -> 0.50742066
B31: Combo Win Freq | C31: =C3/'Data Analysis'!AK357 -> 20.894275
B32: Combo Win Multi | C32: ='Data Analysis'!AL357/'Data Analysis'!AK357 -> 7.6216977
B34: Category | C34: Freq | D34: Prob. | E34: Odds Dist. | F34: Value Dist. | G34: Hit Dist.
B35: NIL | C35: ='Data Analysis'!E2 -> 1466392 | D35: =C35/$C$46 -> 0.733196 | E35: =1/D35 -> 1.3638918 | F35: - | G35: -
B36: >0 to <1 | C36: ='Data Analysis'!M357 -> 190004 | D36: =C36/$C$46 -> 0.095002 | E36: =1/D36 -> 10.526094 | F36: ='Data Analysis'!N357/Summary!C6 -> 0.026627169 | G36: =C36/SUM($C$36:$C$45) -> 0.35607412
B37: =1 -> 1 | C37: ='Data Analysis'!O357 -> 133806 | D37: =C37/$C$46 -> 0.066903 | E37: =1/D37 -> 14.947013 | F37: ='Data Analysis'!P357/Summary!C6 -> 0.080606024 | G37: =C37/SUM($C$36:$C$45) -> 0.25075711
B38: >1 to 2 | C38: ='Data Analysis'!Q357 -> 142772 | D38: =C38/$C$46 -> 0.071386 | E38: =1/D38 -> 14.008349 | F38: ='Data Analysis'!R357/Summary!C6 -> 0.14475542 | G38: =C38/SUM($C$36:$C$45) -> 0.26755971
B39: >2 to 5 | C39: ='Data Analysis'!S357 -> 11912 | D39: =C39/$C$46 -> 0.005956 | E39: =1/D39 -> 167.89792 | F39: ='Data Analysis'!T357/Summary!C6 -> 0.027734639 | G39: =C39/SUM($C$36:$C$45) -> 0.022323503 | H39: =F36+F37+F38+F39 -> 0.27972325
B40: >5 to 10 | C40: ='Data Analysis'!U357 -> 10924 | D40: =C40/$C$46 -> 0.005462 | E40: =1/D40 -> 183.08312 | F40: ='Data Analysis'!V357/Summary!C6 -> 0.058778554 | G40: =C40/SUM($C$36:$C$45) -> 0.020471957 | H40: =F40+F41 -> 0.27419319
B41: >10 to 20 | C41: ='Data Analysis'!W357 -> 21594 | D41: =C41/$C$46 -> 0.010797 | E41: =1/D41 -> 92.61832 | F41: ='Data Analysis'!X357/Summary!C6 -> 0.21541464 | G41: =C41/SUM($C$36:$C$45) -> 0.040467909 | H41: =F42+F43+F44+F45 -> 0.44608355
B42: >20 to 30 | C42: ='Data Analysis'!Y357 -> 13920 | D42: =C42/$C$46 -> 0.00696 | E42: =1/D42 -> 143.67816 | F42: ='Data Analysis'!Z357/Summary!C6 -> 0.21372693 | G42: =C42/SUM($C$36:$C$45) -> 0.026086565
B43: >30 to 50 | C43: ='Data Analysis'!AA357 -> 6916 | D43: =C43/$C$46 -> 0.003458 | E43: =1/D43 -> 289.1845 | F43: ='Data Analysis'!AB357/Summary!C6 -> 0.1636903 | G43: =C43/SUM($C$36:$C$45) -> 0.012960825
B44: >50 to 100 | C44: ='Data Analysis'!AC357 -> 1745 | D44: =C44/$C$46 -> 0.0008725 | E44: =1/D44 -> 1146.1318 | F44: ='Data Analysis'!AD357/Summary!C6 -> 0.066097771 | G44: =C44/SUM($C$36:$C$45) -> 0.0032701909
B45: >100 | C45: ='Data Analysis'!AE357 -> 15 | D45: =C45/$C$46 -> 7.5e-06 | E45: =1/D45 -> 133333.33 | F45: ='Data Analysis'!AF357/Summary!C6 -> 0.0025685542 | G45: =C45/SUM($C$36:$C$45) -> 2.8110523e-05
C46: =SUM(C35:C45) -> 2000000 | F46: =SUM(F36:F45) -> 1 | G46: =SUM(G36:G45) -> 1

Sheet Tiers
B2: Tier | C2: Total Prize | D2: Multiplier | E2: Method 1 | F2: Prize 1 | G2: Method 2 | H2: Prize 2 | I2: Method 3 | J2: Prize 3 | K2: Method 4 | L2: Prize 4 | M2: Method 5 | N2: Prize 5 | O2: Method 6 | P2: Prize 6 | Q2: Method 7 | R2: Prize 7 | S2: Method 8 | T2: Prize 8 | U2: Method 9 | V2: Prize 9 | W2: Method 10 | X2: Prize 10 | Y2: Method
B3: 0 | C3: =(F3+H3+J3+L3+N3+P3+R3+T3+V3+X3)*D3 -> 0 | D3: 1 | F3: =VLOOKUP(E3,'Win Methods'!$C$4:$F$4992,4,FALSE) -> 0 | H3: =VLOOKUP(G3,'Win Methods'!$C$4:$F$4992,4,FALSE) -> 0 | J3: =VLOOKUP(I3,'Win Methods'!$C$4:$F$4992,4,FALSE) -> 0 | L3: =VLOOKUP(K3,'Win Methods'!$C$4:$F$4992,4,FALSE) -> 0 | N3: =VLOOKUP(M3,'Win Methods'!$C$4:$F$4992,4,FALSE) -> 0 | P3: =VLOOKUP(O3,'Win Methods'!$C$4:$F$4992,4,FALSE) -> 0 | R3: =VLOOKUP(Q3,'Win Methods'!$C$4:$F$4992,4,FALSE) -> 0 | T3: =VLOOKUP(S3,'Win Methods'!$C$4:$F$4992,4,FALSE) -> 0 | V3: =VLOOKUP(U3,'Win Methods'!$C$4:$F$4992,4,FALSE) -> 0 | X3: =VLOOKUP(W3,'Win Methods'!$C$4:$F$4992,4,FALSE) -> 0 | Y3: =E3&"|"&G3&"|"&I3&"|"&K3&"|"&M3&"|"&O3&"|"&Q3&"|"&S3&"|"&U3&"|"&W3 &" x "&D3 -> ||||||||| x 1
B4: 1 | C4: =(F4+H4+J4+L4+N4+P4+R4+T4+V4+X4)*D4 -> 0.1 | D4: 1 | E4: main-0 | F4: =VLOOKUP(E4,'Win Methods'!$C$4:$F$4992,4,FALSE) -> 0.1 | H4: =VLOOKUP(G4,'Win Methods'!$C$4:$F$4992,4,FALSE) -> 0 | J4: =VLOOKUP(I4,'Win Methods'!$C$4:$F$4992,4,FALSE) -> 0 | L4: =VLOOKUP(K4,'Win Methods'!$C$4:$F$4992,4,FALSE) -> 0 | N4: =VLOOKUP(M4,'Win Methods'!$C$4:$F$4992,4,FALSE) -> 0 | P4: =VLOOKUP(O4,'Win Methods'!$C$4:$F$4992,4,FALSE) -> 0 | R4: =VLOOKUP(Q4,'Win Methods'!$C$4:$F$4992,4,FALSE) -> 0 | T4: =VLOOKUP(S4,'Win Methods'!$C$4:$F$4992,4,FALSE) -> 0 | V4: =VLOOKUP(U4,'Win Methods'!$C$4:$F$4992,4,FALSE) -> 0 | X4: =VLOOKUP(W4,'Win Methods'!$C$4:$F$4992,4,FALSE) -> 0 | Y4: =E4&"|"&G4&"|"&I4&"|"&K4&"|"&M4&"|"&O4&"|"&Q4&"|"&S4&"|"&U4&"|"&W4 &" x "&D4 -> main-0||||||||| x 1
B5: 2 | C5: =(F5+H5+J5+L5+N5+P5+R5+T5+V5+X5)*D5 -> 0.2 | D5: 1 | E5: main-1 | F5: =VLOOKUP(E5,'Win Methods'!$C$4:$F$4992,4,FALSE) -> 0.2 | H5: =VLOOKUP(G5,'Win Methods'!$C$4:$F$4992,4,FALSE) -> 0 | J5: =VLOOKUP(I5,'Win Methods'!$C$4:$F$4992,4,FALSE) -> 0 | L5: =VLOOKUP(K5,'Win Methods'!$C$4:$F$4992,4,FALSE) -> 0 | N5: =VLOOKUP(M5,'Win Methods'!$C$4:$F$4992,4,FALSE) -> 0 | P5: =VLOOKUP(O5,'Win Methods'!$C$4:$F$4992,4,FALSE) -> 0 | R5: =VLOOKUP(Q5,'Win Methods'!$C$4:$F$4992,4,FALSE) -> 0 | T5: =VLOOKUP(S5,'Win Methods'!$C$4:$F$4992,4,FALSE) -> 0 | V5: =VLOOKUP(U5,'Win Methods'!$C$4:$F$4992,4,FALSE) -> 0 | X5: =VLOOKUP(W5,'Win Methods'!$C$4:$F$4992,4,FALSE) -> 0 | Y5: =E5&"|"&G5&"|"&I5&"|"&K5&"|"&M5&"|"&O5&"|"&Q5&"|"&S5&"|"&U5&"|"&W5 &" x "&D5 -> main-1||||||||| x 1
B6: 3 | C6: =(F6+H6+J6+L6+N6+P6+R6+T6+V6+X6)*D6 -> 0.5 | D6: 1 | E6: main-2 | F6: =VLOOKUP(E6,'Win Methods'!$C$4:$F$4992,4,FALSE) -> 0.5 | H6: =VLOOKUP(G6,'Win Methods'!$C$4:$F$4992,4,FALSE) -> 0 | J6: =VLOOKUP(I6,'Win Methods'!$C$4:$F$4992,4,FALSE) -> 0 | L6: =VLOOKUP(K6,'Win Methods'!$C$4:$F$4992,4,FALSE) -> 0 | N6: =VLOOKUP(M6,'Win Methods'!$C$4:$F$4992,4,FALSE) -> 0 | P6: =VLOOKUP(O6,'Win Methods'!$C$4:$F$4992,4,FALSE) -> 0 | R6: =VLOOKUP(Q6,'Win Methods'!$C$4:$F$4992,4,FALSE) -> 0 | T6: =VLOOKUP(S6,'Win Methods'!$C$4:$F$4992,4,FALSE) -> 0 | V6: =VLOOKUP(U6,'Win Methods'!$C$4:$F$4992,4,FALSE) -> 0 | X6: =VLOOKUP(W6,'Win Methods'!$C$4:$F$4992,4,FALSE) -> 0 | Y6: =E6&"|"&G6&"|"&I6&"|"&K6&"|"&M6&"|"&O6&"|"&Q6&"|"&S6&"|"&U6&"|"&W6 &" x "&D6 -> main-2||||||||| x 1
B7: 4 | C7: =(F7+H7+J7+L7+N7+P7+R7+T7+V7+X7)*D7 -> 1 | D7: 1 | E7: main-3 | F7: =VLOOKUP(E7,'Win Methods'!$C$4:$F$4992,4,FALSE) -> 1 | H7: =VLOOKUP(G7,'Win Methods'!$C$4:$F$4992,4,FALSE) -> 0 | J7: =VLOOKUP(I7,'Win Methods'!$C$4:$F$4992,4,FALSE) -> 0 | L7: =VLOOKUP(K7,'Win Methods'!$C$4:$F$4992,4,FALSE) -> 0 | N7: =VLOOKUP(M7,'Win Methods'!$C$4:$F$4992,4,FALSE) -> 0 | P7: =VLOOKUP(O7,'Win Methods'!$C$4:$F$4992,4,FALSE) -> 0 | R7: =VLOOKUP(Q7,'Win Methods'!$C$4:$F$4992,4,FALSE) -> 0 | T7: =VLOOKUP(S7,'Win Methods'!$C$4:$F$4992,4,FALSE) -> 0 | V7: =VLOOKUP(U7,'Win Methods'!$C$4:$F$4992,4,FALSE) -> 0 | X7: =VLOOKUP(W7,'Win Methods'!$C$4:$F$4992,4,FALSE) -> 0 | Y7: =E7&"|"&G7&"|"&I7&"|"&K7&"|"&M7&"|"&O7&"|"&Q7&"|"&S7&"|"&U7&"|"&W7 &" x "&D7 -> main-3||||||||| x 1
B8: 5 | C8: =(F8+H8+J8+L8+N8+P8+R8+T8+V8+X8)*D8 -> 1.5 | D8: 1 | E8: main-4 | F8: =VLOOKUP(E8,'Win Methods'!$C$4:$F$4992,4,FALSE) -> 1.5 | H8: =VLOOKUP(G8,'Win Methods'!$C$4:$F$4992,4,FALSE) -> 0 | J8: =VLOOKUP(I8,'Win Methods'!$C$4:$F$4992,4,FALSE) -> 0 | L8: =VLOOKUP(K8,'Win Methods'!$C$4:$F$4992,4,FALSE) -> 0 | N8: =VLOOKUP(M8,'Win Methods'!$C$4:$F$4992,4,FALSE) -> 0 | P8: =VLOOKUP(O8,'Win Methods'!$C$4:$F$4992,4,FALSE) -> 0 | R8: =VLOOKUP(Q8,'Win Methods'!$C$4:$F$4992,4,FALSE) -> 0 | T8: =VLOOKUP(S8,'Win Methods'!$C$4:$F$4992,4,FALSE) -> 0 | V8: =VLOOKUP(U8,'Win Methods'!$C$4:$F$4992,4,FALSE) -> 0 | X8: =VLOOKUP(W8,'Win Methods'!$C$4:$F$4992,4,FALSE) -> 0 | Y8: =E8&"|"&G8&"|"&I8&"|"&K8&"|"&M8&"|"&O8&"|"&Q8&"|"&S8&"|"&U8&"|"&W8 &" x "&D8 -> main-4||||||||| x 1
B9: 6 | C9: =(F9+H9+J9+L9+N9+P9+R9+T9+V9+X9)*D9 -> 2 | D9: 1 | E9: main-5 | F9: =VLOOKUP(E9,'Win Methods'!$C$4:$F$4992,4,FALSE) -> 2 | H9: =VLOOKUP(G9,'Win Methods'!$C$4:$F$4992,4,FALSE) -> 0 | J9: =VLOOKUP(I9,'Win Methods'!$C$4:$F$4992,4,FALSE) -> 0 | L9: =VLOOKUP(K9,'Win Methods'!$C$4:$F$4992,4,FALSE) -> 0 | N9: =VLOOKUP(M9,'Win Methods'!$C$4:$F$4992,4,FALSE) -> 0 | P9: =VLOOKUP(O9,'Win Methods'!$C$4:$F$4992,4,FALSE) -> 0 | R9: =VLOOKUP(Q9,'Win Methods'!$C$4:$F$4992,4,FALSE) -> 0 | T9: =VLOOKUP(S9,'Win Methods'!$C$4:$F$4992,4,FALSE) -> 0 | V9: =VLOOKUP(U9,'Win Methods'!$C$4:$F$4992,4,FALSE) -> 0 | X9: =VLOOKUP(W9,'Win Methods'!$C$4:$F$4992,4,FALSE) -> 0 | Y9: =E9&"|"&G9&"|"&I9&"|"&K9&"|"&M9&"|"&O9&"|"&Q9&"|"&S9&"|"&U9&"|"&W9 &" x "&D9 -> main-5||||||||| x 1
B10: 7 | C10: =(F10+H10+J10+L10+N10+P10+R10+T10+V10+X10)*D10 -> 2.5 | D10: 1 | E10: main-6 | F10: =VLOOKUP(E10,'Win Methods'!$C$4:$F$4992,4,FALSE) -> 2.5 | H10: =VLOOKUP(G10,'Win Methods'!$C$4:$F$4992,4,FALSE) -> 0 | J10: =VLOOKUP(I10,'Win Methods'!$C$4:$F$4992,4,FALSE) -> 0 | L10: =VLOOKUP(K10,'Win Methods'!$C$4:$F$4992,4,FALSE) -> 0 | N10: =VLOOKUP(M10,'Win Methods'!$C$4:$F$4992,4,FALSE) -> 0 | P10: =VLOOKUP(O10,'Win Methods'!$C$4:$F$4992,4,FALSE) -> 0 | R10: =VLOOKUP(Q10,'Win Methods'!$C$4:$F$4992,4,FALSE) -> 0 | T10: =VLOOKUP(S10,'Win Methods'!$C$4:$F$4992,4,FALSE) -> 0 | V10: =VLOOKUP(U10,'Win Methods'!$C$4:$F$4992,4,FALSE) -> 0 | X10: =VLOOKUP(W10,'Win Methods'!$C$4:$F$4992,4,FALSE) -> 0 | Y10: =E10&"|"&G10&"|"&I10&"|"&K10&"|"&M10&"|"&O10&"|"&Q10&"|"&S10&"|"&U10&"|"&W10 &" x "&D10 -> main-6||||||||| x 1
B11: 8 | C11: =(F11+H11+J11+L11+N11+P11+R11+T11+V11+X11)*D11 -> 3 | D11: 1 | E11: main-7 | F11: =VLOOKUP(E11,'Win Methods'!$C$4:$F$4992,4,FALSE) -> 3 | H11: =VLOOKUP(G11,'Win Methods'!$C$4:$F$4992,4,FALSE) -> 0 | J11: =VLOOKUP(I11,'Win Methods'!$C$4:$F$4992,4,FALSE) -> 0 | L11: =VLOOKUP(K11,'Win Methods'!$C$4:$F$4992,4,FALSE) -> 0 | N11: =VLOOKUP(M11,'Win Methods'!$C$4:$F$4992,4,FALSE) -> 0 | P11: =VLOOKUP(O11,'Win Methods'!$C$4:$F$4992,4,FALSE) -> 0 | R11: =VLOOKUP(Q11,'Win Methods'!$C$4:$F$4992,4,FALSE) -> 0 | T11: =VLOOKUP(S11,'Win Methods'!$C$4:$F$4992,4,FALSE) -> 0 | V11: =VLOOKUP(U11,'Win Methods'!$C$4:$F$4992,4,FALSE) -> 0 | X11: =VLOOKUP(W11,'Win Methods'!$C$4:$F$4992,4,FALSE) -> 0 | Y11: =E11&"|"&G11&"|"&I11&"|"&K11&"|"&M11&"|"&O11&"|"&Q11&"|"&S11&"|"&U11&"|"&W11 &" x "&D11 -> main-7||||||||| x 1
B12: 9 | C12: =(F12+H12+J12+L12+N12+P12+R12+T12+V12+X12)*D12 -> 5 | D12: 1 | E12: main-8 | F12: =VLOOKUP(E12,'Win Methods'!$C$4:$F$4992,4,FALSE) -> 5 | H12: =VLOOKUP(G12,'Win Methods'!$C$4:$F$4992,4,FALSE) -> 0 | J12: =VLOOKUP(I12,'Win Methods'!$C$4:$F$4992,4,FALSE) -> 0 | L12: =VLOOKUP(K12,'Win Methods'!$C$4:$F$4992,4,FALSE) -> 0 | N12: =VLOOKUP(M12,'Win Methods'!$C$4:$F$4992,4,FALSE) -> 0 | P12: =VLOOKUP(O12,'Win Methods'!$C$4:$F$4992,4,FALSE) -> 0 | R12: =VLOOKUP(Q12,'Win Methods'!$C$4:$F$4992,4,FALSE) -> 0 | T12: =VLOOKUP(S12,'Win Methods'!$C$4:$F$4992,4,FALSE) -> 0 | V12: =VLOOKUP(U12,'Win Methods'!$C$4:$F$4992,4,FALSE) -> 0 | X12: =VLOOKUP(W12,'Win Methods'!$C$4:$F$4992,4,FALSE) -> 0 | Y12: =E12&"|"&G12&"|"&I12&"|"&K12&"|"&M12&"|"&O12&"|"&Q12&"|"&S12&"|"&U12&"|"&W12 &" x "&D12 -> main-8||||||||| x 1
B13: 10 | C13: =(F13+H13+J13+L13+N13+P13+R13+T13+V13+X13)*D13 -> 10 | D13: 1 | E13: main-9 | F13: =VLOOKUP(E13,'Win Methods'!$C$4:$F$4992,4,FALSE) -> 10 | H13: =VLOOKUP(G13,'Win Methods'!$C$4:$F$4992,4,FALSE) -> 0 | J13: =VLOOKUP(I13,'Win Methods'!$C$4:$F$4992,4,FALSE) -> 0 | L13: =VLOOKUP(K13,'Win Methods'!$C$4:$F$4992,4,FALSE) -> 0 | N13: =VLOOKUP(M13,'Win Methods'!$C$4:$F$4992,4,FALSE) -> 0 | P13: =VLOOKUP(O13,'Win Methods'!$C$4:$F$4992,4,FALSE) -> 0 | R13: =VLOOKUP(Q13,'Win Methods'!$C$4:$F$4992,4,FALSE) -> 0 | T13: =VLOOKUP(S13,'Win Methods'!$C$4:$F$4992,4,FALSE) -> 0 | V13: =VLOOKUP(U13,'Win Methods'!$C$4:$F$4992,4,FALSE) -> 0 | X13: =VLOOKUP(W13,'Win Methods'!$C$4:$F$4992,4,FALSE) -> 0 | Y13: =E13&"|"&G13&"|"&I13&"|"&K13&"|"&M13&"|"&O13&"|"&Q13&"|"&S13&"|"&U13&"|"&W13 &" x "&D13 -> main-9||||||||| x 1
B14: 11 | C14: =(F14+H14+J14+L14+N14+P14+R14+T14+V14+X14)*D14 -> 1 | D14: 1 | E14: main-10 | F14: =VLOOKUP(E14,'Win Methods'!$C$4:$F$4992,4,FALSE) -> 1 | H14: =VLOOKUP(G14,'Win Methods'!$C$4:$F$4992,4,FALSE) -> 0 | J14: =VLOOKUP(I14,'Win Methods'!$C$4:$F$4992,4,FALSE) -> 0 | L14: =VLOOKUP(K14,'Win Methods'!$C$4:$F$4992,4,FALSE) -> 0 | N14: =VLOOKUP(M14,'Win Methods'!$C$4:$F$4992,4,FALSE) -> 0 | P14: =VLOOKUP(O14,'Win Methods'!$C$4:$F$4992,4,FALSE) -> 0 | R14: =VLOOKUP(Q14,'Win Methods'!$C$4:$F$4992,4,FALSE) -> 0 | T14: =VLOOKUP(S14,'Win Methods'!$C$4:$F$4992,4,FALSE) -> 0 | V14: =VLOOKUP(U14,'Win Methods'!$C$4:$F$4992,4,FALSE) -> 0 | X14: =VLOOKUP(W14,'Win Methods'!$C$4:$F$4992,4,FALSE) -> 0 | Y14: =E14&"|"&G14&"|"&I14&"|"&K14&"|"&M14&"|"&O14&"|"&Q14&"|"&S14&"|"&U14&"|"&W14 &" x "&D14 -> main-10||||||||| x 1
B15: 12 | C15: =(F15+H15+J15+L15+N15+P15+R15+T15+V15+X15)*D15 -> 1.5 | D15: 1 | E15: main-11 | F15: =VLOOKUP(E15,'Win Methods'!$C$4:$F$4992,4,FALSE) -> 1.5 | H15: =VLOOKUP(G15,'Win Methods'!$C$4:$F$4992,4,FALSE) -> 0 | J15: =VLOOKUP(I15,'Win Methods'!$C$4:$F$4992,4,FALSE) -> 0 | L15: =VLOOKUP(K15,'Win Methods'!$C$4:$F$4992,4,FALSE) -> 0 | N15: =VLOOKUP(M15,'Win Methods'!$C$4:$F$4992,4,FALSE) -> 0 | P15: =VLOOKUP(O15,'Win Methods'!$C$4:$F$4992,4,FALSE) -> 0 | R15: =VLOOKUP(Q15,'Win Methods'!$C$4:$F$4992,4,FALSE) -> 0 | T15: =VLOOKUP(S15,'Win Methods'!$C$4:$F$4992,4,FALSE) -> 0 | V15: =VLOOKUP(U15,'Win Methods'!$C$4:$F$4992,4,FALSE) -> 0 | X15: =VLOOKUP(W15,'Win Methods'!$C$4:$F$4992,4,FALSE) -> 0 | Y15: =E15&"|"&G15&"|"&I15&"|"&K15&"|"&M15&"|"&O15&"|"&Q15&"|"&S15&"|"&U15&"|"&W15 &" x "&D15 -> main-11||||||||| x 1
... B46: 43 | C46: =(F46+H46+J46+L46+N46+P46+R46+T46+V46+X46)*D46 -> 30 | D46: 1 | E46: main-42 | F46: =VLOOKUP(E46,'Win Methods'!$C$4:$F$4992,4,FALSE) -> 30 | H46: =VLOOKUP(G46,'Win Methods'!$C$4:$F$4992,4,FALSE) -> 0 | J46: =VLOOKUP(I46,'Win Methods'!$C$4:$F$4992,4,FALSE) -> 0 | L46: =VLOOKUP(K46,'Win Methods'!$C$4:$F$4992,4,FALSE) -> 0 | N46: =VLOOKUP(M46,'Win Methods'!$C$4:$F$4992,4,FALSE) -> 0 | P46: =VLOOKUP(O46,'Win Methods'!$C$4:$F$4992,4,FALSE) -> 0 | R46: =VLOOKUP(Q46,'Win Methods'!$C$4:$F$4992,4,FALSE) -> 0 | T46: =VLOOKUP(S46,'Win Methods'!$C$4:$F$4992,4,FALSE) -> 0 | V46: =VLOOKUP(U46,'Win Methods'!$C$4:$F$4992,4,FALSE) -> 0 | X46: =VLOOKUP(W46,'Win Methods'!$C$4:$F$4992,4,FALSE) -> 0 | Y46: =E46&"|"&G46&"|"&I46&"|"&K46&"|"&M46&"|"&O46&"|"&Q46&"|"&S46&"|"&U46&"|"&W46 &" x "&D46 -> main-42||||||||| x 1
B47: 44 | C47: =(F47+H47+J47+L47+N47+P47+R47+T47+V47+X47)*D47 -> 0.2 | D47: 1 | E47: main-0 | F47: =VLOOKUP(E47,'Win Methods'!$C$4:$F$4992,4,FALSE) -> 0.1 | G47: main-0 | H47: =VLOOKUP(G47,'Win Methods'!$C$4:$F$4992,4,FALSE) -> 0.1 | J47: =VLOOKUP(I47,'Win Methods'!$C$4:$F$4992,4,FALSE) -> 0 | L47: =VLOOKUP(K47,'Win Methods'!$C$4:$F$4992,4,FALSE) -> 0 | N47: =VLOOKUP(M47,'Win Methods'!$C$4:$F$4992,4,FALSE) -> 0 | P47: =VLOOKUP(O47,'Win Methods'!$C$4:$F$4992,4,FALSE) -> 0 | R47: =VLOOKUP(Q47,'Win Methods'!$C$4:$F$4992,4,FALSE) -> 0 | T47: =VLOOKUP(S47,'Win Methods'!$C$4:$F$4992,4,FALSE) -> 0 | V47: =VLOOKUP(U47,'Win Methods'!$C$4:$F$4992,4,FALSE) -> 0 | X47: =VLOOKUP(W47,'Win Methods'!$C$4:$F$4992,4,FALSE) -> 0 | Y47: =E47&"|"&G47&"|"&I47&"|"&K47&"|"&M47&"|"&O47&"|"&Q47&"|"&S47&"|"&U47&"|"&W47 &" x "&D47 -> main-0|main-0|||||||| x 1
B48: 45 | C48: =(F48+H48+J48+L48+N48+P48+R48+T48+V48+X48)*D48 -> 0.3 | D48: 1 | E48: main-0 | F48: =VLOOKUP(E48,'Win Methods'!$C$4:$F$4992,4,FALSE) -> 0.1 | G48: main-1 | H48: =VLOOKUP(G48,'Win Methods'!$C$4:$F$4992,4,FALSE) -> 0.2 | J48: =VLOOKUP(I48,'Win Methods'!$C$4:$F$4992,4,FALSE) -> 0 | L48: =VLOOKUP(K48,'Win Methods'!$C$4:$F$4992,4,FALSE) -> 0 | N48: =VLOOKUP(M48,'Win Methods'!$C$4:$F$4992,4,FALSE) -> 0 | P48: =VLOOKUP(O48,'Win Methods'!$C$4:$F$4992,4,FALSE) -> 0 | R48: =VLOOKUP(Q48,'Win Methods'!$C$4:$F$4992,4,FALSE) -> 0 | T48: =VLOOKUP(S48,'Win Methods'!$C$4:$F$4992,4,FALSE) -> 0 | V48: =VLOOKUP(U48,'Win Methods'!$C$4:$F$4992,4,FALSE) -> 0 | X48: =VLOOKUP(W48,'Win Methods'!$C$4:$F$4992,4,FALSE) -> 0 | Y48: =E48&"|"&G48&"|"&I48&"|"&K48&"|"&M48&"|"&O48&"|"&Q48&"|"&S48&"|"&U48&"|"&W48 &" x "&D48 -> main-0|main-1|||||||| x 1
B49: 46 | C49: =(F49+H49+J49+L49+N49+P49+R49+T49+V49+X49)*D49 -> 0.4 | D49: 1 | E49: main-1 | F49: =VLOOKUP(E49,'Win Methods'!$C$4:$F$4992,4,FALSE) -> 0.2 | G49: main-1 | H49: =VLOOKUP(G49,'Win Methods'!$C$4:$F$4992,4,FALSE) -> 0.2 | J49: =VLOOKUP(I49,'Win Methods'!$C$4:$F$4992,4,FALSE) -> 0 | L49: =VLOOKUP(K49,'Win Methods'!$C$4:$F$4992,4,FALSE) -> 0 | N49: =VLOOKUP(M49,'Win Methods'!$C$4:$F$4992,4,FALSE) -> 0 | P49: =VLOOKUP(O49,'Win Methods'!$C$4:$F$4992,4,FALSE) -> 0 | R49: =VLOOKUP(Q49,'Win Methods'!$C$4:$F$4992,4,FALSE) -> 0 | T49: =VLOOKUP(S49,'Win Methods'!$C$4:$F$4992,4,FALSE) -> 0 | V49: =VLOOKUP(U49,'Win Methods'!$C$4:$F$4992,4,FALSE) -> 0 | X49: =VLOOKUP(W49,'Win Methods'!$C$4:$F$4992,4,FALSE) -> 0 | Y49: =E49&"|"&G49&"|"&I49&"|"&K49&"|"&M49&"|"&O49&"|"&Q49&"|"&S49&"|"&U49&"|"&W49 &" x "&D49 -> main-1|main-1|||||||| x 1
B50: 47 | C50: =(F50+H50+J50+L50+N50+P50+R50+T50+V50+X50)*D50 -> 0.6 | D50: 1 | E50: main-0 | F50: =VLOOKUP(E50,'Win Methods'!$C$4:$F$4992,4,FALSE) -> 0.1 | G50: main-2 | H50: =VLOOKUP(G50,'Win Methods'!$C$4:$F$4992,4,FALSE) -> 0.5 | J50: =VLOOKUP(I50,'Win Methods'!$C$4:$F$4992,4,FALSE) -> 0 | L50: =VLOOKUP(K50,'Win Methods'!$C$4:$F$4992,4,FALSE) -> 0 | N50: =VLOOKUP(M50,'Win Methods'!$C$4:$F$4992,4,FALSE) -> 0 | P50: =VLOOKUP(O50,'Win Methods'!$C$4:$F$4992,4,FALSE) -> 0 | R50: =VLOOKUP(Q50,'Win Methods'!$C$4:$F$4992,4,FALSE) -> 0 | T50: =VLOOKUP(S50,'Win Methods'!$C$4:$F$4992,4,FALSE) -> 0 | V50: =VLOOKUP(U50,'Win Methods'!$C$4:$F$4992,4,FALSE) -> 0 | X50: =VLOOKUP(W50,'Win Methods'!$C$4:$F$4992,4,FALSE) -> 0 | Y50: =E50&"|"&G50&"|"&I50&"|"&K50&"|"&M50&"|"&O50&"|"&Q50&"|"&S50&"|"&U50&"|"&W50 &" x "&D50 -> main-0|main-2|||||||| x 1
B51: 48 | C51: =(F51+H51+J51+L51+N51+P51+R51+T51+V51+X51)*D51 -> 2 | D51: 1 | E51: main-11 | F51: =VLOOKUP(E51,'Win Methods'!$C$4:$F$4992,4,FALSE) -> 1.5 | G51: main-2 | H51: =VLOOKUP(G51,'Win Methods'!$C$4:$F$4992,4,FALSE) -> 0.5 | J51: =VLOOKUP(I51,'Win Methods'!$C$4:$F$4992,4,FALSE) -> 0 | L51: =VLOOKUP(K51,'Win Methods'!$C$4:$F$4992,4,FALSE) -> 0 | N51: =VLOOKUP(M51,'Win Methods'!$C$4:$F$4992,4,FALSE) -> 0 | P51: =VLOOKUP(O51,'Win Methods'!$C$4:$F$4992,4,FALSE) -> 0 | R51: =VLOOKUP(Q51,'Win Methods'!$C$4:$F$4992,4,FALSE) -> 0 | T51: =VLOOKUP(S51,'Win Methods'!$C$4:$F$4992,4,FALSE) -> 0 | V51: =VLOOKUP(U51,'Win Methods'!$C$4:$F$4992,4,FALSE) -> 0 | X51: =VLOOKUP(W51,'Win Methods'!$C$4:$F$4992,4,FALSE) -> 0 | Y51: =E51&"|"&G51&"|"&I51&"|"&K51&"|"&M51&"|"&O51&"|"&Q51&"|"&S51&"|"&U51&"|"&W51 &" x "&D51 -> main-11|main-2|||||||| x 1
B52: 49 | C52: =(F52+H52+J52+L52+N52+P52+R52+T52+V52+X52)*D52 -> 1.5 | D52: 1 | E52: main-3 | F52: =VLOOKUP(E52,'Win Methods'!$C$4:$F$4992,4,FALSE) -> 1 | G52: main-2 | H52: =VLOOKUP(G52,'Win Methods'!$C$4:$F$4992,4,FALSE) -> 0.5 | J52: =VLOOKUP(I52,'Win Methods'!$C$4:$F$4992,4,FALSE) -> 0 | L52: =VLOOKUP(K52,'Win Methods'!$C$4:$F$4992,4,FALSE) -> 0 | N52: =VLOOKUP(M52,'Win Methods'!$C$4:$F$4992,4,FALSE) -> 0 | P52: =VLOOKUP(O52,'Win Methods'!$C$4:$F$4992,4,FALSE) -> 0 | R52: =VLOOKUP(Q52,'Win Methods'!$C$4:$F$4992,4,FALSE) -> 0 | T52: =VLOOKUP(S52,'Win Methods'!$C$4:$F$4992,4,FALSE) -> 0 | V52: =VLOOKUP(U52,'Win Methods'!$C$4:$F$4992,4,FALSE) -> 0 | X52: =VLOOKUP(W52,'Win Methods'!$C$4:$F$4992,4,FALSE) -> 0 | Y52: =E52&"|"&G52&"|"&I52&"|"&K52&"|"&M52&"|"&O52&"|"&Q52&"|"&S52&"|"&U52&"|"&W52 &" x "&D52 -> main-3|main-2|||||||| x 1
B53: 50 | C53: =(F53+H53+J53+L53+N53+P53+R53+T53+V53+X53)*D53 -> 3 | D53: 1 | E53: main-3 | F53: =VLOOKUP(E53,'Win Methods'!$C$4:$F$4992,4,FALSE) -> 1 | G53: main-21 | H53: =VLOOKUP(G53,'Win Methods'!$C$4:$F$4992,4,FALSE) -> 2 | J53: =VLOOKUP(I53,'Win Methods'!$C$4:$F$4992,4,FALSE) -> 0 | L53: =VLOOKUP(K53,'Win Methods'!$C$4:$F$4992,4,FALSE) -> 0 | N53: =VLOOKUP(M53,'Win Methods'!$C$4:$F$4992,4,FALSE) -> 0 | P53: =VLOOKUP(O53,'Win Methods'!$C$4:$F$4992,4,FALSE) -> 0 | R53: =VLOOKUP(Q53,'Win Methods'!$C$4:$F$4992,4,FALSE) -> 0 | T53: =VLOOKUP(S53,'Win Methods'!$C$4:$F$4992,4,FALSE) -> 0 | V53: =VLOOKUP(U53,'Win Methods'!$C$4:$F$4992,4,FALSE) -> 0 | X53: =VLOOKUP(W53,'Win Methods'!$C$4:$F$4992,4,FALSE) -> 0 | Y53: =E53&"|"&G53&"|"&I53&"|"&K53&"|"&M53&"|"&O53&"|"&Q53&"|"&S53&"|"&U53&"|"&W53 &" x "&D53 -> main-3|main-21|||||||| x 1
B54: 51 | C54: =(F54+H54+J54+L54+N54+P54+R54+T54+V54+X54)*D54 -> 2.5 | D54: 1 | E54: main-2 | F54: =VLOOKUP(E54,'Win Methods'!$C$4:$F$4992,4,FALSE) -> 0.5 | G54: main-5 | H54: =VLOOKUP(G54,'Win Methods'!$C$4:$F$4992,4,FALSE) -> 2 | J54: =VLOOKUP(I54,'Win Methods'!$C$4:$F$4992,4,FALSE) -> 0 | L54: =VLOOKUP(K54,'Win Methods'!$C$4:$F$4992,4,FALSE) -> 0 | N54: =VLOOKUP(M54,'Win Methods'!$C$4:$F$4992,4,FALSE) -> 0 | P54: =VLOOKUP(O54,'Win Methods'!$C$4:$F$4992,4,FALSE) -> 0 | R54: =VLOOKUP(Q54,'Win Methods'!$C$4:$F$4992,4,FALSE) -> 0 | T54: =VLOOKUP(S54,'Win Methods'!$C$4:$F$4992,4,FALSE) -> 0 | V54: =VLOOKUP(U54,'Win Methods'!$C$4:$F$4992,4,FALSE) -> 0 | X54: =VLOOKUP(W54,'Win Methods'!$C$4:$F$4992,4,FALSE) -> 0 | Y54: =E54&"|"&G54&"|"&I54&"|"&K54&"|"&M54&"|"&O54&"|"&Q54&"|"&S54&"|"&U54&"|"&W54 &" x "&D54 -> main-2|main-5|||||||| x 1
B55: 52 | C55: =(F55+H55+J55+L55+N55+P55+R55+T55+V55+X55)*D55 -> 6.5 | D55: 1 | E55: main-4 | F55: =VLOOKUP(E55,'Win Methods'!$C$4:$F$4992,4,FALSE) -> 1.5 | G55: main-22 | H55: =VLOOKUP(G55,'Win Methods'!$C$4:$F$4992,4,FALSE) -> 5 | J55: =VLOOKUP(I55,'Win Methods'!$C$4:$F$4992,4,FALSE) -> 0 | L55: =VLOOKUP(K55,'Win Methods'!$C$4:$F$4992,4,FALSE) -> 0 | N55: =VLOOKUP(M55,'Win Methods'!$C$4:$F$4992,4,FALSE) -> 0 | P55: =VLOOKUP(O55,'Win Methods'!$C$4:$F$4992,4,FALSE) -> 0 | R55: =VLOOKUP(Q55,'Win Methods'!$C$4:$F$4992,4,FALSE) -> 0 | T55: =VLOOKUP(S55,'Win Methods'!$C$4:$F$4992,4,FALSE) -> 0 | V55: =VLOOKUP(U55,'Win Methods'!$C$4:$F$4992,4,FALSE) -> 0 | X55: =VLOOKUP(W55,'Win Methods'!$C$4:$F$4992,4,FALSE) -> 0 | Y55: =E55&"|"&G55&"|"&I55&"|"&K55&"|"&M55&"|"&O55&"|"&Q55&"|"&S55&"|"&U55&"|"&W55 &" x "&D55 -> main-4|main-22|||||||| x 1
B56: 53 | C56: =(F56+H56+J56+L56+N56+P56+R56+T56+V56+X56)*D56 -> 3 | D56: 1 | E56: main-4 | F56: =VLOOKUP(E56,'Win Methods'!$C$4:$F$4992,4,FALSE) -> 1.5 | G56: main-4 | H56: =VLOOKUP(G56,'Win Methods'!$C$4:$F$4992,4,FALSE) -> 1.5 | J56: =VLOOKUP(I56,'Win Methods'!$C$4:$F$4992,4,FALSE) -> 0 | L56: =VLOOKUP(K56,'Win Methods'!$C$4:$F$4992,4,FALSE) -> 0 | N56: =VLOOKUP(M56,'Win Methods'!$C$4:$F$4992,4,FALSE) -> 0 | P56: =VLOOKUP(O56,'Win Methods'!$C$4:$F$4992,4,FALSE) -> 0 | R56: =VLOOKUP(Q56,'Win Methods'!$C$4:$F$4992,4,FALSE) -> 0 | T56: =VLOOKUP(S56,'Win Methods'!$C$4:$F$4992,4,FALSE) -> 0 | V56: =VLOOKUP(U56,'Win Methods'!$C$4:$F$4992,4,FALSE) -> 0 | X56: =VLOOKUP(W56,'Win Methods'!$C$4:$F$4992,4,FALSE) -> 0 | Y56: =E56&"|"&G56&"|"&I56&"|"&K56&"|"&M56&"|"&O56&"|"&Q56&"|"&S56&"|"&U56&"|"&W56 &" x "&D56 -> main-4|main-4|||||||| x 1
B57: 54 | C57: =(F57+H57+J57+L57+N57+P57+R57+T57+V57+X57)*D57 -> 16 | D57: 1 | E57: main-3 | F57: =VLOOKUP(E57,'Win Methods'!$C$4:$F$4992,4,FALSE) -> 1 | G57: main-15 | H57: =VLOOKUP(G57,'Win Methods'!$C$4:$F$4992,4,FALSE) -> 15 | J57: =VLOOKUP(I57,'Win Methods'!$C$4:$F$4992,4,FALSE) -> 0 | L57: =VLOOKUP(K57,'Win Methods'!$C$4:$F$4992,4,FALSE) -> 0 | N57: =VLOOKUP(M57,'Win Methods'!$C$4:$F$4992,4,FALSE) -> 0 | P57: =VLOOKUP(O57,'Win Methods'!$C$4:$F$4992,4,FALSE) -> 0 | R57: =VLOOKUP(Q57,'Win Methods'!$C$4:$F$4992,4,FALSE) -> 0 | T57: =VLOOKUP(S57,'Win Methods'!$C$4:$F$4992,4,FALSE) -> 0 | V57: =VLOOKUP(U57,'Win Methods'!$C$4:$F$4992,4,FALSE) -> 0 | X57: =VLOOKUP(W57,'Win Methods'!$C$4:$F$4992,4,FALSE) -> 0 | Y57: =E57&"|"&G57&"|"&I57&"|"&K57&"|"&M57&"|"&O57&"|"&Q57&"|"&S57&"|"&U57&"|"&W57 &" x "&D57 -> main-3|main-15|||||||| x 1
B58: 55 | C58: =(F58+H58+J58+L58+N58+P58+R58+T58+V58+X58)*D58 -> 17 | D58: 1 | E58: main-5 | F58: =VLOOKUP(E58,'Win Methods'!$C$4:$F$4992,4,FALSE) -> 2 | G58: main-15 | H58: =VLOOKUP(G58,'Win Methods'!$C$4:$F$4992,4,FALSE) -> 15 | J58: =VLOOKUP(I58,'Win Methods'!$C$4:$F$4992,4,FALSE) -> 0 | L58: =VLOOKUP(K58,'Win Methods'!$C$4:$F$4992,4,FALSE) -> 0 | N58: =VLOOKUP(M58,'Win Methods'!$C$4:$F$4992,4,FALSE) -> 0 | P58: =VLOOKUP(O58,'Win Methods'!$C$4:$F$4992,4,FALSE) -> 0 | R58: =VLOOKUP(Q58,'Win Methods'!$C$4:$F$4992,4,FALSE) -> 0 | T58: =VLOOKUP(S58,'Win Methods'!$C$4:$F$4992,4,FALSE) -> 0 | V58: =VLOOKUP(U58,'Win Methods'!$C$4:$F$4992,4,FALSE) -> 0 | X58: =VLOOKUP(W58,'Win Methods'!$C$4:$F$4992,4,FALSE) -> 0 | Y58: =E58&"|"&G58&"|"&I58&"|"&K58&"|"&M58&"|"&O58&"|"&Q58&"|"&S58&"|"&U58&"|"&W58 &" x "&D58 -> main-5|main-15|||||||| x 1
... B61: 58 | C61: =(F61+H61+J61+L61+N61+P61+R61+T61+V61+X61)*D61 -> 10.5 | D61: 1 | E61: main-14 | F61: =VLOOKUP(E61,'Win Methods'!$C$4:$F$4992,4,FALSE) -> 10 | G61: main-2 | H61: =VLOOKUP(G61,'Win Methods'!$C$4:$F$4992,4,FALSE) -> 0.5 | J61: =VLOOKUP(I61,'Win Methods'!$C$4:$F$4992,4,FALSE) -> 0 | L61: =VLOOKUP(K61,'Win Methods'!$C$4:$F$4992,4,FALSE) -> 0 | N61: =VLOOKUP(M61,'Win Methods'!$C$4:$F$4992,4,FALSE) -> 0 | P61: =VLOOKUP(O61,'Win Methods'!$C$4:$F$4992,4,FALSE) -> 0 | R61: =VLOOKUP(Q61,'Win Methods'!$C$4:$F$4992,4,FALSE) -> 0 | T61: =VLOOKUP(S61,'Win Methods'!$C$4:$F$4992,4,FALSE) -> 0 | V61: =VLOOKUP(U61,'Win Methods'!$C$4:$F$4992,4,FALSE) -> 0 | X61: =VLOOKUP(W61,'Win Methods'!$C$4:$F$4992,4,FALSE) -> 0 | Y61: =E61&"|"&G61&"|"&I61&"|"&K61&"|"&M61&"|"&O61&"|"&Q61&"|"&S61&"|"&U61&"|"&W61 &" x "&D61 -> main-14|main-2|||||||| x 1
B62: 59 | C62: =(F62+H62+J62+L62+N62+P62+R62+T62+V62+X62)*D62 -> 4 | D62: 1 | E62: main-3 | F62: =VLOOKUP(E62,'Win Methods'!$C$4:$F$4992,4,FALSE) -> 1 | G62: main-20 | H62: =VLOOKUP(G62,'Win Methods'!$C$4:$F$4992,4,FALSE) -> 1.5 | I62: main-4 | J62: =VLOOKUP(I62,'Win Methods'!$C$4:$F$4992,4,FALSE) -> 1.5 | L62: =VLOOKUP(K62,'Win Methods'!$C$4:$F$4992,4,FALSE) -> 0 | N62: =VLOOKUP(M62,'Win Methods'!$C$4:$F$4992,4,FALSE) -> 0 | P62: =VLOOKUP(O62,'Win Methods'!$C$4:$F$4992,4,FALSE) -> 0 | R62: =VLOOKUP(Q62,'Win Methods'!$C$4:$F$4992,4,FALSE) -> 0 | T62: =VLOOKUP(S62,'Win Methods'!$C$4:$F$4992,4,FALSE) -> 0 | V62: =VLOOKUP(U62,'Win Methods'!$C$4:$F$4992,4,FALSE) -> 0 | X62: =VLOOKUP(W62,'Win Methods'!$C$4:$F$4992,4,FALSE) -> 0 | Y62: =E62&"|"&G62&"|"&I62&"|"&K62&"|"&M62&"|"&O62&"|"&Q62&"|"&S62&"|"&U62&"|"&W62 &" x "&D62 -> main-3|main-20|main-4||||||| x 1
B63: 60 | C63: =(F63+H63+J63+L63+N63+P63+R63+T63+V63+X63)*D63 -> 8.5 | D63: 1 | E63: main-4 | F63: =VLOOKUP(E63,'Win Methods'!$C$4:$F$4992,4,FALSE) -> 1.5 | G63: main-5 | H63: =VLOOKUP(G63,'Win Methods'!$C$4:$F$4992,4,FALSE) -> 2 | I63: main-13 | J63: =VLOOKUP(I63,'Win Methods'!$C$4:$F$4992,4,FALSE) -> 5 | L63: =VLOOKUP(K63,'Win Methods'!$C$4:$F$4992,4,FALSE) -> 0 | N63: =VLOOKUP(M63,'Win Methods'!$C$4:$F$4992,4,FALSE) -> 0 | P63: =VLOOKUP(O63,'Win Methods'!$C$4:$F$4992,4,FALSE) -> 0 | R63: =VLOOKUP(Q63,'Win Methods'!$C$4:$F$4992,4,FALSE) -> 0 | T63: =VLOOKUP(S63,'Win Methods'!$C$4:$F$4992,4,FALSE) -> 0 | V63: =VLOOKUP(U63,'Win Methods'!$C$4:$F$4992,4,FALSE) -> 0 | X63: =VLOOKUP(W63,'Win Methods'!$C$4:$F$4992,4,FALSE) -> 0 | Y63: =E63&"|"&G63&"|"&I63&"|"&K63&"|"&M63&"|"&O63&"|"&Q63&"|"&S63&"|"&U63&"|"&W63 &" x "&D63 -> main-4|main-5|main-13||||||| x 1
B64: 61 | C64: =(F64+H64+J64+L64+N64+P64+R64+T64+V64+X64)*D64 -> 17 | D64: 1 | E64: main-4 | F64: =VLOOKUP(E64,'Win Methods'!$C$4:$F$4992,4,FALSE) -> 1.5 | G64: main-2 | H64: =VLOOKUP(G64,'Win Methods'!$C$4:$F$4992,4,FALSE) -> 0.5 | I64: main-24 | J64: =VLOOKUP(I64,'Win Methods'!$C$4:$F$4992,4,FALSE) -> 15 | L64: =VLOOKUP(K64,'Win Methods'!$C$4:$F$4992,4,FALSE) -> 0 | N64: =VLOOKUP(M64,'Win Methods'!$C$4:$F$4992,4,FALSE) -> 0 | P64: =VLOOKUP(O64,'Win Methods'!$C$4:$F$4992,4,FALSE) -> 0 | R64: =VLOOKUP(Q64,'Win Methods'!$C$4:$F$4992,4,FALSE) -> 0 | T64: =VLOOKUP(S64,'Win Methods'!$C$4:$F$4992,4,FALSE) -> 0 | V64: =VLOOKUP(U64,'Win Methods'!$C$4:$F$4992,4,FALSE) -> 0 | X64: =VLOOKUP(W64,'Win Methods'!$C$4:$F$4992,4,FALSE) -> 0 | Y64: =E64&"|"&G64&"|"&I64&"|"&K64&"|"&M64&"|"&O64&"|"&Q64&"|"&S64&"|"&U64&"|"&W64 &" x "&D64 -> main-4|main-2|main-24||||||| x 1
B65: 62 | C65: =(F65+H65+J65+L65+N65+P65+R65+T65+V65+X65)*D65 -> 25 | D65: 1 | E65: main-15 | F65: =VLOOKUP(E65,'Win Methods'!$C$4:$F$4992,4,FALSE) -> 15 | G65: main-13 | H65: =VLOOKUP(G65,'Win Methods'!$C$4:$F$4992,4,FALSE) -> 5 | I65: main-13 | J65: =VLOOKUP(I65,'Win Methods'!$C$4:$F$4992,4,FALSE) -> 5 | L65: =VLOOKUP(K65,'Win Methods'!$C$4:$F$4992,4,FALSE) -> 0 | N65: =VLOOKUP(M65,'Win Methods'!$C$4:$F$4992,4,FALSE) -> 0 | P65: =VLOOKUP(O65,'Win Methods'!$C$4:$F$4992,4,FALSE) -> 0 | R65: =VLOOKUP(Q65,'Win Methods'!$C$4:$F$4992,4,FALSE) -> 0 | T65: =VLOOKUP(S65,'Win Methods'!$C$4:$F$4992,4,FALSE) -> 0 | V65: =VLOOKUP(U65,'Win Methods'!$C$4:$F$4992,4,FALSE) -> 0 | X65: =VLOOKUP(W65,'Win Methods'!$C$4:$F$4992,4,FALSE) -> 0 | Y65: =E65&"|"&G65&"|"&I65&"|"&K65&"|"&M65&"|"&O65&"|"&Q65&"|"&S65&"|"&U65&"|"&W65 &" x "&D65 -> main-15|main-13|main-13||||||| x 1
B66: 63 | C66: =(F66+H66+J66+L66+N66+P66+R66+T66+V66+X66)*D66 -> 27 | D66: 1 | E66: main-30 | F66: =VLOOKUP(E66,'Win Methods'!$C$4:$F$4992,4,FALSE) -> 2 | G66: main-14 | H66: =VLOOKUP(G66,'Win Methods'!$C$4:$F$4992,4,FALSE) -> 10 | I66: main-15 | J66: =VLOOKUP(I66,'Win Methods'!$C$4:$F$4992,4,FALSE) -> 15 | L66: =VLOOKUP(K66,'Win Methods'!$C$4:$F$4992,4,FALSE) -> 0 | N66: =VLOOKUP(M66,'Win Methods'!$C$4:$F$4992,4,FALSE) -> 0 | P66: =VLOOKUP(O66,'Win Methods'!$C$4:$F$4992,4,FALSE) -> 0 | R66: =VLOOKUP(Q66,'Win Methods'!$C$4:$F$4992,4,FALSE) -> 0 | T66: =VLOOKUP(S66,'Win Methods'!$C$4:$F$4992,4,FALSE) -> 0 | V66: =VLOOKUP(U66,'Win Methods'!$C$4:$F$4992,4,FALSE) -> 0 | X66: =VLOOKUP(W66,'Win Methods'!$C$4:$F$4992,4,FALSE) -> 0 | Y66: =E66&"|"&G66&"|"&I66&"|"&K66&"|"&M66&"|"&O66&"|"&Q66&"|"&S66&"|"&U66&"|"&W66 &" x "&D66 -> main-30|main-14|main-15||||||| x 1
B67: 64 | C67: =(F67+H67+J67+L67+N67+P67+R67+T67+V67+X67)*D67 -> 5 | D67: 1 | E67: main-2 | F67: =VLOOKUP(E67,'Win Methods'!$C$4:$F$4992,4,FALSE) -> 0.5 | G67: main-7 | H67: =VLOOKUP(G67,'Win Methods'!$C$4:$F$4992,4,FALSE) -> 3 | I67: main-4 | J67: =VLOOKUP(I67,'Win Methods'!$C$4:$F$4992,4,FALSE) -> 1.5 | L67: =VLOOKUP(K67,'Win Methods'!$C$4:$F$4992,4,FALSE) -> 0 | N67: =VLOOKUP(M67,'Win Methods'!$C$4:$F$4992,4,FALSE) -> 0 | P67: =VLOOKUP(O67,'Win Methods'!$C$4:$F$4992,4,FALSE) -> 0 | R67: =VLOOKUP(Q67,'Win Methods'!$C$4:$F$4992,4,FALSE) -> 0 | T67: =VLOOKUP(S67,'Win Methods'!$C$4:$F$4992,4,FALSE) -> 0 | V67: =VLOOKUP(U67,'Win Methods'!$C$4:$F$4992,4,FALSE) -> 0 | X67: =VLOOKUP(W67,'Win Methods'!$C$4:$F$4992,4,FALSE) -> 0 | Y67: =E67&"|"&G67&"|"&I67&"|"&K67&"|"&M67&"|"&O67&"|"&Q67&"|"&S67&"|"&U67&"|"&W67 &" x "&D67 -> main-2|main-7|main-4||||||| x 1
B68: 65 | C68: =(F68+H68+J68+L68+N68+P68+R68+T68+V68+X68)*D68 -> 26.5 | D68: 1 | E68: main-11 | F68: =VLOOKUP(E68,'Win Methods'!$C$4:$F$4992,4,FALSE) -> 1.5 | G68: main-25 | H68: =VLOOKUP(G68,'Win Methods'!$C$4:$F$4992,4,FALSE) -> 20 | I68: main-31 | J68: =VLOOKUP(I68,'Win Methods'!$C$4:$F$4992,4,FALSE) -> 5 | L68: =VLOOKUP(K68,'Win Methods'!$C$4:$F$4992,4,FALSE) -> 0 | N68: =VLOOKUP(M68,'Win Methods'!$C$4:$F$4992,4,FALSE) -> 0 | P68: =VLOOKUP(O68,'Win Methods'!$C$4:$F$4992,4,FALSE) -> 0 | R68: =VLOOKUP(Q68,'Win Methods'!$C$4:$F$4992,4,FALSE) -> 0 | T68: =VLOOKUP(S68,'Win Methods'!$C$4:$F$4992,4,FALSE) -> 0 | V68: =VLOOKUP(U68,'Win Methods'!$C$4:$F$4992,4,FALSE) -> 0 | X68: =VLOOKUP(W68,'Win Methods'!$C$4:$F$4992,4,FALSE) -> 0 | Y68: =E68&"|"&G68&"|"&I68&"|"&K68&"|"&M68&"|"&O68&"|"&Q68&"|"&S68&"|"&U68&"|"&W68 &" x "&D68 -> main-11|main-25|main-31||||||| x 1
B69: 66 | C69: =(F69+H69+J69+L69+N69+P69+R69+T69+V69+X69)*D69 -> 24 | D69: 1 | E69: main-5 | F69: =VLOOKUP(E69,'Win Methods'!$C$4:$F$4992,4,FALSE) -> 2 | G69: main-25 | H69: =VLOOKUP(G69,'Win Methods'!$C$4:$F$4992,4,FALSE) -> 20 | I69: main-12 | J69: =VLOOKUP(I69,'Win Methods'!$C$4:$F$4992,4,FALSE) -> 2 | L69: =VLOOKUP(K69,'Win Methods'!$C$4:$F$4992,4,FALSE) -> 0 | N69: =VLOOKUP(M69,'Win Methods'!$C$4:$F$4992,4,FALSE) -> 0 | P69: =VLOOKUP(O69,'Win Methods'!$C$4:$F$4992,4,FALSE) -> 0 | R69: =VLOOKUP(Q69,'Win Methods'!$C$4:$F$4992,4,FALSE) -> 0 | T69: =VLOOKUP(S69,'Win Methods'!$C$4:$F$4992,4,FALSE) -> 0 | V69: =VLOOKUP(U69,'Win Methods'!$C$4:$F$4992,4,FALSE) -> 0 | X69: =VLOOKUP(W69,'Win Methods'!$C$4:$F$4992,4,FALSE) -> 0 | Y69: =E69&"|"&G69&"|"&I69&"|"&K69&"|"&M69&"|"&O69&"|"&Q69&"|"&S69&"|"&U69&"|"&W69 &" x "&D69 -> main-5|main-25|main-12||||||| x 1
B70: 67 | C70: =(F70+H70+J70+L70+N70+P70+R70+T70+V70+X70)*D70 -> 36 | D70: 1 | E70: main-3 | F70: =VLOOKUP(E70,'Win Methods'!$C$4:$F$4992,4,FALSE) -> 1 | G70: main-33 | H70: =VLOOKUP(G70,'Win Methods'!$C$4:$F$4992,4,FALSE) -> 15 | I70: main-16 | J70: =VLOOKUP(I70,'Win Methods'!$C$4:$F$4992,4,FALSE) -> 20 | L70: =VLOOKUP(K70,'Win Methods'!$C$4:$F$4992,4,FALSE) -> 0 | N70: =VLOOKUP(M70,'Win Methods'!$C$4:$F$4992,4,FALSE) -> 0 | P70: =VLOOKUP(O70,'Win Methods'!$C$4:$F$4992,4,FALSE) -> 0 | R70: =VLOOKUP(Q70,'Win Methods'!$C$4:$F$4992,4,FALSE) -> 0 | T70: =VLOOKUP(S70,'Win Methods'!$C$4:$F$4992,4,FALSE) -> 0 | V70: =VLOOKUP(U70,'Win Methods'!$C$4:$F$4992,4,FALSE) -> 0 | X70: =VLOOKUP(W70,'Win Methods'!$C$4:$F$4992,4,FALSE) -> 0 | Y70: =E70&"|"&G70&"|"&I70&"|"&K70&"|"&M70&"|"&O70&"|"&Q70&"|"&S70&"|"&U70&"|"&W70 &" x "&D70 -> main-3|main-33|main-16||||||| x 1
B71: 68 | C71: =(F71+H71+J71+L71+N71+P71+R71+T71+V71+X71)*D71 -> 7.5 | D71: 1 | E71: main-30 | F71: =VLOOKUP(E71,'Win Methods'!$C$4:$F$4992,4,FALSE) -> 2 | G71: main-6 | H71: =VLOOKUP(G71,'Win Methods'!$C$4:$F$4992,4,FALSE) -> 2.5 | I71: main-7 | J71: =VLOOKUP(I71,'Win Methods'!$C$4:$F$4992,4,FALSE) -> 3 | L71: =VLOOKUP(K71,'Win Methods'!$C$4:$F$4992,4,FALSE) -> 0 | N71: =VLOOKUP(M71,'Win Methods'!$C$4:$F$4992,4,FALSE) -> 0 | P71: =VLOOKUP(O71,'Win Methods'!$C$4:$F$4992,4,FALSE) -> 0 | R71: =VLOOKUP(Q71,'Win Methods'!$C$4:$F$4992,4,FALSE) -> 0 | T71: =VLOOKUP(S71,'Win Methods'!$C$4:$F$4992,4,FALSE) -> 0 | V71: =VLOOKUP(U71,'Win Methods'!$C$4:$F$4992,4,FALSE) -> 0 | X71: =VLOOKUP(W71,'Win Methods'!$C$4:$F$4992,4,FALSE) -> 0 | Y71: =E71&"|"&G71&"|"&I71&"|"&K71&"|"&M71&"|"&O71&"|"&Q71&"|"&S71&"|"&U71&"|"&W71 &" x "&D71 -> main-30|main-6|main-7||||||| x 1
B72: 69 | C72: =(F72+H72+J72+L72+N72+P72+R72+T72+V72+X72)*D72 -> 25 | D72: 1 | E72: main-21 | F72: =VLOOKUP(E72,'Win Methods'!$C$4:$F$4992,4,FALSE) -> 2 | G72: main-25 | H72: =VLOOKUP(G72,'Win Methods'!$C$4:$F$4992,4,FALSE) -> 20 | I72: main-7 | J72: =VLOOKUP(I72,'Win Methods'!$C$4:$F$4992,4,FALSE) -> 3 | L72: =VLOOKUP(K72,'Win Methods'!$C$4:$F$4992,4,FALSE) -> 0 | N72: =VLOOKUP(M72,'Win Methods'!$C$4:$F$4992,4,FALSE) -> 0 | P72: =VLOOKUP(O72,'Win Methods'!$C$4:$F$4992,4,FALSE) -> 0 | R72: =VLOOKUP(Q72,'Win Methods'!$C$4:$F$4992,4,FALSE) -> 0 | T72: =VLOOKUP(S72,'Win Methods'!$C$4:$F$4992,4,FALSE) -> 0 | V72: =VLOOKUP(U72,'Win Methods'!$C$4:$F$4992,4,FALSE) -> 0 | X72: =VLOOKUP(W72,'Win Methods'!$C$4:$F$4992,4,FALSE) -> 0 | Y72: =E72&"|"&G72&"|"&I72&"|"&K72&"|"&M72&"|"&O72&"|"&Q72&"|"&S72&"|"&U72&"|"&W72 &" x "&D72 -> main-21|main-25|main-7||||||| x 1
B73: 70 | C73: =(F73+H73+J73+L73+N73+P73+R73+T73+V73+X73)*D73 -> 42 | D73: 1 | E73: main-5 | F73: =VLOOKUP(E73,'Win Methods'!$C$4:$F$4992,4,FALSE) -> 2 | G73: main-25 | H73: =VLOOKUP(G73,'Win Methods'!$C$4:$F$4992,4,FALSE) -> 20 | I73: main-25 | J73: =VLOOKUP(I73,'Win Methods'!$C$4:$F$4992,4,FALSE) -> 20 | L73: =VLOOKUP(K73,'Win Methods'!$C$4:$F$4992,4,FALSE) -> 0 | N73: =VLOOKUP(M73,'Win Methods'!$C$4:$F$4992,4,FALSE) -> 0 | P73: =VLOOKUP(O73,'Win Methods'!$C$4:$F$4992,4,FALSE) -> 0 | R73: =VLOOKUP(Q73,'Win Methods'!$C$4:$F$4992,4,FALSE) -> 0 | T73: =VLOOKUP(S73,'Win Methods'!$C$4:$F$4992,4,FALSE) -> 0 | V73: =VLOOKUP(U73,'Win Methods'!$C$4:$F$4992,4,FALSE) -> 0 | X73: =VLOOKUP(W73,'Win Methods'!$C$4:$F$4992,4,FALSE) -> 0 | Y73: =E73&"|"&G73&"|"&I73&"|"&K73&"|"&M73&"|"&O73&"|"&Q73&"|"&S73&"|"&U73&"|"&W73 &" x "&D73 -> main-5|main-25|main-25||||||| x 1
... B78: 75 | C78: =(F78+H78+J78+L78+N78+P78+R78+T78+V78+X78)*D78 -> 22.2 | D78: 1 | E78: main-30 | F78: =VLOOKUP(E78,'Win Methods'!$C$4:$F$4992,4,FALSE) -> 2 | G78: main-25 | H78: =VLOOKUP(G78,'Win Methods'!$C$4:$F$4992,4,FALSE) -> 20 | I78: main-1 | J78: =VLOOKUP(I78,'Win Methods'!$C$4:$F$4992,4,FALSE) -> 0.2 | L78: =VLOOKUP(K78,'Win Methods'!$C$4:$F$4992,4,FALSE) -> 0 | N78: =VLOOKUP(M78,'Win Methods'!$C$4:$F$4992,4,FALSE) -> 0 | P78: =VLOOKUP(O78,'Win Methods'!$C$4:$F$4992,4,FALSE) -> 0 | R78: =VLOOKUP(Q78,'Win Methods'!$C$4:$F$4992,4,FALSE) -> 0 | T78: =VLOOKUP(S78,'Win Methods'!$C$4:$F$4992,4,FALSE) -> 0 | V78: =VLOOKUP(U78,'Win Methods'!$C$4:$F$4992,4,FALSE) -> 0 | X78: =VLOOKUP(W78,'Win Methods'!$C$4:$F$4992,4,FALSE) -> 0 | Y78: =E78&"|"&G78&"|"&I78&"|"&K78&"|"&M78&"|"&O78&"|"&Q78&"|"&S78&"|"&U78&"|"&W78 &" x "&D78 -> main-30|main-25|main-1||||||| x 1
B79: 76 | C79: =(F79+H79+J79+L79+N79+P79+R79+T79+V79+X79)*D79 -> 2 | D79: 1 | E79: main-4 | F79: =VLOOKUP(E79,'Win Methods'!$C$4:$F$4992,4,FALSE) -> 1.5 | G79: main-0 | H79: =VLOOKUP(G79,'Win Methods'!$C$4:$F$4992,4,FALSE) -> 0.1 | I79: main-1 | J79: =VLOOKUP(I79,'Win Methods'!$C$4:$F$4992,4,FALSE) -> 0.2 | K79: main-1 | L79: =VLOOKUP(K79,'Win Methods'!$C$4:$F$4992,4,FALSE) -> 0.2 | N79: =VLOOKUP(M79,'Win Methods'!$C$4:$F$4992,4,FALSE) -> 0 | P79: =VLOOKUP(O79,'Win Methods'!$C$4:$F$4992,4,FALSE) -> 0 | R79: =VLOOKUP(Q79,'Win Methods'!$C$4:$F$4992,4,FALSE) -> 0 | T79: =VLOOKUP(S79,'Win Methods'!$C$4:$F$4992,4,FALSE) -> 0 | V79: =VLOOKUP(U79,'Win Methods'!$C$4:$F$4992,4,FALSE) -> 0 | X79: =VLOOKUP(W79,'Win Methods'!$C$4:$F$4992,4,FALSE) -> 0 | Y79: =E79&"|"&G79&"|"&I79&"|"&K79&"|"&M79&"|"&O79&"|"&Q79&"|"&S79&"|"&U79&"|"&W79 &" x "&D79 -> main-4|main-0|main-1|main-1|||||| x 1
B80: 77 | C80: =(F80+H80+J80+L80+N80+P80+R80+T80+V80+X80)*D80 -> 5 | D80: 1 | E80: main-3 | F80: =VLOOKUP(E80,'Win Methods'!$C$4:$F$4992,4,FALSE) -> 1 | G80: main-4 | H80: =VLOOKUP(G80,'Win Methods'!$C$4:$F$4992,4,FALSE) -> 1.5 | I80: main-2 | J80: =VLOOKUP(I80,'Win Methods'!$C$4:$F$4992,4,FALSE) -> 0.5 | K80: main-21 | L80: =VLOOKUP(K80,'Win Methods'!$C$4:$F$4992,4,FALSE) -> 2 | N80: =VLOOKUP(M80,'Win Methods'!$C$4:$F$4992,4,FALSE) -> 0 | P80: =VLOOKUP(O80,'Win Methods'!$C$4:$F$4992,4,FALSE) -> 0 | R80: =VLOOKUP(Q80,'Win Methods'!$C$4:$F$4992,4,FALSE) -> 0 | T80: =VLOOKUP(S80,'Win Methods'!$C$4:$F$4992,4,FALSE) -> 0 | V80: =VLOOKUP(U80,'Win Methods'!$C$4:$F$4992,4,FALSE) -> 0 | X80: =VLOOKUP(W80,'Win Methods'!$C$4:$F$4992,4,FALSE) -> 0 | Y80: =E80&"|"&G80&"|"&I80&"|"&K80&"|"&M80&"|"&O80&"|"&Q80&"|"&S80&"|"&U80&"|"&W80 &" x "&D80 -> main-3|main-4|main-2|main-21|||||| x 1
B81: 78 | C81: =(F81+H81+J81+L81+N81+P81+R81+T81+V81+X81)*D81 -> 20 | D81: 1 | E81: main-5 | F81: =VLOOKUP(E81,'Win Methods'!$C$4:$F$4992,4,FALSE) -> 2 | G81: main-3 | H81: =VLOOKUP(G81,'Win Methods'!$C$4:$F$4992,4,FALSE) -> 1 | I81: main-5 | J81: =VLOOKUP(I81,'Win Methods'!$C$4:$F$4992,4,FALSE) -> 2 | K81: main-15 | L81: =VLOOKUP(K81,'Win Methods'!$C$4:$F$4992,4,FALSE) -> 15 | N81: =VLOOKUP(M81,'Win Methods'!$C$4:$F$4992,4,FALSE) -> 0 | P81: =VLOOKUP(O81,'Win Methods'!$C$4:$F$4992,4,FALSE) -> 0 | R81: =VLOOKUP(Q81,'Win Methods'!$C$4:$F$4992,4,FALSE) -> 0 | T81: =VLOOKUP(S81,'Win Methods'!$C$4:$F$4992,4,FALSE) -> 0 | V81: =VLOOKUP(U81,'Win Methods'!$C$4:$F$4992,4,FALSE) -> 0 | X81: =VLOOKUP(W81,'Win Methods'!$C$4:$F$4992,4,FALSE) -> 0 | Y81: =E81&"|"&G81&"|"&I81&"|"&K81&"|"&M81&"|"&O81&"|"&Q81&"|"&S81&"|"&U81&"|"&W81 &" x "&D81 -> main-5|main-3|main-5|main-15|||||| x 1
B82: 79 | C82: =(F82+H82+J82+L82+N82+P82+R82+T82+V82+X82)*D82 -> 32 | D82: 1 | E82: main-5 | F82: =VLOOKUP(E82,'Win Methods'!$C$4:$F$4992,4,FALSE) -> 2 | G82: main-13 | H82: =VLOOKUP(G82,'Win Methods'!$C$4:$F$4992,4,FALSE) -> 5 | I82: main-25 | J82: =VLOOKUP(I82,'Win Methods'!$C$4:$F$4992,4,FALSE) -> 20 | K82: main-22 | L82: =VLOOKUP(K82,'Win Methods'!$C$4:$F$4992,4,FALSE) -> 5 | N82: =VLOOKUP(M82,'Win Methods'!$C$4:$F$4992,4,FALSE) -> 0 | P82: =VLOOKUP(O82,'Win Methods'!$C$4:$F$4992,4,FALSE) -> 0 | R82: =VLOOKUP(Q82,'Win Methods'!$C$4:$F$4992,4,FALSE) -> 0 | T82: =VLOOKUP(S82,'Win Methods'!$C$4:$F$4992,4,FALSE) -> 0 | V82: =VLOOKUP(U82,'Win Methods'!$C$4:$F$4992,4,FALSE) -> 0 | X82: =VLOOKUP(W82,'Win Methods'!$C$4:$F$4992,4,FALSE) -> 0 | Y82: =E82&"|"&G82&"|"&I82&"|"&K82&"|"&M82&"|"&O82&"|"&Q82&"|"&S82&"|"&U82&"|"&W82 &" x "&D82 -> main-5|main-13|main-25|main-22|||||| x 1
B83: 80 | C83: =(F83+H83+J83+L83+N83+P83+R83+T83+V83+X83)*D83 -> 50 | D83: 1 | E83: main-22 | F83: =VLOOKUP(E83,'Win Methods'!$C$4:$F$4992,4,FALSE) -> 5 | G83: main-13 | H83: =VLOOKUP(G83,'Win Methods'!$C$4:$F$4992,4,FALSE) -> 5 | I83: main-34 | J83: =VLOOKUP(I83,'Win Methods'!$C$4:$F$4992,4,FALSE) -> 20 | K83: main-25 | L83: =VLOOKUP(K83,'Win Methods'!$C$4:$F$4992,4,FALSE) -> 20 | N83: =VLOOKUP(M83,'Win Methods'!$C$4:$F$4992,4,FALSE) -> 0 | P83: =VLOOKUP(O83,'Win Methods'!$C$4:$F$4992,4,FALSE) -> 0 | R83: =VLOOKUP(Q83,'Win Methods'!$C$4:$F$4992,4,FALSE) -> 0 | T83: =VLOOKUP(S83,'Win Methods'!$C$4:$F$4992,4,FALSE) -> 0 | V83: =VLOOKUP(U83,'Win Methods'!$C$4:$F$4992,4,FALSE) -> 0 | X83: =VLOOKUP(W83,'Win Methods'!$C$4:$F$4992,4,FALSE) -> 0 | Y83: =E83&"|"&G83&"|"&I83&"|"&K83&"|"&M83&"|"&O83&"|"&Q83&"|"&S83&"|"&U83&"|"&W83 &" x "&D83 -> main-22|main-13|main-34|main-25|||||| x 1
B84: 81 | C84: =(F84+H84+J84+L84+N84+P84+R84+T84+V84+X84)*D84 -> 4.5 | D84: 1 | E84: main-3 | F84: =VLOOKUP(E84,'Win Methods'!$C$4:$F$4992,4,FALSE) -> 1 | G84: main-12 | H84: =VLOOKUP(G84,'Win Methods'!$C$4:$F$4992,4,FALSE) -> 2 | I84: main-3 | J84: =VLOOKUP(I84,'Win Methods'!$C$4:$F$4992,4,FALSE) -> 1 | K84: main-2 | L84: =VLOOKUP(K84,'Win Methods'!$C$4:$F$4992,4,FALSE) -> 0.5 | N84: =VLOOKUP(M84,'Win Methods'!$C$4:$F$4992,4,FALSE) -> 0 | P84: =VLOOKUP(O84,'Win Methods'!$C$4:$F$4992,4,FALSE) -> 0 | R84: =VLOOKUP(Q84,'Win Methods'!$C$4:$F$4992,4,FALSE) -> 0 | T84: =VLOOKUP(S84,'Win Methods'!$C$4:$F$4992,4,FALSE) -> 0 | V84: =VLOOKUP(U84,'Win Methods'!$C$4:$F$4992,4,FALSE) -> 0 | X84: =VLOOKUP(W84,'Win Methods'!$C$4:$F$4992,4,FALSE) -> 0 | Y84: =E84&"|"&G84&"|"&I84&"|"&K84&"|"&M84&"|"&O84&"|"&Q84&"|"&S84&"|"&U84&"|"&W84 &" x "&D84 -> main-3|main-12|main-3|main-2|||||| x 1
B85: 82 | C85: =(F85+H85+J85+L85+N85+P85+R85+T85+V85+X85)*D85 -> 10 | D85: 1 | E85: main-8 | F85: =VLOOKUP(E85,'Win Methods'!$C$4:$F$4992,4,FALSE) -> 5 | G85: main-5 | H85: =VLOOKUP(G85,'Win Methods'!$C$4:$F$4992,4,FALSE) -> 2 | I85: main-12 | J85: =VLOOKUP(I85,'Win Methods'!$C$4:$F$4992,4,FALSE) -> 2 | K85: main-3 | L85: =VLOOKUP(K85,'Win Methods'!$C$4:$F$4992,4,FALSE) -> 1 | N85: =VLOOKUP(M85,'Win Methods'!$C$4:$F$4992,4,FALSE) -> 0 | P85: =VLOOKUP(O85,'Win Methods'!$C$4:$F$4992,4,FALSE) -> 0 | R85: =VLOOKUP(Q85,'Win Methods'!$C$4:$F$4992,4,FALSE) -> 0 | T85: =VLOOKUP(S85,'Win Methods'!$C$4:$F$4992,4,FALSE) -> 0 | V85: =VLOOKUP(U85,'Win Methods'!$C$4:$F$4992,4,FALSE) -> 0 | X85: =VLOOKUP(W85,'Win Methods'!$C$4:$F$4992,4,FALSE) -> 0 | Y85: =E85&"|"&G85&"|"&I85&"|"&K85&"|"&M85&"|"&O85&"|"&Q85&"|"&S85&"|"&U85&"|"&W85 &" x "&D85 -> main-8|main-5|main-12|main-3|||||| x 1
B86: 83 | C86: =(F86+H86+J86+L86+N86+P86+R86+T86+V86+X86)*D86 -> 28 | D86: 1 | E86: main-9 | F86: =VLOOKUP(E86,'Win Methods'!$C$4:$F$4992,4,FALSE) -> 10 | G86: main-4 | H86: =VLOOKUP(G86,'Win Methods'!$C$4:$F$4992,4,FALSE) -> 1.5 | I86: main-11 | J86: =VLOOKUP(I86,'Win Methods'!$C$4:$F$4992,4,FALSE) -> 1.5 | K86: main-15 | L86: =VLOOKUP(K86,'Win Methods'!$C$4:$F$4992,4,FALSE) -> 15 | N86: =VLOOKUP(M86,'Win Methods'!$C$4:$F$4992,4,FALSE) -> 0 | P86: =VLOOKUP(O86,'Win Methods'!$C$4:$F$4992,4,FALSE) -> 0 | R86: =VLOOKUP(Q86,'Win Methods'!$C$4:$F$4992,4,FALSE) -> 0 | T86: =VLOOKUP(S86,'Win Methods'!$C$4:$F$4992,4,FALSE) -> 0 | V86: =VLOOKUP(U86,'Win Methods'!$C$4:$F$4992,4,FALSE) -> 0 | X86: =VLOOKUP(W86,'Win Methods'!$C$4:$F$4992,4,FALSE) -> 0 | Y86: =E86&"|"&G86&"|"&I86&"|"&K86&"|"&M86&"|"&O86&"|"&Q86&"|"&S86&"|"&U86&"|"&W86 &" x "&D86 -> main-9|main-4|main-11|main-15|||||| x 1
B87: 84 | C87: =(F87+H87+J87+L87+N87+P87+R87+T87+V87+X87)*D87 -> 27 | D87: 1 | E87: main-4 | F87: =VLOOKUP(E87,'Win Methods'!$C$4:$F$4992,4,FALSE) -> 1.5 | G87: main-25 | H87: =VLOOKUP(G87,'Win Methods'!$C$4:$F$4992,4,FALSE) -> 20 | I87: main-8 | J87: =VLOOKUP(I87,'Win Methods'!$C$4:$F$4992,4,FALSE) -> 5 | K87: main-2 | L87: =VLOOKUP(K87,'Win Methods'!$C$4:$F$4992,4,FALSE) -> 0.5 | N87: =VLOOKUP(M87,'Win Methods'!$C$4:$F$4992,4,FALSE) -> 0 | P87: =VLOOKUP(O87,'Win Methods'!$C$4:$F$4992,4,FALSE) -> 0 | R87: =VLOOKUP(Q87,'Win Methods'!$C$4:$F$4992,4,FALSE) -> 0 | T87: =VLOOKUP(S87,'Win Methods'!$C$4:$F$4992,4,FALSE) -> 0 | V87: =VLOOKUP(U87,'Win Methods'!$C$4:$F$4992,4,FALSE) -> 0 | X87: =VLOOKUP(W87,'Win Methods'!$C$4:$F$4992,4,FALSE) -> 0 | Y87: =E87&"|"&G87&"|"&I87&"|"&K87&"|"&M87&"|"&O87&"|"&Q87&"|"&S87&"|"&U87&"|"&W87 &" x "&D87 -> main-4|main-25|main-8|main-2|||||| x 1
B88: 85 | C88: =(F88+H88+J88+L88+N88+P88+R88+T88+V88+X88)*D88 -> 6 | D88: 1 | E88: main-4 | F88: =VLOOKUP(E88,'Win Methods'!$C$4:$F$4992,4,FALSE) -> 1.5 | G88: main-2 | H88: =VLOOKUP(G88,'Win Methods'!$C$4:$F$4992,4,FALSE) -> 0.5 | I88: main-5 | J88: =VLOOKUP(I88,'Win Methods'!$C$4:$F$4992,4,FALSE) -> 2 | K88: main-3 | L88: =VLOOKUP(K88,'Win Methods'!$C$4:$F$4992,4,FALSE) -> 1 | M88: main-3 | N88: =VLOOKUP(M88,'Win Methods'!$C$4:$F$4992,4,FALSE) -> 1 | P88: =VLOOKUP(O88,'Win Methods'!$C$4:$F$4992,4,FALSE) -> 0 | R88: =VLOOKUP(Q88,'Win Methods'!$C$4:$F$4992,4,FALSE) -> 0 | T88: =VLOOKUP(S88,'Win Methods'!$C$4:$F$4992,4,FALSE) -> 0 | V88: =VLOOKUP(U88,'Win Methods'!$C$4:$F$4992,4,FALSE) -> 0 | X88: =VLOOKUP(W88,'Win Methods'!$C$4:$F$4992,4,FALSE) -> 0 | Y88: =E88&"|"&G88&"|"&I88&"|"&K88&"|"&M88&"|"&O88&"|"&Q88&"|"&S88&"|"&U88&"|"&W88 &" x "&D88 -> main-4|main-2|main-5|main-3|main-3||||| x 1
B89: 86 | C89: =(F89+H89+J89+L89+N89+P89+R89+T89+V89+X89)*D89 -> 21 | D89: 1 | E89: main-15 | F89: =VLOOKUP(E89,'Win Methods'!$C$4:$F$4992,4,FALSE) -> 15 | G89: main-5 | H89: =VLOOKUP(G89,'Win Methods'!$C$4:$F$4992,4,FALSE) -> 2 | I89: main-2 | J89: =VLOOKUP(I89,'Win Methods'!$C$4:$F$4992,4,FALSE) -> 0.5 | K89: main-12 | L89: =VLOOKUP(K89,'Win Methods'!$C$4:$F$4992,4,FALSE) -> 2 | M89: main-4 | N89: =VLOOKUP(M89,'Win Methods'!$C$4:$F$4992,4,FALSE) -> 1.5 | P89: =VLOOKUP(O89,'Win Methods'!$C$4:$F$4992,4,FALSE) -> 0 | R89: =VLOOKUP(Q89,'Win Methods'!$C$4:$F$4992,4,FALSE) -> 0 | T89: =VLOOKUP(S89,'Win Methods'!$C$4:$F$4992,4,FALSE) -> 0 | V89: =VLOOKUP(U89,'Win Methods'!$C$4:$F$4992,4,FALSE) -> 0 | X89: =VLOOKUP(W89,'Win Methods'!$C$4:$F$4992,4,FALSE) -> 0 | Y89: =E89&"|"&G89&"|"&I89&"|"&K89&"|"&M89&"|"&O89&"|"&Q89&"|"&S89&"|"&U89&"|"&W89 &" x "&D89 -> main-15|main-5|main-2|main-12|main-4||||| x 1
B90: 87 | C90: =(F90+H90+J90+L90+N90+P90+R90+T90+V90+X90)*D90 -> 28.5 | D90: 1 | E90: main-3 | F90: =VLOOKUP(E90,'Win Methods'!$C$4:$F$4992,4,FALSE) -> 1 | G90: main-31 | H90: =VLOOKUP(G90,'Win Methods'!$C$4:$F$4992,4,FALSE) -> 5 | I90: main-4 | J90: =VLOOKUP(I90,'Win Methods'!$C$4:$F$4992,4,FALSE) -> 1.5 | K90: main-16 | L90: =VLOOKUP(K90,'Win Methods'!$C$4:$F$4992,4,FALSE) -> 20 | M90: main-3 | N90: =VLOOKUP(M90,'Win Methods'!$C$4:$F$4992,4,FALSE) -> 1 | P90: =VLOOKUP(O90,'Win Methods'!$C$4:$F$4992,4,FALSE) -> 0 | R90: =VLOOKUP(Q90,'Win Methods'!$C$4:$F$4992,4,FALSE) -> 0 | T90: =VLOOKUP(S90,'Win Methods'!$C$4:$F$4992,4,FALSE) -> 0 | V90: =VLOOKUP(U90,'Win Methods'!$C$4:$F$4992,4,FALSE) -> 0 | X90: =VLOOKUP(W90,'Win Methods'!$C$4:$F$4992,4,FALSE) -> 0 | Y90: =E90&"|"&G90&"|"&I90&"|"&K90&"|"&M90&"|"&O90&"|"&Q90&"|"&S90&"|"&U90&"|"&W90 &" x "&D90 -> main-3|main-31|main-4|main-16|main-3||||| x 1
B91: 88 | C91: =(F91+H91+J91+L91+N91+P91+R91+T91+V91+X91)*D91 -> 10 | D91: 1 | E91: main-3 | F91: =VLOOKUP(E91,'Win Methods'!$C$4:$F$4992,4,FALSE) -> 1 | G91: main-4 | H91: =VLOOKUP(G91,'Win Methods'!$C$4:$F$4992,4,FALSE) -> 1.5 | I91: main-2 | J91: =VLOOKUP(I91,'Win Methods'!$C$4:$F$4992,4,FALSE) -> 0.5 | K91: main-8 | L91: =VLOOKUP(K91,'Win Methods'!$C$4:$F$4992,4,FALSE) -> 5 | M91: main-5 | N91: =VLOOKUP(M91,'Win Methods'!$C$4:$F$4992,4,FALSE) -> 2 | P91: =VLOOKUP(O91,'Win Methods'!$C$4:$F$4992,4,FALSE) -> 0 | R91: =VLOOKUP(Q91,'Win Methods'!$C$4:$F$4992,4,FALSE) -> 0 | T91: =VLOOKUP(S91,'Win Methods'!$C$4:$F$4992,4,FALSE) -> 0 | V91: =VLOOKUP(U91,'Win Methods'!$C$4:$F$4992,4,FALSE) -> 0 | X91: =VLOOKUP(W91,'Win Methods'!$C$4:$F$4992,4,FALSE) -> 0 | Y91: =E91&"|"&G91&"|"&I91&"|"&K91&"|"&M91&"|"&O91&"|"&Q91&"|"&S91&"|"&U91&"|"&W91 &" x "&D91 -> main-3|main-4|main-2|main-8|main-5||||| x 1
B92: 89 | C92: =(F92+H92+J92+L92+N92+P92+R92+T92+V92+X92)*D92 -> 24 | D92: 1 | E92: main-6 | F92: =VLOOKUP(E92,'Win Methods'!$C$4:$F$4992,4,FALSE) -> 2.5 | G92: main-32 | H92: =VLOOKUP(G92,'Win Methods'!$C$4:$F$4992,4,FALSE) -> 10 | I92: main-31 | J92: =VLOOKUP(I92,'Win Methods'!$C$4:$F$4992,4,FALSE) -> 5 | K92: main-8 | L92: =VLOOKUP(K92,'Win Methods'!$C$4:$F$4992,4,FALSE) -> 5 | M92: main-4 | N92: =VLOOKUP(M92,'Win Methods'!$C$4:$F$4992,4,FALSE) -> 1.5 | P92: =VLOOKUP(O92,'Win Methods'!$C$4:$F$4992,4,FALSE) -> 0 | R92: =VLOOKUP(Q92,'Win Methods'!$C$4:$F$4992,4,FALSE) -> 0 | T92: =VLOOKUP(S92,'Win Methods'!$C$4:$F$4992,4,FALSE) -> 0 | V92: =VLOOKUP(U92,'Win Methods'!$C$4:$F$4992,4,FALSE) -> 0 | X92: =VLOOKUP(W92,'Win Methods'!$C$4:$F$4992,4,FALSE) -> 0 | Y92: =E92&"|"&G92&"|"&I92&"|"&K92&"|"&M92&"|"&O92&"|"&Q92&"|"&S92&"|"&U92&"|"&W92 &" x "&D92 -> main-6|main-32|main-31|main-8|main-4||||| x 1
B93: 90 | C93: =(F93+H93+J93+L93+N93+P93+R93+T93+V93+X93)*D93 -> 25.5 | D93: 1 | E93: main-4 | F93: =VLOOKUP(E93,'Win Methods'!$C$4:$F$4992,4,FALSE) -> 1.5 | G93: main-4 | H93: =VLOOKUP(G93,'Win Methods'!$C$4:$F$4992,4,FALSE) -> 1.5 | I93: main-4 | J93: =VLOOKUP(I93,'Win Methods'!$C$4:$F$4992,4,FALSE) -> 1.5 | K93: main-3 | L93: =VLOOKUP(K93,'Win Methods'!$C$4:$F$4992,4,FALSE) -> 1 | M93: main-34 | N93: =VLOOKUP(M93,'Win Methods'!$C$4:$F$4992,4,FALSE) -> 20 | P93: =VLOOKUP(O93,'Win Methods'!$C$4:$F$4992,4,FALSE) -> 0 | R93: =VLOOKUP(Q93,'Win Methods'!$C$4:$F$4992,4,FALSE) -> 0 | T93: =VLOOKUP(S93,'Win Methods'!$C$4:$F$4992,4,FALSE) -> 0 | V93: =VLOOKUP(U93,'Win Methods'!$C$4:$F$4992,4,FALSE) -> 0 | X93: =VLOOKUP(W93,'Win Methods'!$C$4:$F$4992,4,FALSE) -> 0 | Y93: =E93&"|"&G93&"|"&I93&"|"&K93&"|"&M93&"|"&O93&"|"&Q93&"|"&S93&"|"&U93&"|"&W93 &" x "&D93 -> main-4|main-4|main-4|main-3|main-34||||| x 1
B94: 91 | C94: =(F94+H94+J94+L94+N94+P94+R94+T94+V94+X94)*D94 -> 7.2 | D94: 1 | E94: main-5 | F94: =VLOOKUP(E94,'Win Methods'!$C$4:$F$4992,4,FALSE) -> 2 | G94: main-21 | H94: =VLOOKUP(G94,'Win Methods'!$C$4:$F$4992,4,FALSE) -> 2 | I94: main-4 | J94: =VLOOKUP(I94,'Win Methods'!$C$4:$F$4992,4,FALSE) -> 1.5 | K94: main-4 | L94: =VLOOKUP(K94,'Win Methods'!$C$4:$F$4992,4,FALSE) -> 1.5 | M94: main-1 | N94: =VLOOKUP(M94,'Win Methods'!$C$4:$F$4992,4,FALSE) -> 0.2 | P94: =VLOOKUP(O94,'Win Methods'!$C$4:$F$4992,4,FALSE) -> 0 | R94: =VLOOKUP(Q94,'Win Methods'!$C$4:$F$4992,4,FALSE) -> 0 | T94: =VLOOKUP(S94,'Win Methods'!$C$4:$F$4992,4,FALSE) -> 0 | V94: =VLOOKUP(U94,'Win Methods'!$C$4:$F$4992,4,FALSE) -> 0 | X94: =VLOOKUP(W94,'Win Methods'!$C$4:$F$4992,4,FALSE) -> 0 | Y94: =E94&"|"&G94&"|"&I94&"|"&K94&"|"&M94&"|"&O94&"|"&Q94&"|"&S94&"|"&U94&"|"&W94 &" x "&D94 -> main-5|main-21|main-4|main-4|main-1||||| x 1
B95: 92 | C95: =(F95+H95+J95+L95+N95+P95+R95+T95+V95+X95)*D95 -> 18 | D95: 1 | E95: main-7 | F95: =VLOOKUP(E95,'Win Methods'!$C$4:$F$4992,4,FALSE) -> 3 | G95: main-5 | H95: =VLOOKUP(G95,'Win Methods'!$C$4:$F$4992,4,FALSE) -> 2 | I95: main-5 | J95: =VLOOKUP(I95,'Win Methods'!$C$4:$F$4992,4,FALSE) -> 2 | K95: main-14 | L95: =VLOOKUP(K95,'Win Methods'!$C$4:$F$4992,4,FALSE) -> 10 | M95: main-3 | N95: =VLOOKUP(M95,'Win Methods'!$C$4:$F$4992,4,FALSE) -> 1 | P95: =VLOOKUP(O95,'Win Methods'!$C$4:$F$4992,4,FALSE) -> 0 | R95: =VLOOKUP(Q95,'Win Methods'!$C$4:$F$4992,4,FALSE) -> 0 | T95: =VLOOKUP(S95,'Win Methods'!$C$4:$F$4992,4,FALSE) -> 0 | V95: =VLOOKUP(U95,'Win Methods'!$C$4:$F$4992,4,FALSE) -> 0 | X95: =VLOOKUP(W95,'Win Methods'!$C$4:$F$4992,4,FALSE) -> 0 | Y95: =E95&"|"&G95&"|"&I95&"|"&K95&"|"&M95&"|"&O95&"|"&Q95&"|"&S95&"|"&U95&"|"&W95 &" x "&D95 -> main-7|main-5|main-5|main-14|main-3||||| x 1
B96: 93 | C96: =(F96+H96+J96+L96+N96+P96+R96+T96+V96+X96)*D96 -> 26 | D96: 1 | E96: main-5 | F96: =VLOOKUP(E96,'Win Methods'!$C$4:$F$4992,4,FALSE) -> 2 | G96: main-3 | H96: =VLOOKUP(G96,'Win Methods'!$C$4:$F$4992,4,FALSE) -> 1 | I96: main-9 | J96: =VLOOKUP(I96,'Win Methods'!$C$4:$F$4992,4,FALSE) -> 10 | K96: main-32 | L96: =VLOOKUP(K96,'Win Methods'!$C$4:$F$4992,4,FALSE) -> 10 | M96: main-7 | N96: =VLOOKUP(M96,'Win Methods'!$C$4:$F$4992,4,FALSE) -> 3 | P96: =VLOOKUP(O96,'Win Methods'!$C$4:$F$4992,4,FALSE) -> 0 | R96: =VLOOKUP(Q96,'Win Methods'!$C$4:$F$4992,4,FALSE) -> 0 | T96: =VLOOKUP(S96,'Win Methods'!$C$4:$F$4992,4,FALSE) -> 0 | V96: =VLOOKUP(U96,'Win Methods'!$C$4:$F$4992,4,FALSE) -> 0 | X96: =VLOOKUP(W96,'Win Methods'!$C$4:$F$4992,4,FALSE) -> 0 | Y96: =E96&"|"&G96&"|"&I96&"|"&K96&"|"&M96&"|"&O96&"|"&Q96&"|"&S96&"|"&U96&"|"&W96 &" x "&D96 -> main-5|main-3|main-9|main-32|main-7||||| x 1
B97: 94 | C97: =(F97+H97+J97+L97+N97+P97+R97+T97+V97+X97)*D97 -> 24.5 | D97: 1 | E97: main-2 | F97: =VLOOKUP(E97,'Win Methods'!$C$4:$F$4992,4,FALSE) -> 0.5 | G97: main-23 | H97: =VLOOKUP(G97,'Win Methods'!$C$4:$F$4992,4,FALSE) -> 10 | I97: main-3 | J97: =VLOOKUP(I97,'Win Methods'!$C$4:$F$4992,4,FALSE) -> 1 | K97: main-7 | L97: =VLOOKUP(K97,'Win Methods'!$C$4:$F$4992,4,FALSE) -> 3 | M97: main-14 | N97: =VLOOKUP(M97,'Win Methods'!$C$4:$F$4992,4,FALSE) -> 10 | P97: =VLOOKUP(O97,'Win Methods'!$C$4:$F$4992,4,FALSE) -> 0 | R97: =VLOOKUP(Q97,'Win Methods'!$C$4:$F$4992,4,FALSE) -> 0 | T97: =VLOOKUP(S97,'Win Methods'!$C$4:$F$4992,4,FALSE) -> 0 | V97: =VLOOKUP(U97,'Win Methods'!$C$4:$F$4992,4,FALSE) -> 0 | X97: =VLOOKUP(W97,'Win Methods'!$C$4:$F$4992,4,FALSE) -> 0 | Y97: =E97&"|"&G97&"|"&I97&"|"&K97&"|"&M97&"|"&O97&"|"&Q97&"|"&S97&"|"&U97&"|"&W97 &" x "&D97 -> main-2|main-23|main-3|main-7|main-14||||| x 1
B98: 95 | C98: =(F98+H98+J98+L98+N98+P98+R98+T98+V98+X98)*D98 -> 2 | D98: 20 | E98: main-0 | F98: =VLOOKUP(E98,'Win Methods'!$C$4:$F$4992,4,FALSE) -> 0.1 | H98: =VLOOKUP(G98,'Win Methods'!$C$4:$F$4992,4,FALSE) -> 0 | J98: =VLOOKUP(I98,'Win Methods'!$C$4:$F$4992,4,FALSE) -> 0 | L98: =VLOOKUP(K98,'Win Methods'!$C$4:$F$4992,4,FALSE) -> 0 | N98: =VLOOKUP(M98,'Win Methods'!$C$4:$F$4992,4,FALSE) -> 0 | P98: =VLOOKUP(O98,'Win Methods'!$C$4:$F$4992,4,FALSE) -> 0 | R98: =VLOOKUP(Q98,'Win Methods'!$C$4:$F$4992,4,FALSE) -> 0 | T98: =VLOOKUP(S98,'Win Methods'!$C$4:$F$4992,4,FALSE) -> 0 | V98: =VLOOKUP(U98,'Win Methods'!$C$4:$F$4992,4,FALSE) -> 0 | X98: =VLOOKUP(W98,'Win Methods'!$C$4:$F$4992,4,FALSE) -> 0 | Y98: =E98&"|"&G98&"|"&I98&"|"&K98&"|"&M98&"|"&O98&"|"&Q98&"|"&S98&"|"&U98&"|"&W98 &" x "&D98 -> main-0||||||||| x 20
B99: 96 | C99: =(F99+H99+J99+L99+N99+P99+R99+T99+V99+X99)*D99 -> 4 | D99: 20 | E99: main-1 | F99: =VLOOKUP(E99,'Win Methods'!$C$4:$F$4992,4,FALSE) -> 0.2 | H99: =VLOOKUP(G99,'Win Methods'!$C$4:$F$4992,4,FALSE) -> 0 | J99: =VLOOKUP(I99,'Win Methods'!$C$4:$F$4992,4,FALSE) -> 0 | L99: =VLOOKUP(K99,'Win Methods'!$C$4:$F$4992,4,FALSE) -> 0 | N99: =VLOOKUP(M99,'Win Methods'!$C$4:$F$4992,4,FALSE) -> 0 | P99: =VLOOKUP(O99,'Win Methods'!$C$4:$F$4992,4,FALSE) -> 0 | R99: =VLOOKUP(Q99,'Win Methods'!$C$4:$F$4992,4,FALSE) -> 0 | T99: =VLOOKUP(S99,'Win Methods'!$C$4:$F$4992,4,FALSE) -> 0 | V99: =VLOOKUP(U99,'Win Methods'!$C$4:$F$4992,4,FALSE) -> 0 | X99: =VLOOKUP(W99,'Win Methods'!$C$4:$F$4992,4,FALSE) -> 0 | Y99: =E99&"|"&G99&"|"&I99&"|"&K99&"|"&M99&"|"&O99&"|"&Q99&"|"&S99&"|"&U99&"|"&W99 &" x "&D99 -> main-1||||||||| x 20
B100: 97 | C100: =(F100+H100+J100+L100+N100+P100+R100+T100+V100+X100)*D100 -> 10 | D100: 20 | E100: main-2 | F100: =VLOOKUP(E100,'Win Methods'!$C$4:$F$4992,4,FALSE) -> 0.5 | H100: =VLOOKUP(G100,'Win Methods'!$C$4:$F$4992,4,FALSE) -> 0 | J100: =VLOOKUP(I100,'Win Methods'!$C$4:$F$4992,4,FALSE) -> 0 | L100: =VLOOKUP(K100,'Win Methods'!$C$4:$F$4992,4,FALSE) -> 0 | N100: =VLOOKUP(M100,'Win Methods'!$C$4:$F$4992,4,FALSE) -> 0 | P100: =VLOOKUP(O100,'Win Methods'!$C$4:$F$4992,4,FALSE) -> 0 | R100: =VLOOKUP(Q100,'Win Methods'!$C$4:$F$4992,4,FALSE) -> 0 | T100: =VLOOKUP(S100,'Win Methods'!$C$4:$F$4992,4,FALSE) -> 0 | V100: =VLOOKUP(U100,'Win Methods'!$C$4:$F$4992,4,FALSE) -> 0 | X100: =VLOOKUP(W100,'Win Methods'!$C$4:$F$4992,4,FALSE) -> 0 | Y100: =E100&"|"&G100&"|"&I100&"|"&K100&"|"&M100&"|"&O100&"|"&Q100&"|"&S100&"|"&U100&"|"&W100 &" x "&D100 -> main-2||||||||| x 20
B101: 98 | C101: =(F101+H101+J101+L101+N101+P101+R101+T101+V101+X101)*D101 -> 20 | D101: 20 | E101: main-3 | F101: =VLOOKUP(E101,'Win Methods'!$C$4:$F$4992,4,FALSE) -> 1 | H101: =VLOOKUP(G101,'Win Methods'!$C$4:$F$4992,4,FALSE) -> 0 | J101: =VLOOKUP(I101,'Win Methods'!$C$4:$F$4992,4,FALSE) -> 0 | L101: =VLOOKUP(K101,'Win Methods'!$C$4:$F$4992,4,FALSE) -> 0 | N101: =VLOOKUP(M101,'Win Methods'!$C$4:$F$4992,4,FALSE) -> 0 | P101: =VLOOKUP(O101,'Win Methods'!$C$4:$F$4992,4,FALSE) -> 0 | R101: =VLOOKUP(Q101,'Win Methods'!$C$4:$F$4992,4,FALSE) -> 0 | T101: =VLOOKUP(S101,'Win Methods'!$C$4:$F$4992,4,FALSE) -> 0 | V101: =VLOOKUP(U101,'Win Methods'!$C$4:$F$4992,4,FALSE) -> 0 | X101: =VLOOKUP(W101,'Win Methods'!$C$4:$F$4992,4,FALSE) -> 0 | Y101: =E101&"|"&G101&"|"&I101&"|"&K101&"|"&M101&"|"&O101&"|"&Q101&"|"&S101&"|"&U101&"|"&W101 &" x "&D101 -> main-3||||||||| x 20
B102: 99 | C102: =(F102+H102+J102+L102+N102+P102+R102+T102+V102+X102)*D102 -> 30 | D102: 20 | E102: main-4 | F102: =VLOOKUP(E102,'Win Methods'!$C$4:$F$4992,4,FALSE) -> 1.5 | H102: =VLOOKUP(G102,'Win Methods'!$C$4:$F$4992,4,FALSE) -> 0 | J102: =VLOOKUP(I102,'Win Methods'!$C$4:$F$4992,4,FALSE) -> 0 | L102: =VLOOKUP(K102,'Win Methods'!$C$4:$F$4992,4,FALSE) -> 0 | N102: =VLOOKUP(M102,'Win Methods'!$C$4:$F$4992,4,FALSE) -> 0 | P102: =VLOOKUP(O102,'Win Methods'!$C$4:$F$4992,4,FALSE) -> 0 | R102: =VLOOKUP(Q102,'Win Methods'!$C$4:$F$4992,4,FALSE) -> 0 | T102: =VLOOKUP(S102,'Win Methods'!$C$4:$F$4992,4,FALSE) -> 0 | V102: =VLOOKUP(U102,'Win Methods'!$C$4:$F$4992,4,FALSE) -> 0 | X102: =VLOOKUP(W102,'Win Methods'!$C$4:$F$4992,4,FALSE) -> 0 | Y102: =E102&"|"&G102&"|"&I102&"|"&K102&"|"&M102&"|"&O102&"|"&Q102&"|"&S102&"|"&U102&"|"&W102 &" x "&D102 -> main-4||||||||| x 20
B103: 100 | C103: =(F103+H103+J103+L103+N103+P103+R103+T103+V103+X103)*D103 -> 40 | D103: 20 | E103: main-5 | F103: =VLOOKUP(E103,'Win Methods'!$C$4:$F$4992,4,FALSE) -> 2 | H103: =VLOOKUP(G103,'Win Methods'!$C$4:$F$4992,4,FALSE) -> 0 | J103: =VLOOKUP(I103,'Win Methods'!$C$4:$F$4992,4,FALSE) -> 0 | L103: =VLOOKUP(K103,'Win Methods'!$C$4:$F$4992,4,FALSE) -> 0 | N103: =VLOOKUP(M103,'Win Methods'!$C$4:$F$4992,4,FALSE) -> 0 | P103: =VLOOKUP(O103,'Win Methods'!$C$4:$F$4992,4,FALSE) -> 0 | R103: =VLOOKUP(Q103,'Win Methods'!$C$4:$F$4992,4,FALSE) -> 0 | T103: =VLOOKUP(S103,'Win Methods'!$C$4:$F$4992,4,FALSE) -> 0 | V103: =VLOOKUP(U103,'Win Methods'!$C$4:$F$4992,4,FALSE) -> 0 | X103: =VLOOKUP(W103,'Win Methods'!$C$4:$F$4992,4,FALSE) -> 0 | Y103: =E103&"|"&G103&"|"&I103&"|"&K103&"|"&M103&"|"&O103&"|"&Q103&"|"&S103&"|"&U103&"|"&W103 &" x "&D103 -> main-5||||||||| x 20
B104: 101 | C104: =(F104+H104+J104+L104+N104+P104+R104+T104+V104+X104)*D104 -> 20 | D104: 20 | E104: main-10 | F104: =VLOOKUP(E104,'Win Methods'!$C$4:$F$4992,4,FALSE) -> 1 | H104: =VLOOKUP(G104,'Win Methods'!$C$4:$F$4992,4,FALSE) -> 0 | J104: =VLOOKUP(I104,'Win Methods'!$C$4:$F$4992,4,FALSE) -> 0 | L104: =VLOOKUP(K104,'Win Methods'!$C$4:$F$4992,4,FALSE) -> 0 | N104: =VLOOKUP(M104,'Win Methods'!$C$4:$F$4992,4,FALSE) -> 0 | P104: =VLOOKUP(O104,'Win Methods'!$C$4:$F$4992,4,FALSE) -> 0 | R104: =VLOOKUP(Q104,'Win Methods'!$C$4:$F$4992,4,FALSE) -> 0 | T104: =VLOOKUP(S104,'Win Methods'!$C$4:$F$4992,4,FALSE) -> 0 | V104: =VLOOKUP(U104,'Win Methods'!$C$4:$F$4992,4,FALSE) -> 0 | X104: =VLOOKUP(W104,'Win Methods'!$C$4:$F$4992,4,FALSE) -> 0 | Y104: =E104&"|"&G104&"|"&I104&"|"&K104&"|"&M104&"|"&O104&"|"&Q104&"|"&S104&"|"&U104&"|"&W104 &" x "&D104 -> main-10||||||||| x 20
B105: 102 | C105: =(F105+H105+J105+L105+N105+P105+R105+T105+V105+X105)*D105 -> 30 | D105: 20 | E105: main-11 | F105: =VLOOKUP(E105,'Win Methods'!$C$4:$F$4992,4,FALSE) -> 1.5 | H105: =VLOOKUP(G105,'Win Methods'!$C$4:$F$4992,4,FALSE) -> 0 | J105: =VLOOKUP(I105,'Win Methods'!$C$4:$F$4992,4,FALSE) -> 0 | L105: =VLOOKUP(K105,'Win Methods'!$C$4:$F$4992,4,FALSE) -> 0 | N105: =VLOOKUP(M105,'Win Methods'!$C$4:$F$4992,4,FALSE) -> 0 | P105: =VLOOKUP(O105,'Win Methods'!$C$4:$F$4992,4,FALSE) -> 0 | R105: =VLOOKUP(Q105,'Win Methods'!$C$4:$F$4992,4,FALSE) -> 0 | T105: =VLOOKUP(S105,'Win Methods'!$C$4:$F$4992,4,FALSE) -> 0 | V105: =VLOOKUP(U105,'Win Methods'!$C$4:$F$4992,4,FALSE) -> 0 | X105: =VLOOKUP(W105,'Win Methods'!$C$4:$F$4992,4,FALSE) -> 0 | Y105: =E105&"|"&G105&"|"&I105&"|"&K105&"|"&M105&"|"&O105&"|"&Q105&"|"&S105&"|"&U105&"|"&W105 &" x "&D105 -> main-11||||||||| x 20
B106: 103 | C106: =(F106+H106+J106+L106+N106+P106+R106+T106+V106+X106)*D106 -> 40 | D106: 20 | E106: main-12 | F106: =VLOOKUP(E106,'Win Methods'!$C$4:$F$4992,4,FALSE) -> 2 | H106: =VLOOKUP(G106,'Win Methods'!$C$4:$F$4992,4,FALSE) -> 0 | J106: =VLOOKUP(I106,'Win Methods'!$C$4:$F$4992,4,FALSE) -> 0 | L106: =VLOOKUP(K106,'Win Methods'!$C$4:$F$4992,4,FALSE) -> 0 | N106: =VLOOKUP(M106,'Win Methods'!$C$4:$F$4992,4,FALSE) -> 0 | P106: =VLOOKUP(O106,'Win Methods'!$C$4:$F$4992,4,FALSE) -> 0 | R106: =VLOOKUP(Q106,'Win Methods'!$C$4:$F$4992,4,FALSE) -> 0 | T106: =VLOOKUP(S106,'Win Methods'!$C$4:$F$4992,4,FALSE) -> 0 | V106: =VLOOKUP(U106,'Win Methods'!$C$4:$F$4992,4,FALSE) -> 0 | X106: =VLOOKUP(W106,'Win Methods'!$C$4:$F$4992,4,FALSE) -> 0 | Y106: =E106&"|"&G106&"|"&I106&"|"&K106&"|"&M106&"|"&O106&"|"&Q106&"|"&S106&"|"&U106&"|"&W106 &" x "&D106 -> main-12||||||||| x 20
B107: 104 | C107: =(F107+H107+J107+L107+N107+P107+R107+T107+V107+X107)*D107 -> 100 | D107: 20 | E107: main-13 | F107: =VLOOKUP(E107,'Win Methods'!$C$4:$F$4992,4,FALSE) -> 5 | H107: =VLOOKUP(G107,'Win Methods'!$C$4:$F$4992,4,FALSE) -> 0 | J107: =VLOOKUP(I107,'Win Methods'!$C$4:$F$4992,4,FALSE) -> 0 | L107: =VLOOKUP(K107,'Win Methods'!$C$4:$F$4992,4,FALSE) -> 0 | N107: =VLOOKUP(M107,'Win Methods'!$C$4:$F$4992,4,FALSE) -> 0 | P107: =VLOOKUP(O107,'Win Methods'!$C$4:$F$4992,4,FALSE) -> 0 | R107: =VLOOKUP(Q107,'Win Methods'!$C$4:$F$4992,4,FALSE) -> 0 | T107: =VLOOKUP(S107,'Win Methods'!$C$4:$F$4992,4,FALSE) -> 0 | V107: =VLOOKUP(U107,'Win Methods'!$C$4:$F$4992,4,FALSE) -> 0 | X107: =VLOOKUP(W107,'Win Methods'!$C$4:$F$4992,4,FALSE) -> 0 | Y107: =E107&"|"&G107&"|"&I107&"|"&K107&"|"&M107&"|"&O107&"|"&Q107&"|"&S107&"|"&U107&"|"&W107 &" x "&D107 -> main-13||||||||| x 20
B108: 105 | C108: =(F108+H108+J108+L108+N108+P108+R108+T108+V108+X108)*D108 -> 30 | D108: 20 | E108: main-20 | F108: =VLOOKUP(E108,'Win Methods'!$C$4:$F$4992,4,FALSE) -> 1.5 | H108: =VLOOKUP(G108,'Win Methods'!$C$4:$F$4992,4,FALSE) -> 0 | J108: =VLOOKUP(I108,'Win Methods'!$C$4:$F$4992,4,FALSE) -> 0 | L108: =VLOOKUP(K108,'Win Methods'!$C$4:$F$4992,4,FALSE) -> 0 | N108: =VLOOKUP(M108,'Win Methods'!$C$4:$F$4992,4,FALSE) -> 0 | P108: =VLOOKUP(O108,'Win Methods'!$C$4:$F$4992,4,FALSE) -> 0 | R108: =VLOOKUP(Q108,'Win Methods'!$C$4:$F$4992,4,FALSE) -> 0 | T108: =VLOOKUP(S108,'Win Methods'!$C$4:$F$4992,4,FALSE) -> 0 | V108: =VLOOKUP(U108,'Win Methods'!$C$4:$F$4992,4,FALSE) -> 0 | X108: =VLOOKUP(W108,'Win Methods'!$C$4:$F$4992,4,FALSE) -> 0 | Y108: =E108&"|"&G108&"|"&I108&"|"&K108&"|"&M108&"|"&O108&"|"&Q108&"|"&S108&"|"&U108&"|"&W108 &" x "&D108 -> main-20||||||||| x 20
B109: 106 | C109: =(F109+H109+J109+L109+N109+P109+R109+T109+V109+X109)*D109 -> 40 | D109: 20 | E109: main-21 | F109: =VLOOKUP(E109,'Win Methods'!$C$4:$F$4992,4,FALSE) -> 2 | H109: =VLOOKUP(G109,'Win Methods'!$C$4:$F$4992,4,FALSE) -> 0 | J109: =VLOOKUP(I109,'Win Methods'!$C$4:$F$4992,4,FALSE) -> 0 | L109: =VLOOKUP(K109,'Win Methods'!$C$4:$F$4992,4,FALSE) -> 0 | N109: =VLOOKUP(M109,'Win Methods'!$C$4:$F$4992,4,FALSE) -> 0 | P109: =VLOOKUP(O109,'Win Methods'!$C$4:$F$4992,4,FALSE) -> 0 | R109: =VLOOKUP(Q109,'Win Methods'!$C$4:$F$4992,4,FALSE) -> 0 | T109: =VLOOKUP(S109,'Win Methods'!$C$4:$F$4992,4,FALSE) -> 0 | V109: =VLOOKUP(U109,'Win Methods'!$C$4:$F$4992,4,FALSE) -> 0 | X109: =VLOOKUP(W109,'Win Methods'!$C$4:$F$4992,4,FALSE) -> 0 | Y109: =E109&"|"&G109&"|"&I109&"|"&K109&"|"&M109&"|"&O109&"|"&Q109&"|"&S109&"|"&U109&"|"&W109 &" x "&D109 -> main-21||||||||| x 20
B110: 107 | C110: =(F110+H110+J110+L110+N110+P110+R110+T110+V110+X110)*D110 -> 40 | D110: 20 | E110: main-30 | F110: =VLOOKUP(E110,'Win Methods'!$C$4:$F$4992,4,FALSE) -> 2 | H110: =VLOOKUP(G110,'Win Methods'!$C$4:$F$4992,4,FALSE) -> 0 | J110: =VLOOKUP(I110,'Win Methods'!$C$4:$F$4992,4,FALSE) -> 0 | L110: =VLOOKUP(K110,'Win Methods'!$C$4:$F$4992,4,FALSE) -> 0 | N110: =VLOOKUP(M110,'Win Methods'!$C$4:$F$4992,4,FALSE) -> 0 | P110: =VLOOKUP(O110,'Win Methods'!$C$4:$F$4992,4,FALSE) -> 0 | R110: =VLOOKUP(Q110,'Win Methods'!$C$4:$F$4992,4,FALSE) -> 0 | T110: =VLOOKUP(S110,'Win Methods'!$C$4:$F$4992,4,FALSE) -> 0 | V110: =VLOOKUP(U110,'Win Methods'!$C$4:$F$4992,4,FALSE) -> 0 | X110: =VLOOKUP(W110,'Win Methods'!$C$4:$F$4992,4,FALSE) -> 0 | Y110: =E110&"|"&G110&"|"&I110&"|"&K110&"|"&M110&"|"&O110&"|"&Q110&"|"&S110&"|"&U110&"|"&W110 &" x "&D110 -> main-30||||||||| x 20
B111: 108 | C111: =(F111+H111+J111+L111+N111+P111+R111+T111+V111+X111)*D111 -> 4 | D111: 20 | E111: main-0 | F111: =VLOOKUP(E111,'Win Methods'!$C$4:$F$4992,4,FALSE) -> 0.1 | G111: main-0 | H111: =VLOOKUP(G111,'Win Methods'!$C$4:$F$4992,4,FALSE) -> 0.1 | J111: =VLOOKUP(I111,'Win Methods'!$C$4:$F$4992,4,FALSE) -> 0 | L111: =VLOOKUP(K111,'Win Methods'!$C$4:$F$4992,4,FALSE) -> 0 | N111: =VLOOKUP(M111,'Win Methods'!$C$4:$F$4992,4,FALSE) -> 0 | P111: =VLOOKUP(O111,'Win Methods'!$C$4:$F$4992,4,FALSE) -> 0 | R111: =VLOOKUP(Q111,'Win Methods'!$C$4:$F$4992,4,FALSE) -> 0 | T111: =VLOOKUP(S111,'Win Methods'!$C$4:$F$4992,4,FALSE) -> 0 | V111: =VLOOKUP(U111,'Win Methods'!$C$4:$F$4992,4,FALSE) -> 0 | X111: =VLOOKUP(W111,'Win Methods'!$C$4:$F$4992,4,FALSE) -> 0 | Y111: =E111&"|"&G111&"|"&I111&"|"&K111&"|"&M111&"|"&O111&"|"&Q111&"|"&S111&"|"&U111&"|"&W111 &" x "&D111 -> main-0|main-0|||||||| x 20
B112: 109 | C112: =(F112+H112+J112+L112+N112+P112+R112+T112+V112+X112)*D112 -> 6 | D112: 20 | E112: main-0 | F112: =VLOOKUP(E112,'Win Methods'!$C$4:$F$4992,4,FALSE) -> 0.1 | G112: main-1 | H112: =VLOOKUP(G112,'Win Methods'!$C$4:$F$4992,4,FALSE) -> 0.2 | J112: =VLOOKUP(I112,'Win Methods'!$C$4:$F$4992,4,FALSE) -> 0 | L112: =VLOOKUP(K112,'Win Methods'!$C$4:$F$4992,4,FALSE) -> 0 | N112: =VLOOKUP(M112,'Win Methods'!$C$4:$F$4992,4,FALSE) -> 0 | P112: =VLOOKUP(O112,'Win Methods'!$C$4:$F$4992,4,FALSE) -> 0 | R112: =VLOOKUP(Q112,'Win Methods'!$C$4:$F$4992,4,FALSE) -> 0 | T112: =VLOOKUP(S112,'Win Methods'!$C$4:$F$4992,4,FALSE) -> 0 | V112: =VLOOKUP(U112,'Win Methods'!$C$4:$F$4992,4,FALSE) -> 0 | X112: =VLOOKUP(W112,'Win Methods'!$C$4:$F$4992,4,FALSE) -> 0 | Y112: =E112&"|"&G112&"|"&I112&"|"&K112&"|"&M112&"|"&O112&"|"&Q112&"|"&S112&"|"&U112&"|"&W112 &" x "&D112 -> main-0|main-1|||||||| x 20
B113: 110 | C113: =(F113+H113+J113+L113+N113+P113+R113+T113+V113+X113)*D113 -> 8 | D113: 20 | E113: main-1 | F113: =VLOOKUP(E113,'Win Methods'!$C$4:$F$4992,4,FALSE) -> 0.2 | G113: main-1 | H113: =VLOOKUP(G113,'Win Methods'!$C$4:$F$4992,4,FALSE) -> 0.2 | J113: =VLOOKUP(I113,'Win Methods'!$C$4:$F$4992,4,FALSE) -> 0 | L113: =VLOOKUP(K113,'Win Methods'!$C$4:$F$4992,4,FALSE) -> 0 | N113: =VLOOKUP(M113,'Win Methods'!$C$4:$F$4992,4,FALSE) -> 0 | P113: =VLOOKUP(O113,'Win Methods'!$C$4:$F$4992,4,FALSE) -> 0 | R113: =VLOOKUP(Q113,'Win Methods'!$C$4:$F$4992,4,FALSE) -> 0 | T113: =VLOOKUP(S113,'Win Methods'!$C$4:$F$4992,4,FALSE) -> 0 | V113: =VLOOKUP(U113,'Win Methods'!$C$4:$F$4992,4,FALSE) -> 0 | X113: =VLOOKUP(W113,'Win Methods'!$C$4:$F$4992,4,FALSE) -> 0 | Y113: =E113&"|"&G113&"|"&I113&"|"&K113&"|"&M113&"|"&O113&"|"&Q113&"|"&S113&"|"&U113&"|"&W113 &" x "&D113 -> main-1|main-1|||||||| x 20
B114: 111 | C114: =(F114+H114+J114+L114+N114+P114+R114+T114+V114+X114)*D114 -> 12 | D114: 20 | E114: main-0 | F114: =VLOOKUP(E114,'Win Methods'!$C$4:$F$4992,4,FALSE) -> 0.1 | G114: main-2 | H114: =VLOOKUP(G114,'Win Methods'!$C$4:$F$4992,4,FALSE) -> 0.5 | J114: =VLOOKUP(I114,'Win Methods'!$C$4:$F$4992,4,FALSE) -> 0 | L114: =VLOOKUP(K114,'Win Methods'!$C$4:$F$4992,4,FALSE) -> 0 | N114: =VLOOKUP(M114,'Win Methods'!$C$4:$F$4992,4,FALSE) -> 0 | P114: =VLOOKUP(O114,'Win Methods'!$C$4:$F$4992,4,FALSE) -> 0 | R114: =VLOOKUP(Q114,'Win Methods'!$C$4:$F$4992,4,FALSE) -> 0 | T114: =VLOOKUP(S114,'Win Methods'!$C$4:$F$4992,4,FALSE) -> 0 | V114: =VLOOKUP(U114,'Win Methods'!$C$4:$F$4992,4,FALSE) -> 0 | X114: =VLOOKUP(W114,'Win Methods'!$C$4:$F$4992,4,FALSE) -> 0 | Y114: =E114&"|"&G114&"|"&I114&"|"&K114&"|"&M114&"|"&O114&"|"&Q114&"|"&S114&"|"&U114&"|"&W114 &" x "&D114 -> main-0|main-2|||||||| x 20
B115: 112 | C115: =(F115+H115+J115+L115+N115+P115+R115+T115+V115+X115)*D115 -> 22 | D115: 20 | E115: main-0 | F115: =VLOOKUP(E115,'Win Methods'!$C$4:$F$4992,4,FALSE) -> 0.1 | G115: main-3 | H115: =VLOOKUP(G115,'Win Methods'!$C$4:$F$4992,4,FALSE) -> 1 | J115: =VLOOKUP(I115,'Win Methods'!$C$4:$F$4992,4,FALSE) -> 0 | L115: =VLOOKUP(K115,'Win Methods'!$C$4:$F$4992,4,FALSE) -> 0 | N115: =VLOOKUP(M115,'Win Methods'!$C$4:$F$4992,4,FALSE) -> 0 | P115: =VLOOKUP(O115,'Win Methods'!$C$4:$F$4992,4,FALSE) -> 0 | R115: =VLOOKUP(Q115,'Win Methods'!$C$4:$F$4992,4,FALSE) -> 0 | T115: =VLOOKUP(S115,'Win Methods'!$C$4:$F$4992,4,FALSE) -> 0 | V115: =VLOOKUP(U115,'Win Methods'!$C$4:$F$4992,4,FALSE) -> 0 | X115: =VLOOKUP(W115,'Win Methods'!$C$4:$F$4992,4,FALSE) -> 0 | Y115: =E115&"|"&G115&"|"&I115&"|"&K115&"|"&M115&"|"&O115&"|"&Q115&"|"&S115&"|"&U115&"|"&W115 &" x "&D115 -> main-0|main-3|||||||| x 20
B116: 113 | C116: =(F116+H116+J116+L116+N116+P116+R116+T116+V116+X116)*D116 -> 32 | D116: 20 | E116: main-0 | F116: =VLOOKUP(E116,'Win Methods'!$C$4:$F$4992,4,FALSE) -> 0.1 | G116: main-4 | H116: =VLOOKUP(G116,'Win Methods'!$C$4:$F$4992,4,FALSE) -> 1.5 | J116: =VLOOKUP(I116,'Win Methods'!$C$4:$F$4992,4,FALSE) -> 0 | L116: =VLOOKUP(K116,'Win Methods'!$C$4:$F$4992,4,FALSE) -> 0 | N116: =VLOOKUP(M116,'Win Methods'!$C$4:$F$4992,4,FALSE) -> 0 | P116: =VLOOKUP(O116,'Win Methods'!$C$4:$F$4992,4,FALSE) -> 0 | R116: =VLOOKUP(Q116,'Win Methods'!$C$4:$F$4992,4,FALSE) -> 0 | T116: =VLOOKUP(S116,'Win Methods'!$C$4:$F$4992,4,FALSE) -> 0 | V116: =VLOOKUP(U116,'Win Methods'!$C$4:$F$4992,4,FALSE) -> 0 | X116: =VLOOKUP(W116,'Win Methods'!$C$4:$F$4992,4,FALSE) -> 0 | Y116: =E116&"|"&G116&"|"&I116&"|"&K116&"|"&M116&"|"&O116&"|"&Q116&"|"&S116&"|"&U116&"|"&W116 &" x "&D116 -> main-0|main-4|||||||| x 20
B117: 114 | C117: =(F117+H117+J117+L117+N117+P117+R117+T117+V117+X117)*D117 -> 40 | D117: 20 | E117: main-2 | F117: =VLOOKUP(E117,'Win Methods'!$C$4:$F$4992,4,FALSE) -> 0.5 | G117: main-20 | H117: =VLOOKUP(G117,'Win Methods'!$C$4:$F$4992,4,FALSE) -> 1.5 | J117: =VLOOKUP(I117,'Win Methods'!$C$4:$F$4992,4,FALSE) -> 0 | L117: =VLOOKUP(K117,'Win Methods'!$C$4:$F$4992,4,FALSE) -> 0 | N117: =VLOOKUP(M117,'Win Methods'!$C$4:$F$4992,4,FALSE) -> 0 | P117: =VLOOKUP(O117,'Win Methods'!$C$4:$F$4992,4,FALSE) -> 0 | R117: =VLOOKUP(Q117,'Win Methods'!$C$4:$F$4992,4,FALSE) -> 0 | T117: =VLOOKUP(S117,'Win Methods'!$C$4:$F$4992,4,FALSE) -> 0 | V117: =VLOOKUP(U117,'Win Methods'!$C$4:$F$4992,4,FALSE) -> 0 | X117: =VLOOKUP(W117,'Win Methods'!$C$4:$F$4992,4,FALSE) -> 0 | Y117: =E117&"|"&G117&"|"&I117&"|"&K117&"|"&M117&"|"&O117&"|"&Q117&"|"&S117&"|"&U117&"|"&W117 &" x "&D117 -> main-2|main-20|||||||| x 20
B118: 115 | C118: =(F118+H118+J118+L118+N118+P118+R118+T118+V118+X118)*D118 -> 60 | D118: 20 | E118: main-4 | F118: =VLOOKUP(E118,'Win Methods'!$C$4:$F$4992,4,FALSE) -> 1.5 | G118: main-4 | H118: =VLOOKUP(G118,'Win Methods'!$C$4:$F$4992,4,FALSE) -> 1.5 | J118: =VLOOKUP(I118,'Win Methods'!$C$4:$F$4992,4,FALSE) -> 0 | L118: =VLOOKUP(K118,'Win Methods'!$C$4:$F$4992,4,FALSE) -> 0 | N118: =VLOOKUP(M118,'Win Methods'!$C$4:$F$4992,4,FALSE) -> 0 | P118: =VLOOKUP(O118,'Win Methods'!$C$4:$F$4992,4,FALSE) -> 0 | R118: =VLOOKUP(Q118,'Win Methods'!$C$4:$F$4992,4,FALSE) -> 0 | T118: =VLOOKUP(S118,'Win Methods'!$C$4:$F$4992,4,FALSE) -> 0 | V118: =VLOOKUP(U118,'Win Methods'!$C$4:$F$4992,4,FALSE) -> 0 | X118: =VLOOKUP(W118,'Win Methods'!$C$4:$F$4992,4,FALSE) -> 0 | Y118: =E118&"|"&G118&"|"&I118&"|"&K118&"|"&M118&"|"&O118&"|"&Q118&"|"&S118&"|"&U118&"|"&W118 &" x "&D118 -> main-4|main-4|||||||| x 20
B119: 116 | C119: =(F119+H119+J119+L119+N119+P119+R119+T119+V119+X119)*D119 -> 60 | D119: 20 | E119: main-4 | F119: =VLOOKUP(E119,'Win Methods'!$C$4:$F$4992,4,FALSE) -> 1.5 | G119: main-11 | H119: =VLOOKUP(G119,'Win Methods'!$C$4:$F$4992,4,FALSE) -> 1.5 | J119: =VLOOKUP(I119,'Win Methods'!$C$4:$F$4992,4,FALSE) -> 0 | L119: =VLOOKUP(K119,'Win Methods'!$C$4:$F$4992,4,FALSE) -> 0 | N119: =VLOOKUP(M119,'Win Methods'!$C$4:$F$4992,4,FALSE) -> 0 | P119: =VLOOKUP(O119,'Win Methods'!$C$4:$F$4992,4,FALSE) -> 0 | R119: =VLOOKUP(Q119,'Win Methods'!$C$4:$F$4992,4,FALSE) -> 0 | T119: =VLOOKUP(S119,'Win Methods'!$C$4:$F$4992,4,FALSE) -> 0 | V119: =VLOOKUP(U119,'Win Methods'!$C$4:$F$4992,4,FALSE) -> 0 | X119: =VLOOKUP(W119,'Win Methods'!$C$4:$F$4992,4,FALSE) -> 0 | Y119: =E119&"|"&G119&"|"&I119&"|"&K119&"|"&M119&"|"&O119&"|"&Q119&"|"&S119&"|"&U119&"|"&W119 &" x "&D119 -> main-4|main-11|||||||| x 20
B120: 117 | C120: =(F120+H120+J120+L120+N120+P120+R120+T120+V120+X120)*D120 -> 60 | D120: 20 | E120: main-10 | F120: =VLOOKUP(E120,'Win Methods'!$C$4:$F$4992,4,FALSE) -> 1 | G120: main-30 | H120: =VLOOKUP(G120,'Win Methods'!$C$4:$F$4992,4,FALSE) -> 2 | J120: =VLOOKUP(I120,'Win Methods'!$C$4:$F$4992,4,FALSE) -> 0 | L120: =VLOOKUP(K120,'Win Methods'!$C$4:$F$4992,4,FALSE) -> 0 | N120: =VLOOKUP(M120,'Win Methods'!$C$4:$F$4992,4,FALSE) -> 0 | P120: =VLOOKUP(O120,'Win Methods'!$C$4:$F$4992,4,FALSE) -> 0 | R120: =VLOOKUP(Q120,'Win Methods'!$C$4:$F$4992,4,FALSE) -> 0 | T120: =VLOOKUP(S120,'Win Methods'!$C$4:$F$4992,4,FALSE) -> 0 | V120: =VLOOKUP(U120,'Win Methods'!$C$4:$F$4992,4,FALSE) -> 0 | X120: =VLOOKUP(W120,'Win Methods'!$C$4:$F$4992,4,FALSE) -> 0 | Y120: =E120&"|"&G120&"|"&I120&"|"&K120&"|"&M120&"|"&O120&"|"&Q120&"|"&S120&"|"&U120&"|"&W120 &" x "&D120 -> main-10|main-30|||||||| x 20
B121: 118 | C121: =(F121+H121+J121+L121+N121+P121+R121+T121+V121+X121)*D121 -> 14 | D121: 20 | E121: main-0 | F121: =VLOOKUP(E121,'Win Methods'!$C$4:$F$4992,4,FALSE) -> 0.1 | G121: main-0 | H121: =VLOOKUP(G121,'Win Methods'!$C$4:$F$4992,4,FALSE) -> 0.1 | I121: main-2 | J121: =VLOOKUP(I121,'Win Methods'!$C$4:$F$4992,4,FALSE) -> 0.5 | L121: =VLOOKUP(K121,'Win Methods'!$C$4:$F$4992,4,FALSE) -> 0 | N121: =VLOOKUP(M121,'Win Methods'!$C$4:$F$4992,4,FALSE) -> 0 | P121: =VLOOKUP(O121,'Win Methods'!$C$4:$F$4992,4,FALSE) -> 0 | R121: =VLOOKUP(Q121,'Win Methods'!$C$4:$F$4992,4,FALSE) -> 0 | T121: =VLOOKUP(S121,'Win Methods'!$C$4:$F$4992,4,FALSE) -> 0 | V121: =VLOOKUP(U121,'Win Methods'!$C$4:$F$4992,4,FALSE) -> 0 | X121: =VLOOKUP(W121,'Win Methods'!$C$4:$F$4992,4,FALSE) -> 0 | Y121: =E121&"|"&G121&"|"&I121&"|"&K121&"|"&M121&"|"&O121&"|"&Q121&"|"&S121&"|"&U121&"|"&W121 &" x "&D121 -> main-0|main-0|main-2||||||| x 20
B122: 119 | C122: =(F122+H122+J122+L122+N122+P122+R122+T122+V122+X122)*D122 -> 18 | D122: 20 | E122: main-1 | F122: =VLOOKUP(E122,'Win Methods'!$C$4:$F$4992,4,FALSE) -> 0.2 | G122: main-1 | H122: =VLOOKUP(G122,'Win Methods'!$C$4:$F$4992,4,FALSE) -> 0.2 | I122: main-2 | J122: =VLOOKUP(I122,'Win Methods'!$C$4:$F$4992,4,FALSE) -> 0.5 | L122: =VLOOKUP(K122,'Win Methods'!$C$4:$F$4992,4,FALSE) -> 0 | N122: =VLOOKUP(M122,'Win Methods'!$C$4:$F$4992,4,FALSE) -> 0 | P122: =VLOOKUP(O122,'Win Methods'!$C$4:$F$4992,4,FALSE) -> 0 | R122: =VLOOKUP(Q122,'Win Methods'!$C$4:$F$4992,4,FALSE) -> 0 | T122: =VLOOKUP(S122,'Win Methods'!$C$4:$F$4992,4,FALSE) -> 0 | V122: =VLOOKUP(U122,'Win Methods'!$C$4:$F$4992,4,FALSE) -> 0 | X122: =VLOOKUP(W122,'Win Methods'!$C$4:$F$4992,4,FALSE) -> 0 | Y122: =E122&"|"&G122&"|"&I122&"|"&K122&"|"&M122&"|"&O122&"|"&Q122&"|"&S122&"|"&U122&"|"&W122 &" x "&D122 -> main-1|main-1|main-2||||||| x 20
B123: 120 | C123: =(F123+H123+J123+L123+N123+P123+R123+T123+V123+X123)*D123 -> 50 | D123: 20 | E123: main-2 | F123: =VLOOKUP(E123,'Win Methods'!$C$4:$F$4992,4,FALSE) -> 0.5 | G123: main-3 | H123: =VLOOKUP(G123,'Win Methods'!$C$4:$F$4992,4,FALSE) -> 1 | I123: main-10 | J123: =VLOOKUP(I123,'Win Methods'!$C$4:$F$4992,4,FALSE) -> 1 | L123: =VLOOKUP(K123,'Win Methods'!$C$4:$F$4992,4,FALSE) -> 0 | N123: =VLOOKUP(M123,'Win Methods'!$C$4:$F$4992,4,FALSE) -> 0 | P123: =VLOOKUP(O123,'Win Methods'!$C$4:$F$4992,4,FALSE) -> 0 | R123: =VLOOKUP(Q123,'Win Methods'!$C$4:$F$4992,4,FALSE) -> 0 | T123: =VLOOKUP(S123,'Win Methods'!$C$4:$F$4992,4,FALSE) -> 0 | V123: =VLOOKUP(U123,'Win Methods'!$C$4:$F$4992,4,FALSE) -> 0 | X123: =VLOOKUP(W123,'Win Methods'!$C$4:$F$4992,4,FALSE) -> 0 | Y123: =E123&"|"&G123&"|"&I123&"|"&K123&"|"&M123&"|"&O123&"|"&Q123&"|"&S123&"|"&U123&"|"&W123 &" x "&D123 -> main-2|main-3|main-10||||||| x 20
B124: 121 | C124: =(F124+H124+J124+L124+N124+P124+R124+T124+V124+X124)*D124 -> 44 | D124: 20 | E124: main-0 | F124: =VLOOKUP(E124,'Win Methods'!$C$4:$F$4992,4,FALSE) -> 0.1 | G124: main-0 | H124: =VLOOKUP(G124,'Win Methods'!$C$4:$F$4992,4,FALSE) -> 0.1 | I124: main-12 | J124: =VLOOKUP(I124,'Win Methods'!$C$4:$F$4992,4,FALSE) -> 2 | L124: =VLOOKUP(K124,'Win Methods'!$C$4:$F$4992,4,FALSE) -> 0 | N124: =VLOOKUP(M124,'Win Methods'!$C$4:$F$4992,4,FALSE) -> 0 | P124: =VLOOKUP(O124,'Win Methods'!$C$4:$F$4992,4,FALSE) -> 0 | R124: =VLOOKUP(Q124,'Win Methods'!$C$4:$F$4992,4,FALSE) -> 0 | T124: =VLOOKUP(S124,'Win Methods'!$C$4:$F$4992,4,FALSE) -> 0 | V124: =VLOOKUP(U124,'Win Methods'!$C$4:$F$4992,4,FALSE) -> 0 | X124: =VLOOKUP(W124,'Win Methods'!$C$4:$F$4992,4,FALSE) -> 0 | Y124: =E124&"|"&G124&"|"&I124&"|"&K124&"|"&M124&"|"&O124&"|"&Q124&"|"&S124&"|"&U124&"|"&W124 &" x "&D124 -> main-0|main-0|main-12||||||| x 20
B125: 122 | C125: =(F125+H125+J125+L125+N125+P125+R125+T125+V125+X125)*D125 -> 8 | D125: 20 | E125: main-0 | F125: =VLOOKUP(E125,'Win Methods'!$C$4:$F$4992,4,FALSE) -> 0.1 | G125: main-0 | H125: =VLOOKUP(G125,'Win Methods'!$C$4:$F$4992,4,FALSE) -> 0.1 | I125: main-1 | J125: =VLOOKUP(I125,'Win Methods'!$C$4:$F$4992,4,FALSE) -> 0.2 | L125: =VLOOKUP(K125,'Win Methods'!$C$4:$F$4992,4,FALSE) -> 0 | N125: =VLOOKUP(M125,'Win Methods'!$C$4:$F$4992,4,FALSE) -> 0 | P125: =VLOOKUP(O125,'Win Methods'!$C$4:$F$4992,4,FALSE) -> 0 | R125: =VLOOKUP(Q125,'Win Methods'!$C$4:$F$4992,4,FALSE) -> 0 | T125: =VLOOKUP(S125,'Win Methods'!$C$4:$F$4992,4,FALSE) -> 0 | V125: =VLOOKUP(U125,'Win Methods'!$C$4:$F$4992,4,FALSE) -> 0 | X125: =VLOOKUP(W125,'Win Methods'!$C$4:$F$4992,4,FALSE) -> 0 | Y125: =E125&"|"&G125&"|"&I125&"|"&K125&"|"&M125&"|"&O125&"|"&Q125&"|"&S125&"|"&U125&"|"&W125 &" x "&D125 -> main-0|main-0|main-1||||||| x 20
B126: 123 | C126: =(F126+H126+J126+L126+N126+P126+R126+T126+V126+X126)*D126 -> 26 | D126: 20 | E126: main-0 | F126: =VLOOKUP(E126,'Win Methods'!$C$4:$F$4992,4,FALSE) -> 0.1 | G126: main-1 | H126: =VLOOKUP(G126,'Win Methods'!$C$4:$F$4992,4,FALSE) -> 0.2 | I126: main-2 | J126: =VLOOKUP(I126,'Win Methods'!$C$4:$F$4992,4,FALSE) -> 0.5 | K126: main-2 | L126: =VLOOKUP(K126,'Win Methods'!$C$4:$F$4992,4,FALSE) -> 0.5 | N126: =VLOOKUP(M126,'Win Methods'!$C$4:$F$4992,4,FALSE) -> 0 | P126: =VLOOKUP(O126,'Win Methods'!$C$4:$F$4992,4,FALSE) -> 0 | R126: =VLOOKUP(Q126,'Win Methods'!$C$4:$F$4992,4,FALSE) -> 0 | T126: =VLOOKUP(S126,'Win Methods'!$C$4:$F$4992,4,FALSE) -> 0 | V126: =VLOOKUP(U126,'Win Methods'!$C$4:$F$4992,4,FALSE) -> 0 | X126: =VLOOKUP(W126,'Win Methods'!$C$4:$F$4992,4,FALSE) -> 0 | Y126: =E126&"|"&G126&"|"&I126&"|"&K126&"|"&M126&"|"&O126&"|"&Q126&"|"&S126&"|"&U126&"|"&W126 &" x "&D126 -> main-0|main-1|main-2|main-2|||||| x 20
B127: 124 | C127: =(F127+H127+J127+L127+N127+P127+R127+T127+V127+X127)*D127 -> 40 | D127: 20 | E127: main-0 | F127: =VLOOKUP(E127,'Win Methods'!$C$4:$F$4992,4,FALSE) -> 0.1 | G127: main-1 | H127: =VLOOKUP(G127,'Win Methods'!$C$4:$F$4992,4,FALSE) -> 0.2 | I127: main-1 | J127: =VLOOKUP(I127,'Win Methods'!$C$4:$F$4992,4,FALSE) -> 0.2 | K127: main-4 | L127: =VLOOKUP(K127,'Win Methods'!$C$4:$F$4992,4,FALSE) -> 1.5 | N127: =VLOOKUP(M127,'Win Methods'!$C$4:$F$4992,4,FALSE) -> 0 | P127: =VLOOKUP(O127,'Win Methods'!$C$4:$F$4992,4,FALSE) -> 0 | R127: =VLOOKUP(Q127,'Win Methods'!$C$4:$F$4992,4,FALSE) -> 0 | T127: =VLOOKUP(S127,'Win Methods'!$C$4:$F$4992,4,FALSE) -> 0 | V127: =VLOOKUP(U127,'Win Methods'!$C$4:$F$4992,4,FALSE) -> 0 | X127: =VLOOKUP(W127,'Win Methods'!$C$4:$F$4992,4,FALSE) -> 0 | Y127: =E127&"|"&G127&"|"&I127&"|"&K127&"|"&M127&"|"&O127&"|"&Q127&"|"&S127&"|"&U127&"|"&W127 &" x "&D127 -> main-0|main-1|main-1|main-4|||||| x 20
B128: 125 | C128: =(F128+H128+J128+L128+N128+P128+R128+T128+V128+X128)*D128 -> 28 | D128: 20 | E128: main-0 | F128: =VLOOKUP(E128,'Win Methods'!$C$4:$F$4992,4,FALSE) -> 0.1 | G128: main-0 | H128: =VLOOKUP(G128,'Win Methods'!$C$4:$F$4992,4,FALSE) -> 0.1 | I128: main-1 | J128: =VLOOKUP(I128,'Win Methods'!$C$4:$F$4992,4,FALSE) -> 0.2 | K128: main-10 | L128: =VLOOKUP(K128,'Win Methods'!$C$4:$F$4992,4,FALSE) -> 1 | N128: =VLOOKUP(M128,'Win Methods'!$C$4:$F$4992,4,FALSE) -> 0 | P128: =VLOOKUP(O128,'Win Methods'!$C$4:$F$4992,4,FALSE) -> 0 | R128: =VLOOKUP(Q128,'Win Methods'!$C$4:$F$4992,4,FALSE) -> 0 | T128: =VLOOKUP(S128,'Win Methods'!$C$4:$F$4992,4,FALSE) -> 0 | V128: =VLOOKUP(U128,'Win Methods'!$C$4:$F$4992,4,FALSE) -> 0 | X128: =VLOOKUP(W128,'Win Methods'!$C$4:$F$4992,4,FALSE) -> 0 | Y128: =E128&"|"&G128&"|"&I128&"|"&K128&"|"&M128&"|"&O128&"|"&Q128&"|"&S128&"|"&U128&"|"&W128 &" x "&D128 -> main-0|main-0|main-1|main-10|||||| x 20
B129: 126 | C129: =(F129+H129+J129+L129+N129+P129+R129+T129+V129+X129)*D129 -> 10 | D129: 20 | E129: main-0 | F129: =VLOOKUP(E129,'Win Methods'!$C$4:$F$4992,4,FALSE) -> 0.1 | G129: main-0 | H129: =VLOOKUP(G129,'Win Methods'!$C$4:$F$4992,4,FALSE) -> 0.1 | I129: main-0 | J129: =VLOOKUP(I129,'Win Methods'!$C$4:$F$4992,4,FALSE) -> 0.1 | K129: main-1 | L129: =VLOOKUP(K129,'Win Methods'!$C$4:$F$4992,4,FALSE) -> 0.2 | N129: =VLOOKUP(M129,'Win Methods'!$C$4:$F$4992,4,FALSE) -> 0 | P129: =VLOOKUP(O129,'Win Methods'!$C$4:$F$4992,4,FALSE) -> 0 | R129: =VLOOKUP(Q129,'Win Methods'!$C$4:$F$4992,4,FALSE) -> 0 | T129: =VLOOKUP(S129,'Win Methods'!$C$4:$F$4992,4,FALSE) -> 0 | V129: =VLOOKUP(U129,'Win Methods'!$C$4:$F$4992,4,FALSE) -> 0 | X129: =VLOOKUP(W129,'Win Methods'!$C$4:$F$4992,4,FALSE) -> 0 | Y129: =E129&"|"&G129&"|"&I129&"|"&K129&"|"&M129&"|"&O129&"|"&Q129&"|"&S129&"|"&U129&"|"&W129 &" x "&D129 -> main-0|main-0|main-0|main-1|||||| x 20
B130: 127 | C130: =(F130+H130+J130+L130+N130+P130+R130+T130+V130+X130)*D130 -> 12 | D130: 20 | E130: main-0 | F130: =VLOOKUP(E130,'Win Methods'!$C$4:$F$4992,4,FALSE) -> 0.1 | G130: main-0 | H130: =VLOOKUP(G130,'Win Methods'!$C$4:$F$4992,4,FALSE) -> 0.1 | I130: main-1 | J130: =VLOOKUP(I130,'Win Methods'!$C$4:$F$4992,4,FALSE) -> 0.2 | K130: main-1 | L130: =VLOOKUP(K130,'Win Methods'!$C$4:$F$4992,4,FALSE) -> 0.2 | N130: =VLOOKUP(M130,'Win Methods'!$C$4:$F$4992,4,FALSE) -> 0 | P130: =VLOOKUP(O130,'Win Methods'!$C$4:$F$4992,4,FALSE) -> 0 | R130: =VLOOKUP(Q130,'Win Methods'!$C$4:$F$4992,4,FALSE) -> 0 | T130: =VLOOKUP(S130,'Win Methods'!$C$4:$F$4992,4,FALSE) -> 0 | V130: =VLOOKUP(U130,'Win Methods'!$C$4:$F$4992,4,FALSE) -> 0 | X130: =VLOOKUP(W130,'Win Methods'!$C$4:$F$4992,4,FALSE) -> 0 | Y130: =E130&"|"&G130&"|"&I130&"|"&K130&"|"&M130&"|"&O130&"|"&Q130&"|"&S130&"|"&U130&"|"&W130 &" x "&D130 -> main-0|main-0|main-1|main-1|||||| x 20
B131: 128 | C131: =(F131+H131+J131+L131+N131+P131+R131+T131+V131+X131)*D131 -> 48 | D131: 20 | E131: main-0 | F131: =VLOOKUP(E131,'Win Methods'!$C$4:$F$4992,4,FALSE) -> 0.1 | G131: main-0 | H131: =VLOOKUP(G131,'Win Methods'!$C$4:$F$4992,4,FALSE) -> 0.1 | I131: main-1 | J131: =VLOOKUP(I131,'Win Methods'!$C$4:$F$4992,4,FALSE) -> 0.2 | K131: main-30 | L131: =VLOOKUP(K131,'Win Methods'!$C$4:$F$4992,4,FALSE) -> 2 | N131: =VLOOKUP(M131,'Win Methods'!$C$4:$F$4992,4,FALSE) -> 0 | P131: =VLOOKUP(O131,'Win Methods'!$C$4:$F$4992,4,FALSE) -> 0 | R131: =VLOOKUP(Q131,'Win Methods'!$C$4:$F$4992,4,FALSE) -> 0 | T131: =VLOOKUP(S131,'Win Methods'!$C$4:$F$4992,4,FALSE) -> 0 | V131: =VLOOKUP(U131,'Win Methods'!$C$4:$F$4992,4,FALSE) -> 0 | X131: =VLOOKUP(W131,'Win Methods'!$C$4:$F$4992,4,FALSE) -> 0 | Y131: =E131&"|"&G131&"|"&I131&"|"&K131&"|"&M131&"|"&O131&"|"&Q131&"|"&S131&"|"&U131&"|"&W131 &" x "&D131 -> main-0|main-0|main-1|main-30|||||| x 20
B132: 129 | C132: =(F132+H132+J132+L132+N132+P132+R132+T132+V132+X132)*D132 -> 22 | D132: 20 | E132: main-0 | F132: =VLOOKUP(E132,'Win Methods'!$C$4:$F$4992,4,FALSE) -> 0.1 | G132: main-0 | H132: =VLOOKUP(G132,'Win Methods'!$C$4:$F$4992,4,FALSE) -> 0.1 | I132: main-1 | J132: =VLOOKUP(I132,'Win Methods'!$C$4:$F$4992,4,FALSE) -> 0.2 | K132: main-1 | L132: =VLOOKUP(K132,'Win Methods'!$C$4:$F$4992,4,FALSE) -> 0.2 | M132: main-2 | N132: =VLOOKUP(M132,'Win Methods'!$C$4:$F$4992,4,FALSE) -> 0.5 | P132: =VLOOKUP(O132,'Win Methods'!$C$4:$F$4992,4,FALSE) -> 0 | R132: =VLOOKUP(Q132,'Win Methods'!$C$4:$F$4992,4,FALSE) -> 0 | T132: =VLOOKUP(S132,'Win Methods'!$C$4:$F$4992,4,FALSE) -> 0 | V132: =VLOOKUP(U132,'Win Methods'!$C$4:$F$4992,4,FALSE) -> 0 | X132: =VLOOKUP(W132,'Win Methods'!$C$4:$F$4992,4,FALSE) -> 0 | Y132: =E132&"|"&G132&"|"&I132&"|"&K132&"|"&M132&"|"&O132&"|"&Q132&"|"&S132&"|"&U132&"|"&W132 &" x "&D132 -> main-0|main-0|main-1|main-1|main-2||||| x 20
B133: 130 | C133: =(F133+H133+J133+L133+N133+P133+R133+T133+V133+X133)*D133 -> 58 | D133: 20 | E133: main-0 | F133: =VLOOKUP(E133,'Win Methods'!$C$4:$F$4992,4,FALSE) -> 0.1 | G133: main-0 | H133: =VLOOKUP(G133,'Win Methods'!$C$4:$F$4992,4,FALSE) -> 0.1 | I133: main-1 | J133: =VLOOKUP(I133,'Win Methods'!$C$4:$F$4992,4,FALSE) -> 0.2 | K133: main-10 | L133: =VLOOKUP(K133,'Win Methods'!$C$4:$F$4992,4,FALSE) -> 1 | M133: main-20 | N133: =VLOOKUP(M133,'Win Methods'!$C$4:$F$4992,4,FALSE) -> 1.5 | P133: =VLOOKUP(O133,'Win Methods'!$C$4:$F$4992,4,FALSE) -> 0 | R133: =VLOOKUP(Q133,'Win Methods'!$C$4:$F$4992,4,FALSE) -> 0 | T133: =VLOOKUP(S133,'Win Methods'!$C$4:$F$4992,4,FALSE) -> 0 | V133: =VLOOKUP(U133,'Win Methods'!$C$4:$F$4992,4,FALSE) -> 0 | X133: =VLOOKUP(W133,'Win Methods'!$C$4:$F$4992,4,FALSE) -> 0 | Y133: =E133&"|"&G133&"|"&I133&"|"&K133&"|"&M133&"|"&O133&"|"&Q133&"|"&S133&"|"&U133&"|"&W133 &" x "&D133 -> main-0|main-0|main-1|main-10|main-20||||| x 20
B134: 131 | C134: =(F134+H134+J134+L134+N134+P134+R134+T134+V134+X134)*D134 -> 11 | D134: 1 | E134: main-10 | F134: =VLOOKUP(E134,'Win Methods'!$C$4:$F$4992,4,FALSE) -> 1 | G134: bonusA-0 | H134: =VLOOKUP(G134,'Win Methods'!$C$4:$F$4992,4,FALSE) -> 10 | J134: =VLOOKUP(I134,'Win Methods'!$C$4:$F$4992,4,FALSE) -> 0 | L134: =VLOOKUP(K134,'Win Methods'!$C$4:$F$4992,4,FALSE) -> 0 | N134: =VLOOKUP(M134,'Win Methods'!$C$4:$F$4992,4,FALSE) -> 0 | P134: =VLOOKUP(O134,'Win Methods'!$C$4:$F$4992,4,FALSE) -> 0 | R134: =VLOOKUP(Q134,'Win Methods'!$C$4:$F$4992,4,FALSE) -> 0 | T134: =VLOOKUP(S134,'Win Methods'!$C$4:$F$4992,4,FALSE) -> 0 | V134: =VLOOKUP(U134,'Win Methods'!$C$4:$F$4992,4,FALSE) -> 0 | X134: =VLOOKUP(W134,'Win Methods'!$C$4:$F$4992,4,FALSE) -> 0 | Y134: =E134&"|"&G134&"|"&I134&"|"&K134&"|"&M134&"|"&O134&"|"&Q134&"|"&S134&"|"&U134&"|"&W134 &" x "&D134 -> main-10|bonusA-0|||||||| x 1
B135: 132 | C135: =(F135+H135+J135+L135+N135+P135+R135+T135+V135+X135)*D135 -> 15.1 | D135: 1 | E135: main-0 | F135: =VLOOKUP(E135,'Win Methods'!$C$4:$F$4992,4,FALSE) -> 0.1 | G135: bonusA-1 | H135: =VLOOKUP(G135,'Win Methods'!$C$4:$F$4992,4,FALSE) -> 15 | J135: =VLOOKUP(I135,'Win Methods'!$C$4:$F$4992,4,FALSE) -> 0 | L135: =VLOOKUP(K135,'Win Methods'!$C$4:$F$4992,4,FALSE) -> 0 | N135: =VLOOKUP(M135,'Win Methods'!$C$4:$F$4992,4,FALSE) -> 0 | P135: =VLOOKUP(O135,'Win Methods'!$C$4:$F$4992,4,FALSE) -> 0 | R135: =VLOOKUP(Q135,'Win Methods'!$C$4:$F$4992,4,FALSE) -> 0 | T135: =VLOOKUP(S135,'Win Methods'!$C$4:$F$4992,4,FALSE) -> 0 | V135: =VLOOKUP(U135,'Win Methods'!$C$4:$F$4992,4,FALSE) -> 0 | X135: =VLOOKUP(W135,'Win Methods'!$C$4:$F$4992,4,FALSE) -> 0 | Y135: =E135&"|"&G135&"|"&I135&"|"&K135&"|"&M135&"|"&O135&"|"&Q135&"|"&S135&"|"&U135&"|"&W135 &" x "&D135 -> main-0|bonusA-1|||||||| x 1
B136: 133 | C136: =(F136+H136+J136+L136+N136+P136+R136+T136+V136+X136)*D136 -> 16.5 | D136: 1 | E136: main-11 | F136: =VLOOKUP(E136,'Win Methods'!$C$4:$F$4992,4,FALSE) -> 1.5 | G136: bonusA-1 | H136: =VLOOKUP(G136,'Win Methods'!$C$4:$F$4992,4,FALSE) -> 15 | J136: =VLOOKUP(I136,'Win Methods'!$C$4:$F$4992,4,FALSE) -> 0 | L136: =VLOOKUP(K136,'Win Methods'!$C$4:$F$4992,4,FALSE) -> 0 | N136: =VLOOKUP(M136,'Win Methods'!$C$4:$F$4992,4,FALSE) -> 0 | P136: =VLOOKUP(O136,'Win Methods'!$C$4:$F$4992,4,FALSE) -> 0 | R136: =VLOOKUP(Q136,'Win Methods'!$C$4:$F$4992,4,FALSE) -> 0 | T136: =VLOOKUP(S136,'Win Methods'!$C$4:$F$4992,4,FALSE) -> 0 | V136: =VLOOKUP(U136,'Win Methods'!$C$4:$F$4992,4,FALSE) -> 0 | X136: =VLOOKUP(W136,'Win Methods'!$C$4:$F$4992,4,FALSE) -> 0 | Y136: =E136&"|"&G136&"|"&I136&"|"&K136&"|"&M136&"|"&O136&"|"&Q136&"|"&S136&"|"&U136&"|"&W136 &" x "&D136 -> main-11|bonusA-1|||||||| x 1
B137: 134 | C137: =(F137+H137+J137+L137+N137+P137+R137+T137+V137+X137)*D137 -> 17 | D137: 1 | E137: main-30 | F137: =VLOOKUP(E137,'Win Methods'!$C$4:$F$4992,4,FALSE) -> 2 | G137: bonusA-1 | H137: =VLOOKUP(G137,'Win Methods'!$C$4:$F$4992,4,FALSE) -> 15 | J137: =VLOOKUP(I137,'Win Methods'!$C$4:$F$4992,4,FALSE) -> 0 | L137: =VLOOKUP(K137,'Win Methods'!$C$4:$F$4992,4,FALSE) -> 0 | N137: =VLOOKUP(M137,'Win Methods'!$C$4:$F$4992,4,FALSE) -> 0 | P137: =VLOOKUP(O137,'Win Methods'!$C$4:$F$4992,4,FALSE) -> 0 | R137: =VLOOKUP(Q137,'Win Methods'!$C$4:$F$4992,4,FALSE) -> 0 | T137: =VLOOKUP(S137,'Win Methods'!$C$4:$F$4992,4,FALSE) -> 0 | V137: =VLOOKUP(U137,'Win Methods'!$C$4:$F$4992,4,FALSE) -> 0 | X137: =VLOOKUP(W137,'Win Methods'!$C$4:$F$4992,4,FALSE) -> 0 | Y137: =E137&"|"&G137&"|"&I137&"|"&K137&"|"&M137&"|"&O137&"|"&Q137&"|"&S137&"|"&U137&"|"&W137 &" x "&D137 -> main-30|bonusA-1|||||||| x 1
...

Sheet Win Methods
B2: Win methods
B3: Methods | C3: Win Methods | D3: Symbol | E3: Quantity | F3: Prize | G3: Multiplier | H3: Note
C4: 0
B5: 1 | C5: main-0 | D5: 0,1,2,3 | E5: 3 | F5: =VLOOKUP(D5,'Pay Table'!$C$3:$M$13,E5-1,FALSE)*G5*Frequency!$N$7 -> 0.1 | G5: 1
B6: 2 | C6: main-1 | D6: 0,1,2,3 | E6: 4 | F6: =VLOOKUP(D6,'Pay Table'!$C$3:$M$13,E6-1,FALSE)*G6*Frequency!$N$7 -> 0.2 | G6: 1
B7: 3 | C7: main-2 | D7: 0,1,2,3 | E7: 5 | F7: =VLOOKUP(D7,'Pay Table'!$C$3:$M$13,E7-1,FALSE)*G7*Frequency!$N$7 -> 0.5 | G7: 1
B8: 4 | C8: main-3 | D8: 0,1,2,3 | E8: 6 | F8: =VLOOKUP(D8,'Pay Table'!$C$3:$M$13,E8-1,FALSE)*G8*Frequency!$N$7 -> 1 | G8: 1
B9: 5 | C9: main-4 | D9: 0,1,2,3 | E9: 7 | F9: =VLOOKUP(D9,'Pay Table'!$C$3:$M$13,E9-1,FALSE)*G9*Frequency!$N$7 -> 1.5 | G9: 1
B10: 6 | C10: main-5 | D10: 0,1,2,3 | E10: 8 | F10: =VLOOKUP(D10,'Pay Table'!$C$3:$M$13,E10-1,FALSE)*G10*Frequency!$N$7 -> 2 | G10: 1
B11: 7 | C11: main-6 | D11: 0,1,2,3 | E11: 9 | F11: =VLOOKUP(D11,'Pay Table'!$C$3:$M$13,E11-1,FALSE)*G11*Frequency!$N$7 -> 2.5 | G11: 1
B12: 8 | C12: main-7 | D12: 0,1,2,3 | E12: 10 | F12: =VLOOKUP(D12,'Pay Table'!$C$3:$M$13,E12-1,FALSE)*G12*Frequency!$N$7 -> 3 | G12: 1
B13: 9 | C13: main-8 | D13: 0,1,2,3 | E13: 11 | F13: =VLOOKUP(D13,'Pay Table'!$C$3:$M$13,E13-1,FALSE)*G13*Frequency!$N$7 -> 5 | G13: 1
B14: 10 | C14: main-9 | D14: 0 | E14: 12 | F14: =VLOOKUP(D14,'Pay Table'!$C$3:$M$13,E14-1,FALSE)*G14*Frequency!$N$7 -> 10 | G14: 1
B15: 11 | C15: main-10 | D15: 4 | E15: 3 | F15: =VLOOKUP(D15,'Pay Table'!$C$3:$M$13,E15-1,FALSE)*G15*Frequency!$N$7 -> 1 | G15: 1
B16: 12 | C16: main-11 | D16: 4 | E16: 4 | F16: =VLOOKUP(D16,'Pay Table'!$C$3:$M$13,E16-1,FALSE)*G16*Frequency!$N$7 -> 1.5 | G16: 1
B17: 13 | C17: main-12 | D17: 4 | E17: 5 | F17: =VLOOKUP(D17,'Pay Table'!$C$3:$M$13,E17-1,FALSE)*G17*Frequency!$N$7 -> 2 | G17: 1
B18: 14 | C18: main-13 | D18: 4 | E18: 6 | F18: =VLOOKUP(D18,'Pay Table'!$C$3:$M$13,E18-1,FALSE)*G18*Frequency!$N$7 -> 5 | G18: 1
B19: 15 | C19: main-14 | D19: 4 | E19: 7 | F19: =VLOOKUP(D19,'Pay Table'!$C$3:$M$13,E19-1,FALSE)*G19*Frequency!$N$7 -> 10 | G19: 1
B20: 16 | C20: main-15 | D20: 4 | E20: 8 | F20: =VLOOKUP(D20,'Pay Table'!$C$3:$M$13,E20-1,FALSE)*G20*Frequency!$N$7 -> 15 | G20: 1
B21: 17 | C21: main-16 | D21: 4 | E21: 9 | F21: =VLOOKUP(D21,'Pay Table'!$C$3:$M$13,E21-1,FALSE)*G21*Frequency!$N$7 -> 20 | G21: 1
B22: 18 | C22: main-17 | D22: 4 | E22: 10 | F22: =VLOOKUP(D22,'Pay Table'!$C$3:$M$13,E22-1,FALSE)*G22*Frequency!$N$7 -> 50 | G22: 1
B23: 19 | C23: main-18 | D23: 4 | E23: 11 | F23: =VLOOKUP(D23,'Pay Table'!$C$3:$M$13,E23-1,FALSE)*G23*Frequency!$N$7 -> 100 | G23: 1
B24: 20 | C24: main-19 | D24: 4 | E24: 12 | F24: =VLOOKUP(D24,'Pay Table'!$C$3:$M$13,E24-1,FALSE)*G24*Frequency!$N$7 -> 200 | G24: 1
B25: 21 | C25: main-20 | D25: 5 | E25: 3 | F25: =VLOOKUP(D25,'Pay Table'!$C$3:$M$13,E25-1,FALSE)*G25*Frequency!$N$7 -> 1.5 | G25: 1
... B47: 43 | C47: main-42 | D47: 3 | E47: 12 | F47: =VLOOKUP(D47,'Pay Table'!$C$3:$M$13,E47-1,FALSE)*G47*Frequency!$N$7 -> 30 | G47: 1
B48: 224 | C48: freeplayA-0 | F48: {=SUM(VLOOKUP('Free Plays'!E3:AH3,Tiers!$B:$C,2,FALSE))*G48} -> 16.3 | G48: 1
B49: 225 | C49: freeplayA-1 | F49: {=SUM(VLOOKUP('Free Plays'!E4:AH4,Tiers!$B:$C,2,FALSE))*G49} -> 24.7 | G49: 1
B50: 226 | C50: freeplayA-2 | F50: {=SUM(VLOOKUP('Free Plays'!E5:AH5,Tiers!$B:$C,2,FALSE))*G50} -> 11.4 | G50: 1
B51: 227 | C51: freeplayA-3 | F51: {=SUM(VLOOKUP('Free Plays'!E6:AH6,Tiers!$B:$C,2,FALSE))*G51} -> 35 | G51: 1
B52: 228 | C52: freeplayA-4 | F52: {=SUM(VLOOKUP('Free Plays'!E7:AH7,Tiers!$B:$C,2,FALSE))*G52} -> 18.6 | G52: 1
B53: 229 | C53: freeplayA-5 | F53: {=SUM(VLOOKUP('Free Plays'!E8:AH8,Tiers!$B:$C,2,FALSE))*G53} -> 25.3 | G53: 1
B54: 230 | C54: freeplayA-6 | F54: {=SUM(VLOOKUP('Free Plays'!E9:AH9,Tiers!$B:$C,2,FALSE))*G54} -> 29 | G54: 1
B55: 231 | C55: freeplayA-7 | F55: {=SUM(VLOOKUP('Free Plays'!E10:AH10,Tiers!$B:$C,2,FALSE))*G55} -> 41.9 | G55: 1
B56: 232 | C56: freeplayA-8 | F56: {=SUM(VLOOKUP('Free Plays'!E11:AH11,Tiers!$B:$C,2,FALSE))*G56} -> 27 | G56: 1
B57: 233 | C57: freeplayA-9 | F57: {=SUM(VLOOKUP('Free Plays'!E12:AH12,Tiers!$B:$C,2,FALSE))*G57} -> 44.1 | G57: 1
B58: 234 | C58: freeplayA-10 | F58: {=SUM(VLOOKUP('Free Plays'!E13:AH13,Tiers!$B:$C,2,FALSE))*G58} -> 16 | G58: 1
B59: 235 | C59: freeplayA-11 | F59: {=SUM(VLOOKUP('Free Plays'!E14:AH14,Tiers!$B:$C,2,FALSE))*G59} -> 25.4 | G59: 1
... B72: 248 | C72: freeplayA-24 | F72: {=SUM(VLOOKUP('Free Plays'!E27:AH27,Tiers!$B:$C,2,FALSE))*G72} -> 87.9 | G72: 1
B73: 249 | C73: freeplayA-25 | F73: {=SUM(VLOOKUP('Free Plays'!E28:AH28,Tiers!$B:$C,2,FALSE))*G73} -> 58.6 | G73: 1 | H73: Trigger Bonus
B74: 250 | C74: freeplayA-26 | F74: {=SUM(VLOOKUP('Free Plays'!E29:AH29,Tiers!$B:$C,2,FALSE))*G74} -> 72.8 | G74: 1 | H74: Trigger Bonus
B75: 251 | C75: freeplayA-27 | F75: {=SUM(VLOOKUP('Free Plays'!E30:AH30,Tiers!$B:$C,2,FALSE))*G75} -> 56 | G75: 1 | H75: Trigger Bonus
B76: 252 | C76: freeplayA-28 | F76: {=SUM(VLOOKUP('Free Plays'!E31:AH31,Tiers!$B:$C,2,FALSE))*G76} -> 44.1 | G76: 1 | H76: Trigger Bonus
B77: 253 | C77: freeplayA-29 | F77: {=SUM(VLOOKUP('Free Plays'!E32:AH32,Tiers!$B:$C,2,FALSE))*G77} -> 81.5 | G77: 1 | H77: Trigger Bonus
B78: 254 | C78: freeplayA-30 | F78: {=SUM(VLOOKUP('Free Plays'!E33:AH33,Tiers!$B:$C,2,FALSE))*G78} -> 46.9 | G78: 1 | H78: Trigger Bonus
B79: 348 | C79: bonusA-0 | F79: =VLOOKUP(C79,'Pay Table'!$B:$C,2,FALSE)*G79*Frequency!$N$7 -> 10 | G79: 1 | H79: SSJ
B80: 349 | C80: bonusA-1 | F80: =VLOOKUP(C80,'Pay Table'!$B:$C,2,FALSE)*G80*Frequency!$N$7 -> 15 | G80: 1
B81: 350 | C81: bonusA-2 | F81: =VLOOKUP(C81,'Pay Table'!$B:$C,2,FALSE)*G81*Frequency!$N$7 -> 20 | G81: 1
B82: 351 | C82: bonusA-3 | F82: =VLOOKUP(C82,'Pay Table'!$B:$C,2,FALSE)*G82*Frequency!$N$7 -> 25 | G82: 1
B83: 352 | C83: bonusA-4 | F83: =VLOOKUP(C83,'Pay Table'!$B:$C,2,FALSE)*G83*Frequency!$N$7 -> 30 | G83: 1
B84: 353 | C84: bonusA-5 | F84: =VLOOKUP(C84,'Pay Table'!$B:$C,2,FALSE)*G84*Frequency!$N$7 -> 50 | G84: 1
B85: 354 | C85: bonusA-6 | F85: =VLOOKUP(C85,'Pay Table'!$B:$C,2,FALSE)*G85*Frequency!$N$7 -> 100 | G85: 1

Sheet Free Plays
B2: TIER | C2: ROUNDS | D2: WIN METHOD | E2: ROUND 1 | F2: ROUND 2 | G2: ROUND 3 | H2: ROUND 4 | I2: ROUND 5 | J2: ROUND 6 | K2: ROUND 7 | L2: ROUND 8 | M2: ROUND 9 | N2: ROUND 10 | O2: ROUND 11 | P2: ROUND 12 | Q2: ROUND 13 | R2: ROUND 14 | S2: ROUND 15 | T2: ROUND 16 | U2: ROUND 17 | V2: ROUND 18 | W2: ROUND 19 | X2: ROUND 20 | Y2: ROUND 21 | Z2: ROUND 22 | AA2: ROUND 23 | AB2: ROUND 24 | AC2: ROUND 25 | AD2: ROUND 26 | AE2: ROUND 27 | AF2: ROUND 28 | AG2: ROUND 29 | AH2: ROUND 30
B3: 224 | C3: 20 | D3: freeplayA-0 | E3: 48 | F3: 3 | G3: 45 | H3: 6 | I3: 8 | J3: 7 | K3: 1 | L3: 3 | M3: 23 | N3: 46
B4: 225 | C4: 20 | D4: freeplayA-1 | E4: 7 | F4: 9 | G4: 1 | H4: 13 | I4: 44 | J4: 108 | K4: 45 | L4: 46 | M4: 15 | N4: 2
B5: 226 | C5: 20 | D5: freeplayA-2 | E5: 3 | F5: 1 | G5: 23 | H5: 46 | I5: 76 | J5: 2 | K5: 6 | L5: 3 | M5: 3 | N5: 2
B6: 227 | C6: 20 | D6: freeplayA-3 | E6: 12 | F6: 4 | G6: 32 | H6: 31 | I6: 14 | J6: 111 | K6: 4 | L6: 6 | M6: 46 | N6: 1 | O6: 9
B7: 228 | C7: 20 | D7: freeplayA-4 | E7: 13 | F7: 3 | G7: 3 | H7: 5 | I7: 6 | J7: 5 | K7: 8 | L7: 1 | M7: 5 | N7: 14 | O7: 11
B8: 229 | C8: 20 | D8: freeplayA-5 | E8: 1 | F8: 1 | G8: 46 | H8: 82 | I8: 51 | J8: 2 | K8: 108 | L8: 5 | M8: 31 | N8: 13 | O8: 7
B9: 230 | C9: 20 | D9: freeplayA-6 | E9: 85 | F9: 48 | G9: 45 | H9: 44 | I9: 77 | J9: 53 | K9: 122 | L9: 3 | M9: 50 | N9: 46 | O9: 47
B10: 231 | C10: 20 | D10: freeplayA-7 | E10: 1 | F10: 74 | G10: 76 | H10: 13 | I10: 9 | J10: 77 | K10: 2 | L10: 46 | M10: 91 | N10: 81 | O10: 14 | P10: 12
B11: 232 | C11: 20 | D11: freeplayA-8 | E11: 53 | F11: 48 | G11: 48 | H11: 46 | I11: 76 | J11: 7 | K11: 77 | L11: 85 | M11: 3 | N11: 76 | O11: 5 | P11: 1
B12: 233 | C12: 20 | D12: freeplayA-9 | E12: 44 | F12: 108 | G12: 5 | H12: 6 | I12: 14 | J12: 12 | K12: 8 | L12: 53 | M12: 46 | N12: 61 | O12: 77 | P12: 49
B13: 234 | C13: 20 | D13: freeplayA-10 | E13: 3 | F13: 2 | G13: 3 | H13: 2 | I13: 3 | J13: 5 | K13: 9 | L13: 45 | M13: 77 | N13: 1 | O13: 2 | P13: 13 | Q13: 0
B14: 235 | C14: 20 | D14: freeplayA-11 | E14: 77 | F14: 2 | G14: 46 | H14: 23 | I14: 9 | J14: 45 | K14: 4 | L14: 46 | M14: 47 | N14: 1 | O14: 23 | P14: 46 | Q14: 76
B15: 236 | C15: 20 | D15: freeplayA-12 | E15: 7 | F15: 1 | G15: 21 | H15: 22 | I15: 48 | J15: 12 | K15: 14 | L15: 3 | M15: 108 | N15: 44 | O15: 15 | P15: 47 | Q15: 14
B16: 237 | C16: 20 | D16: freeplayA-13 | E16: 12 | F16: 1 | G16: 3 | H16: 1 | I16: 21 | J16: 76 | K16: 1 | L16: 5 | M16: 2 | N16: 64 | O16: 3 | P16: 45 | Q16: 82
B17: 238 | C17: 20 | D17: freeplayA-14 | E17: 3 | F17: 45 | G17: 6 | H17: 1 | I17: 3 | J17: 77 | K17: 9 | L17: 6 | M17: 1 | N17: 12 | O17: 46 | P17: 46 | Q17: 44
B18: 239 | C18: 20 | D18: freeplayA-15 | E18: 1 | F18: 3 | G18: 13 | H18: 2 | I18: 4 | J18: 12 | K18: 1 | L18: 11 | M18: 59 | N18: 13 | O18: 45 | P18: 47 | Q18: 77 | R18: 53
B19: 240 | C19: 20 | D19: freeplayA-16 | E19: 2 | F19: 23 | G19: 46 | H19: 3 | I19: 64 | J19: 108 | K19: 4 | L19: 44 | M19: 48 | N19: 14 | O19: 59 | P19: 13 | Q19: 9 | R19: 50
B20: 241 | C20: 20 | D20: freeplayA-17 | E20: 1 | F20: 5 | G20: 6 | H20: 4 | I20: 5 | J20: 1 | K20: 13 | L20: 3 | M20: 5 | N20: 1 | O20: 23 | P20: 46 | Q20: 76 | R20: 74
B21: 242 | C21: 20 | D21: freeplayA-18 | E21: 49 | F21: 3 | G21: 7 | H21: 76 | I21: 1 | J21: 108 | K21: 7 | L21: 46 | M21: 48 | N21: 50 | O21: 91 | P21: 44 | Q21: 74 | R21: 85
B22: 243 | C22: 20 | D22: freeplayA-19 | E22: 2 | F22: 46 | G22: 52 | H22: 5 | I22: 11 | J22: 14 | K22: 9 | L22: 45 | M22: 49 | N22: 77 | O22: 2 | P22: 45 | Q22: 61 | R22: 23
B23: 244 | C23: 20 | D23: freeplayA-20 | E23: 6 | F23: 50 | G23: 51 | H23: 59 | I23: 82 | J23: 111 | K23: 4 | L23: 50 | M23: 13 | N23: 9 | O23: 108 | P23: 122 | Q23: 2 | R23: 53 | S23: 91
B24: 245 | C24: 20 | D24: freeplayA-21 | E24: 5 | F24: 77 | G24: 9 | H24: 1 | I24: 81 | J24: 48 | K24: 46 | L24: 47 | M24: 46 | N24: 76 | O24: 15 | P24: 3 | Q24: 46 | R24: 90 | S24: 76
B25: 246 | C25: 20 | D25: freeplayA-22 | E25: 12 | F25: 13 | G25: 13 | H25: 14 | I25: 3 | J25: 49 | K25: 3 | L25: 11 | M25: 1 | N25: 84 | O25: 59 | P25: 77 | Q25: 23 | R25: 15 | S25: 3
B26: 247 | C26: 20 | D26: freeplayA-23 | E26: 111 | F26: 1 | G26: 76 | H26: 111 | I26: 108 | J26: 7 | K26: 108 | L26: 77 | M26: 111 | N26: 8 | O26: 2 | P26: 49 | Q26: 2 | R26: 31 | S26: 32 | T26: 11
B27: 248 | C27: 20 | D27: freeplayA-24 | E27: 13 | F27: 9 | G27: 7 | H27: 5 | I27: 2 | J27: 2 | K27: 21 | L27: 32 | M27: 11 | N27: 55 | O27: 84 | P27: 50 | Q27: 108 | R27: 127 | S27: 108 | T27: 76
B28: 249 | C28: 20 | D28: freeplayA-25 | E28: 21 | F28: 46 | G28: 4 | H28: 22 | I28: 1 | J28: 108 | K28: 22 | L28: 3 | M28: 1 | N28: 3 | O28: 72 | P28: 45 | Q28: 44 | R28: 350
B29: 250 | C29: 20 | D29: freeplayA-26 | E29: 1 | F29: 14 | G29: 61 | H29: 77 | I29: 1 | J29: 44 | K29: 23 | L29: 4 | M29: 85 | N29: 11 | O29: 46 | P29: 77 | Q29: 76 | R29: 351
B30: 251 | C30: 20 | D30: freeplayA-27 | E30: 12 | F30: 45 | G30: 3 | H30: 14 | I30: 46 | J30: 108 | K30: 49 | L30: 5 | M30: 3 | N30: 5 | O30: 59 | P30: 45 | Q30: 77 | R30: 352
B31: 252 | C31: 20 | D31: freeplayA-28 | E31: 47 | F31: 59 | G31: 6 | H31: 108 | I31: 1 | J31: 44 | K31: 1 | L31: 6 | M31: 31 | N31: 49 | O31: 76 | P31: 32 | Q31: 47 | R31: 350
B32: 253 | C32: 20 | D32: freeplayA-29 | E32: 77 | F32: 53 | G32: 76 | H32: 127 | I32: 21 | J32: 3 | K32: 5 | L32: 8 | M32: 32 | N32: 108 | O32: 127 | P32: 108 | Q32: 53 | R32: 351
B33: 254 | C33: 20 | D33: freeplayA-30 | E33: 53 | F33: 11 | G33: 13 | H33: 46 | I33: 47 | J33: 21 | K33: 2 | L33: 8 | M33: 76 | N33: 11 | O33: 5 | P33: 2 | Q33: 3 | R33: 352

Sheet Pay Table
C2: Paytable
B3: Symbols | C3: Code | D3: 3 | E3: 4 | F3: 5 | G3: 6 | H3: 7 | I3: 8 | J3: 9 | K3: 10 | L3: 11 | M3: 12
B4: A | C4: 0 | D4: 0.1 | E4: 0.2 | F4: 0.5 | G4: 1 | H4: 1.5 | I4: 2 | J4: 2.5 | K4: 3 | L4: 5 | M4: 10
B5: B | C5: 1 | D5: 0.1 | E5: 0.2 | F5: 0.5 | G5: 1 | H5: 1.5 | I5: 2 | J5: 2.5 | K5: 3 | L5: 5 | M5: 15
B6: C | C6: 2 | D6: 0.1 | E6: 0.2 | F6: 0.5 | G6: 1 | H6: 1.5 | I6: 2 | J6: 2.5 | K6: 3 | L6: 5 | M6: 20
B7: D | C7: 3 | D7: 0.1 | E7: 0.2 | F7: 0.5 | G7: 1 | H7: 1.5 | I7: 2 | J7: 2.5 | K7: 3 | L7: 5 | M7: 30
B8: E | C8: 4 | D8: 1 | E8: 1.5 | F8: 2 | G8: 5 | H8: 10 | I8: 15 | J8: 20 | K8: 50 | L8: 100 | M8: 200
B9: F | C9: 5 | D9: 1.5 | E9: 2 | F9: 5 | G9: 10 | H9: 15 | I9: 20 | J9: 50 | K9: 100 | L9: 200 | M9: 500
B10: G | C10: 6 | D10: 2 | E10: 5 | F10: 10 | G10: 15 | H10: 20 | I10: 50 | J10: 100 | K10: 200 | L10: 500 | M10: 1000
B11: A/B/C/D | C11: 0,1,2,3 | D11: 0.1 | E11: 0.2 | F11: 0.5 | G11: 1 | H11: 1.5 | I11: 2 | J11: 2.5 | K11: 3 | L11: 5 | M11: -
B14: Bonus | C14: Prize
B15: bonusA-0 | C15: 10
B16: bonusA-1 | C16: 15
B17: bonusA-2 | C17: 20
B18: bonusA-3 | C18: 25
B19: bonusA-4 | C19: 30
B20: bonusA-5 | C20: 50
B21: bonusA-6 | C21: 100

Sheet Data Analysis
B1: TIER | C1: WIN METHOD | D1: PRIZE | E1: ODDS UP | F1: Value | G1: 20x Multi Freq | H1: 20x Multi Value | I1: >0 to <5 value | J1: >=5 to <10 value | K1: >=10 to <25 value | L1: >= 25 value | M1: >0 to <1 | N1: >0 to <1 value | O1: =1 -> 1 | P1: 1 value | Q1: >1 to 2 | R1: >1 to 2 value | S1: >2 to 5 | T1: >2 to 5 value | U1: >5 to 10 | V1: >5 to 10 value | W1: >10 to 20 | X1: >10 to 20 value | Y1: >20 to 30 | Z1: >20 to 30 value | AA1: >30 to 50 | AB1: >30 to 50 value | AC1: >50 to 100 | AD1: >50 to 100 value | AE1: >100 | AF1: >100 value | AG1: Freeplay Freq | AH1: Bonus Freq | AI1: Instant Freq | AJ1: is Combo Win | AK1: Combo Win Freq | AL1: Combo Win Value | AM1: is Wild | AN1: Wild Freq | AO1: Wild Value | AP1: is Normal Wild | AQ1: Normal Wild Freq | AR1: Normal Wild Value | AS1: is Multi Wild | AT1: Multi Wild Freq | AU1: Multi Wild Value | AV1: freeplayA Count | AW1: freeplayA Value | AX1: FreeplayB Count | AY1: FreeplayB Value | AZ1: FreeplayC Count | BA1: FreeplayC Value | BB1: FreeplayD Count | BC1: FreeplayD Value | BD1: bonusA Count | BE1: bonusA Value | BF1: BonusB Count | BG1: BonusB Value | BH1: BonusC Count | BI1: BonuC Value | BJ1: is Instant Freq | BK1: Instant Value | BL1: Freeplay rounds | BM1: Human read part1 | BN1: Human read part2 | BO1: MSE | BP1: Freeplay Multi | BQ1: Bonus Multi | BR1: Instant Multi | BS1: sum of Free game rounds
B2: =Tiers!B3 -> 0 | C2: =Tiers!Y3 -> ||||||||| x 1 | D2: =Tiers!C3 -> 0 | E2: =Frequency!E4 -> 1466392 | F2: =E2*D2 -> 0 | G2: =IF(Tiers!D3>1,'Data Analysis'!E2,0) -> 0 | H2: =G2*D2 -> 0 | I2: =IF(AND(D2/Summary!$C$4>0, D2/Summary!$C$4<5),E2,0) * D2 -> 0 | J2: =IF(AND(D2/Summary!$C$4>= 5, D2/Summary!$C$4<10),E2,0) * D2 -> 0 | K2: =IF(AND(D2/Summary!$C$4>=10, D2/Summary!$C$4<25),E2,0)*D2 -> 0 | L2: =IF(D2/Summary!$C$4>=25,E2,0)*D2 -> 0 | M2: =IF(AND(D2/Summary!$C$4>0, D2/Summary!$C$4<1),E2,0) -> 0 | N2: =IF(M2>0,D2*E2,0) -> 0 | O2: =IF(D2/Summary!$C$4=1,1,0)*E2 -> 0 | P2: =IF(O2>0,D2*E2,0) -> 0 | Q2: =IF(AND(D2/Summary!$C$4>1, D2/Summary!$C$4<=2),1,0)*E2 -> 0 | R2: =IF(Q2>0,D2*E2,0) -> 0 | S2: =IF(AND(D2/Summary!$C$4>2,D2/Summary!$C$4<=5),1,0)*E2 -> 0 | T2: =IF(S2>0,D2*E2,0) -> 0 | U2: =IF(AND(D2/Summary!$C$4>5, D2/Summary!$C$4<=10),1,0)*E2 -> 0 | V2: =IF(U2>0,D2*E2,0) -> 0 | W2: =IF(AND(D2/Summary!$C$4>10, D2/Summary!$C$4<=20),1,0)*E2 -> 0 | X2: =IF(W2>0,D2*E2,0) -> 0 | Y2: =IF(AND(D2/Summary!$C$4>20, D2/Summary!$C$4<=30),1,0)*E2 -> 0 | Z2: =IF(Y2>0,D2*E2,0) -> 0 | AA2: =IF(AND(D2/Summary!$C$4>30, D2/Summary!$C$4<=50),1,0)*E2 -> 0 | AB2: =IF(AA2>0,D2*E2,0) -> 0 | AC2: =IF(AND(D2/Summary!$C$4>50, D2/Summary!$C$4<=100),1,0)*E2 -> 0 | AD2: =IF(AC2>0,D2*E2,0) -> 0 | AE2: =IF(D2/Summary!$C$4>100,1,0)*E2 -> 0 | AF2: =IF(AE2>0,D2*E2,0) -> 0 | AG2: =IF(AV2>0,E2,0) -> 0 | AH2: =IF(BD2>0,E2,0) -> 0 | AI2: =IF(BJ2>0,E2,0) -> 0 | AJ2: =IF(ISNUMBER(SEARCH("|||||||||",C2)),0,1) -> 0 | AK2: =IF(AJ2=1, E2,0) -> 0 | AL2: =IF(AK2>0,D2*E2,0) -> 0 | AM2: =IF(ISNUMBER(SEARCH("Wild",C2)),1,0) -> 0 | AN2: =IF(AM2=1, E2,0) -> 0 | AO2: =IF(AN2>0,D2*E2,0) -> 0 | AP2: =IF(ISNUMBER(SEARCH("Wild-",C2)),1,0) -> 0 | AQ2: =IF(AP2=1, E2,0) -> 0 | AR2: =IF(AQ2>0,D2*E2,0) -> 0 | AS2: =IF(ISNUMBER(SEARCH("WildX",C2)),1,0) -> 0 | AT2: =IF(AS2=1, E2,0) -> 0 | AU2: =IF(AT2>0,D2*E2,0) -> 0 | AV2: =IF(ISNUMBER(SEARCH("freeplayA",C2)),E2,0) -> 0 | AW2: =AV2*D2 -> 0 | AX2: =IF(ISNUMBER(SEARCH("FreePlayB",C2)),E2,0) -> 0 | AY2: =AX2*D2 -> 0 | AZ2: =IF(ISNUMBER(SEARCH("FreePlayC",C2)),E2,0) -> 0 | BA2: =AZ2*D2 -> 0 | BB2: =IF(ISNUMBER(SEARCH("FreePlayD",C2)),E2,0) -> 0 | BC2: =BB2*D2 -> 0 | BD2: =IF(ISNUMBER(SEARCH("bonusA",C2)),E2,0) -> 0 | BE2: =BD2*D2 -> 0 | BF2: =IF(ISNUMBER(SEARCH("BonusB",C2)),E2,0) -> 0 | BG2: =BF2*D2 -> 0 | BH2: =IF(ISNUMBER(SEARCH("BonusC",C2)),E2,0) -> 0 | BI2: =BH2*D2 -> 0 | BJ2: =IF(ISNUMBER(SEARCH("Instant",C2)),E2,0) -> 0 | BK2: =BJ2*D2 -> 0 | BL2: 0 | BM2: =IF(D2 < $D$367, $C$367, IF(D2 = $D$368, $C$368, IF(D2 < $D$369, $C$369, IF(D2 < $D$370, $C$370, IF(D2 < $D$371, $C$371, $C$372))))) -> Less than Stake | BN2: =IF(AV2 > 0,$C$376, IF(AX2 > 0,$C$377, IF(AZ2 > 0,$C$378, IF(BB2 > 0,$C$379, IF(BD2 > 0,$C$380, IF(BF2 > 0,$C$381, IF(BH2 > 0,$C$382, IF(BJ2 > 0,$C$383, IF(ISNUMBER(SEARCH("|||||||||",C2)), $C$384,$C$385))))))))) -> Single Win | BO2: =(D2/Summary!$C$4-Summary!$C$8)^2*E2 -> 1010197.4 | BP2: =IF(AV2=1, E2*D2,0) -> 0 | BQ2: =IF(BD2=1, E2*D2,0) -> 0 | BR2: =IF(BJ2=1, D2*E2,0) -> 0 | BS2: =IF(BL2>0,BL2*E2,0) -> 0
B3: =Tiers!B4 -> 1 | C3: =Tiers!Y4 -> main-0||||||||| x 1 | D3: =Tiers!C4 -> 0.1 | E3: =Frequency!E5 -> 70000 | F3: =E3*D3 -> 7000 | G3: =IF(Tiers!D4>1,'Data Analysis'!E3,0) -> 0 | H3: =G3*D3 -> 0 | I3: =IF(AND(D3/Summary!$C$4>0, D3/Summary!$C$4<5),E3,0) * D3 -> 7000 | J3: =IF(AND(D3/Summary!$C$4>= 5, D3/Summary!$C$4<10),E3,0) * D3 -> 0 | K3: =IF(AND(D3/Summary!$C$4>=10, D3/Summary!$C$4<25),E3,0)*D3 -> 0 | L3: =IF(D3/Summary!$C$4>=25,E3,0)*D3 -> 0 | M3: =IF(AND(D3/Summary!$C$4>0, D3/Summary!$C$4<1),E3,0) -> 70000 | N3: =IF(M3>0,D3*E3,0) -> 7000 | O3: =IF(D3/Summary!$C$4=1,1,0)*E3 -> 0 | P3: =IF(O3>0,D3*E3,0) -> 0 | Q3: =IF(AND(D3/Summary!$C$4>1, D3/Summary!$C$4<=2),1,0)*E3 -> 0 | R3: =IF(Q3>0,D3*E3,0) -> 0 | S3: =IF(AND(D3/Summary!$C$4>2,D3/Summary!$C$4<=5),1,0)*E3 -> 0 | T3: =IF(S3>0,D3*E3,0) -> 0 | U3: =IF(AND(D3/Summary!$C$4>5, D3/Summary!$C$4<=10),1,0)*E3 -> 0 | V3: =IF(U3>0,D3*E3,0) -> 0 | W3: =IF(AND(D3/Summary!$C$4>10, D3/Summary!$C$4<=20),1,0)*E3 -> 0 | X3: =IF(W3>0,D3*E3,0) -> 0 | Y3: =IF(AND(D3/Summary!$C$4>20, D3/Summary!$C$4<=30),1,0)*E3 -> 0 | Z3: =IF(Y3>0,D3*E3,0) -> 0 | AA3: =IF(AND(D3/Summary!$C$4>30, D3/Summary!$C$4<=50),1,0)*E3 -> 0 | AB3: =IF(AA3>0,D3*E3,0) -> 0 | AC3: =IF(AND(D3/Summary!$C$4>50, D3/Summary!$C$4<=100),1,0)*E3 -> 0 | AD3: =IF(AC3>0,D3*E3,0) -> 0 | AE3: =IF(D3/Summary!$C$4>100,1,0)*E3 -> 0 | AF3: =IF(AE3>0,D3*E3,0) -> 0 | AG3: =IF(AV3>0,E3,0) -> 0 | AH3: =IF(BD3>0,E3,0) -> 0 | AI3: =IF(BJ3>0,E3,0) -> 0 | AJ3: =IF(ISNUMBER(SEARCH("|||||||||",C3)),0,1) -> 0 | AK3: =IF(AJ3=1, E3,0) -> 0 | AL3: =IF(AK3>0,D3*E3,0) -> 0 | AM3: =IF(ISNUMBER(SEARCH("Wild",C3)),1,0) -> 0 | AN3: =IF(AM3=1, E3,0) -> 0 | AO3: =IF(AN3>0,D3*E3,0) -> 0 | AP3: =IF(ISNUMBER(SEARCH("Wild-",C3)),1,0) -> 0 | AQ3: =IF(AP3=1, E3,0) -> 0 | AR3: =IF(AQ3>0,D3*E3,0) -> 0 | AS3: =IF(ISNUMBER(SEARCH("WildX",C3)),1,0) -> 0 | AT3: =IF(AS3=1, E3,0) -> 0 | AU3: =IF(AT3>0,D3*E3,0) -> 0 | AV3: =IF(ISNUMBER(SEARCH("freeplayA",C3)),E3,0) -> 0 | AW3: =AV3*D3 -> 0 | AX3: =IF(ISNUMBER(SEARCH("FreePlayB",C3)),E3,0) -> 0 | AY3: =AX3*D3 -> 0 | AZ3: =IF(ISNUMBER(SEARCH("FreePlayC",C3)),E3,0) -> 0 | BA3: =AZ3*D3 -> 0 | BB3: =IF(ISNUMBER(SEARCH("FreePlayD",C3)),E3,0) -> 0 | BC3: =BB3*D3 -> 0 | BD3: =IF(ISNUMBER(SEARCH("bonusA",C3)),E3,0) -> 0 | BE3: =BD3*D3 -> 0 | BF3: =IF(ISNUMBER(SEARCH("BonusB",C3)),E3,0) -> 0 | BG3: =BF3*D3 -> 0 | BH3: =IF(ISNUMBER(SEARCH("BonusC",C3)),E3,0) -> 0 | BI3: =BH3*D3 -> 0 | BJ3: =IF(ISNUMBER(SEARCH("Instant",C3)),E3,0) -> 0 | BK3: =BJ3*D3 -> 0 | BL3: 0 | BM3: =IF(D3 < $D$367, $C$367, IF(D3 = $D$368, $C$368, IF(D3 < $D$369, $C$369, IF(D3 < $D$370, $C$370, IF(D3 < $D$371, $C$371, $C$372))))) -> Less than Stake | BN3: =IF(AV3 > 0,$C$376, IF(AX3 > 0,$C$377, IF(AZ3 > 0,$C$378, IF(BB3 > 0,$C$379, IF(BD3 > 0,$C$380, IF(BF3 > 0,$C$381, IF(BH3 > 0,$C$382, IF(BJ3 > 0,$C$383, IF(ISNUMBER(SEARCH("|||||||||",C3)), $C$384,$C$385))))))))) -> Single Win | BO3: =(D3/Summary!$C$4-Summary!$C$8)^2*E3 -> 37303 | BP3: =IF(AV3=1, E3*D3,0) -> 0 | BQ3: =IF(BD3=1, E3*D3,0) -> 0 | BR3: =IF(BJ3=1, D3*E3,0) -> 0 | BS3: =IF(BL3>0,BL3*E3,0) -> 0
B4: =Tiers!B5 -> 2 | C4: =Tiers!Y5 -> main-1||||||||| x 1 | D4: =Tiers!C5 -> 0.2 | E4: =Frequency!E6 -> 40003 | F4: =E4*D4 -> 8000.6 | G4: =IF(Tiers!D5>1,'Data Analysis'!E4,0) -> 0 | H4: =G4*D4 -> 0 | I4: =IF(AND(D4/Summary!$C$4>0, D4/Summary!$C$4<5),E4,0) * D4 -> 8000.6 | J4: =IF(AND(D4/Summary!$C$4>= 5, D4/Summary!$C$4<10),E4,0) * D4 -> 0 | K4: =IF(AND(D4/Summary!$C$4>=10, D4/Summary!$C$4<25),E4,0)*D4 -> 0 | L4: =IF(D4/Summary!$C$4>=25,E4,0)*D4 -> 0 | M4: =IF(AND(D4/Summary!$C$4>0, D4/Summary!$C$4<1),E4,0) -> 40003 | N4: =IF(M4>0,D4*E4,0) -> 8000.6 | O4: =IF(D4/Summary!$C$4=1,1,0)*E4 -> 0 | P4: =IF(O4>0,D4*E4,0) -> 0 | Q4: =IF(AND(D4/Summary!$C$4>1, D4/Summary!$C$4<=2),1,0)*E4 -> 0 | R4: =IF(Q4>0,D4*E4,0) -> 0 | S4: =IF(AND(D4/Summary!$C$4>2,D4/Summary!$C$4<=5),1,0)*E4 -> 0 | T4: =IF(S4>0,D4*E4,0) -> 0 | U4: =IF(AND(D4/Summary!$C$4>5, D4/Summary!$C$4<=10),1,0)*E4 -> 0 | V4: =IF(U4>0,D4*E4,0) -> 0 | W4: =IF(AND(D4/Summary!$C$4>10, D4/Summary!$C$4<=20),1,0)*E4 -> 0 | X4: =IF(W4>0,D4*E4,0) -> 0 | Y4: =IF(AND(D4/Summary!$C$4>20, D4/Summary!$C$4<=30),1,0)*E4 -> 0 | Z4: =IF(Y4>0,D4*E4,0) -> 0 | AA4: =IF(AND(D4/Summary!$C$4>30, D4/Summary!$C$4<=50),1,0)*E4 -> 0 | AB4: =IF(AA4>0,D4*E4,0) -> 0 | AC4: =IF(AND(D4/Summary!$C$4>50, D4/Summary!$C$4<=100),1,0)*E4 -> 0 | AD4: =IF(AC4>0,D4*E4,0) -> 0 | AE4: =IF(D4/Summary!$C$4>100,1,0)*E4 -> 0 | AF4: =IF(AE4>0,D4*E4,0) -> 0 | AG4: =IF(AV4>0,E4,0) -> 0 | AH4: =IF(BD4>0,E4,0) -> 0 | AI4: =IF(BJ4>0,E4,0) -> 0 | AJ4: =IF(ISNUMBER(SEARCH("|||||||||",C4)),0,1) -> 0 | AK4: =IF(AJ4=1, E4,0) -> 0 | AL4: =IF(AK4>0,D4*E4,0) -> 0 | AM4: =IF(ISNUMBER(SEARCH("Wild",C4)),1,0) -> 0 | AN4: =IF(AM4=1, E4,0) -> 0 | AO4: =IF(AN4>0,D4*E4,0) -> 0 | AP4: =IF(ISNUMBER(SEARCH("Wild-",C4)),1,0) -> 0 | AQ4: =IF(AP4=1, E4,0) -> 0 | AR4: =IF(AQ4>0,D4*E4,0) -> 0 | AS4: =IF(ISNUMBER(SEARCH("WildX",C4)),1,0) -> 0 | AT4: =IF(AS4=1, E4,0) -> 0 | AU4: =IF(AT4>0,D4*E4,0) -> 0 | AV4: =IF(ISNUMBER(SEARCH("freeplayA",C4)),E4,0) -> 0 | AW4: =AV4*D4 -> 0 | AX4: =IF(ISNUMBER(SEARCH("FreePlayB",C4)),E4,0) -> 0 | AY4: =AX4*D4 -> 0 | AZ4: =IF(ISNUMBER(SEARCH("FreePlayC",C4)),E4,0) -> 0 | BA4: =AZ4*D4 -> 0 | BB4: =IF(ISNUMBER(SEARCH("FreePlayD",C4)),E4,0) -> 0 | BC4: =BB4*D4 -> 0 | BD4: =IF(ISNUMBER(SEARCH("bonusA",C4)),E4,0) -> 0 | BE4: =BD4*D4 -> 0 | BF4: =IF(ISNUMBER(SEARCH("BonusB",C4)),E4,0) -> 0 | BG4: =BF4*D4 -> 0 | BH4: =IF(ISNUMBER(SEARCH("BonusC",C4)),E4,0) -> 0 | BI4: =BH4*D4 -> 0 | BJ4: =IF(ISNUMBER(SEARCH("Instant",C4)),E4,0) -> 0 | BK4: =BJ4*D4 -> 0 | BL4: 0 | BM4: =IF(D4 < $D$367, $C$367, IF(D4 = $D$368, $C$368, IF(D4 < $D$369, $C$369, IF(D4 < $D$370, $C$370, IF(D4 < $D$371, $C$371, $C$372))))) -> Less than Stake | BN4: =IF(AV4 > 0,$C$376, IF(AX4 > 0,$C$377, IF(AZ4 > 0,$C$378, IF(BB4 > 0,$C$379, IF(BD4 > 0,$C$380, IF(BF4 > 0,$C$381, IF(BH4 > 0,$C$382, IF(BJ4 > 0,$C$383, IF(ISNUMBER(SEARCH("|||||||||",C4)), $C$384,$C$385))))))))) -> Single Win | BO4: =(D4/Summary!$C$4-Summary!$C$8)^2*E4 -> 15877.191 | BP4: =IF(AV4=1, E4*D4,0) -> 0 | BQ4: =IF(BD4=1, E4*D4,0) -> 0 | BR4: =IF(BJ4=1, D4*E4,0) -> 0 | BS4: =IF(BL4>0,BL4*E4,0) -> 0
B5: =Tiers!B6 -> 3 | C5: =Tiers!Y6 -> main-2||||||||| x 1 | D5: =Tiers!C6 -> 0.5 | E5: =Frequency!E7 -> 20001 | F5: =E5*D5 -> 10000.5 | G5: =IF(Tiers!D6>1,'Data Analysis'!E5,0) -> 0 | H5: =G5*D5 -> 0 | I5: =IF(AND(D5/Summary!$C$4>0, D5/Summary!$C$4<5),E5,0) * D5 -> 10000.5 | J5: =IF(AND(D5/Summary!$C$4>= 5, D5/Summary!$C$4<10),E5,0) * D5 -> 0 | K5: =IF(AND(D5/Summary!$C$4>=10, D5/Summary!$C$4<25),E5,0)*D5 -> 0 | L5: =IF(D5/Summary!$C$4>=25,E5,0)*D5 -> 0 | M5: =IF(AND(D5/Summary!$C$4>0, D5/Summary!$C$4<1),E5,0) -> 20001 | N5: =IF(M5>0,D5*E5,0) -> 10000.5 | O5: =IF(D5/Summary!$C$4=1,1,0)*E5 -> 0 | P5: =IF(O5>0,D5*E5,0) -> 0 | Q5: =IF(AND(D5/Summary!$C$4>1, D5/Summary!$C$4<=2),1,0)*E5 -> 0 | R5: =IF(Q5>0,D5*E5,0) -> 0 | S5: =IF(AND(D5/Summary!$C$4>2,D5/Summary!$C$4<=5),1,0)*E5 -> 0 | T5: =IF(S5>0,D5*E5,0) -> 0 | U5: =IF(AND(D5/Summary!$C$4>5, D5/Summary!$C$4<=10),1,0)*E5 -> 0 | V5: =IF(U5>0,D5*E5,0) -> 0 | W5: =IF(AND(D5/Summary!$C$4>10, D5/Summary!$C$4<=20),1,0)*E5 -> 0 | X5: =IF(W5>0,D5*E5,0) -> 0 | Y5: =IF(AND(D5/Summary!$C$4>20, D5/Summary!$C$4<=30),1,0)*E5 -> 0 | Z5: =IF(Y5>0,D5*E5,0) -> 0 | AA5: =IF(AND(D5/Summary!$C$4>30, D5/Summary!$C$4<=50),1,0)*E5 -> 0 | AB5: =IF(AA5>0,D5*E5,0) -> 0 | AC5: =IF(AND(D5/Summary!$C$4>50, D5/Summary!$C$4<=100),1,0)*E5 -> 0 | AD5: =IF(AC5>0,D5*E5,0) -> 0 | AE5: =IF(D5/Summary!$C$4>100,1,0)*E5 -> 0 | AF5: =IF(AE5>0,D5*E5,0) -> 0 | AG5: =IF(AV5>0,E5,0) -> 0 | AH5: =IF(BD5>0,E5,0) -> 0 | AI5: =IF(BJ5>0,E5,0) -> 0 | AJ5: =IF(ISNUMBER(SEARCH("|||||||||",C5)),0,1) -> 0 | AK5: =IF(AJ5=1, E5,0) -> 0 | AL5: =IF(AK5>0,D5*E5,0) -> 0 | AM5: =IF(ISNUMBER(SEARCH("Wild",C5)),1,0) -> 0 | AN5: =IF(AM5=1, E5,0) -> 0 | AO5: =IF(AN5>0,D5*E5,0) -> 0 | AP5: =IF(ISNUMBER(SEARCH("Wild-",C5)),1,0) -> 0 | AQ5: =IF(AP5=1, E5,0) -> 0 | AR5: =IF(AQ5>0,D5*E5,0) -> 0 | AS5: =IF(ISNUMBER(SEARCH("WildX",C5)),1,0) -> 0 | AT5: =IF(AS5=1, E5,0) -> 0 | AU5: =IF(AT5>0,D5*E5,0) -> 0 | AV5: =IF(ISNUMBER(SEARCH("freeplayA",C5)),E5,0) -> 0 | AW5: =AV5*D5 -> 0 | AX5: =IF(ISNUMBER(SEARCH("FreePlayB",C5)),E5,0) -> 0 | AY5: =AX5*D5 -> 0 | AZ5: =IF(ISNUMBER(SEARCH("FreePlayC",C5)),E5,0) -> 0 | BA5: =AZ5*D5 -> 0 | BB5: =IF(ISNUMBER(SEARCH("FreePlayD",C5)),E5,0) -> 0 | BC5: =BB5*D5 -> 0 | BD5: =IF(ISNUMBER(SEARCH("bonusA",C5)),E5,0) -> 0 | BE5: =BD5*D5 -> 0 | BF5: =IF(ISNUMBER(SEARCH("BonusB",C5)),E5,0) -> 0 | BG5: =BF5*D5 -> 0 | BH5: =IF(ISNUMBER(SEARCH("BonusC",C5)),E5,0) -> 0 | BI5: =BH5*D5 -> 0 | BJ5: =IF(ISNUMBER(SEARCH("Instant",C5)),E5,0) -> 0 | BK5: =BJ5*D5 -> 0 | BL5: 0 | BM5: =IF(D5 < $D$367, $C$367, IF(D5 = $D$368, $C$368, IF(D5 < $D$369, $C$369, IF(D5 < $D$370, $C$370, IF(D5 < $D$371, $C$371, $C$372))))) -> Less than Stake | BN5: =IF(AV5 > 0,$C$376, IF(AX5 > 0,$C$377, IF(AZ5 > 0,$C$378, IF(BB5 > 0,$C$379, IF(BD5 > 0,$C$380, IF(BF5 > 0,$C$381, IF(BH5 > 0,$C$382, IF(BJ5 > 0,$C$383, IF(ISNUMBER(SEARCH("|||||||||",C5)), $C$384,$C$385))))))))) -> Single Win | BO5: =(D5/Summary!$C$4-Summary!$C$8)^2*E5 -> 2178.1089 | BP5: =IF(AV5=1, E5*D5,0) -> 0 | BQ5: =IF(BD5=1, E5*D5,0) -> 0 | BR5: =IF(BJ5=1, D5*E5,0) -> 0 | BS5: =IF(BL5>0,BL5*E5,0) -> 0
B6: =Tiers!B7 -> 4 | C6: =Tiers!Y7 -> main-3||||||||| x 1 | D6: =Tiers!C7 -> 1 | E6: =Frequency!E8 -> 66424 | F6: =E6*D6 -> 66424 | G6: =IF(Tiers!D7>1,'Data Analysis'!E6,0) -> 0 | H6: =G6*D6 -> 0 | I6: =IF(AND(D6/Summary!$C$4>0, D6/Summary!$C$4<5),E6,0) * D6 -> 66424 | J6: =IF(AND(D6/Summary!$C$4>= 5, D6/Summary!$C$4<10),E6,0) * D6 -> 0 | K6: =IF(AND(D6/Summary!$C$4>=10, D6/Summary!$C$4<25),E6,0)*D6 -> 0 | L6: =IF(D6/Summary!$C$4>=25,E6,0)*D6 -> 0 | M6: =IF(AND(D6/Summary!$C$4>0, D6/Summary!$C$4<1),E6,0) -> 0 | N6: =IF(M6>0,D6*E6,0) -> 0 | O6: =IF(D6/Summary!$C$4=1,1,0)*E6 -> 66424 | P6: =IF(O6>0,D6*E6,0) -> 66424 | Q6: =IF(AND(D6/Summary!$C$4>1, D6/Summary!$C$4<=2),1,0)*E6 -> 0 | R6: =IF(Q6>0,D6*E6,0) -> 0 | S6: =IF(AND(D6/Summary!$C$4>2,D6/Summary!$C$4<=5),1,0)*E6 -> 0 | T6: =IF(S6>0,D6*E6,0) -> 0 | U6: =IF(AND(D6/Summary!$C$4>5, D6/Summary!$C$4<=10),1,0)*E6 -> 0 | V6: =IF(U6>0,D6*E6,0) -> 0 | W6: =IF(AND(D6/Summary!$C$4>10, D6/Summary!$C$4<=20),1,0)*E6 -> 0 | X6: =IF(W6>0,D6*E6,0) -> 0 | Y6: =IF(AND(D6/Summary!$C$4>20, D6/Summary!$C$4<=30),1,0)*E6 -> 0 | Z6: =IF(Y6>0,D6*E6,0) -> 0 | AA6: =IF(AND(D6/Summary!$C$4>30, D6/Summary!$C$4<=50),1,0)*E6 -> 0 | AB6: =IF(AA6>0,D6*E6,0) -> 0 | AC6: =IF(AND(D6/Summary!$C$4>50, D6/Summary!$C$4<=100),1,0)*E6 -> 0 | AD6: =IF(AC6>0,D6*E6,0) -> 0 | AE6: =IF(D6/Summary!$C$4>100,1,0)*E6 -> 0 | AF6: =IF(AE6>0,D6*E6,0) -> 0 | AG6: =IF(AV6>0,E6,0) -> 0 | AH6: =IF(BD6>0,E6,0) -> 0 | AI6: =IF(BJ6>0,E6,0) -> 0 | AJ6: =IF(ISNUMBER(SEARCH("|||||||||",C6)),0,1) -> 0 | AK6: =IF(AJ6=1, E6,0) -> 0 | AL6: =IF(AK6>0,D6*E6,0) -> 0 | AM6: =IF(ISNUMBER(SEARCH("Wild",C6)),1,0) -> 0 | AN6: =IF(AM6=1, E6,0) -> 0 | AO6: =IF(AN6>0,D6*E6,0) -> 0 | AP6: =IF(ISNUMBER(SEARCH("Wild-",C6)),1,0) -> 0 | AQ6: =IF(AP6=1, E6,0) -> 0 | AR6: =IF(AQ6>0,D6*E6,0) -> 0 | AS6: =IF(ISNUMBER(SEARCH("WildX",C6)),1,0) -> 0 | AT6: =IF(AS6=1, E6,0) -> 0 | AU6: =IF(AT6>0,D6*E6,0) -> 0 | AV6: =IF(ISNUMBER(SEARCH("freeplayA",C6)),E6,0) -> 0 | AW6: =AV6*D6 -> 0 | AX6: =IF(ISNUMBER(SEARCH("FreePlayB",C6)),E6,0) -> 0 | AY6: =AX6*D6 -> 0 | AZ6: =IF(ISNUMBER(SEARCH("FreePlayC",C6)),E6,0) -> 0 | BA6: =AZ6*D6 -> 0 | BB6: =IF(ISNUMBER(SEARCH("FreePlayD",C6)),E6,0) -> 0 | BC6: =BB6*D6 -> 0 | BD6: =IF(ISNUMBER(SEARCH("bonusA",C6)),E6,0) -> 0 | BE6: =BD6*D6 -> 0 | BF6: =IF(ISNUMBER(SEARCH("BonusB",C6)),E6,0) -> 0 | BG6: =BF6*D6 -> 0 | BH6: =IF(ISNUMBER(SEARCH("BonusC",C6)),E6,0) -> 0 | BI6: =BH6*D6 -> 0 | BJ6: =IF(ISNUMBER(SEARCH("Instant",C6)),E6,0) -> 0 | BK6: =BJ6*D6 -> 0 | BL6: 0 | BM6: =IF(D6 < $D$367, $C$367, IF(D6 = $D$368, $C$368, IF(D6 < $D$369, $C$369, IF(D6 < $D$370, $C$370, IF(D6 < $D$371, $C$371, $C$372))))) -> Stake Back | BN6: =IF(AV6 > 0,$C$376, IF(AX6 > 0,$C$377, IF(AZ6 > 0,$C$378, IF(BB6 > 0,$C$379, IF(BD6 > 0,$C$380, IF(BF6 > 0,$C$381, IF(BH6 > 0,$C$382, IF(BJ6 > 0,$C$383, IF(ISNUMBER(SEARCH("|||||||||",C6)), $C$384,$C$385))))))))) -> Single Win | BO6: =(D6/Summary!$C$4-Summary!$C$8)^2*E6 -> 1919.6536 | BP6: =IF(AV6=1, E6*D6,0) -> 0 | BQ6: =IF(BD6=1, E6*D6,0) -> 0 | BR6: =IF(BJ6=1, D6*E6,0) -> 0 | BS6: =IF(BL6>0,BL6*E6,0) -> 0
B7: =Tiers!B8 -> 5 | C7: =Tiers!Y8 -> main-4||||||||| x 1 | D7: =Tiers!C8 -> 1.5 | E7: =Frequency!E9 -> 30000 | F7: =E7*D7 -> 45000 | G7: =IF(Tiers!D8>1,'Data Analysis'!E7,0) -> 0 | H7: =G7*D7 -> 0 | I7: =IF(AND(D7/Summary!$C$4>0, D7/Summary!$C$4<5),E7,0) * D7 -> 45000 | J7: =IF(AND(D7/Summary!$C$4>= 5, D7/Summary!$C$4<10),E7,0) * D7 -> 0 | K7: =IF(AND(D7/Summary!$C$4>=10, D7/Summary!$C$4<25),E7,0)*D7 -> 0 | L7: =IF(D7/Summary!$C$4>=25,E7,0)*D7 -> 0 | M7: =IF(AND(D7/Summary!$C$4>0, D7/Summary!$C$4<1),E7,0) -> 0 | N7: =IF(M7>0,D7*E7,0) -> 0 | O7: =IF(D7/Summary!$C$4=1,1,0)*E7 -> 0 | P7: =IF(O7>0,D7*E7,0) -> 0 | Q7: =IF(AND(D7/Summary!$C$4>1, D7/Summary!$C$4<=2),1,0)*E7 -> 30000 | R7: =IF(Q7>0,D7*E7,0) -> 45000 | S7: =IF(AND(D7/Summary!$C$4>2,D7/Summary!$C$4<=5),1,0)*E7 -> 0 | T7: =IF(S7>0,D7*E7,0) -> 0 | U7: =IF(AND(D7/Summary!$C$4>5, D7/Summary!$C$4<=10),1,0)*E7 -> 0 | V7: =IF(U7>0,D7*E7,0) -> 0 | W7: =IF(AND(D7/Summary!$C$4>10, D7/Summary!$C$4<=20),1,0)*E7 -> 0 | X7: =IF(W7>0,D7*E7,0) -> 0 | Y7: =IF(AND(D7/Summary!$C$4>20, D7/Summary!$C$4<=30),1,0)*E7 -> 0 | Z7: =IF(Y7>0,D7*E7,0) -> 0 | AA7: =IF(AND(D7/Summary!$C$4>30, D7/Summary!$C$4<=50),1,0)*E7 -> 0 | AB7: =IF(AA7>0,D7*E7,0) -> 0 | AC7: =IF(AND(D7/Summary!$C$4>50, D7/Summary!$C$4<=100),1,0)*E7 -> 0 | AD7: =IF(AC7>0,D7*E7,0) -> 0 | AE7: =IF(D7/Summary!$C$4>100,1,0)*E7 -> 0 | AF7: =IF(AE7>0,D7*E7,0) -> 0 | AG7: =IF(AV7>0,E7,0) -> 0 | AH7: =IF(BD7>0,E7,0) -> 0 | AI7: =IF(BJ7>0,E7,0) -> 0 | AJ7: =IF(ISNUMBER(SEARCH("|||||||||",C7)),0,1) -> 0 | AK7: =IF(AJ7=1, E7,0) -> 0 | AL7: =IF(AK7>0,D7*E7,0) -> 0 | AM7: =IF(ISNUMBER(SEARCH("Wild",C7)),1,0) -> 0 | AN7: =IF(AM7=1, E7,0) -> 0 | AO7: =IF(AN7>0,D7*E7,0) -> 0 | AP7: =IF(ISNUMBER(SEARCH("Wild-",C7)),1,0) -> 0 | AQ7: =IF(AP7=1, E7,0) -> 0 | AR7: =IF(AQ7>0,D7*E7,0) -> 0 | AS7: =IF(ISNUMBER(SEARCH("WildX",C7)),1,0) -> 0 | AT7: =IF(AS7=1, E7,0) -> 0 | AU7: =IF(AT7>0,D7*E7,0) -> 0 | AV7: =IF(ISNUMBER(SEARCH("freeplayA",C7)),E7,0) -> 0 | AW7: =AV7*D7 -> 0 | AX7: =IF(ISNUMBER(SEARCH("FreePlayB",C7)),E7,0) -> 0 | AY7: =AX7*D7 -> 0 | AZ7: =IF(ISNUMBER(SEARCH("FreePlayC",C7)),E7,0) -> 0 | BA7: =AZ7*D7 -> 0 | BB7: =IF(ISNUMBER(SEARCH("FreePlayD",C7)),E7,0) -> 0 | BC7: =BB7*D7 -> 0 | BD7: =IF(ISNUMBER(SEARCH("bonusA",C7)),E7,0) -> 0 | BE7: =BD7*D7 -> 0 | BF7: =IF(ISNUMBER(SEARCH("BonusB",C7)),E7,0) -> 0 | BG7: =BF7*D7 -> 0 | BH7: =IF(ISNUMBER(SEARCH("BonusC",C7)),E7,0) -> 0 | BI7: =BH7*D7 -> 0 | BJ7: =IF(ISNUMBER(SEARCH("Instant",C7)),E7,0) -> 0 | BK7: =BJ7*D7 -> 0 | BL7: 0 | BM7: =IF(D7 < $D$367, $C$367, IF(D7 = $D$368, $C$368, IF(D7 < $D$369, $C$369, IF(D7 < $D$370, $C$370, IF(D7 < $D$371, $C$371, $C$372))))) -> Standard Win | BN7: =IF(AV7 > 0,$C$376, IF(AX7 > 0,$C$377, IF(AZ7 > 0,$C$378, IF(BB7 > 0,$C$379, IF(BD7 > 0,$C$380, IF(BF7 > 0,$C$381, IF(BH7 > 0,$C$382, IF(BJ7 > 0,$C$383, IF(ISNUMBER(SEARCH("|||||||||",C7)), $C$384,$C$385))))))))) -> Single Win | BO7: =(D7/Summary!$C$4-Summary!$C$8)^2*E7 -> 13467 | BP7: =IF(AV7=1, E7*D7,0) -> 0 | BQ7: =IF(BD7=1, E7*D7,0) -> 0 | BR7: =IF(BJ7=1, D7*E7,0) -> 0 | BS7: =IF(BL7>0,BL7*E7,0) -> 0
B8: =Tiers!B9 -> 6 | C8: =Tiers!Y9 -> main-5||||||||| x 1 | D8: =Tiers!C9 -> 2 | E8: =Frequency!E10 -> 15000 | F8: =E8*D8 -> 30000 | G8: =IF(Tiers!D9>1,'Data Analysis'!E8,0) -> 0 | H8: =G8*D8 -> 0 | I8: =IF(AND(D8/Summary!$C$4>0, D8/Summary!$C$4<5),E8,0) * D8 -> 30000 | J8: =IF(AND(D8/Summary!$C$4>= 5, D8/Summary!$C$4<10),E8,0) * D8 -> 0 | K8: =IF(AND(D8/Summary!$C$4>=10, D8/Summary!$C$4<25),E8,0)*D8 -> 0 | L8: =IF(D8/Summary!$C$4>=25,E8,0)*D8 -> 0 | M8: =IF(AND(D8/Summary!$C$4>0, D8/Summary!$C$4<1),E8,0) -> 0 | N8: =IF(M8>0,D8*E8,0) -> 0 | O8: =IF(D8/Summary!$C$4=1,1,0)*E8 -> 0 | P8: =IF(O8>0,D8*E8,0) -> 0 | Q8: =IF(AND(D8/Summary!$C$4>1, D8/Summary!$C$4<=2),1,0)*E8 -> 15000 | R8: =IF(Q8>0,D8*E8,0) -> 30000 | S8: =IF(AND(D8/Summary!$C$4>2,D8/Summary!$C$4<=5),1,0)*E8 -> 0 | T8: =IF(S8>0,D8*E8,0) -> 0 | U8: =IF(AND(D8/Summary!$C$4>5, D8/Summary!$C$4<=10),1,0)*E8 -> 0 | V8: =IF(U8>0,D8*E8,0) -> 0 | W8: =IF(AND(D8/Summary!$C$4>10, D8/Summary!$C$4<=20),1,0)*E8 -> 0 | X8: =IF(W8>0,D8*E8,0) -> 0 | Y8: =IF(AND(D8/Summary!$C$4>20, D8/Summary!$C$4<=30),1,0)*E8 -> 0 | Z8: =IF(Y8>0,D8*E8,0) -> 0 | AA8: =IF(AND(D8/Summary!$C$4>30, D8/Summary!$C$4<=50),1,0)*E8 -> 0 | AB8: =IF(AA8>0,D8*E8,0) -> 0 | AC8: =IF(AND(D8/Summary!$C$4>50, D8/Summary!$C$4<=100),1,0)*E8 -> 0 | AD8: =IF(AC8>0,D8*E8,0) -> 0 | AE8: =IF(D8/Summary!$C$4>100,1,0)*E8 -> 0 | AF8: =IF(AE8>0,D8*E8,0) -> 0 | AG8: =IF(AV8>0,E8,0) -> 0 | AH8: =IF(BD8>0,E8,0) -> 0 | AI8: =IF(BJ8>0,E8,0) -> 0 | AJ8: =IF(ISNUMBER(SEARCH("|||||||||",C8)),0,1) -> 0 | AK8: =IF(AJ8=1, E8,0) -> 0 | AL8: =IF(AK8>0,D8*E8,0) -> 0 | AM8: =IF(ISNUMBER(SEARCH("Wild",C8)),1,0) -> 0 | AN8: =IF(AM8=1, E8,0) -> 0 | AO8: =IF(AN8>0,D8*E8,0) -> 0 | AP8: =IF(ISNUMBER(SEARCH("Wild-",C8)),1,0) -> 0 | AQ8: =IF(AP8=1, E8,0) -> 0 | AR8: =IF(AQ8>0,D8*E8,0) -> 0 | AS8: =IF(ISNUMBER(SEARCH("WildX",C8)),1,0) -> 0 | AT8: =IF(AS8=1, E8,0) -> 0 | AU8: =IF(AT8>0,D8*E8,0) -> 0 | AV8: =IF(ISNUMBER(SEARCH("freeplayA",C8)),E8,0) -> 0 | AW8: =AV8*D8 -> 0 | AX8: =IF(ISNUMBER(SEARCH("FreePlayB",C8)),E8,0) -> 0 | AY8: =AX8*D8 -> 0 | AZ8: =IF(ISNUMBER(SEARCH("FreePlayC",C8)),E8,0) -> 0 | BA8: =AZ8*D8 -> 0 | BB8: =IF(ISNUMBER(SEARCH("FreePlayD",C8)),E8,0) -> 0 | BC8: =BB8*D8 -> 0 | BD8: =IF(ISNUMBER(SEARCH("bonusA",C8)),E8,0) -> 0 | BE8: =BD8*D8 -> 0 | BF8: =IF(ISNUMBER(SEARCH("BonusB",C8)),E8,0) -> 0 | BG8: =BF8*D8 -> 0 | BH8: =IF(ISNUMBER(SEARCH("BonusC",C8)),E8,0) -> 0 | BI8: =BH8*D8 -> 0 | BJ8: =IF(ISNUMBER(SEARCH("Instant",C8)),E8,0) -> 0 | BK8: =BJ8*D8 -> 0 | BL8: 0 | BM8: =IF(D8 < $D$367, $C$367, IF(D8 = $D$368, $C$368, IF(D8 < $D$369, $C$369, IF(D8 < $D$370, $C$370, IF(D8 < $D$371, $C$371, $C$372))))) -> Standard Win | BN8: =IF(AV8 > 0,$C$376, IF(AX8 > 0,$C$377, IF(AZ8 > 0,$C$378, IF(BB8 > 0,$C$379, IF(BD8 > 0,$C$380, IF(BF8 > 0,$C$381, IF(BH8 > 0,$C$382, IF(BJ8 > 0,$C$383, IF(ISNUMBER(SEARCH("|||||||||",C8)), $C$384,$C$385))))))))) -> Single Win | BO8: =(D8/Summary!$C$4-Summary!$C$8)^2*E8 -> 20533.5 | BP8: =IF(AV8=1, E8*D8,0) -> 0 | BQ8: =IF(BD8=1, E8*D8,0) -> 0 | BR8: =IF(BJ8=1, D8*E8,0) -> 0 | BS8: =IF(BL8>0,BL8*E8,0) -> 0
B9: =Tiers!B10 -> 7 | C9: =Tiers!Y10 -> main-6||||||||| x 1 | D9: =Tiers!C10 -> 2.5 | E9: =Frequency!E11 -> 3000 | F9: =E9*D9 -> 7500 | G9: =IF(Tiers!D10>1,'Data Analysis'!E9,0) -> 0 | H9: =G9*D9 -> 0 | I9: =IF(AND(D9/Summary!$C$4>0, D9/Summary!$C$4<5),E9,0) * D9 -> 7500 | J9: =IF(AND(D9/Summary!$C$4>= 5, D9/Summary!$C$4<10),E9,0) * D9 -> 0 | K9: =IF(AND(D9/Summary!$C$4>=10, D9/Summary!$C$4<25),E9,0)*D9 -> 0 | L9: =IF(D9/Summary!$C$4>=25,E9,0)*D9 -> 0 | M9: =IF(AND(D9/Summary!$C$4>0, D9/Summary!$C$4<1),E9,0) -> 0 | N9: =IF(M9>0,D9*E9,0) -> 0 | O9: =IF(D9/Summary!$C$4=1,1,0)*E9 -> 0 | P9: =IF(O9>0,D9*E9,0) -> 0 | Q9: =IF(AND(D9/Summary!$C$4>1, D9/Summary!$C$4<=2),1,0)*E9 -> 0 | R9: =IF(Q9>0,D9*E9,0) -> 0 | S9: =IF(AND(D9/Summary!$C$4>2,D9/Summary!$C$4<=5),1,0)*E9 -> 3000 | T9: =IF(S9>0,D9*E9,0) -> 7500 | U9: =IF(AND(D9/Summary!$C$4>5, D9/Summary!$C$4<=10),1,0)*E9 -> 0 | V9: =IF(U9>0,D9*E9,0) -> 0 | W9: =IF(AND(D9/Summary!$C$4>10, D9/Summary!$C$4<=20),1,0)*E9 -> 0 | X9: =IF(W9>0,D9*E9,0) -> 0 | Y9: =IF(AND(D9/Summary!$C$4>20, D9/Summary!$C$4<=30),1,0)*E9 -> 0 | Z9: =IF(Y9>0,D9*E9,0) -> 0 | AA9: =IF(AND(D9/Summary!$C$4>30, D9/Summary!$C$4<=50),1,0)*E9 -> 0 | AB9: =IF(AA9>0,D9*E9,0) -> 0 | AC9: =IF(AND(D9/Summary!$C$4>50, D9/Summary!$C$4<=100),1,0)*E9 -> 0 | AD9: =IF(AC9>0,D9*E9,0) -> 0 | AE9: =IF(D9/Summary!$C$4>100,1,0)*E9 -> 0 | AF9: =IF(AE9>0,D9*E9,0) -> 0 | AG9: =IF(AV9>0,E9,0) -> 0 | AH9: =IF(BD9>0,E9,0) -> 0 | AI9: =IF(BJ9>0,E9,0) -> 0 | AJ9: =IF(ISNUMBER(SEARCH("|||||||||",C9)),0,1) -> 0 | AK9: =IF(AJ9=1, E9,0) -> 0 | AL9: =IF(AK9>0,D9*E9,0) -> 0 | AM9: =IF(ISNUMBER(SEARCH("Wild",C9)),1,0) -> 0 | AN9: =IF(AM9=1, E9,0) -> 0 | AO9: =IF(AN9>0,D9*E9,0) -> 0 | AP9: =IF(ISNUMBER(SEARCH("Wild-",C9)),1,0) -> 0 | AQ9: =IF(AP9=1, E9,0) -> 0 | AR9: =IF(AQ9>0,D9*E9,0) -> 0 | AS9: =IF(ISNUMBER(SEARCH("WildX",C9)),1,0) -> 0 | AT9: =IF(AS9=1, E9,0) -> 0 | AU9: =IF(AT9>0,D9*E9,0) -> 0 | AV9: =IF(ISNUMBER(SEARCH("freeplayA",C9)),E9,0) -> 0 | AW9: =AV9*D9 -> 0 | AX9: =IF(ISNUMBER(SEARCH("FreePlayB",C9)),E9,0) -> 0 | AY9: =AX9*D9 -> 0 | AZ9: =IF(ISNUMBER(SEARCH("FreePlayC",C9)),E9,0) -> 0 | BA9: =AZ9*D9 -> 0 | BB9: =IF(ISNUMBER(SEARCH("FreePlayD",C9)),E9,0) -> 0 | BC9: =BB9*D9 -> 0 | BD9: =IF(ISNUMBER(SEARCH("bonusA",C9)),E9,0) -> 0 | BE9: =BD9*D9 -> 0 | BF9: =IF(ISNUMBER(SEARCH("BonusB",C9)),E9,0) -> 0 | BG9: =BF9*D9 -> 0 | BH9: =IF(ISNUMBER(SEARCH("BonusC",C9)),E9,0) -> 0 | BI9: =BH9*D9 -> 0 | BJ9: =IF(ISNUMBER(SEARCH("Instant",C9)),E9,0) -> 0 | BK9: =BJ9*D9 -> 0 | BL9: 0 | BM9: =IF(D9 < $D$367, $C$367, IF(D9 = $D$368, $C$368, IF(D9 < $D$369, $C$369, IF(D9 < $D$370, $C$370, IF(D9 < $D$371, $C$371, $C$372))))) -> Standard Win | BN9: =IF(AV9 > 0,$C$376, IF(AX9 > 0,$C$377, IF(AZ9 > 0,$C$378, IF(BB9 > 0,$C$379, IF(BD9 > 0,$C$380, IF(BF9 > 0,$C$381, IF(BH9 > 0,$C$382, IF(BJ9 > 0,$C$383, IF(ISNUMBER(SEARCH("|||||||||",C9)), $C$384,$C$385))))))))) -> Single Win | BO9: =(D9/Summary!$C$4-Summary!$C$8)^2*E9 -> 8366.7 | BP9: =IF(AV9=1, E9*D9,0) -> 0 | BQ9: =IF(BD9=1, E9*D9,0) -> 0 | BR9: =IF(BJ9=1, D9*E9,0) -> 0 | BS9: =IF(BL9>0,BL9*E9,0) -> 0
B10: =Tiers!B11 -> 8 | C10: =Tiers!Y11 -> main-7||||||||| x 1 | D10: =Tiers!C11 -> 3 | E10: =Frequency!E12 -> 1000 | F10: =E10*D10 -> 3000 | G10: =IF(Tiers!D11>1,'Data Analysis'!E10,0) -> 0 | H10: =G10*D10 -> 0 | I10: =IF(AND(D10/Summary!$C$4>0, D10/Summary!$C$4<5),E10,0) * D10 -> 3000 | J10: =IF(AND(D10/Summary!$C$4>= 5, D10/Summary!$C$4<10),E10,0) * D10 -> 0 | K10: =IF(AND(D10/Summary!$C$4>=10, D10/Summary!$C$4<25),E10,0)*D10 -> 0 | L10: =IF(D10/Summary!$C$4>=25,E10,0)*D10 -> 0 | M10: =IF(AND(D10/Summary!$C$4>0, D10/Summary!$C$4<1),E10,0) -> 0 | N10: =IF(M10>0,D10*E10,0) -> 0 | O10: =IF(D10/Summary!$C$4=1,1,0)*E10 -> 0 | P10: =IF(O10>0,D10*E10,0) -> 0 | Q10: =IF(AND(D10/Summary!$C$4>1, D10/Summary!$C$4<=2),1,0)*E10 -> 0 | R10: =IF(Q10>0,D10*E10,0) -> 0 | S10: =IF(AND(D10/Summary!$C$4>2,D10/Summary!$C$4<=5),1,0)*E10 -> 1000 | T10: =IF(S10>0,D10*E10,0) -> 3000 | U10: =IF(AND(D10/Summary!$C$4>5, D10/Summary!$C$4<=10),1,0)*E10 -> 0 | V10: =IF(U10>0,D10*E10,0) -> 0 | W10: =IF(AND(D10/Summary!$C$4>10, D10/Summary!$C$4<=20),1,0)*E10 -> 0 | X10: =IF(W10>0,D10*E10,0) -> 0 | Y10: =IF(AND(D10/Summary!$C$4>20, D10/Summary!$C$4<=30),1,0)*E10 -> 0 | Z10: =IF(Y10>0,D10*E10,0) -> 0 | AA10: =IF(AND(D10/Summary!$C$4>30, D10/Summary!$C$4<=50),1,0)*E10 -> 0 | AB10: =IF(AA10>0,D10*E10,0) -> 0 | AC10: =IF(AND(D10/Summary!$C$4>50, D10/Summary!$C$4<=100),1,0)*E10 -> 0 | AD10: =IF(AC10>0,D10*E10,0) -> 0 | AE10: =IF(D10/Summary!$C$4>100,1,0)*E10 -> 0 | AF10: =IF(AE10>0,D10*E10,0) -> 0 | AG10: =IF(AV10>0,E10,0) -> 0 | AH10: =IF(BD10>0,E10,0) -> 0 | AI10: =IF(BJ10>0,E10,0) -> 0 | AJ10: =IF(ISNUMBER(SEARCH("|||||||||",C10)),0,1) -> 0 | AK10: =IF(AJ10=1, E10,0) -> 0 | AL10: =IF(AK10>0,D10*E10,0) -> 0 | AM10: =IF(ISNUMBER(SEARCH("Wild",C10)),1,0) -> 0 | AN10: =IF(AM10=1, E10,0) -> 0 | AO10: =IF(AN10>0,D10*E10,0) -> 0 | AP10: =IF(ISNUMBER(SEARCH("Wild-",C10)),1,0) -> 0 | AQ10: =IF(AP10=1, E10,0) -> 0 | AR10: =IF(AQ10>0,D10*E10,0) -> 0 | AS10: =IF(ISNUMBER(SEARCH("WildX",C10)),1,0) -> 0 | AT10: =IF(AS10=1, E10,0) -> 0 | AU10: =IF(AT10>0,D10*E10,0) -> 0 | AV10: =IF(ISNUMBER(SEARCH("freeplayA",C10)),E10,0) -> 0 | AW10: =AV10*D10 -> 0 | AX10: =IF(ISNUMBER(SEARCH("FreePlayB",C10)),E10,0) -> 0 | AY10: =AX10*D10 -> 0 | AZ10: =IF(ISNUMBER(SEARCH("FreePlayC",C10)),E10,0) -> 0 | BA10: =AZ10*D10 -> 0 | BB10: =IF(ISNUMBER(SEARCH("FreePlayD",C10)),E10,0) -> 0 | BC10: =BB10*D10 -> 0 | BD10: =IF(ISNUMBER(SEARCH("bonusA",C10)),E10,0) -> 0 | BE10: =BD10*D10 -> 0 | BF10: =IF(ISNUMBER(SEARCH("BonusB",C10)),E10,0) -> 0 | BG10: =BF10*D10 -> 0 | BH10: =IF(ISNUMBER(SEARCH("BonusC",C10)),E10,0) -> 0 | BI10: =BH10*D10 -> 0 | BJ10: =IF(ISNUMBER(SEARCH("Instant",C10)),E10,0) -> 0 | BK10: =BJ10*D10 -> 0 | BL10: 0 | BM10: =IF(D10 < $D$367, $C$367, IF(D10 = $D$368, $C$368, IF(D10 < $D$369, $C$369, IF(D10 < $D$370, $C$370, IF(D10 < $D$371, $C$371, $C$372))))) -> Standard Win | BN10: =IF(AV10 > 0,$C$376, IF(AX10 > 0,$C$377, IF(AZ10 > 0,$C$378, IF(BB10 > 0,$C$379, IF(BD10 > 0,$C$380, IF(BF10 > 0,$C$381, IF(BH10 > 0,$C$382, IF(BJ10 > 0,$C$383, IF(ISNUMBER(SEARCH("|||||||||",C10)), $C$384,$C$385))))))))) -> Single Win | BO10: =(D10/Summary!$C$4-Summary!$C$8)^2*E10 -> 4708.9 | BP10: =IF(AV10=1, E10*D10,0) -> 0 | BQ10: =IF(BD10=1, E10*D10,0) -> 0 | BR10: =IF(BJ10=1, D10*E10,0) -> 0 | BS10: =IF(BL10>0,BL10*E10,0) -> 0
B11: =Tiers!B12 -> 9 | C11: =Tiers!Y12 -> main-8||||||||| x 1 | D11: =Tiers!C12 -> 5 | E11: =Frequency!E13 -> 967 | F11: =E11*D11 -> 4835 | G11: =IF(Tiers!D12>1,'Data Analysis'!E11,0) -> 0 | H11: =G11*D11 -> 0 | I11: =IF(AND(D11/Summary!$C$4>0, D11/Summary!$C$4<5),E11,0) * D11 -> 0 | J11: =IF(AND(D11/Summary!$C$4>= 5, D11/Summary!$C$4<10),E11,0) * D11 -> 4835 | K11: =IF(AND(D11/Summary!$C$4>=10, D11/Summary!$C$4<25),E11,0)*D11 -> 0 | L11: =IF(D11/Summary!$C$4>=25,E11,0)*D11 -> 0 | M11: =IF(AND(D11/Summary!$C$4>0, D11/Summary!$C$4<1),E11,0) -> 0 | N11: =IF(M11>0,D11*E11,0) -> 0 | O11: =IF(D11/Summary!$C$4=1,1,0)*E11 -> 0 | P11: =IF(O11>0,D11*E11,0) -> 0 | Q11: =IF(AND(D11/Summary!$C$4>1, D11/Summary!$C$4<=2),1,0)*E11 -> 0 | R11: =IF(Q11>0,D11*E11,0) -> 0 | S11: =IF(AND(D11/Summary!$C$4>2,D11/Summary!$C$4<=5),1,0)*E11 -> 967 | T11: =IF(S11>0,D11*E11,0) -> 4835 | U11: =IF(AND(D11/Summary!$C$4>5, D11/Summary!$C$4<=10),1,0)*E11 -> 0 | V11: =IF(U11>0,D11*E11,0) -> 0 | W11: =IF(AND(D11/Summary!$C$4>10, D11/Summary!$C$4<=20),1,0)*E11 -> 0 | X11: =IF(W11>0,D11*E11,0) -> 0 | Y11: =IF(AND(D11/Summary!$C$4>20, D11/Summary!$C$4<=30),1,0)*E11 -> 0 | Z11: =IF(Y11>0,D11*E11,0) -> 0 | AA11: =IF(AND(D11/Summary!$C$4>30, D11/Summary!$C$4<=50),1,0)*E11 -> 0 | AB11: =IF(AA11>0,D11*E11,0) -> 0 | AC11: =IF(AND(D11/Summary!$C$4>50, D11/Summary!$C$4<=100),1,0)*E11 -> 0 | AD11: =IF(AC11>0,D11*E11,0) -> 0 | AE11: =IF(D11/Summary!$C$4>100,1,0)*E11 -> 0 | AF11: =IF(AE11>0,D11*E11,0) -> 0 | AG11: =IF(AV11>0,E11,0) -> 0 | AH11: =IF(BD11>0,E11,0) -> 0 | AI11: =IF(BJ11>0,E11,0) -> 0 | AJ11: =IF(ISNUMBER(SEARCH("|||||||||",C11)),0,1) -> 0 | AK11: =IF(AJ11=1, E11,0) -> 0 | AL11: =IF(AK11>0,D11*E11,0) -> 0 | AM11: =IF(ISNUMBER(SEARCH("Wild",C11)),1,0) -> 0 | AN11: =IF(AM11=1, E11,0) -> 0 | AO11: =IF(AN11>0,D11*E11,0) -> 0 | AP11: =IF(ISNUMBER(SEARCH("Wild-",C11)),1,0) -> 0 | AQ11: =IF(AP11=1, E11,0) -> 0 | AR11: =IF(AQ11>0,D11*E11,0) -> 0 | AS11: =IF(ISNUMBER(SEARCH("WildX",C11)),1,0) -> 0 | AT11: =IF(AS11=1, E11,0) -> 0 | AU11: =IF(AT11>0,D11*E11,0) -> 0 | AV11: =IF(ISNUMBER(SEARCH("freeplayA",C11)),E11,0) -> 0 | AW11: =AV11*D11 -> 0 | AX11: =IF(ISNUMBER(SEARCH("FreePlayB",C11)),E11,0) -> 0 | AY11: =AX11*D11 -> 0 | AZ11: =IF(ISNUMBER(SEARCH("FreePlayC",C11)),E11,0) -> 0 | BA11: =AZ11*D11 -> 0 | BB11: =IF(ISNUMBER(SEARCH("FreePlayD",C11)),E11,0) -> 0 | BC11: =BB11*D11 -> 0 | BD11: =IF(ISNUMBER(SEARCH("bonusA",C11)),E11,0) -> 0 | BE11: =BD11*D11 -> 0 | BF11: =IF(ISNUMBER(SEARCH("BonusB",C11)),E11,0) -> 0 | BG11: =BF11*D11 -> 0 | BH11: =IF(ISNUMBER(SEARCH("BonusC",C11)),E11,0) -> 0 | BI11: =BH11*D11 -> 0 | BJ11: =IF(ISNUMBER(SEARCH("Instant",C11)),E11,0) -> 0 | BK11: =BJ11*D11 -> 0 | BL11: 0 | BM11: =IF(D11 < $D$367, $C$367, IF(D11 = $D$368, $C$368, IF(D11 < $D$369, $C$369, IF(D11 < $D$370, $C$370, IF(D11 < $D$371, $C$371, $C$372))))) -> Standard Win | BN11: =IF(AV11 > 0,$C$376, IF(AX11 > 0,$C$377, IF(AZ11 > 0,$C$378, IF(BB11 > 0,$C$379, IF(BD11 > 0,$C$380, IF(BF11 > 0,$C$381, IF(BH11 > 0,$C$382, IF(BJ11 > 0,$C$383, IF(ISNUMBER(SEARCH("|||||||||",C11)), $C$384,$C$385))))))))) -> Single Win | BO11: =(D11/Summary!$C$4-Summary!$C$8)^2*E11 -> 16815.066 | BP11: =IF(AV11=1, E11*D11,0) -> 0 | BQ11: =IF(BD11=1, E11*D11,0) -> 0 | BR11: =IF(BJ11=1, D11*E11,0) -> 0 | BS11: =IF(BL11>0,BL11*E11,0) -> 0
B12: =Tiers!B13 -> 10 | C12: =Tiers!Y13 -> main-9||||||||| x 1 | D12: =Tiers!C13 -> 10 | E12: =Frequency!E14 -> 484 | F12: =E12*D12 -> 4840 | G12: =IF(Tiers!D13>1,'Data Analysis'!E12,0) -> 0 | H12: =G12*D12 -> 0 | I12: =IF(AND(D12/Summary!$C$4>0, D12/Summary!$C$4<5),E12,0) * D12 -> 0 | J12: =IF(AND(D12/Summary!$C$4>= 5, D12/Summary!$C$4<10),E12,0) * D12 -> 0 | K12: =IF(AND(D12/Summary!$C$4>=10, D12/Summary!$C$4<25),E12,0)*D12 -> 4840 | L12: =IF(D12/Summary!$C$4>=25,E12,0)*D12 -> 0 | M12: =IF(AND(D12/Summary!$C$4>0, D12/Summary!$C$4<1),E12,0) -> 0 | N12: =IF(M12>0,D12*E12,0) -> 0 | O12: =IF(D12/Summary!$C$4=1,1,0)*E12 -> 0 | P12: =IF(O12>0,D12*E12,0) -> 0 | Q12: =IF(AND(D12/Summary!$C$4>1, D12/Summary!$C$4<=2),1,0)*E12 -> 0 | R12: =IF(Q12>0,D12*E12,0) -> 0 | S12: =IF(AND(D12/Summary!$C$4>2,D12/Summary!$C$4<=5),1,0)*E12 -> 0 | T12: =IF(S12>0,D12*E12,0) -> 0 | U12: =IF(AND(D12/Summary!$C$4>5, D12/Summary!$C$4<=10),1,0)*E12 -> 484 | V12: =IF(U12>0,D12*E12,0) -> 4840 | W12: =IF(AND(D12/Summary!$C$4>10, D12/Summary!$C$4<=20),1,0)*E12 -> 0 | X12: =IF(W12>0,D12*E12,0) -> 0 | Y12: =IF(AND(D12/Summary!$C$4>20, D12/Summary!$C$4<=30),1,0)*E12 -> 0 | Z12: =IF(Y12>0,D12*E12,0) -> 0 | AA12: =IF(AND(D12/Summary!$C$4>30, D12/Summary!$C$4<=50),1,0)*E12 -> 0 | AB12: =IF(AA12>0,D12*E12,0) -> 0 | AC12: =IF(AND(D12/Summary!$C$4>50, D12/Summary!$C$4<=100),1,0)*E12 -> 0 | AD12: =IF(AC12>0,D12*E12,0) -> 0 | AE12: =IF(D12/Summary!$C$4>100,1,0)*E12 -> 0 | AF12: =IF(AE12>0,D12*E12,0) -> 0 | AG12: =IF(AV12>0,E12,0) -> 0 | AH12: =IF(BD12>0,E12,0) -> 0 | AI12: =IF(BJ12>0,E12,0) -> 0 | AJ12: =IF(ISNUMBER(SEARCH("|||||||||",C12)),0,1) -> 0 | AK12: =IF(AJ12=1, E12,0) -> 0 | AL12: =IF(AK12>0,D12*E12,0) -> 0 | AM12: =IF(ISNUMBER(SEARCH("Wild",C12)),1,0) -> 0 | AN12: =IF(AM12=1, E12,0) -> 0 | AO12: =IF(AN12>0,D12*E12,0) -> 0 | AP12: =IF(ISNUMBER(SEARCH("Wild-",C12)),1,0) -> 0 | AQ12: =IF(AP12=1, E12,0) -> 0 | AR12: =IF(AQ12>0,D12*E12,0) -> 0 | AS12: =IF(ISNUMBER(SEARCH("WildX",C12)),1,0) -> 0 | AT12: =IF(AS12=1, E12,0) -> 0 | AU12: =IF(AT12>0,D12*E12,0) -> 0 | AV12: =IF(ISNUMBER(SEARCH("freeplayA",C12)),E12,0) -> 0 | AW12: =AV12*D12 -> 0 | AX12: =IF(ISNUMBER(SEARCH("FreePlayB",C12)),E12,0) -> 0 | AY12: =AX12*D12 -> 0 | AZ12: =IF(ISNUMBER(SEARCH("FreePlayC",C12)),E12,0) -> 0 | BA12: =AZ12*D12 -> 0 | BB12: =IF(ISNUMBER(SEARCH("FreePlayD",C12)),E12,0) -> 0 | BC12: =BB12*D12 -> 0 | BD12: =IF(ISNUMBER(SEARCH("bonusA",C12)),E12,0) -> 0 | BE12: =BD12*D12 -> 0 | BF12: =IF(ISNUMBER(SEARCH("BonusB",C12)),E12,0) -> 0 | BG12: =BF12*D12 -> 0 | BH12: =IF(ISNUMBER(SEARCH("BonusC",C12)),E12,0) -> 0 | BI12: =BH12*D12 -> 0 | BJ12: =IF(ISNUMBER(SEARCH("Instant",C12)),E12,0) -> 0 | BK12: =BJ12*D12 -> 0 | BL12: 0 | BM12: =IF(D12 < $D$367, $C$367, IF(D12 = $D$368, $C$368, IF(D12 < $D$369, $C$369, IF(D12 < $D$370, $C$370, IF(D12 < $D$371, $C$371, $C$372))))) -> Big Win | BN12: =IF(AV12 > 0,$C$376, IF(AX12 > 0,$C$377, IF(AZ12 > 0,$C$378, IF(BB12 > 0,$C$379, IF(BD12 > 0,$C$380, IF(BF12 > 0,$C$381, IF(BH12 > 0,$C$382, IF(BJ12 > 0,$C$383, IF(ISNUMBER(SEARCH("|||||||||",C12)), $C$384,$C$385))))))))) -> Single Win | BO12: =(D12/Summary!$C$4-Summary!$C$8)^2*E12 -> 40699.028 | BP12: =IF(AV12=1, E12*D12,0) -> 0 | BQ12: =IF(BD12=1, E12*D12,0) -> 0 | BR12: =IF(BJ12=1, D12*E12,0) -> 0 | BS12: =IF(BL12>0,BL12*E12,0) -> 0
B13: =Tiers!B14 -> 11 | C13: =Tiers!Y14 -> main-10||||||||| x 1 | D13: =Tiers!C14 -> 1 | E13: =Frequency!E15 -> 67382 | F13: =E13*D13 -> 67382 | G13: =IF(Tiers!D14>1,'Data Analysis'!E13,0) -> 0 | H13: =G13*D13 -> 0 | I13: =IF(AND(D13/Summary!$C$4>0, D13/Summary!$C$4<5),E13,0) * D13 -> 67382 | J13: =IF(AND(D13/Summary!$C$4>= 5, D13/Summary!$C$4<10),E13,0) * D13 -> 0 | K13: =IF(AND(D13/Summary!$C$4>=10, D13/Summary!$C$4<25),E13,0)*D13 -> 0 | L13: =IF(D13/Summary!$C$4>=25,E13,0)*D13 -> 0 | M13: =IF(AND(D13/Summary!$C$4>0, D13/Summary!$C$4<1),E13,0) -> 0 | N13: =IF(M13>0,D13*E13,0) -> 0 | O13: =IF(D13/Summary!$C$4=1,1,0)*E13 -> 67382 | P13: =IF(O13>0,D13*E13,0) -> 67382 | Q13: =IF(AND(D13/Summary!$C$4>1, D13/Summary!$C$4<=2),1,0)*E13 -> 0 | R13: =IF(Q13>0,D13*E13,0) -> 0 | S13: =IF(AND(D13/Summary!$C$4>2,D13/Summary!$C$4<=5),1,0)*E13 -> 0 | T13: =IF(S13>0,D13*E13,0) -> 0 | U13: =IF(AND(D13/Summary!$C$4>5, D13/Summary!$C$4<=10),1,0)*E13 -> 0 | V13: =IF(U13>0,D13*E13,0) -> 0 | W13: =IF(AND(D13/Summary!$C$4>10, D13/Summary!$C$4<=20),1,0)*E13 -> 0 | X13: =IF(W13>0,D13*E13,0) -> 0 | Y13: =IF(AND(D13/Summary!$C$4>20, D13/Summary!$C$4<=30),1,0)*E13 -> 0 | Z13: =IF(Y13>0,D13*E13,0) -> 0 | AA13: =IF(AND(D13/Summary!$C$4>30, D13/Summary!$C$4<=50),1,0)*E13 -> 0 | AB13: =IF(AA13>0,D13*E13,0) -> 0 | AC13: =IF(AND(D13/Summary!$C$4>50, D13/Summary!$C$4<=100),1,0)*E13 -> 0 | AD13: =IF(AC13>0,D13*E13,0) -> 0 | AE13: =IF(D13/Summary!$C$4>100,1,0)*E13 -> 0 | AF13: =IF(AE13>0,D13*E13,0) -> 0 | AG13: =IF(AV13>0,E13,0) -> 0 | AH13: =IF(BD13>0,E13,0) -> 0 | AI13: =IF(BJ13>0,E13,0) -> 0 | AJ13: =IF(ISNUMBER(SEARCH("|||||||||",C13)),0,1) -> 0 | AK13: =IF(AJ13=1, E13,0) -> 0 | AL13: =IF(AK13>0,D13*E13,0) -> 0 | AM13: =IF(ISNUMBER(SEARCH("Wild",C13)),1,0) -> 0 | AN13: =IF(AM13=1, E13,0) -> 0 | AO13: =IF(AN13>0,D13*E13,0) -> 0 | AP13: =IF(ISNUMBER(SEARCH("Wild-",C13)),1,0) -> 0 | AQ13: =IF(AP13=1, E13,0) -> 0 | AR13: =IF(AQ13>0,D13*E13,0) -> 0 | AS13: =IF(ISNUMBER(SEARCH("WildX",C13)),1,0) -> 0 | AT13: =IF(AS13=1, E13,0) -> 0 | AU13: =IF(AT13>0,D13*E13,0) -> 0 | AV13: =IF(ISNUMBER(SEARCH("freeplayA",C13)),E13,0) -> 0 | AW13: =AV13*D13 -> 0 | AX13: =IF(ISNUMBER(SEARCH("FreePlayB",C13)),E13,0) -> 0 | AY13: =AX13*D13 -> 0 | AZ13: =IF(ISNUMBER(SEARCH("FreePlayC",C13)),E13,0) -> 0 | BA13: =AZ13*D13 -> 0 | BB13: =IF(ISNUMBER(SEARCH("FreePlayD",C13)),E13,0) -> 0 | BC13: =BB13*D13 -> 0 | BD13: =IF(ISNUMBER(SEARCH("bonusA",C13)),E13,0) -> 0 | BE13: =BD13*D13 -> 0 | BF13: =IF(ISNUMBER(SEARCH("BonusB",C13)),E13,0) -> 0 | BG13: =BF13*D13 -> 0 | BH13: =IF(ISNUMBER(SEARCH("BonusC",C13)),E13,0) -> 0 | BI13: =BH13*D13 -> 0 | BJ13: =IF(ISNUMBER(SEARCH("Instant",C13)),E13,0) -> 0 | BK13: =BJ13*D13 -> 0 | BL13: 0 | BM13: =IF(D13 < $D$367, $C$367, IF(D13 = $D$368, $C$368, IF(D13 < $D$369, $C$369, IF(D13 < $D$370, $C$370, IF(D13 < $D$371, $C$371, $C$372))))) -> Stake Back | BN13: =IF(AV13 > 0,$C$376, IF(AX13 > 0,$C$377, IF(AZ13 > 0,$C$378, IF(BB13 > 0,$C$379, IF(BD13 > 0,$C$380, IF(BF13 > 0,$C$381, IF(BH13 > 0,$C$382, IF(BJ13 > 0,$C$383, IF(ISNUMBER(SEARCH("|||||||||",C13)), $C$384,$C$385))))))))) -> Single Win | BO13: =(D13/Summary!$C$4-Summary!$C$8)^2*E13 -> 1947.3398 | BP13: =IF(AV13=1, E13*D13,0) -> 0 | BQ13: =IF(BD13=1, E13*D13,0) -> 0 | BR13: =IF(BJ13=1, D13*E13,0) -> 0 | BS13: =IF(BL13>0,BL13*E13,0) -> 0
... B356: =Tiers!B357 -> 354 | C356: =Tiers!Y357 -> bonusA-6||||||||| x 1 | D356: =Tiers!C357 -> 100 | E356: =Frequency!E358 -> 100 | F356: =E356*D356 -> 10000 | G356: =IF(Tiers!D357>1,'Data Analysis'!E356,0) -> 0 | H356: =G356*D356 -> 0 | I356: =IF(AND(D356/Summary!$C$4>0, D356/Summary!$C$4<5),E356,0) * D356 -> 0 | J356: =IF(AND(D356/Summary!$C$4>= 5, D356/Summary!$C$4<10),E356,0) * D356 -> 0 | K356: =IF(AND(D356/Summary!$C$4>=10, D356/Summary!$C$4<25),E356,0)*D356 -> 0 | L356: =IF(D356/Summary!$C$4>=25,E356,0)*D356 -> 10000 | M356: =IF(AND(D356/Summary!$C$4>0, D356/Summary!$C$4<1),E356,0) -> 0 | N356: =IF(M356>0,D356*E356,0) -> 0 | O356: =IF(D356/Summary!$C$4=1,1,0)*E356 -> 0 | P356: =IF(O356>0,D356*E356,0) -> 0 | Q356: =IF(AND(D356/Summary!$C$4>1, D356/Summary!$C$4<=2),1,0)*E356 -> 0 | R356: =IF(Q356>0,D356*E356,0) -> 0 | S356: =IF(AND(D356/Summary!$C$4>2,D356/Summary!$C$4<=5),1,0)*E356 -> 0 | T356: =IF(S356>0,D356*E356,0) -> 0 | U356: =IF(AND(D356/Summary!$C$4>5, D356/Summary!$C$4<=10),1,0)*E356 -> 0 | V356: =IF(U356>0,D356*E356,0) -> 0 | W356: =IF(AND(D356/Summary!$C$4>10, D356/Summary!$C$4<=20),1,0)*E356 -> 0 | X356: =IF(W356>0,D356*E356,0) -> 0 | Y356: =IF(AND(D356/Summary!$C$4>20, D356/Summary!$C$4<=30),1,0)*E356 -> 0 | Z356: =IF(Y356>0,D356*E356,0) -> 0 | AA356: =IF(AND(D356/Summary!$C$4>30, D356/Summary!$C$4<=50),1,0)*E356 -> 0 | AB356: =IF(AA356>0,D356*E356,0) -> 0 | AC356: =IF(AND(D356/Summary!$C$4>50, D356/Summary!$C$4<=100),1,0)*E356 -> 100 | AD356: =IF(AC356>0,D356*E356,0) -> 10000 | AE356: =IF(D356/Summary!$C$4>100,1,0)*E356 -> 0 | AF356: =IF(AE356>0,D356*E356,0) -> 0 | AG356: =IF(AV356>0,E356,0) -> 0 | AH356: =IF(BD356>0,E356,0) -> 100 | AI356: =IF(BJ356>0,E356,0) -> 0 | AJ356: =IF(ISNUMBER(SEARCH("|||||||||",C356)),0,1) -> 0 | AK356: =IF(AJ356=1, E356,0) -> 0 | AL356: =IF(AK356>0,D356*E356,0) -> 0 | AM356: =IF(ISNUMBER(SEARCH("Wild",C356)),1,0) -> 0 | AN356: =IF(AM356=1, E356,0) -> 0 | AO356: =IF(AN356>0,D356*E356,0) -> 0 | AP356: =IF(ISNUMBER(SEARCH("Wild-",C356)),1,0) -> 0 | AQ356: =IF(AP356=1, E356,0) -> 0 | AR356: =IF(AQ356>0,D356*E356,0) -> 0 | AS356: =IF(ISNUMBER(SEARCH("WildX",C356)),1,0) -> 0 | AT356: =IF(AS356=1, E356,0) -> 0 | AU356: =IF(AT356>0,D356*E356,0) -> 0 | AV356: =IF(ISNUMBER(SEARCH("freeplayA",C356)),E356,0) -> 0 | AW356: =AV356*D356 -> 0 | AX356: =IF(ISNUMBER(SEARCH("FreePlayB",C356)),E356,0) -> 0 | AY356: =AX356*D356 -> 0 | AZ356: =IF(ISNUMBER(SEARCH("FreePlayC",C356)),E356,0) -> 0 | BA356: =AZ356*D356 -> 0 | BB356: =IF(ISNUMBER(SEARCH("FreePlayD",C356)),E356,0) -> 0 | BC356: =BB356*D356 -> 0 | BD356: =IF(ISNUMBER(SEARCH("bonusA",C356)),E356,0) -> 100 | BE356: =BD356*D356 -> 10000 | BF356: =IF(ISNUMBER(SEARCH("BonusB",C356)),E356,0) -> 0 | BG356: =BF356*D356 -> 0 | BH356: =IF(ISNUMBER(SEARCH("BonusC",C356)),E356,0) -> 0 | BI356: =BH356*D356 -> 0 | BJ356: =IF(ISNUMBER(SEARCH("Instant",C356)),E356,0) -> 0 | BK356: =BJ356*D356 -> 0 | BL356: 0 | BM356: =IF(D356 < $D$367, $C$367, IF(D356 = $D$368, $C$368, IF(D356 < $D$369, $C$369, IF(D356 < $D$370, $C$370, IF(D356 < $D$371, $C$371, $C$372))))) -> Huge Win | BN356: =IF(AV356 > 0,$C$376, IF(AX356 > 0,$C$377, IF(AZ356 > 0,$C$378, IF(BB356 > 0,$C$379, IF(BD356 > 0,$C$380, IF(BF356 > 0,$C$381, IF(BH356 > 0,$C$382, IF(BJ356 > 0,$C$383, IF(ISNUMBER(SEARCH("|||||||||",C356)), $C$384,$C$385))))))))) -> Bonus Game A | BO356: =(D356/Summary!$C$4-Summary!$C$8)^2*E356 -> 983468.89 | BP356: =IF(AV356=1, E356*D356,0) -> 0 | BQ356: =IF(BD356=1, E356*D356,0) -> 0 | BR356: =IF(BJ356=1, D356*E356,0) -> 0 | BS356: =IF(BL356>0,BL356*E356,0) -> 0
E357: =SUM(E2:E356) -> 2000000 | F357: =SUM(F2:F356) -> 1660000 | G357: =SUM(G2:G356) -> 30628 | H357: =SUM(H2:H356) -> 550016.8 | I357: =SUM(I2:I356) -> 443875.6 | J357: =SUM(J2:J356) -> 51857.4 | K357: =SUM(K2:K356) -> 528256 | L357: =SUM(L2:L356) -> 636011 | ... BS357: =SUM(BS2:BS356) -> 0
C363: Ticket Price | D363: =Summary!C4 -> 1
C364: Max prize | D364: =Summary!C7 -> 1000
C366: Humad Read part 1 | D366: Actual Prize | E366: Multiplier
B367: 1 | C367: Less than Stake | D367: =E367*D363 -> 1 | E367: 1
B368: 2 | C368: Stake Back | D368: =E368*D363 -> 1 | E368: 1
B369: 3 | C369: Standard Win | D369: =E369*D363 -> 10 | E369: 10
B370: 4 | C370: Big Win | D370: =E370*D363 -> 50 | E370: 50
B371: 5 | C371: Huge Win | D371: =D364 -> 1000 | E371: =D364 -> 1000
B372: 6 | C372: Top Prize
C375: Humad Read part 2
B376: 1 | C376: Free Plays A
B377: 2 | C377: Free Plays B
B378: 3 | C378: Free Plays C
B379: 4 | C379: Free Plays D
B380: 5 | C380: Bonus Game A
B381: 6 | C381: Bonus Game B
B382: 7 | C382: Bonus Game C
B383: 8 | C383: Instant Prize A
B384: 9 | C384: Single Win
B385: 10 | C385: Combo Win

Sheet Unit Test
B2: No. | C2: PPS Check item | D2: Check | G2: *Tier order
B3: 1 | C3: Title | D3: x | G3: single win
B4: 2 | C4: Client | D4: x | G4: combo win
B5: 3 | C5: Max Prize | D5: x | G5: instant
B6: 4 | C6: PPS source | D6: x | G6: base+instant
B7: 5 | C7: Sum of winning tiers | D7: x | G7: freeplay
B8: 6 | C8: Sum of non-win tiers | D8: x | G8: base+freeplay
B9: 7 | C9: File name | D9: x | G9: bonus
B10: 8 | C10: Date | D10: x | G10: base+bonus
B11: 9 | C11: Scenario counts | D11: x
B12: 10 | C12: Actual RTP | D12: x
B13: 11 | C13: Actual Hit rate | D13: x
B14: 12 | C14: Num of tiers are matched | D14: x
B15: 13 | C15: category are in *order(new game) | D15: x
B16: 14 | C16: base tiers are exist in mixed tiers(new game) | D16: x
B17: 15 | C17: Add 1 in odds col exist | D17: x
B18: 16 | C18: Paytable check | D18: x
B19: 17 | C19: Prize double digits | D19: x
B20: 18 | C20: ticket price related | D20: x
B22: No. | C22: JP check | D22: check
B23: 1 | C23: Seed number | D23: x
B24: 2 | C24: Trigger target number | D24: x
B25: 3 | C25: Odds up number | D25: x
B26: 4 | C26: Odds down | D26: x
B27: 5 | C27: Seed RTP | D27: x
B28: 6 | C28: Contribution RTP | D28: x
B29: 7 | C29: Total RTP | D29: x
B30: 8 | C30: Different price point | D30: x
B31: 9 | C31: lowerest price 5 decimal | D31: x
B33: No. | C33: Delivery | D33: check
B34: 1 | C34: update the delivery(check Boundary) | D34: x
B35: 2 | C35: lock the delivery tab | D35: x
B36: 3 | C36: ticket info | D36: x
B37: 4 | C37: Check non win tiers match | D37: x
